Workbook
Name Slicer_Year: #N/A

Sheet Cover Page

Sheet Summary
B2: Scenario: | D2: Base | F2: Afro Brunch and Fitness Studio Co | I2: Last Updated:
C5: Company Name: | F5: Afrobeats Brunch & Fitness Studio
C7: Sector: | F7: Food & Beverage / Boutique Fitness
C10: Owner Equity Contribution | F10: =Assumptions!$C$51 -> 40000
C11: Enterprise Value (DCF) | F11: =Valuation!$B$31 -> 271957.24
C12: Equity Value (DCF) | F12: =Valuation!$B$33 -> 233182.24
C13: Equity Value (EBITDA multiple, Mid case) | F13: =Valuation!$C$41 -> 488753.6
F15: Year 1 | G15: Year 2 | H15: Year 3 | I15: Year 4 | J15: Year 5
C16: Income Statement
C17: Revenue | F17: ='Income Statement'!B8 -> 194579.26 | G17: ='Income Statement'!C8 -> 285569.93 | H17: ='Income Statement'!D8 -> 308415.52 | I17: ='Income Statement'!E8 -> 326920.46 | J17: ='Income Statement'!F8 -> 336728.07
C18: Cost of Sales | F18: =-'Income Statement'!B10 -> -59069.823 | G18: =-'Income Statement'!C10 -> -86777.314 | H18: =-'Income Statement'!D10 -> -93719.499 | I18: =-'Income Statement'!E10 -> -99342.669 | J18: =-'Income Statement'!F10 -> -102322.95
C19: Gross Profit | F19: ='Income Statement'!B11 -> 135509.44 | G19: ='Income Statement'!C11 -> 198792.62 | H19: ='Income Statement'!D11 -> 214696.03 | I19: ='Income Statement'!E11 -> 227577.79 | J19: ='Income Statement'!F11 -> 234405.12
C20: Operating Expenses | F20: =-'Income Statement'!B22 -> -131116.3 | G20: =-'Income Statement'!C22 -> -136244.61 | H20: =-'Income Statement'!D22 -> -137824.28 | I20: =-'Income Statement'!E22 -> -139103.8 | J20: =-'Income Statement'!F22 -> -139781.96
C21: EBITDA | F21: ='Income Statement'!B24 -> 4393.1339 | G21: ='Income Statement'!C24 -> 62548.006 | H21: ='Income Statement'!D24 -> 76871.75 | I21: ='Income Statement'!E24 -> 88473.982 | J21: ='Income Statement'!F24 -> 94623.165
C22: Net Profit After Tax | F22: ='Income Statement'!B29 -> -13256.632 | G22: ='Income Statement'!C29 -> 35732.729 | H22: ='Income Statement'!D29 -> 47226.13 | I22: ='Income Statement'!E29 -> 56736.667 | J22: ='Income Statement'!F29 -> 62220.212
C24: Full detail: Income Statement, Balance Sheet, Cashflow statement, pivot Summary, and Valuation tabs. See Table of Content for a full map of this workbook.

Sheet Table of Content
B1: Scenario: | C1: Base | F1: Afro Brunch and Fitness Studio Co | L1: Last Updated: | M1: =TODAY() -> 46233
B5: S/N | C5: Details
B6: 1 | C6: Dasboard
B7: 2 | C7: Startup costs
B8: 3 | C8: Workings
B9: 4 | C9: Income statement
B10: 5 | C10: Balance Sheet
B11: 6 | C11: CashFlow Statement
B12: 7 | C12: Valuation
B13: 8 | C13: Scenario Analysis
B14: 9 | C14: Data
B15: 10 | C15: Assumptions
B16: 11 | C16: Seasonality Data Breakdown
B17: 12 | C17: Five year monthly
... B22: 17 | C22: Break Even

Sheet Dashboard
F1: Afro Brunch Café and Fitness studio
C2: 2
T23: =AVERAGE('monthly model engine'!Z8:Z68) -> 16849.683
S26: =AVERAGE('monthly model engine'!AU8:AU68) -> 3144.3184

Sheet Startup Costs
B2: Scenario: | C2: Base | E2: Afro Brunch and Fitness Studio Co | F2: Last Updated: | G2: =TODAY() -> 46233
A4: Startup (One-Off) Costs
A5: Capital required before opening day. Ranges reflect UK 2025-26 sources
A6: Item | B6: Low (£) | C6: High (£) | D6: Model Assumption (£) | E6: Source
A7: Rent deposit (3 months) + legal fees | B7: 6000 | C7: 12000 | D7: =Assumptions!$C$10*Assumptions!$C$9/12*Assumptions!$C$11+1500 -> 7500 | E7: Huxley & Co (2026): typical deposit 3-6 months' rent + solicitor fees; linked to Assumptions rent figures plus a £1,500 legal-fee estimate
A8: Café fit-out (light food service, no full kitchen) | B8: 11000 | C8: 30000 | D8: 18000 | E8: Huxley & Co (2026): kitchen fit-out for drinks + light snacks/sandwiches typically £11,000-£30,000
A9: Café equipment (espresso machine, grinder, fridge, dishwasher, POS) | B9: 10000 | C9: 15000 | D9: 12000 | E9: AT Coffee (2025) / Afida (2026): UK café equipment package typically £10,000-£15,000
A10: Fitness studio fit-out (flooring, mirrors, sound, lighting) | B10: 6000 | C10: 25000 | D10: 14000 | E10: CYC Fitness / RDX Wholesale (2026): boutique studio fit-out and specialist kit typically £6,000-£25,000
A11: Fitness equipment (mats, light weights, resistance bands) | B11: 2000 | C11: 8000 | D11: 4000 | E11: RDX Wholesale (2026): boutique studio (yoga/Pilates/dance-style) equipment £2,000-£8,000
A12: Café furniture (tables, chairs, shelving) | B12: 3000 | C12: 5000 | D12: 4000 | E12: AT Coffee (2025): furniture typically £3,000-£5,000
A13: Signage & shopfront | B13: 1000 | C13: 5000 | D13: 3000 | E13: Huxley & Co (2026): bifold doors £2,500-£5,000, canopy £1,000-£5,000; mid-range shopfront assumed
A14: Initial F&B stock | B14: 1500 | C14: 3000 | D14: 2000 | E14: AT Coffee (2025): initial stock (coffee, milk, pastries, packaging) typically £1,500-£3,000
A15: Licences, insurance setup, food hygiene registration, PPL PRS music licence | B15: 500 | C15: 3000 | D15: 2000 | E15: Grove HR (2026): PPL PRS licence £500-£1,500/yr, ICO registration £40/yr, food hygiene registration is free via local council; insurance setup estimated
A16: Marketing & launch campaign | B16: 1000 | C16: 3000 | D16: 2000 | E16: AT Coffee (2025): signage, logo design, launch campaign typically £1,000-£3,000
A17: Subtotal — fit-out, equipment & launch costs | D17: =SUM(D7:D16) -> 68500
A19: Contingency (15% of subtotal above) | D19: =D17*0.15 -> 10275 | E19: Resawod (2026): fit-out quotes routinely run over; build in a 15-20% contingency
A20: Working capital reserve (3 months of fixed operating costs) | D20: ='monthly model engine'!$AK$19*3 -> 31074.697 | E20: AT Coffee / Bellwether Coffee (2026): plan for 3-6 months of fixed costs as a cash buffer before trade builds; linked from Monthly P&L
A22: TOTAL STARTUP CAPITAL REQUIRED | D22: =D17+D19+D20 -> 109849.7
A24: of which: capitalised as fixed assets (fit-out, equipment, furniture, signage) | D24: =D8+D9+D10+D11+D12+D13 -> 55000 | E24: Feeds the opening Balance Sheet as Fixed Assets at cost. Excludes rent deposit, initial stock, licences and launch marketing, which are treated as expensed pre-trading costs.

Sheet Scenario Analysis
B1: Scenario: | C1: Base | E1: Afro Brunch and Fitness Studio Co | F1: Last Updated: | G1: =TODAY() -> 46233
A4: Scenario Switch — Base / Best / Worst Case
A5: ACTIVE SCENARIO: | B5: Base | H5: Worst
H6: Base
A7: Driver | B7: Worst Case | C7: Base Case | D7: Best Case | E7: Selected (active) | F7: Rationale | H7: Best
A8: Steady-state café covers/day | B8: 40 | C8: 65 | D8: 90 | E8: =CHOOSE(MATCH($B$5,{"Worst","Base","Best"},0),B8,C8,D8) -> 65 | F8: No public benchmark exists for this hybrid concept. Worst reflects slow footfall build; Best reflects strong local word-of-mouth.
A9: Classes run per week, steady state | B9: 8 | C9: 14 | D9: 20 | E9: =CHOOSE(MATCH($B$5,{"Worst","Base","Best"},0),B9,C9,D9) -> 14 | F9: Reflects a thinner (Worst) or fuller (Best) class timetable than the base daytime schedule, constrained by instructor availability and demand
A10: Paying monthly members, steady state | B10: 30 | C10: 55 | D10: 85 | E10: =CHOOSE(MATCH($B$5,{"Worst","Base","Best"},0),B10,C10,D10) -> 55 | F10: No benchmark exists for this concept. Worst assumes membership take-up stays low; Best assumes strong conversion from class attendees to members
A11: Year 2 revenue growth vs Year 1 | B11: 0.05 | C11: 0.15 | D11: 0.3 | E11: =CHOOSE(MATCH($B$5,{"Worst","Base","Best"},0),B11,C11,D11) -> 0.15 | F11: ASSUMPTION range, not a forecast — Worst assumes growth stalls after opening buzz fades; Best assumes strong repeat custom and word-of-mouth
A12: Year 3 revenue growth vs Year 2 | B12: 0.02 | C12: 0.08 | D12: 0.15 | E12: =CHOOSE(MATCH($B$5,{"Worst","Base","Best"},0),B12,C12,D12) -> 0.08 | F12: ASSUMPTION range — growth typically moderates as a single site approaches its capacity ceiling
A13: Year 4 revenue growth vs Year 3 | B13: 0 | C13: 0.06 | D13: 0.12 | E13: =CHOOSE(MATCH($B$5,{"Worst","Base","Best"},0),B13,C13,D13) -> 0.06 | F13: ASSUMPTION range - Worst assumes growth has fully stalled by Year 4; Best assumes the site still has room to grow before hitting a capacity ceiling
A14: Year 5 revenue growth vs Year 4 | B14: -0.03 | C14: 0.03 | D14: 0.08 | E14: =CHOOSE(MATCH($B$5,{"Worst","Base","Best"},0),B14,C14,D14) -> 0.03 | F14: ASSUMPTION range - Worst assumes slight decline as the concept ages without reinvestment; Best assumes modest continued growth
A16: NOTE: cost-side assumptions (rent, wages, food cost %, prices) are held constant across scenarios. Only footfall, class demand, membership take-up and multi-year growth vary - the assumptions with no external benchmark, flagged yellow on the Assumption Tab.
A22: Metric | B22: Worst Case | C22: Base Case | D22: Best Case
A23: Year 1 Revenue | B23: 117896 | C23: 194579 | D23: 270110
A24: Year 1 EBITDA | B24: -45246 | C24: 4393 | D24: 52934
A25: Year 5 Revenue | B25: 156104 | C25: 336728 | D25: 623497
A26: Year 5 EBITDA | B26: -20654 | C26: 94623 | D26: 277017
A27: Cash balance, end of Year 1 | B27: -30967 | C27: 14587 | D27: 56387
A28: Cash balance, end of Year 5 | B28: -173811 | C28: 197994 | D28: 677608

Sheet Assumptions
B1: Scenario: | C1: Base | E1: Afro Brunch and Fitness Studio Co | F1: Last Updated: | G1: =TODAY() -> 46233
A5: Assumptions
A6: All UK-sourced or explicitly flagged as an estimate. Location basis: Greater London, non-prime suburban high street, ~800 sq ft.
A7: Category | B7: Assumption | C7: Value | D7: Unit | E7: Source / Note
A8: PREMISES & LOCATION
A9: Premises | B9: Floor area | C9: 800 | D9: sq ft | E9: (small studio, under 1,000 sq ft)
A10: Premises | B10: Annual rent, Greater London suburban high street (non-prime) | C10: 30 | D10: £/sq ft/yr | E10: Huxley & Co (2026): London zones 2-6 typically £2,500-£5,000/month for a small unit; DOUBLE PUC Café (2025): suburban London £25-£50/sq ft vs. £60-£150 prime high street. Midpoint of suburban range used.
A11: Premises | B11: Rent deposit required | C11: 3 | D11: months | E11: Huxley & Co (2026): most landlords require 3-6 months' rent deposit
A12: Premises | B12: Business rates, net of relief (estimate) | C12: 1500 | D12: £/yr | E12: ESTIMATE. Small units are typically well under the £51,000 rateable-value threshold and commonly qualify for Small Business Rate Relief plus 75% Retail, Hospitality & Leisure relief, capped at £110,000/business (gov.uk; DineOpen, 2026). Actual rateable value must be confirmed with the VOA/local council before funding.
A13: Premises | B13: Utilities (gas/electric/water) | C13: 0.03 | D13: % of revenue | E13: Brikly (2026): UK cafés typically pay 2.5-3.5% of revenue on gas and electric
A14: Premises | B14: Insurance (public liability, contents, instructor indemnity) | C14: 1800 | D14: £/yr | E14: ESTIMATE — combined hospitality + fitness liability cover; obtain broker quotes (e.g. specialist gym/café insurers) before funding.
A15: Premises | B15: Card processing fees | C15: 0.0175 | D15: % of card revenue | E15: Brikly (2026): card mix is 90%+ in most UK cafés at an all-in cost of ~1.5-2%
A17: CAFÉ / BRUNCH REVENUE
A18: Café | B18: Trading days per year | C18: 313 | D18: days | E18: 6 days/week x 52 weeks; bsness.co.uk (2026): UK cafés typically trade 300-360 days/yr
A19: Café | B19: Steady-state covers per day | C19: ='Scenario Analysis'!$E$8 -> 65 | D19: covers | E19: ESTIMATE — no public benchmark exists for this hybrid concept.
A20: Café | B20: Average spend per head | C20: 8.5 | D20: £ | E20: bsness.co.uk (2026): UK café average spend per head is £5-£12; a brunch/food-forward menu is assumed to sit toward the upper-middle of this range.
A21: Café | B21: Food & drink cost of sales | C21: 0.3 | D21: % of café revenue | E21: The Caterer / AHBS Ltd benchmark (2025): UK food cost 28-32% of food sales, beverage 18-24% of beverage sales; 30% blended used
A23: FITNESS / AFROBEATS CLASSES
A24: Fitness | B24: Classes run per week, steady state | C24: ='Scenario Analysis'!$E$9 -> 14 | D24: classes | E24: ESTIMATE — a realistic daytime schedule for a small studio (school-run friendly slots)
A25: Fitness | B25: Average attendees per class | C25: 10 | D25: people | E25: ESTIMATE based on 800 sq ft floor capacity for a moderate-intensity dance/fitness class
A26: Fitness | B26: Drop-in class price | C26: 12 | D26: £ | E26: StudioGrowth (2026) and PayScale UK cite UK group fitness classes typically £10-£20-plus; priced at the accessible end to fit a community-first, non-premium positioning
A27: Fitness | B27: Paying monthly members, steady state | C27: ='Scenario Analysis'!$E$10 -> 55 | D27: members | E27: ESTIMATE — no public benchmark for this concept; treat as the number to validate via a pre-launch waiting list or founding-member offer.
A28: Fitness | B28: Monthly membership price (unlimited/bundled classes) | C28: 45 | D28: £/month | E28: Leisure DB 2025 State of the Fitness Industry: average UK gym membership £48.45/month (£76 in London). Priced below the national average to reflect community/accessible positioning.
A29: Fitness | B29: Freelance instructor rate per class | C29: 30 | D29: £/class | E29: Healthworks (2025): £25/hour for freelance class cover; activecareers.org.uk: freelance instructors typically earn up to £35/class outside London and £45/hour in London. Midpoint used for Greater London suburban location.
A31: STAFFING & WAGES
A32: Staffing | B32: Front-of-house / barista hours per week, steady state | C32: 65 | D32: hrs/wk | E32: ESTIMATE — covers opening hours with 2 staff overlapping at peak (e.g. 7am-3pm, 6 days)
A33: Staffing | B33: Front-of-house hourly wage | C33: 13.25 | D33: £/hr | E33: GOV.UK: National Living Wage (21+) is £12.71/hour from 1 April 2026. Set slightly above the statutory floor to aid retention in a customer-facing role.
A34: Staffing | B34: Owner/manager annual salary or draw | C34: 26000 | D34: £/yr | E34: ESTIMATE — below TRAINFITNESS UK fitness-manager guide range (£27,000-£50,000) to reflect a pre-revenue-proven, single-site startup
A35: Staffing | B35: Employer NI + auto-enrolment pension on wages | C35: 0.15 | D35: % of gross wages | E35: ESTIMATE combining current employer NI rate and minimum 3% auto-enrolment pension contribution
A37: OTHER OPERATING COSTS & TAX
A38: Opex | B38: Ongoing marketing | C38: 400 | D38: £/month | E38: ESTIMATE — local social media, launch offers, community partnerships
A39: Opex | B39: POS + class-booking software | C39: 150 | D39: £/month | E39: GoTeamUp (2026): studio/gym management software typically $100-$500/month
A40: Opex | B40: Cleaning, repairs, accountancy, admin | C40: 500 | D40: £/month | E40: ESTIMATE — combined light-touch back-office costs for a single small site
A41: Tax | B41: Corporation tax rate (small profits) | C41: 0.25 | D41: % | E41: bsness.co.uk (2026): current UK Corporation Tax main/small-profits rate is 25% for most small companies — confirm current rate and marginal relief with HMRC/accountant
A42: Tax | B42: VAT registration threshold | C42: 90000 | D42: £ turnover | E42: Current UK VAT registration threshold to be reconfirm on gov.uk before trading, as thresholds are reviewed periodically
A44: GROWTH ASSUMPTIONS (YEARS 2-3)
A45: Growth | B45: Year 2 revenue growth vs Year 1 | C45: ='Scenario Analysis'!$E$11 -> 0.15 | D45: % | E45: ASSUMPTION, not a forecast — a maturing single site commonly grows as awareness builds and word-of-mouth spreads
A46: Growth | B46: Year 3 revenue growth vs Year 2 | C46: ='Scenario Analysis'!$E$12 -> 0.08 | D46: % | E46: ASSUMPTION — growth typically slows as a single site approaches its capacity ceiling.
A48: Fitness | B48: Average classes attended per member, per month | C48: 6 | D48: classes/member/month | E48: ESTIMATE — assumes an unlimited member attends roughly 1.5x/week on average. No public benchmark exists
A50: FINANCING & DEPRECIATION
A51: Financing | B51: Owner equity contribution | C51: 40000 | D51: £ | E51: ESTIMATE -the remainder is modelled as a loan.
A52: Financing | B52: Loan interest rate (blended) | C52: 0.075 | D52: % per year | E52: Blends the British Business Bank Start Up Loans scheme (6% fixed, capped at £25,000 per founder) with typical unsecured small-business loan rates for any balance above that cap; confirm actual terms with a lender.
A53: Financing | B53: Loan term | C53: 5 | D53: years | E53: Standard term for small-business/Start Up Loans finance
A54: Financing | B54: Depreciation useful life (fit-out & equipment) | C54: 5 | D54: years | E54: Standard straight-line assumption for leasehold improvements and catering/fitness equipment; confirm with your accountant
A55: Growth | B55: Year 4 revenue growth vs Year 3 | C55: ='Scenario Analysis'!$E$13 -> 0.06 | D55: % | E55: LINKED TO SCENARIOS TAB. ASSUMPTION - growth continuing to moderate as the site matures further.
A56: Growth | B56: Year 5 revenue growth vs Year 4 | C56: ='Scenario Analysis'!$E$14 -> 0.03 | D56: % | E56: LINKED TO SCENARIOS TAB. ASSUMPTION - a single site typically approaches a capacity ceiling by Year 5.
C65: Base

Sheet Seasonality Data Break down
B1: Scenario: | C1: Base | E1: Afro Brunch and Fitness Studio Co | F1: Last Updated: | G1: =TODAY() -> 46233
A4: Seasonality & Marketing Plan (repeats every year, Months 1-12 = Jan-Dec)
A6: Month # | B6: Month | C6: Cafe Seasonality Index | D6: Fitness Seasonality Index | E6: Summer Iced-Drink Spend Uplift (£) | F6: Social Media Ads (£) | G6: Local/Community Marketing (£) | H6: Referral/Loyalty Programme (£) | I6: Total Marketing Base (£) | J6: Rationale
A7: 1 | B7: January | C7: 0.85 | D7: 1.3 | E7: 0 | F7: 300 | G7: 150 | H7: 50 | I7: =F7+G7+H7 -> 500 | J7: Jan: post-holiday spending pullback for cafe; strong New Year fitness-resolution surge; heaviest paid-social push to capture resolution search demand
A8: 2 | B8: February | C8: 0.9 | D8: 1.2 | E8: 0 | F8: 200 | G8: 150 | H8: 50 | I8: =F8+G8+H8 -> 400 | J8: Feb: cafe still building back; fitness resolution demand starting to taper (well-documented gym drop-off pattern)
A9: 3 | B9: March | C9: 0.95 | D9: 1.05 | E9: 0 | F9: 150 | G9: 150 | H9: 50 | I9: =F9+G9+H9 -> 350 | J9: Mar: both approaching baseline as routines normalise
A10: 4 | B10: April | C10: 1 | D10: 1 | E10: 0 | F10: 150 | G10: 150 | H10: 75 | I10: =F10+G10+H10 -> 375 | J10: Apr: baseline month for both
A11: 5 | B11: May | C11: 1.05 | D11: 0.95 | E11: 0 | F11: 150 | G11: 200 | H11: 75 | I11: =F11+G11+H11 -> 425 | J11: May: cafe lifts into Mother's Day/spring; fitness starts easing as weather improves; referral spend ticks up
A12: 6 | B12: June | C12: 1.1 | D12: 0.85 | E12: 0.75 | F12: 250 | G12: 150 | H12: 75 | I12: =F12+G12+H12 -> 475 | J12: Jun: iced-drink/summer menu uplift begins; fitness dips as summer holidays start; summer social campaign begins
A13: 7 | B13: July | C13: 1.15 | D13: 0.8 | E13: 0.75 | F13: 250 | G13: 150 | H13: 75 | I13: =F13+G13+H13 -> 475 | J13: Jul: peak cafe summer trade; fitness at its lowest as holiday season peaks
A14: 8 | B14: August | C14: 1 | D14: 0.85 | E14: 0.75 | F14: 150 | G14: 150 | H14: 75 | I14: =F14+G14+H14 -> 375 | J14: Aug: cafe eases slightly as some regulars travel; fitness still subdued
A15: 9 | B15: September | C15: 0.95 | D15: 1.05 | E15: 0 | F15: 200 | G15: 200 | H15: 75 | I15: =F15+G15+H15 -> 475 | J15: Sep: 'back to routine' bump for fitness; cafe returns to baseline; local partnership push for the new term
A16: 10 | B16: October | C16: 1 | D16: 1 | E16: 0 | F16: 150 | G16: 150 | H16: 50 | I16: =F16+G16+H16 -> 350 | J16: Oct: both at baseline
A17: 11 | B17: November | C17: 1.05 | D17: 0.95 | E17: 0 | F17: 250 | G17: 200 | H17: 75 | I17: =F17+G17+H17 -> 525 | J17: Nov: cafe begins holiday-season lift (gatherings, gifting); fitness dips as routines disrupt; marketing ramps for the festive period
A18: 12 | B18: December | C18: 1.2 | D18: 0.8 | E18: 0 | F18: 300 | G18: 250 | H18: 100 | I18: =F18+G18+H18 -> 650 | J18: Dec: cafe peak (holiday brunches, gifting); fitness at its lowest (well-documented holiday attendance drop); heaviest festive marketing push
A20: Average (should be close to 1.00 for a seasonality index) | C20: =AVERAGE(C7:C18) -> 1.0166667 | D20: =AVERAGE(D7:D18) -> 0.98333333
A22: SOURCING NOTE
A23: These monthly indices are ESTIMATES, not measured local data - built from well-documented general seasonal patterns (January gym-membership surges and summer holiday attendance dips are widely reported industry-wide; UK hospitality holiday-season and summer trade upticks are similarly well documented in general terms) rather than data specific to this concept. There is no public dataset for a combined brunch-cafe/Afrobeats-fitness business.

Sheet 5-Year monthly
B1: Scenario: | C1: Base | E1: Afro Brunch and Fitness Studio Co | F1: Last Updated: | G1: =TODAY() -> 46233
A3: Monthly Profit & Loss
D4: Year 1 | P4: Year 2 | AB4: Year 3 | AN4: Year 4 | AZ4: Year 5
D5: ='monthly model engine'!D8 -> January Y1 | E5: ='monthly model engine'!D9 -> February Y1 | F5: ='monthly model engine'!D10 -> March Y1 | G5: ='monthly model engine'!D11 -> April Y1 | H5: ='monthly model engine'!D12 -> May Y1 | I5: ='monthly model engine'!D13 -> June Y1 | J5: ='monthly model engine'!D14 -> July Y1 | K5: ='monthly model engine'!D15 -> August Y1 | L5: ='monthly model engine'!D16 -> September Y1 | M5: ='monthly model engine'!D17 -> October Y1 | N5: ='monthly model engine'!D18 -> November Y1 | O5: ='monthly model engine'!D19 -> December Y1 | P5: ='monthly model engine'!D20 -> January Y2 | Q5: ='monthly model engine'!D21 -> February Y2 | R5: ='monthly model engine'!D22 -> March Y2 | S5: ='monthly model engine'!D23 -> April Y2 | T5: ='monthly model engine'!D24 -> May Y2 | U5: ='monthly model engine'!D25 -> June Y2 | V5: ='monthly model engine'!D26 -> July Y2 | W5: ='monthly model engine'!D27 -> August Y2 | X5: ='monthly model engine'!D28 -> September Y2 | Y5: ='monthly model engine'!D29 -> October Y2 | Z5: ='monthly model engine'!D30 -> November Y2 | AA5: ='monthly model engine'!D31 -> December Y2 | AB5: ='monthly model engine'!D32 -> January Y3 | AC5: ='monthly model engine'!D33 -> February Y3 | AD5: ='monthly model engine'!D34 -> March Y3 | AE5: ='monthly model engine'!D35 -> April Y3 | AF5: ='monthly model engine'!D36 -> May Y3 | AG5: ='monthly model engine'!D37 -> June Y3 | AH5: ='monthly model engine'!D38 -> July Y3 | AI5: ='monthly model engine'!D39 -> August Y3 | AJ5: ='monthly model engine'!D40 -> September Y3 | AK5: ='monthly model engine'!D41 -> October Y3 | AL5: ='monthly model engine'!D42 -> November Y3 | AM5: ='monthly model engine'!D43 -> December Y3 | AN5: ='monthly model engine'!D44 -> January Y4 | AO5: ='monthly model engine'!D45 -> February Y4 | AP5: ='monthly model engine'!D46 -> March Y4 | AQ5: ='monthly model engine'!D47 -> April Y4 | AR5: ='monthly model engine'!D48 -> May Y4 | AS5: ='monthly model engine'!D49 -> June Y4 | AT5: ='monthly model engine'!D50 -> July Y4 | AU5: ='monthly model engine'!D51 -> August Y4 | AV5: ='monthly model engine'!D52 -> September Y4 | AW5: ='monthly model engine'!D53 -> October Y4 | AX5: ='monthly model engine'!D54 -> November Y4 | AY5: ='monthly model engine'!D55 -> December Y4 | AZ5: ='monthly model engine'!D56 -> January Y5 | BA5: ='monthly model engine'!D57 -> February Y5 | BB5: ='monthly model engine'!D58 -> March Y5 | BC5: ='monthly model engine'!D59 -> April Y5 | BD5: ='monthly model engine'!D60 -> May Y5 | BE5: ='monthly model engine'!D61 -> June Y5 | BF5: ='monthly model engine'!D62 -> July Y5 | BG5: ='monthly model engine'!D63 -> August Y5 | BH5: ='monthly model engine'!D64 -> September Y5 | BI5: ='monthly model engine'!D65 -> October Y5 | BJ5: ='monthly model engine'!D66 -> November Y5 | BK5: ='monthly model engine'!D67 -> December Y5
A7: REVENUE
B8: Cafe revenue | D8: ='monthly model engine'!M8 -> 6124.6927 | E8: ='monthly model engine'!M9 -> 7133.4656 | F8: ='monthly model engine'!M10 -> 8488.1035 | G8: ='monthly model engine'!M11 -> 9799.5083 | H8: ='monthly model engine'!M12 -> 11197.379 | I8: ='monthly model engine'!M13 -> 13800.692 | J8: ='monthly model engine'!M14 -> 15329.746 | K8: ='monthly model engine'!M15 -> 14114.344 | L8: ='monthly model engine'!M16 -> 12869.06 | M8: ='monthly model engine'!M17 -> 13978.71 | N8: ='monthly model engine'!M18 -> 14980.278 | O8: ='monthly model engine'!M19 -> 17293.25 | P8: ='monthly model engine'!M20 -> 14086.793 | Q8: ='monthly model engine'!M21 -> 14915.428 | R8: ='monthly model engine'!M22 -> 15744.063 | S8: ='monthly model engine'!M23 -> 16572.698 | T8: ='monthly model engine'!M24 -> 17401.333 | U8: ='monthly model engine'!M25 -> 19838.494 | V8: ='monthly model engine'!M26 -> 20740.244 | W8: ='monthly model engine'!M27 -> 18034.995 | X8: ='monthly model engine'!M28 -> 15744.063 | Y8: ='monthly model engine'!M29 -> 16572.698 | Z8: ='monthly model engine'!M30 -> 17401.333 | AA8: ='monthly model engine'!M31 -> 19887.237 | AB8: ='monthly model engine'!M32 -> 15213.737 | AC8: ='monthly model engine'!M33 -> 16108.662 | AD8: ='monthly model engine'!M34 -> 17003.588 | AE8: ='monthly model engine'!M35 -> 17898.514 | AF8: ='monthly model engine'!M36 -> 18793.439 | AG8: ='monthly model engine'!M37 -> 21425.574 | AH8: ='monthly model engine'!M38 -> 22399.464 | AI8: ='monthly model engine'!M39 -> 19477.794 | AJ8: ='monthly model engine'!M40 -> 17003.588 | AK8: ='monthly model engine'!M41 -> 17898.514 | AL8: ='monthly model engine'!M42 -> 18793.439 | AM8: ='monthly model engine'!M43 -> 21478.217 | AN8: ='monthly model engine'!M44 -> 16126.561 | AO8: ='monthly model engine'!M45 -> 17075.182 | AP8: ='monthly model engine'!M46 -> 18023.803 | AQ8: ='monthly model engine'!M47 -> 18972.425 | AR8: ='monthly model engine'!M48 -> 19921.046 | AS8: ='monthly model engine'!M49 -> 22711.108 | AT8: ='monthly model engine'!M50 -> 23743.431 | AU8: ='monthly model engine'!M51 -> 20646.462 | AV8: ='monthly model engine'!M52 -> 18023.803 | AW8: ='monthly model engine'!M53 -> 18972.425 | AX8: ='monthly model engine'!M54 -> 19921.046 | AY8: ='monthly model engine'!M55 -> 22766.909 | AZ8: ='monthly model engine'!M56 -> 16610.358 | BA8: ='monthly model engine'!M57 -> 17587.438 | BB8: ='monthly model engine'!M58 -> 18564.517 | BC8: ='monthly model engine'!M59 -> 19541.597 | BD8: ='monthly model engine'!M60 -> 20518.677 | BE8: ='monthly model engine'!M61 -> 23392.441 | BF8: ='monthly model engine'!M62 -> 24455.734 | BG8: ='monthly model engine'!M63 -> 21265.856 | BH8: ='monthly model engine'!M64 -> 18564.517 | BI8: ='monthly model engine'!M65 -> 19541.597 | BJ8: ='monthly model engine'!M66 -> 20518.677 | BK8: ='monthly model engine'!M67 -> 23449.917
B9: Fitness revenue | D9: ='monthly model engine'!W8 -> 3013.1088 | E9: ='monthly model engine'!W9 -> 3337.5974 | F9: ='monthly model engine'!W10 -> 3346.2891 | G9: ='monthly model engine'!W11 -> 3592.5528 | H9: ='monthly model engine'!W12 -> 3743.2082 | I9: ='monthly model engine'!W13 -> 3644.7028 | J9: ='monthly model engine'!W14 -> 3708.4416 | K9: ='monthly model engine'!W15 -> 4186.4829 | L9: ='monthly model engine'!W16 -> 5475.7458 | M9: ='monthly model engine'!W17 -> 5446.7736 | N9: ='monthly model engine'!W18 -> 5339.5765 | O9: ='monthly model engine'!W19 -> 4635.552 | P9: ='monthly model engine'!W20 -> 8662.6878 | Q9: ='monthly model engine'!W21 -> 7996.3272 | R9: ='monthly model engine'!W22 -> 6996.7863 | S9: ='monthly model engine'!W23 -> 6663.606 | T9: ='monthly model engine'!W24 -> 6330.4257 | U9: ='monthly model engine'!W25 -> 5664.0651 | V9: ='monthly model engine'!W26 -> 5330.8848 | W9: ='monthly model engine'!W27 -> 5664.0651 | X9: ='monthly model engine'!W28 -> 6996.7863 | Y9: ='monthly model engine'!W29 -> 6663.606 | Z9: ='monthly model engine'!W30 -> 6330.4257 | AA9: ='monthly model engine'!W31 -> 5330.8848 | AB9: ='monthly model engine'!W32 -> 9355.7028 | AC9: ='monthly model engine'!W33 -> 8636.0334 | AD9: ='monthly model engine'!W34 -> 7556.5292 | AE9: ='monthly model engine'!W35 -> 7196.6945 | AF9: ='monthly model engine'!W36 -> 6836.8598 | AG9: ='monthly model engine'!W37 -> 6117.1903 | AH9: ='monthly model engine'!W38 -> 5757.3556 | AI9: ='monthly model engine'!W39 -> 6117.1903 | AJ9: ='monthly model engine'!W40 -> 7556.5292 | AK9: ='monthly model engine'!W41 -> 7196.6945 | AL9: ='monthly model engine'!W42 -> 6836.8598 | AM9: ='monthly model engine'!W43 -> 5757.3556 | AN9: ='monthly model engine'!W44 -> 9917.045 | AO9: ='monthly model engine'!W45 -> 9154.1954 | AP9: ='monthly model engine'!W46 -> 8009.921 | AQ9: ='monthly model engine'!W47 -> 7628.4961 | AR9: ='monthly model engine'!W48 -> 7247.0713 | AS9: ='monthly model engine'!W49 -> 6484.2217 | AT9: ='monthly model engine'!W50 -> 6102.7969 | AU9: ='monthly model engine'!W51 -> 6484.2217 | AV9: ='monthly model engine'!W52 -> 8009.921 | AW9: ='monthly model engine'!W53 -> 7628.4961 | AX9: ='monthly model engine'!W54 -> 7247.0713 | AY9: ='monthly model engine'!W55 -> 6102.7969 | AZ9: ='monthly model engine'!W56 -> 10214.556 | BA9: ='monthly model engine'!W57 -> 9428.8212 | BB9: ='monthly model engine'!W58 -> 8250.2186 | BC9: ='monthly model engine'!W59 -> 7857.351 | BD9: ='monthly model engine'!W60 -> 7464.4835 | BE9: ='monthly model engine'!W61 -> 6678.7484 | BF9: ='monthly model engine'!W62 -> 6285.8808 | BG9: ='monthly model engine'!W63 -> 6678.7484 | BH9: ='monthly model engine'!W64 -> 8250.2186 | BI9: ='monthly model engine'!W65 -> 7857.351 | BJ9: ='monthly model engine'!W66 -> 7464.4835 | BK9: ='monthly model engine'!W67 -> 6285.8808
B10: TOTAL REVENUE | D10: ='monthly model engine'!X8 -> 9137.8015 | E10: ='monthly model engine'!X9 -> 10471.063 | F10: ='monthly model engine'!X10 -> 11834.393 | G10: ='monthly model engine'!X11 -> 13392.061 | H10: ='monthly model engine'!X12 -> 14940.588 | I10: ='monthly model engine'!X13 -> 17445.394 | J10: ='monthly model engine'!X14 -> 19038.187 | K10: ='monthly model engine'!X15 -> 18300.827 | L10: ='monthly model engine'!X16 -> 18344.806 | M10: ='monthly model engine'!X17 -> 19425.484 | N10: ='monthly model engine'!X18 -> 20319.854 | O10: ='monthly model engine'!X19 -> 21928.802 | P10: ='monthly model engine'!X20 -> 22749.481 | Q10: ='monthly model engine'!X21 -> 22911.755 | R10: ='monthly model engine'!X22 -> 22740.849 | S10: ='monthly model engine'!X23 -> 23236.304 | T10: ='monthly model engine'!X24 -> 23731.759 | U10: ='monthly model engine'!X25 -> 25502.559 | V10: ='monthly model engine'!X26 -> 26071.129 | W10: ='monthly model engine'!X27 -> 23699.06 | X10: ='monthly model engine'!X28 -> 22740.849 | Y10: ='monthly model engine'!X29 -> 23236.304 | Z10: ='monthly model engine'!X30 -> 23731.759 | AA10: ='monthly model engine'!X31 -> 25218.122 | AB10: ='monthly model engine'!X32 -> 24569.44 | AC10: ='monthly model engine'!X33 -> 24744.696 | AD10: ='monthly model engine'!X34 -> 24560.117 | AE10: ='monthly model engine'!X35 -> 25095.208 | AF10: ='monthly model engine'!X36 -> 25630.299 | AG10: ='monthly model engine'!X37 -> 27542.764 | AH10: ='monthly model engine'!X38 -> 28156.819 | AI10: ='monthly model engine'!X39 -> 25594.985 | AJ10: ='monthly model engine'!X40 -> 24560.117 | AK10: ='monthly model engine'!X41 -> 25095.208 | AL10: ='monthly model engine'!X42 -> 25630.299 | AM10: ='monthly model engine'!X43 -> 27235.572 | AN10: ='monthly model engine'!X44 -> 26043.606 | AO10: ='monthly model engine'!X45 -> 26229.377 | AP10: ='monthly model engine'!X46 -> 26033.724 | AQ10: ='monthly model engine'!X47 -> 26600.921 | AR10: ='monthly model engine'!X48 -> 27168.117 | AS10: ='monthly model engine'!X49 -> 29195.33 | AT10: ='monthly model engine'!X50 -> 29846.228 | AU10: ='monthly model engine'!X51 -> 27130.684 | AV10: ='monthly model engine'!X52 -> 26033.724 | AW10: ='monthly model engine'!X53 -> 26600.921 | AX10: ='monthly model engine'!X54 -> 27168.117 | AY10: ='monthly model engine'!X55 -> 28869.706 | AZ10: ='monthly model engine'!X56 -> 26824.914 | BA10: ='monthly model engine'!X57 -> 27016.259 | BB10: ='monthly model engine'!X58 -> 26814.736 | BC10: ='monthly model engine'!X59 -> 27398.948 | BD10: ='monthly model engine'!X60 -> 27983.161 | BE10: ='monthly model engine'!X61 -> 30071.19 | BF10: ='monthly model engine'!X62 -> 30741.615 | BG10: ='monthly model engine'!X63 -> 27944.604 | BH10: ='monthly model engine'!X64 -> 26814.736 | BI10: ='monthly model engine'!X65 -> 27398.948 | BJ10: ='monthly model engine'!X66 -> 27983.161 | BK10: ='monthly model engine'!X67 -> 29735.798
A12: COST OF SALES
B13: Food & drink cost of sales | D13: ='monthly model engine'!N8 -> 1837.4078 | E13: ='monthly model engine'!N9 -> 2140.0397 | F13: ='monthly model engine'!N10 -> 2546.4311 | G13: ='monthly model engine'!N11 -> 2939.8525 | H13: ='monthly model engine'!N12 -> 3359.2138 | I13: ='monthly model engine'!N13 -> 4140.2075 | J13: ='monthly model engine'!N14 -> 4598.9237 | K13: ='monthly model engine'!N15 -> 4234.3031 | L13: ='monthly model engine'!N16 -> 3860.7181 | M13: ='monthly model engine'!N17 -> 4193.6131 | N13: ='monthly model engine'!N18 -> 4494.0833 | O13: ='monthly model engine'!N19 -> 5187.975 | P13: ='monthly model engine'!N20 -> 4226.038 | Q13: ='monthly model engine'!N21 -> 4474.6284 | R13: ='monthly model engine'!N22 -> 4723.2189 | S13: ='monthly model engine'!N23 -> 4971.8094 | T13: ='monthly model engine'!N24 -> 5220.3998 | U13: ='monthly model engine'!N25 -> 5951.5483 | V13: ='monthly model engine'!N26 -> 6222.0732 | W13: ='monthly model engine'!N27 -> 5410.4984 | X13: ='monthly model engine'!N28 -> 4723.2189 | Y13: ='monthly model engine'!N29 -> 4971.8094 | Z13: ='monthly model engine'!N30 -> 5220.3998 | AA13: ='monthly model engine'!N31 -> 5966.1712 | AB13: ='monthly model engine'!N32 -> 4564.121 | AC13: ='monthly model engine'!N33 -> 4832.5987 | AD13: ='monthly model engine'!N34 -> 5101.0764 | AE13: ='monthly model engine'!N35 -> 5369.5541 | AF13: ='monthly model engine'!N36 -> 5638.0318 | AG13: ='monthly model engine'!N37 -> 6427.6721 | AH13: ='monthly model engine'!N38 -> 6719.8391 | AI13: ='monthly model engine'!N39 -> 5843.3383 | AJ13: ='monthly model engine'!N40 -> 5101.0764 | AK13: ='monthly model engine'!N41 -> 5369.5541 | AL13: ='monthly model engine'!N42 -> 5638.0318 | AM13: ='monthly model engine'!N43 -> 6443.465 | AN13: ='monthly model engine'!N44 -> 4837.9683 | AO13: ='monthly model engine'!N45 -> 5122.5546 | AP13: ='monthly model engine'!N46 -> 5407.141 | AQ13: ='monthly model engine'!N47 -> 5691.7274 | AR13: ='monthly model engine'!N48 -> 5976.3137 | AS13: ='monthly model engine'!N49 -> 6813.3325 | AT13: ='monthly model engine'!N50 -> 7123.0294 | AU13: ='monthly model engine'!N51 -> 6193.9386 | AV13: ='monthly model engine'!N52 -> 5407.141 | AW13: ='monthly model engine'!N53 -> 5691.7274 | AX13: ='monthly model engine'!N54 -> 5976.3137 | AY13: ='monthly model engine'!N55 -> 6830.0728 | AZ13: ='monthly model engine'!N56 -> 4983.1073 | BA13: ='monthly model engine'!N57 -> 5276.2313 | BB13: ='monthly model engine'!N58 -> 5569.3552 | BC13: ='monthly model engine'!N59 -> 5862.4792 | BD13: ='monthly model engine'!N60 -> 6155.6032 | BE13: ='monthly model engine'!N61 -> 7017.7324 | BF13: ='monthly model engine'!N62 -> 7336.7203 | BG13: ='monthly model engine'!N63 -> 6379.7568 | BH13: ='monthly model engine'!N64 -> 5569.3552 | BI13: ='monthly model engine'!N65 -> 5862.4792 | BJ13: ='monthly model engine'!N66 -> 6155.6032 | BK13: ='monthly model engine'!N67 -> 7034.975
B14: Freelance instructor costs | D14: ='monthly model engine'!V8 -> 946.3272 | E14: ='monthly model engine'!V9 -> 1048.2394 | F14: ='monthly model engine'!V10 -> 1050.9692 | G14: ='monthly model engine'!V11 -> 1128.3132 | H14: ='monthly model engine'!V12 -> 1175.6296 | I14: ='monthly model engine'!V13 -> 1144.6919 | J14: ='monthly model engine'!V14 -> 1164.7104 | K14: ='monthly model engine'!V15 -> 1314.8489 | L14: ='monthly model engine'!V16 -> 1719.7677 | M14: ='monthly model engine'!V17 -> 1710.6684 | N14: ='monthly model engine'!V18 -> 1677.001 | O14: ='monthly model engine'!V19 -> 1455.888 | P14: ='monthly model engine'!V20 -> 2720.6907 | Q14: ='monthly model engine'!V21 -> 2511.4068 | R14: ='monthly model engine'!V22 -> 2197.481 | S14: ='monthly model engine'!V23 -> 2092.839 | T14: ='monthly model engine'!V24 -> 1988.197 | U14: ='monthly model engine'!V25 -> 1778.9132 | V14: ='monthly model engine'!V26 -> 1674.2712 | W14: ='monthly model engine'!V27 -> 1778.9132 | X14: ='monthly model engine'!V28 -> 2197.481 | Y14: ='monthly model engine'!V29 -> 2092.839 | Z14: ='monthly model engine'!V30 -> 1988.197 | AA14: ='monthly model engine'!V31 -> 1674.2712 | AB14: ='monthly model engine'!V32 -> 2938.346 | AC14: ='monthly model engine'!V33 -> 2712.3193 | AD14: ='monthly model engine'!V34 -> 2373.2794 | AE14: ='monthly model engine'!V35 -> 2260.2661 | AF14: ='monthly model engine'!V36 -> 2147.2528 | AG14: ='monthly model engine'!V37 -> 1921.2262 | AH14: ='monthly model engine'!V38 -> 1808.2129 | AI14: ='monthly model engine'!V39 -> 1921.2262 | AJ14: ='monthly model engine'!V40 -> 2373.2794 | AK14: ='monthly model engine'!V41 -> 2260.2661 | AL14: ='monthly model engine'!V42 -> 2147.2528 | AM14: ='monthly model engine'!V43 -> 1808.2129 | AN14: ='monthly model engine'!V44 -> 3114.6467 | AO14: ='monthly model engine'!V45 -> 2875.0585 | AP14: ='monthly model engine'!V46 -> 2515.6762 | AQ14: ='monthly model engine'!V47 -> 2395.8821 | AR14: ='monthly model engine'!V48 -> 2276.088 | AS14: ='monthly model engine'!V49 -> 2036.4998 | AT14: ='monthly model engine'!V50 -> 1916.7057 | AU14: ='monthly model engine'!V51 -> 2036.4998 | AV14: ='monthly model engine'!V52 -> 2515.6762 | AW14: ='monthly model engine'!V53 -> 2395.8821 | AX14: ='monthly model engine'!V54 -> 2276.088 | AY14: ='monthly model engine'!V55 -> 1916.7057 | AZ14: ='monthly model engine'!V56 -> 3208.0861 | BA14: ='monthly model engine'!V57 -> 2961.3103 | BB14: ='monthly model engine'!V58 -> 2591.1465 | BC14: ='monthly model engine'!V59 -> 2467.7585 | BD14: ='monthly model engine'!V60 -> 2344.3706 | BE14: ='monthly model engine'!V61 -> 2097.5948 | BF14: ='monthly model engine'!V62 -> 1974.2068 | BG14: ='monthly model engine'!V63 -> 2097.5948 | BH14: ='monthly model engine'!V64 -> 2591.1465 | BI14: ='monthly model engine'!V65 -> 2467.7585 | BJ14: ='monthly model engine'!V66 -> 2344.3706 | BK14: ='monthly model engine'!V67 -> 1974.2068
B15: TOTAL COST OF SALES | D15: ='monthly model engine'!Y8 -> 2783.735 | E15: ='monthly model engine'!Y9 -> 3188.279 | F15: ='monthly model engine'!Y10 -> 3597.4002 | G15: ='monthly model engine'!Y11 -> 4068.1657 | H15: ='monthly model engine'!Y12 -> 4534.8434 | I15: ='monthly model engine'!Y13 -> 5284.8994 | J15: ='monthly model engine'!Y14 -> 5763.6341 | K15: ='monthly model engine'!Y15 -> 5549.152 | L15: ='monthly model engine'!Y16 -> 5580.4858 | M15: ='monthly model engine'!Y17 -> 5904.2815 | N15: ='monthly model engine'!Y18 -> 6171.0843 | O15: ='monthly model engine'!Y19 -> 6643.863 | P15: ='monthly model engine'!Y20 -> 6946.7287 | Q15: ='monthly model engine'!Y21 -> 6986.0352 | R15: ='monthly model engine'!Y22 -> 6920.6999 | S15: ='monthly model engine'!Y23 -> 7064.6484 | T15: ='monthly model engine'!Y24 -> 7208.5969 | U15: ='monthly model engine'!Y25 -> 7730.4614 | V15: ='monthly model engine'!Y26 -> 7896.3444 | W15: ='monthly model engine'!Y27 -> 7189.4116 | X15: ='monthly model engine'!Y28 -> 6920.6999 | Y15: ='monthly model engine'!Y29 -> 7064.6484 | Z15: ='monthly model engine'!Y30 -> 7208.5969 | AA15: ='monthly model engine'!Y31 -> 7640.4424 | AB15: ='monthly model engine'!Y32 -> 7502.467 | AC15: ='monthly model engine'!Y33 -> 7544.9181 | AD15: ='monthly model engine'!Y34 -> 7474.3558 | AE15: ='monthly model engine'!Y35 -> 7629.8202 | AF15: ='monthly model engine'!Y36 -> 7785.2846 | AG15: ='monthly model engine'!Y37 -> 8348.8983 | AH15: ='monthly model engine'!Y38 -> 8528.052 | AI15: ='monthly model engine'!Y39 -> 7764.5645 | AJ15: ='monthly model engine'!Y40 -> 7474.3558 | AK15: ='monthly model engine'!Y41 -> 7629.8202 | AL15: ='monthly model engine'!Y42 -> 7785.2846 | AM15: ='monthly model engine'!Y43 -> 8251.6778 | AN15: ='monthly model engine'!Y44 -> 7952.615 | AO15: ='monthly model engine'!Y45 -> 7997.6131 | AP15: ='monthly model engine'!Y46 -> 7922.8172 | AQ15: ='monthly model engine'!Y47 -> 8087.6095 | AR15: ='monthly model engine'!Y48 -> 8252.4017 | AS15: ='monthly model engine'!Y49 -> 8849.8322 | AT15: ='monthly model engine'!Y50 -> 9039.7351 | AU15: ='monthly model engine'!Y51 -> 8230.4384 | AV15: ='monthly model engine'!Y52 -> 7922.8172 | AW15: ='monthly model engine'!Y53 -> 8087.6095 | AX15: ='monthly model engine'!Y54 -> 8252.4017 | AY15: ='monthly model engine'!Y55 -> 8746.7785 | AZ15: ='monthly model engine'!Y56 -> 8191.1934 | BA15: ='monthly model engine'!Y57 -> 8237.5415 | BB15: ='monthly model engine'!Y58 -> 8160.5017 | BC15: ='monthly model engine'!Y59 -> 8330.2377 | BD15: ='monthly model engine'!Y60 -> 8499.9738 | BE15: ='monthly model engine'!Y61 -> 9115.3272 | BF15: ='monthly model engine'!Y62 -> 9310.9271 | BG15: ='monthly model engine'!Y63 -> 8477.3515 | BH15: ='monthly model engine'!Y64 -> 8160.5017 | BI15: ='monthly model engine'!Y65 -> 8330.2377 | BJ15: ='monthly model engine'!Y66 -> 8499.9738 | BK15: ='monthly model engine'!Y67 -> 9009.1819
B17: GROSS PROFIT | D17: ='monthly model engine'!Z8 -> 6354.0665 | E17: ='monthly model engine'!Z9 -> 7282.784 | F17: ='monthly model engine'!Z10 -> 8236.9924 | G17: ='monthly model engine'!Z11 -> 9323.8954 | H17: ='monthly model engine'!Z12 -> 10405.744 | I17: ='monthly model engine'!Z13 -> 12160.495 | J17: ='monthly model engine'!Z14 -> 13274.553 | K17: ='monthly model engine'!Z15 -> 12751.675 | L17: ='monthly model engine'!Z16 -> 12764.32 | M17: ='monthly model engine'!Z17 -> 13521.202 | N17: ='monthly model engine'!Z18 -> 14148.77 | O17: ='monthly model engine'!Z19 -> 15284.939 | P17: ='monthly model engine'!Z20 -> 15802.752 | Q17: ='monthly model engine'!Z21 -> 15925.72 | R17: ='monthly model engine'!Z22 -> 15820.149 | S17: ='monthly model engine'!Z23 -> 16171.656 | T17: ='monthly model engine'!Z24 -> 16523.162 | U17: ='monthly model engine'!Z25 -> 17772.098 | V17: ='monthly model engine'!Z26 -> 18174.784 | W17: ='monthly model engine'!Z27 -> 16509.648 | X17: ='monthly model engine'!Z28 -> 15820.149 | Y17: ='monthly model engine'!Z29 -> 16171.656 | Z17: ='monthly model engine'!Z30 -> 16523.162 | AA17: ='monthly model engine'!Z31 -> 17577.68 | AB17: ='monthly model engine'!Z32 -> 17066.973 | AC17: ='monthly model engine'!Z33 -> 17199.778 | AD17: ='monthly model engine'!Z34 -> 17085.761 | AE17: ='monthly model engine'!Z35 -> 17465.388 | AF17: ='monthly model engine'!Z36 -> 17845.015 | AG17: ='monthly model engine'!Z37 -> 19193.866 | AH17: ='monthly model engine'!Z38 -> 19628.767 | AI17: ='monthly model engine'!Z39 -> 17830.42 | AJ17: ='monthly model engine'!Z40 -> 17085.761 | AK17: ='monthly model engine'!Z41 -> 17465.388 | AL17: ='monthly model engine'!Z42 -> 17845.015 | AM17: ='monthly model engine'!Z43 -> 18983.894 | AN17: ='monthly model engine'!Z44 -> 18090.991 | AO17: ='monthly model engine'!Z45 -> 18231.764 | AP17: ='monthly model engine'!Z46 -> 18110.907 | AQ17: ='monthly model engine'!Z47 -> 18513.311 | AR17: ='monthly model engine'!Z48 -> 18915.715 | AS17: ='monthly model engine'!Z49 -> 20345.498 | AT17: ='monthly model engine'!Z50 -> 20806.493 | AU17: ='monthly model engine'!Z51 -> 18900.245 | AV17: ='monthly model engine'!Z52 -> 18110.907 | AW17: ='monthly model engine'!Z53 -> 18513.311 | AX17: ='monthly model engine'!Z54 -> 18915.715 | AY17: ='monthly model engine'!Z55 -> 20122.928 | AZ17: ='monthly model engine'!Z56 -> 18633.721 | BA17: ='monthly model engine'!Z57 -> 18778.717 | BB17: ='monthly model engine'!Z58 -> 18654.234 | BC17: ='monthly model engine'!Z59 -> 19068.711 | BD17: ='monthly model engine'!Z60 -> 19483.187 | BE17: ='monthly model engine'!Z61 -> 20955.863 | BF17: ='monthly model engine'!Z62 -> 21430.688 | BG17: ='monthly model engine'!Z63 -> 19467.253 | BH17: ='monthly model engine'!Z64 -> 18654.234 | BI17: ='monthly model engine'!Z65 -> 19068.711 | BJ17: ='monthly model engine'!Z66 -> 19483.187 | BK17: ='monthly model engine'!Z67 -> 20726.616
A19: FIXED OPERATING EXPENSES
B20: Rent | D20: ='monthly model engine'!AA8 -> 2000 | E20: ='monthly model engine'!AA9 -> 2000 | F20: ='monthly model engine'!AA10 -> 2000 | G20: ='monthly model engine'!AA11 -> 2000 | H20: ='monthly model engine'!AA12 -> 2000 | I20: ='monthly model engine'!AA13 -> 2000 | J20: ='monthly model engine'!AA14 -> 2000 | K20: ='monthly model engine'!AA15 -> 2000 | L20: ='monthly model engine'!AA16 -> 2000 | M20: ='monthly model engine'!AA17 -> 2000 | N20: ='monthly model engine'!AA18 -> 2000 | O20: ='monthly model engine'!AA19 -> 2000 | P20: ='monthly model engine'!AA20 -> 2000 | Q20: ='monthly model engine'!AA21 -> 2000 | R20: ='monthly model engine'!AA22 -> 2000 | S20: ='monthly model engine'!AA23 -> 2000 | T20: ='monthly model engine'!AA24 -> 2000 | U20: ='monthly model engine'!AA25 -> 2000 | V20: ='monthly model engine'!AA26 -> 2000 | W20: ='monthly model engine'!AA27 -> 2000 | X20: ='monthly model engine'!AA28 -> 2000 | Y20: ='monthly model engine'!AA29 -> 2000 | Z20: ='monthly model engine'!AA30 -> 2000 | AA20: ='monthly model engine'!AA31 -> 2000 | AB20: ='monthly model engine'!AA32 -> 2000 | AC20: ='monthly model engine'!AA33 -> 2000 | AD20: ='monthly model engine'!AA34 -> 2000 | AE20: ='monthly model engine'!AA35 -> 2000 | AF20: ='monthly model engine'!AA36 -> 2000 | AG20: ='monthly model engine'!AA37 -> 2000 | AH20: ='monthly model engine'!AA38 -> 2000 | AI20: ='monthly model engine'!AA39 -> 2000 | AJ20: ='monthly model engine'!AA40 -> 2000 | AK20: ='monthly model engine'!AA41 -> 2000 | AL20: ='monthly model engine'!AA42 -> 2000 | AM20: ='monthly model engine'!AA43 -> 2000 | AN20: ='monthly model engine'!AA44 -> 2000 | AO20: ='monthly model engine'!AA45 -> 2000 | AP20: ='monthly model engine'!AA46 -> 2000 | AQ20: ='monthly model engine'!AA47 -> 2000 | AR20: ='monthly model engine'!AA48 -> 2000 | AS20: ='monthly model engine'!AA49 -> 2000 | AT20: ='monthly model engine'!AA50 -> 2000 | AU20: ='monthly model engine'!AA51 -> 2000 | AV20: ='monthly model engine'!AA52 -> 2000 | AW20: ='monthly model engine'!AA53 -> 2000 | AX20: ='monthly model engine'!AA54 -> 2000 | AY20: ='monthly model engine'!AA55 -> 2000 | AZ20: ='monthly model engine'!AA56 -> 2000 | BA20: ='monthly model engine'!AA57 -> 2000 | BB20: ='monthly model engine'!AA58 -> 2000 | BC20: ='monthly model engine'!AA59 -> 2000 | BD20: ='monthly model engine'!AA60 -> 2000 | BE20: ='monthly model engine'!AA61 -> 2000 | BF20: ='monthly model engine'!AA62 -> 2000 | BG20: ='monthly model engine'!AA63 -> 2000 | BH20: ='monthly model engine'!AA64 -> 2000 | BI20: ='monthly model engine'!AA65 -> 2000 | BJ20: ='monthly model engine'!AA66 -> 2000 | BK20: ='monthly model engine'!AA67 -> 2000
B21: Business rates | D21: ='monthly model engine'!AB8 -> 125 | E21: ='monthly model engine'!AB9 -> 125 | F21: ='monthly model engine'!AB10 -> 125 | G21: ='monthly model engine'!AB11 -> 125 | H21: ='monthly model engine'!AB12 -> 125 | I21: ='monthly model engine'!AB13 -> 125 | J21: ='monthly model engine'!AB14 -> 125 | K21: ='monthly model engine'!AB15 -> 125 | L21: ='monthly model engine'!AB16 -> 125 | M21: ='monthly model engine'!AB17 -> 125 | N21: ='monthly model engine'!AB18 -> 125 | O21: ='monthly model engine'!AB19 -> 125 | P21: ='monthly model engine'!AB20 -> 125 | Q21: ='monthly model engine'!AB21 -> 125 | R21: ='monthly model engine'!AB22 -> 125 | S21: ='monthly model engine'!AB23 -> 125 | T21: ='monthly model engine'!AB24 -> 125 | U21: ='monthly model engine'!AB25 -> 125 | V21: ='monthly model engine'!AB26 -> 125 | W21: ='monthly model engine'!AB27 -> 125 | X21: ='monthly model engine'!AB28 -> 125 | Y21: ='monthly model engine'!AB29 -> 125 | Z21: ='monthly model engine'!AB30 -> 125 | AA21: ='monthly model engine'!AB31 -> 125 | AB21: ='monthly model engine'!AB32 -> 125 | AC21: ='monthly model engine'!AB33 -> 125 | AD21: ='monthly model engine'!AB34 -> 125 | AE21: ='monthly model engine'!AB35 -> 125 | AF21: ='monthly model engine'!AB36 -> 125 | AG21: ='monthly model engine'!AB37 -> 125 | AH21: ='monthly model engine'!AB38 -> 125 | AI21: ='monthly model engine'!AB39 -> 125 | AJ21: ='monthly model engine'!AB40 -> 125 | AK21: ='monthly model engine'!AB41 -> 125 | AL21: ='monthly model engine'!AB42 -> 125 | AM21: ='monthly model engine'!AB43 -> 125 | AN21: ='monthly model engine'!AB44 -> 125 | AO21: ='monthly model engine'!AB45 -> 125 | AP21: ='monthly model engine'!AB46 -> 125 | AQ21: ='monthly model engine'!AB47 -> 125 | AR21: ='monthly model engine'!AB48 -> 125 | AS21: ='monthly model engine'!AB49 -> 125 | AT21: ='monthly model engine'!AB50 -> 125 | AU21: ='monthly model engine'!AB51 -> 125 | AV21: ='monthly model engine'!AB52 -> 125 | AW21: ='monthly model engine'!AB53 -> 125 | AX21: ='monthly model engine'!AB54 -> 125 | AY21: ='monthly model engine'!AB55 -> 125 | AZ21: ='monthly model engine'!AB56 -> 125 | BA21: ='monthly model engine'!AB57 -> 125 | BB21: ='monthly model engine'!AB58 -> 125 | BC21: ='monthly model engine'!AB59 -> 125 | BD21: ='monthly model engine'!AB60 -> 125 | BE21: ='monthly model engine'!AB61 -> 125 | BF21: ='monthly model engine'!AB62 -> 125 | BG21: ='monthly model engine'!AB63 -> 125 | BH21: ='monthly model engine'!AB64 -> 125 | BI21: ='monthly model engine'!AB65 -> 125 | BJ21: ='monthly model engine'!AB66 -> 125 | BK21: ='monthly model engine'!AB67 -> 125
B22: Insurance | D22: ='monthly model engine'!AC8 -> 150 | E22: ='monthly model engine'!AC9 -> 150 | F22: ='monthly model engine'!AC10 -> 150 | G22: ='monthly model engine'!AC11 -> 150 | H22: ='monthly model engine'!AC12 -> 150 | I22: ='monthly model engine'!AC13 -> 150 | J22: ='monthly model engine'!AC14 -> 150 | K22: ='monthly model engine'!AC15 -> 150 | L22: ='monthly model engine'!AC16 -> 150 | M22: ='monthly model engine'!AC17 -> 150 | N22: ='monthly model engine'!AC18 -> 150 | O22: ='monthly model engine'!AC19 -> 150 | P22: ='monthly model engine'!AC20 -> 150 | Q22: ='monthly model engine'!AC21 -> 150 | R22: ='monthly model engine'!AC22 -> 150 | S22: ='monthly model engine'!AC23 -> 150 | T22: ='monthly model engine'!AC24 -> 150 | U22: ='monthly model engine'!AC25 -> 150 | V22: ='monthly model engine'!AC26 -> 150 | W22: ='monthly model engine'!AC27 -> 150 | X22: ='monthly model engine'!AC28 -> 150 | Y22: ='monthly model engine'!AC29 -> 150 | Z22: ='monthly model engine'!AC30 -> 150 | AA22: ='monthly model engine'!AC31 -> 150 | AB22: ='monthly model engine'!AC32 -> 150 | AC22: ='monthly model engine'!AC33 -> 150 | AD22: ='monthly model engine'!AC34 -> 150 | AE22: ='monthly model engine'!AC35 -> 150 | AF22: ='monthly model engine'!AC36 -> 150 | AG22: ='monthly model engine'!AC37 -> 150 | AH22: ='monthly model engine'!AC38 -> 150 | AI22: ='monthly model engine'!AC39 -> 150 | AJ22: ='monthly model engine'!AC40 -> 150 | AK22: ='monthly model engine'!AC41 -> 150 | AL22: ='monthly model engine'!AC42 -> 150 | AM22: ='monthly model engine'!AC43 -> 150 | AN22: ='monthly model engine'!AC44 -> 150 | AO22: ='monthly model engine'!AC45 -> 150 | AP22: ='monthly model engine'!AC46 -> 150 | AQ22: ='monthly model engine'!AC47 -> 150 | AR22: ='monthly model engine'!AC48 -> 150 | AS22: ='monthly model engine'!AC49 -> 150 | AT22: ='monthly model engine'!AC50 -> 150 | AU22: ='monthly model engine'!AC51 -> 150 | AV22: ='monthly model engine'!AC52 -> 150 | AW22: ='monthly model engine'!AC53 -> 150 | AX22: ='monthly model engine'!AC54 -> 150 | AY22: ='monthly model engine'!AC55 -> 150 | AZ22: ='monthly model engine'!AC56 -> 150 | BA22: ='monthly model engine'!AC57 -> 150 | BB22: ='monthly model engine'!AC58 -> 150 | BC22: ='monthly model engine'!AC59 -> 150 | BD22: ='monthly model engine'!AC60 -> 150 | BE22: ='monthly model engine'!AC61 -> 150 | BF22: ='monthly model engine'!AC62 -> 150 | BG22: ='monthly model engine'!AC63 -> 150 | BH22: ='monthly model engine'!AC64 -> 150 | BI22: ='monthly model engine'!AC65 -> 150 | BJ22: ='monthly model engine'!AC66 -> 150 | BK22: ='monthly model engine'!AC67 -> 150
B23: Wages (incl. NI/pension) | D23: ='monthly model engine'!AD8 -> 6783.2324 | E23: ='monthly model engine'!AD9 -> 6783.2324 | F23: ='monthly model engine'!AD10 -> 6783.2324 | G23: ='monthly model engine'!AD11 -> 6783.2324 | H23: ='monthly model engine'!AD12 -> 6783.2324 | I23: ='monthly model engine'!AD13 -> 6783.2324 | J23: ='monthly model engine'!AD14 -> 6783.2324 | K23: ='monthly model engine'!AD15 -> 6783.2324 | L23: ='monthly model engine'!AD16 -> 6783.2324 | M23: ='monthly model engine'!AD17 -> 6783.2324 | N23: ='monthly model engine'!AD18 -> 6783.2324 | O23: ='monthly model engine'!AD19 -> 6783.2324 | P23: ='monthly model engine'!AD20 -> 6783.2324 | Q23: ='monthly model engine'!AD21 -> 6783.2324 | R23: ='monthly model engine'!AD22 -> 6783.2324 | S23: ='monthly model engine'!AD23 -> 6783.2324 | T23: ='monthly model engine'!AD24 -> 6783.2324 | U23: ='monthly model engine'!AD25 -> 6783.2324 | V23: ='monthly model engine'!AD26 -> 6783.2324 | W23: ='monthly model engine'!AD27 -> 6783.2324 | X23: ='monthly model engine'!AD28 -> 6783.2324 | Y23: ='monthly model engine'!AD29 -> 6783.2324 | Z23: ='monthly model engine'!AD30 -> 6783.2324 | AA23: ='monthly model engine'!AD31 -> 6783.2324 | AB23: ='monthly model engine'!AD32 -> 6783.2324 | AC23: ='monthly model engine'!AD33 -> 6783.2324 | AD23: ='monthly model engine'!AD34 -> 6783.2324 | AE23: ='monthly model engine'!AD35 -> 6783.2324 | AF23: ='monthly model engine'!AD36 -> 6783.2324 | AG23: ='monthly model engine'!AD37 -> 6783.2324 | AH23: ='monthly model engine'!AD38 -> 6783.2324 | AI23: ='monthly model engine'!AD39 -> 6783.2324 | AJ23: ='monthly model engine'!AD40 -> 6783.2324 | AK23: ='monthly model engine'!AD41 -> 6783.2324 | AL23: ='monthly model engine'!AD42 -> 6783.2324 | AM23: ='monthly model engine'!AD43 -> 6783.2324 | AN23: ='monthly model engine'!AD44 -> 6783.2324 | AO23: ='monthly model engine'!AD45 -> 6783.2324 | AP23: ='monthly model engine'!AD46 -> 6783.2324 | AQ23: ='monthly model engine'!AD47 -> 6783.2324 | AR23: ='monthly model engine'!AD48 -> 6783.2324 | AS23: ='monthly model engine'!AD49 -> 6783.2324 | AT23: ='monthly model engine'!AD50 -> 6783.2324 | AU23: ='monthly model engine'!AD51 -> 6783.2324 | AV23: ='monthly model engine'!AD52 -> 6783.2324 | AW23: ='monthly model engine'!AD53 -> 6783.2324 | AX23: ='monthly model engine'!AD54 -> 6783.2324 | AY23: ='monthly model engine'!AD55 -> 6783.2324 | AZ23: ='monthly model engine'!AD56 -> 6783.2324 | BA23: ='monthly model engine'!AD57 -> 6783.2324 | BB23: ='monthly model engine'!AD58 -> 6783.2324 | BC23: ='monthly model engine'!AD59 -> 6783.2324 | BD23: ='monthly model engine'!AD60 -> 6783.2324 | BE23: ='monthly model engine'!AD61 -> 6783.2324 | BF23: ='monthly model engine'!AD62 -> 6783.2324 | BG23: ='monthly model engine'!AD63 -> 6783.2324 | BH23: ='monthly model engine'!AD64 -> 6783.2324 | BI23: ='monthly model engine'!AD65 -> 6783.2324 | BJ23: ='monthly model engine'!AD66 -> 6783.2324 | BK23: ='monthly model engine'!AD67 -> 6783.2324
B24: Marketing - social ads | D24: ='monthly model engine'!AE8 -> 300 | E24: ='monthly model engine'!AE9 -> 200 | F24: ='monthly model engine'!AE10 -> 150 | G24: ='monthly model engine'!AE11 -> 150 | H24: ='monthly model engine'!AE12 -> 150 | I24: ='monthly model engine'!AE13 -> 250 | J24: ='monthly model engine'!AE14 -> 250 | K24: ='monthly model engine'!AE15 -> 150 | L24: ='monthly model engine'!AE16 -> 200 | M24: ='monthly model engine'!AE17 -> 150 | N24: ='monthly model engine'!AE18 -> 250 | O24: ='monthly model engine'!AE19 -> 300 | P24: ='monthly model engine'!AE20 -> 345 | Q24: ='monthly model engine'!AE21 -> 230 | R24: ='monthly model engine'!AE22 -> 172.5 | S24: ='monthly model engine'!AE23 -> 172.5 | T24: ='monthly model engine'!AE24 -> 172.5 | U24: ='monthly model engine'!AE25 -> 287.5 | V24: ='monthly model engine'!AE26 -> 287.5 | W24: ='monthly model engine'!AE27 -> 172.5 | X24: ='monthly model engine'!AE28 -> 230 | Y24: ='monthly model engine'!AE29 -> 172.5 | Z24: ='monthly model engine'!AE30 -> 287.5 | AA24: ='monthly model engine'!AE31 -> 345 | AB24: ='monthly model engine'!AE32 -> 372.6 | AC24: ='monthly model engine'!AE33 -> 248.4 | AD24: ='monthly model engine'!AE34 -> 186.3 | AE24: ='monthly model engine'!AE35 -> 186.3 | AF24: ='monthly model engine'!AE36 -> 186.3 | AG24: ='monthly model engine'!AE37 -> 310.5 | AH24: ='monthly model engine'!AE38 -> 310.5 | AI24: ='monthly model engine'!AE39 -> 186.3 | AJ24: ='monthly model engine'!AE40 -> 248.4 | AK24: ='monthly model engine'!AE41 -> 186.3 | AL24: ='monthly model engine'!AE42 -> 310.5 | AM24: ='monthly model engine'!AE43 -> 372.6 | AN24: ='monthly model engine'!AE44 -> 394.956 | AO24: ='monthly model engine'!AE45 -> 263.304 | AP24: ='monthly model engine'!AE46 -> 197.478 | AQ24: ='monthly model engine'!AE47 -> 197.478 | AR24: ='monthly model engine'!AE48 -> 197.478 | AS24: ='monthly model engine'!AE49 -> 329.13 | AT24: ='monthly model engine'!AE50 -> 329.13 | AU24: ='monthly model engine'!AE51 -> 197.478 | AV24: ='monthly model engine'!AE52 -> 263.304 | AW24: ='monthly model engine'!AE53 -> 197.478 | AX24: ='monthly model engine'!AE54 -> 329.13 | AY24: ='monthly model engine'!AE55 -> 394.956 | AZ24: ='monthly model engine'!AE56 -> 406.80468 | BA24: ='monthly model engine'!AE57 -> 271.20312 | BB24: ='monthly model engine'!AE58 -> 203.40234 | BC24: ='monthly model engine'!AE59 -> 203.40234 | BD24: ='monthly model engine'!AE60 -> 203.40234 | BE24: ='monthly model engine'!AE61 -> 339.0039 | BF24: ='monthly model engine'!AE62 -> 339.0039 | BG24: ='monthly model engine'!AE63 -> 203.40234 | BH24: ='monthly model engine'!AE64 -> 271.20312 | BI24: ='monthly model engine'!AE65 -> 203.40234 | BJ24: ='monthly model engine'!AE66 -> 339.0039 | BK24: ='monthly model engine'!AE67 -> 406.80468
B25: Marketing - local/community | D25: ='monthly model engine'!AF8 -> 150 | E25: ='monthly model engine'!AF9 -> 150 | F25: ='monthly model engine'!AF10 -> 150 | G25: ='monthly model engine'!AF11 -> 150 | H25: ='monthly model engine'!AF12 -> 200 | I25: ='monthly model engine'!AF13 -> 150 | J25: ='monthly model engine'!AF14 -> 150 | K25: ='monthly model engine'!AF15 -> 150 | L25: ='monthly model engine'!AF16 -> 200 | M25: ='monthly model engine'!AF17 -> 150 | N25: ='monthly model engine'!AF18 -> 200 | O25: ='monthly model engine'!AF19 -> 250 | P25: ='monthly model engine'!AF20 -> 172.5 | Q25: ='monthly model engine'!AF21 -> 172.5 | R25: ='monthly model engine'!AF22 -> 172.5 | S25: ='monthly model engine'!AF23 -> 172.5 | T25: ='monthly model engine'!AF24 -> 230 | U25: ='monthly model engine'!AF25 -> 172.5 | V25: ='monthly model engine'!AF26 -> 172.5 | W25: ='monthly model engine'!AF27 -> 172.5 | X25: ='monthly model engine'!AF28 -> 230 | Y25: ='monthly model engine'!AF29 -> 172.5 | Z25: ='monthly model engine'!AF30 -> 230 | AA25: ='monthly model engine'!AF31 -> 287.5 | AB25: ='monthly model engine'!AF32 -> 186.3 | AC25: ='monthly model engine'!AF33 -> 186.3 | AD25: ='monthly model engine'!AF34 -> 186.3 | AE25: ='monthly model engine'!AF35 -> 186.3 | AF25: ='monthly model engine'!AF36 -> 248.4 | AG25: ='monthly model engine'!AF37 -> 186.3 | AH25: ='monthly model engine'!AF38 -> 186.3 | AI25: ='monthly model engine'!AF39 -> 186.3 | AJ25: ='monthly model engine'!AF40 -> 248.4 | AK25: ='monthly model engine'!AF41 -> 186.3 | AL25: ='monthly model engine'!AF42 -> 248.4 | AM25: ='monthly model engine'!AF43 -> 310.5 | AN25: ='monthly model engine'!AF44 -> 197.478 | AO25: ='monthly model engine'!AF45 -> 197.478 | AP25: ='monthly model engine'!AF46 -> 197.478 | AQ25: ='monthly model engine'!AF47 -> 197.478 | AR25: ='monthly model engine'!AF48 -> 263.304 | AS25: ='monthly model engine'!AF49 -> 197.478 | AT25: ='monthly model engine'!AF50 -> 197.478 | AU25: ='monthly model engine'!AF51 -> 197.478 | AV25: ='monthly model engine'!AF52 -> 263.304 | AW25: ='monthly model engine'!AF53 -> 197.478 | AX25: ='monthly model engine'!AF54 -> 263.304 | AY25: ='monthly model engine'!AF55 -> 329.13 | AZ25: ='monthly model engine'!AF56 -> 203.40234 | BA25: ='monthly model engine'!AF57 -> 203.40234 | BB25: ='monthly model engine'!AF58 -> 203.40234 | BC25: ='monthly model engine'!AF59 -> 203.40234 | BD25: ='monthly model engine'!AF60 -> 271.20312 | BE25: ='monthly model engine'!AF61 -> 203.40234 | BF25: ='monthly model engine'!AF62 -> 203.40234 | BG25: ='monthly model engine'!AF63 -> 203.40234 | BH25: ='monthly model engine'!AF64 -> 271.20312 | BI25: ='monthly model engine'!AF65 -> 203.40234 | BJ25: ='monthly model engine'!AF66 -> 271.20312 | BK25: ='monthly model engine'!AF67 -> 339.0039
B26: Marketing - referral/loyalty | D26: ='monthly model engine'!AG8 -> 50 | E26: ='monthly model engine'!AG9 -> 50 | F26: ='monthly model engine'!AG10 -> 50 | G26: ='monthly model engine'!AG11 -> 75 | H26: ='monthly model engine'!AG12 -> 75 | I26: ='monthly model engine'!AG13 -> 75 | J26: ='monthly model engine'!AG14 -> 75 | K26: ='monthly model engine'!AG15 -> 75 | L26: ='monthly model engine'!AG16 -> 75 | M26: ='monthly model engine'!AG17 -> 50 | N26: ='monthly model engine'!AG18 -> 75 | O26: ='monthly model engine'!AG19 -> 100 | P26: ='monthly model engine'!AG20 -> 57.5 | Q26: ='monthly model engine'!AG21 -> 57.5 | R26: ='monthly model engine'!AG22 -> 57.5 | S26: ='monthly model engine'!AG23 -> 86.25 | T26: ='monthly model engine'!AG24 -> 86.25 | U26: ='monthly model engine'!AG25 -> 86.25 | V26: ='monthly model engine'!AG26 -> 86.25 | W26: ='monthly model engine'!AG27 -> 86.25 | X26: ='monthly model engine'!AG28 -> 86.25 | Y26: ='monthly model engine'!AG29 -> 57.5 | Z26: ='monthly model engine'!AG30 -> 86.25 | AA26: ='monthly model engine'!AG31 -> 115 | AB26: ='monthly model engine'!AG32 -> 62.1 | AC26: ='monthly model engine'!AG33 -> 62.1 | AD26: ='monthly model engine'!AG34 -> 62.1 | AE26: ='monthly model engine'!AG35 -> 93.15 | AF26: ='monthly model engine'!AG36 -> 93.15 | AG26: ='monthly model engine'!AG37 -> 93.15 | AH26: ='monthly model engine'!AG38 -> 93.15 | AI26: ='monthly model engine'!AG39 -> 93.15 | AJ26: ='monthly model engine'!AG40 -> 93.15 | AK26: ='monthly model engine'!AG41 -> 62.1 | AL26: ='monthly model engine'!AG42 -> 93.15 | AM26: ='monthly model engine'!AG43 -> 124.2 | AN26: ='monthly model engine'!AG44 -> 65.826 | AO26: ='monthly model engine'!AG45 -> 65.826 | AP26: ='monthly model engine'!AG46 -> 65.826 | AQ26: ='monthly model engine'!AG47 -> 98.739 | AR26: ='monthly model engine'!AG48 -> 98.739 | AS26: ='monthly model engine'!AG49 -> 98.739 | AT26: ='monthly model engine'!AG50 -> 98.739 | AU26: ='monthly model engine'!AG51 -> 98.739 | AV26: ='monthly model engine'!AG52 -> 98.739 | AW26: ='monthly model engine'!AG53 -> 65.826 | AX26: ='monthly model engine'!AG54 -> 98.739 | AY26: ='monthly model engine'!AG55 -> 131.652 | AZ26: ='monthly model engine'!AG56 -> 67.80078 | BA26: ='monthly model engine'!AG57 -> 67.80078 | BB26: ='monthly model engine'!AG58 -> 67.80078 | BC26: ='monthly model engine'!AG59 -> 101.70117 | BD26: ='monthly model engine'!AG60 -> 101.70117 | BE26: ='monthly model engine'!AG61 -> 101.70117 | BF26: ='monthly model engine'!AG62 -> 101.70117 | BG26: ='monthly model engine'!AG63 -> 101.70117 | BH26: ='monthly model engine'!AG64 -> 101.70117 | BI26: ='monthly model engine'!AG65 -> 67.80078 | BJ26: ='monthly model engine'!AG66 -> 101.70117 | BK26: ='monthly model engine'!AG67 -> 135.60156
B27: Software | D27: ='monthly model engine'!AI8 -> 150 | E27: ='monthly model engine'!AI9 -> 150 | F27: ='monthly model engine'!AI10 -> 150 | G27: ='monthly model engine'!AI11 -> 150 | H27: ='monthly model engine'!AI12 -> 150 | I27: ='monthly model engine'!AI13 -> 150 | J27: ='monthly model engine'!AI14 -> 150 | K27: ='monthly model engine'!AI15 -> 150 | L27: ='monthly model engine'!AI16 -> 150 | M27: ='monthly model engine'!AI17 -> 150 | N27: ='monthly model engine'!AI18 -> 150 | O27: ='monthly model engine'!AI19 -> 150 | P27: ='monthly model engine'!AI20 -> 150 | Q27: ='monthly model engine'!AI21 -> 150 | R27: ='monthly model engine'!AI22 -> 150 | S27: ='monthly model engine'!AI23 -> 150 | T27: ='monthly model engine'!AI24 -> 150 | U27: ='monthly model engine'!AI25 -> 150 | V27: ='monthly model engine'!AI26 -> 150 | W27: ='monthly model engine'!AI27 -> 150 | X27: ='monthly model engine'!AI28 -> 150 | Y27: ='monthly model engine'!AI29 -> 150 | Z27: ='monthly model engine'!AI30 -> 150 | AA27: ='monthly model engine'!AI31 -> 150 | AB27: ='monthly model engine'!AI32 -> 150 | AC27: ='monthly model engine'!AI33 -> 150 | AD27: ='monthly model engine'!AI34 -> 150 | AE27: ='monthly model engine'!AI35 -> 150 | AF27: ='monthly model engine'!AI36 -> 150 | AG27: ='monthly model engine'!AI37 -> 150 | AH27: ='monthly model engine'!AI38 -> 150 | AI27: ='monthly model engine'!AI39 -> 150 | AJ27: ='monthly model engine'!AI40 -> 150 | AK27: ='monthly model engine'!AI41 -> 150 | AL27: ='monthly model engine'!AI42 -> 150 | AM27: ='monthly model engine'!AI43 -> 150 | AN27: ='monthly model engine'!AI44 -> 150 | AO27: ='monthly model engine'!AI45 -> 150 | AP27: ='monthly model engine'!AI46 -> 150 | AQ27: ='monthly model engine'!AI47 -> 150 | AR27: ='monthly model engine'!AI48 -> 150 | AS27: ='monthly model engine'!AI49 -> 150 | AT27: ='monthly model engine'!AI50 -> 150 | AU27: ='monthly model engine'!AI51 -> 150 | AV27: ='monthly model engine'!AI52 -> 150 | AW27: ='monthly model engine'!AI53 -> 150 | AX27: ='monthly model engine'!AI54 -> 150 | AY27: ='monthly model engine'!AI55 -> 150 | AZ27: ='monthly model engine'!AI56 -> 150 | BA27: ='monthly model engine'!AI57 -> 150 | BB27: ='monthly model engine'!AI58 -> 150 | BC27: ='monthly model engine'!AI59 -> 150 | BD27: ='monthly model engine'!AI60 -> 150 | BE27: ='monthly model engine'!AI61 -> 150 | BF27: ='monthly model engine'!AI62 -> 150 | BG27: ='monthly model engine'!AI63 -> 150 | BH27: ='monthly model engine'!AI64 -> 150 | BI27: ='monthly model engine'!AI65 -> 150 | BJ27: ='monthly model engine'!AI66 -> 150 | BK27: ='monthly model engine'!AI67 -> 150
B28: Admin | D28: ='monthly model engine'!AJ8 -> 500 | E28: ='monthly model engine'!AJ9 -> 500 | F28: ='monthly model engine'!AJ10 -> 500 | G28: ='monthly model engine'!AJ11 -> 500 | H28: ='monthly model engine'!AJ12 -> 500 | I28: ='monthly model engine'!AJ13 -> 500 | J28: ='monthly model engine'!AJ14 -> 500 | K28: ='monthly model engine'!AJ15 -> 500 | L28: ='monthly model engine'!AJ16 -> 500 | M28: ='monthly model engine'!AJ17 -> 500 | N28: ='monthly model engine'!AJ18 -> 500 | O28: ='monthly model engine'!AJ19 -> 500 | P28: ='monthly model engine'!AJ20 -> 500 | Q28: ='monthly model engine'!AJ21 -> 500 | R28: ='monthly model engine'!AJ22 -> 500 | S28: ='monthly model engine'!AJ23 -> 500 | T28: ='monthly model engine'!AJ24 -> 500 | U28: ='monthly model engine'!AJ25 -> 500 | V28: ='monthly model engine'!AJ26 -> 500 | W28: ='monthly model engine'!AJ27 -> 500 | X28: ='monthly model engine'!AJ28 -> 500 | Y28: ='monthly model engine'!AJ29 -> 500 | Z28: ='monthly model engine'!AJ30 -> 500 | AA28: ='monthly model engine'!AJ31 -> 500 | AB28: ='monthly model engine'!AJ32 -> 500 | AC28: ='monthly model engine'!AJ33 -> 500 | AD28: ='monthly model engine'!AJ34 -> 500 | AE28: ='monthly model engine'!AJ35 -> 500 | AF28: ='monthly model engine'!AJ36 -> 500 | AG28: ='monthly model engine'!AJ37 -> 500 | AH28: ='monthly model engine'!AJ38 -> 500 | AI28: ='monthly model engine'!AJ39 -> 500 | AJ28: ='monthly model engine'!AJ40 -> 500 | AK28: ='monthly model engine'!AJ41 -> 500 | AL28: ='monthly model engine'!AJ42 -> 500 | AM28: ='monthly model engine'!AJ43 -> 500 | AN28: ='monthly model engine'!AJ44 -> 500 | AO28: ='monthly model engine'!AJ45 -> 500 | AP28: ='monthly model engine'!AJ46 -> 500 | AQ28: ='monthly model engine'!AJ47 -> 500 | AR28: ='monthly model engine'!AJ48 -> 500 | AS28: ='monthly model engine'!AJ49 -> 500 | AT28: ='monthly model engine'!AJ50 -> 500 | AU28: ='monthly model engine'!AJ51 -> 500 | AV28: ='monthly model engine'!AJ52 -> 500 | AW28: ='monthly model engine'!AJ53 -> 500 | AX28: ='monthly model engine'!AJ54 -> 500 | AY28: ='monthly model engine'!AJ55 -> 500 | AZ28: ='monthly model engine'!AJ56 -> 500 | BA28: ='monthly model engine'!AJ57 -> 500 | BB28: ='monthly model engine'!AJ58 -> 500 | BC28: ='monthly model engine'!AJ59 -> 500 | BD28: ='monthly model engine'!AJ60 -> 500 | BE28: ='monthly model engine'!AJ61 -> 500 | BF28: ='monthly model engine'!AJ62 -> 500 | BG28: ='monthly model engine'!AJ63 -> 500 | BH28: ='monthly model engine'!AJ64 -> 500 | BI28: ='monthly model engine'!AJ65 -> 500 | BJ28: ='monthly model engine'!AJ66 -> 500 | BK28: ='monthly model engine'!AJ67 -> 500
B29: TOTAL FIXED OPEX | D29: ='monthly model engine'!AK8 -> 10208.232 | E29: ='monthly model engine'!AK9 -> 10108.232 | F29: ='monthly model engine'!AK10 -> 10058.232 | G29: ='monthly model engine'!AK11 -> 10083.232 | H29: ='monthly model engine'!AK12 -> 10133.232 | I29: ='monthly model engine'!AK13 -> 10183.232 | J29: ='monthly model engine'!AK14 -> 10183.232 | K29: ='monthly model engine'!AK15 -> 10083.232 | L29: ='monthly model engine'!AK16 -> 10183.232 | M29: ='monthly model engine'!AK17 -> 10058.232 | N29: ='monthly model engine'!AK18 -> 10233.232 | O29: ='monthly model engine'!AK19 -> 10358.232 | P29: ='monthly model engine'!AK20 -> 10283.232 | Q29: ='monthly model engine'!AK21 -> 10168.232 | R29: ='monthly model engine'!AK22 -> 10110.732 | S29: ='monthly model engine'!AK23 -> 10139.482 | T29: ='monthly model engine'!AK24 -> 10196.982 | U29: ='monthly model engine'!AK25 -> 10254.482 | V29: ='monthly model engine'!AK26 -> 10254.482 | W29: ='monthly model engine'!AK27 -> 10139.482 | X29: ='monthly model engine'!AK28 -> 10254.482 | Y29: ='monthly model engine'!AK29 -> 10110.732 | Z29: ='monthly model engine'!AK30 -> 10311.982 | AA29: ='monthly model engine'!AK31 -> 10455.732 | AB29: ='monthly model engine'!AK32 -> 10329.232 | AC29: ='monthly model engine'!AK33 -> 10205.032 | AD29: ='monthly model engine'!AK34 -> 10142.932 | AE29: ='monthly model engine'!AK35 -> 10173.982 | AF29: ='monthly model engine'!AK36 -> 10236.082 | AG29: ='monthly model engine'!AK37 -> 10298.182 | AH29: ='monthly model engine'!AK38 -> 10298.182 | AI29: ='monthly model engine'!AK39 -> 10173.982 | AJ29: ='monthly model engine'!AK40 -> 10298.182 | AK29: ='monthly model engine'!AK41 -> 10142.932 | AL29: ='monthly model engine'!AK42 -> 10360.282 | AM29: ='monthly model engine'!AK43 -> 10515.532 | AN29: ='monthly model engine'!AK44 -> 10366.492 | AO29: ='monthly model engine'!AK45 -> 10234.84 | AP29: ='monthly model engine'!AK46 -> 10169.014 | AQ29: ='monthly model engine'!AK47 -> 10201.927 | AR29: ='monthly model engine'!AK48 -> 10267.753 | AS29: ='monthly model engine'!AK49 -> 10333.579 | AT29: ='monthly model engine'!AK50 -> 10333.579 | AU29: ='monthly model engine'!AK51 -> 10201.927 | AV29: ='monthly model engine'!AK52 -> 10333.579 | AW29: ='monthly model engine'!AK53 -> 10169.014 | AX29: ='monthly model engine'!AK54 -> 10399.405 | AY29: ='monthly model engine'!AK55 -> 10563.97 | AZ29: ='monthly model engine'!AK56 -> 10386.24 | BA29: ='monthly model engine'!AK57 -> 10250.639 | BB29: ='monthly model engine'!AK58 -> 10182.838 | BC29: ='monthly model engine'!AK59 -> 10216.738 | BD29: ='monthly model engine'!AK60 -> 10284.539 | BE29: ='monthly model engine'!AK61 -> 10352.34 | BF29: ='monthly model engine'!AK62 -> 10352.34 | BG29: ='monthly model engine'!AK63 -> 10216.738 | BH29: ='monthly model engine'!AK64 -> 10352.34 | BI29: ='monthly model engine'!AK65 -> 10182.838 | BJ29: ='monthly model engine'!AK66 -> 10420.141 | BK29: ='monthly model engine'!AK67 -> 10589.642
A31: VARIABLE OPERATING EXPENSES
B32: Utilities | D32: ='monthly model engine'!AL8 -> 274.13405 | E32: ='monthly model engine'!AL9 -> 314.13189 | F32: ='monthly model engine'!AL10 -> 355.03178 | G32: ='monthly model engine'!AL11 -> 401.76183 | H32: ='monthly model engine'!AL12 -> 448.21763 | I32: ='monthly model engine'!AL13 -> 523.36183 | J32: ='monthly model engine'!AL14 -> 571.14562 | K32: ='monthly model engine'!AL15 -> 549.0248 | L32: ='monthly model engine'!AL16 -> 550.34418 | M32: ='monthly model engine'!AL17 -> 582.76452 | N32: ='monthly model engine'!AL18 -> 609.59563 | O32: ='monthly model engine'!AL19 -> 657.86406 | P32: ='monthly model engine'!AL20 -> 682.48443 | Q32: ='monthly model engine'!AL21 -> 687.35266 | R32: ='monthly model engine'!AL22 -> 682.22548 | S32: ='monthly model engine'!AL23 -> 697.08912 | T32: ='monthly model engine'!AL24 -> 711.95276 | U32: ='monthly model engine'!AL25 -> 765.07678 | V32: ='monthly model engine'!AL26 -> 782.13386 | W32: ='monthly model engine'!AL27 -> 710.9718 | X32: ='monthly model engine'!AL28 -> 682.22548 | Y32: ='monthly model engine'!AL29 -> 697.08912 | Z32: ='monthly model engine'!AL30 -> 711.95276 | AA32: ='monthly model engine'!AL31 -> 756.54367 | AB32: ='monthly model engine'!AL32 -> 737.08319 | AC32: ='monthly model engine'!AL33 -> 742.34087 | AD32: ='monthly model engine'!AL34 -> 736.80352 | AE32: ='monthly model engine'!AL35 -> 752.85625 | AF32: ='monthly model engine'!AL36 -> 768.90898 | AG32: ='monthly model engine'!AL37 -> 826.28292 | AH32: ='monthly model engine'!AL38 -> 844.70457 | AI32: ='monthly model engine'!AL39 -> 767.84954 | AJ32: ='monthly model engine'!AL40 -> 736.80352 | AK32: ='monthly model engine'!AL41 -> 752.85625 | AL32: ='monthly model engine'!AL42 -> 768.90898 | AM32: ='monthly model engine'!AL43 -> 817.06716 | AN32: ='monthly model engine'!AL44 -> 781.30818 | AO32: ='monthly model engine'!AL45 -> 786.88132 | AP32: ='monthly model engine'!AL46 -> 781.01173 | AQ32: ='monthly model engine'!AL47 -> 798.02762 | AR32: ='monthly model engine'!AL48 -> 815.04351 | AS32: ='monthly model engine'!AL49 -> 875.8599 | AT32: ='monthly model engine'!AL50 -> 895.38685 | AU32: ='monthly model engine'!AL51 -> 813.92051 | AV32: ='monthly model engine'!AL52 -> 781.01173 | AW32: ='monthly model engine'!AL53 -> 798.02762 | AX32: ='monthly model engine'!AL54 -> 815.04351 | AY32: ='monthly model engine'!AL55 -> 866.09119 | AZ32: ='monthly model engine'!AL56 -> 804.74742 | BA32: ='monthly model engine'!AL57 -> 810.48776 | BB32: ='monthly model engine'!AL58 -> 804.44208 | BC32: ='monthly model engine'!AL59 -> 821.96845 | BD32: ='monthly model engine'!AL60 -> 839.49482 | BE32: ='monthly model engine'!AL61 -> 902.1357 | BF32: ='monthly model engine'!AL62 -> 922.24845 | BG32: ='monthly model engine'!AL63 -> 838.33813 | BH32: ='monthly model engine'!AL64 -> 804.44208 | BI32: ='monthly model engine'!AL65 -> 821.96845 | BJ32: ='monthly model engine'!AL66 -> 839.49482 | BK32: ='monthly model engine'!AL67 -> 892.07393
B33: Card processing fees | D33: ='monthly model engine'!AM8 -> 159.91153 | E33: ='monthly model engine'!AM9 -> 183.2436 | F33: ='monthly model engine'!AM10 -> 207.10187 | G33: ='monthly model engine'!AM11 -> 234.36107 | H33: ='monthly model engine'!AM12 -> 261.46028 | I33: ='monthly model engine'!AM13 -> 305.2944 | J33: ='monthly model engine'!AM14 -> 333.16828 | K33: ='monthly model engine'!AM15 -> 320.26447 | L33: ='monthly model engine'!AM16 -> 321.03411 | M33: ='monthly model engine'!AM17 -> 339.94597 | N33: ='monthly model engine'!AM18 -> 355.59745 | O33: ='monthly model engine'!AM19 -> 383.75404 | P33: ='monthly model engine'!AM20 -> 398.11592 | Q33: ='monthly model engine'!AM21 -> 400.95572 | R33: ='monthly model engine'!AM22 -> 397.96486 | S33: ='monthly model engine'!AM23 -> 406.63532 | T33: ='monthly model engine'!AM24 -> 415.30577 | U33: ='monthly model engine'!AM25 -> 446.29479 | V33: ='monthly model engine'!AM26 -> 456.24475 | W33: ='monthly model engine'!AM27 -> 414.73355 | X33: ='monthly model engine'!AM28 -> 397.96486 | Y33: ='monthly model engine'!AM29 -> 406.63532 | Z33: ='monthly model engine'!AM30 -> 415.30577 | AA33: ='monthly model engine'!AM31 -> 441.31714 | AB33: ='monthly model engine'!AM32 -> 429.96519 | AC33: ='monthly model engine'!AM33 -> 433.03218 | AD33: ='monthly model engine'!AM34 -> 429.80205 | AE33: ='monthly model engine'!AM35 -> 439.16614 | AF33: ='monthly model engine'!AM36 -> 448.53024 | AG33: ='monthly model engine'!AM37 -> 481.99837 | AH33: ='monthly model engine'!AM38 -> 492.74433 | AI33: ='monthly model engine'!AM39 -> 447.91223 | AJ33: ='monthly model engine'!AM40 -> 429.80205 | AK33: ='monthly model engine'!AM41 -> 439.16614 | AL33: ='monthly model engine'!AM42 -> 448.53024 | AM33: ='monthly model engine'!AM43 -> 476.62251 | AN33: ='monthly model engine'!AM44 -> 455.7631 | AO33: ='monthly model engine'!AM45 -> 459.01411 | AP33: ='monthly model engine'!AM46 -> 455.59018 | AQ33: ='monthly model engine'!AM47 -> 465.51611 | AR33: ='monthly model engine'!AM48 -> 475.44205 | AS33: ='monthly model engine'!AM49 -> 510.91827 | AT33: ='monthly model engine'!AM50 -> 522.30899 | AU33: ='monthly model engine'!AM51 -> 474.78697 | AV33: ='monthly model engine'!AM52 -> 455.59018 | AW33: ='monthly model engine'!AM53 -> 465.51611 | AX33: ='monthly model engine'!AM54 -> 475.44205 | AY33: ='monthly model engine'!AM55 -> 505.21986 | AZ33: ='monthly model engine'!AM56 -> 469.436 | BA33: ='monthly model engine'!AM57 -> 472.78453 | BB33: ='monthly model engine'!AM58 -> 469.25788 | BC33: ='monthly model engine'!AM59 -> 479.4816 | BD33: ='monthly model engine'!AM60 -> 489.70531 | BE33: ='monthly model engine'!AM61 -> 526.24582 | BF33: ='monthly model engine'!AM62 -> 537.97826 | BG33: ='monthly model engine'!AM63 -> 489.03057 | BH33: ='monthly model engine'!AM64 -> 469.25788 | BI33: ='monthly model engine'!AM65 -> 479.4816 | BJ33: ='monthly model engine'!AM66 -> 489.70531 | BK33: ='monthly model engine'!AM67 -> 520.37646
B34: TOTAL VARIABLE OPEX | D34: ='monthly model engine'!AN8 -> 434.04557 | E34: ='monthly model engine'!AN9 -> 497.3755 | F34: ='monthly model engine'!AN10 -> 562.13365 | G34: ='monthly model engine'!AN11 -> 636.1229 | H34: ='monthly model engine'!AN12 -> 709.67791 | I34: ='monthly model engine'!AN13 -> 828.65624 | J34: ='monthly model engine'!AN14 -> 904.31389 | K34: ='monthly model engine'!AN15 -> 869.28927 | L34: ='monthly model engine'!AN16 -> 871.37829 | M34: ='monthly model engine'!AN17 -> 922.71049 | N34: ='monthly model engine'!AN18 -> 965.19308 | O34: ='monthly model engine'!AN19 -> 1041.6181 | P34: ='monthly model engine'!AN20 -> 1080.6003 | Q34: ='monthly model engine'!AN21 -> 1088.3084 | R34: ='monthly model engine'!AN22 -> 1080.1903 | S34: ='monthly model engine'!AN23 -> 1103.7244 | T34: ='monthly model engine'!AN24 -> 1127.2585 | U34: ='monthly model engine'!AN25 -> 1211.3716 | V34: ='monthly model engine'!AN26 -> 1238.3786 | W34: ='monthly model engine'!AN27 -> 1125.7053 | X34: ='monthly model engine'!AN28 -> 1080.1903 | Y34: ='monthly model engine'!AN29 -> 1103.7244 | Z34: ='monthly model engine'!AN30 -> 1127.2585 | AA34: ='monthly model engine'!AN31 -> 1197.8608 | AB34: ='monthly model engine'!AN32 -> 1167.0484 | AC34: ='monthly model engine'!AN33 -> 1175.373 | AD34: ='monthly model engine'!AN34 -> 1166.6056 | AE34: ='monthly model engine'!AN35 -> 1192.0224 | AF34: ='monthly model engine'!AN36 -> 1217.4392 | AG34: ='monthly model engine'!AN37 -> 1308.2813 | AH34: ='monthly model engine'!AN38 -> 1337.4489 | AI34: ='monthly model engine'!AN39 -> 1215.7618 | AJ34: ='monthly model engine'!AN40 -> 1166.6056 | AK34: ='monthly model engine'!AN41 -> 1192.0224 | AL34: ='monthly model engine'!AN42 -> 1217.4392 | AM34: ='monthly model engine'!AN43 -> 1293.6897 | AN34: ='monthly model engine'!AN44 -> 1237.0713 | AO34: ='monthly model engine'!AN45 -> 1245.8954 | AP34: ='monthly model engine'!AN46 -> 1236.6019 | AQ34: ='monthly model engine'!AN47 -> 1263.5437 | AR34: ='monthly model engine'!AN48 -> 1290.4856 | AS34: ='monthly model engine'!AN49 -> 1386.7782 | AT34: ='monthly model engine'!AN50 -> 1417.6958 | AU34: ='monthly model engine'!AN51 -> 1288.7075 | AV34: ='monthly model engine'!AN52 -> 1236.6019 | AW34: ='monthly model engine'!AN53 -> 1263.5437 | AX34: ='monthly model engine'!AN54 -> 1290.4856 | AY34: ='monthly model engine'!AN55 -> 1371.3111 | AZ34: ='monthly model engine'!AN56 -> 1274.1834 | BA34: ='monthly model engine'!AN57 -> 1283.2723 | BB34: ='monthly model engine'!AN58 -> 1273.7 | BC34: ='monthly model engine'!AN59 -> 1301.45 | BD34: ='monthly model engine'!AN60 -> 1329.2001 | BE34: ='monthly model engine'!AN61 -> 1428.3815 | BF34: ='monthly model engine'!AN62 -> 1460.2267 | BG34: ='monthly model engine'!AN63 -> 1327.3687 | BH34: ='monthly model engine'!AN64 -> 1273.7 | BI34: ='monthly model engine'!AN65 -> 1301.45 | BJ34: ='monthly model engine'!AN66 -> 1329.2001 | BK34: ='monthly model engine'!AN67 -> 1412.4504
B36: TOTAL OPERATING EXPENSES | D36: ='monthly model engine'!AO8 -> 10642.278 | E36: ='monthly model engine'!AO9 -> 10605.608 | F36: ='monthly model engine'!AO10 -> 10620.366 | G36: ='monthly model engine'!AO11 -> 10719.355 | H36: ='monthly model engine'!AO12 -> 10842.91 | I36: ='monthly model engine'!AO13 -> 11011.889 | J36: ='monthly model engine'!AO14 -> 11087.546 | K36: ='monthly model engine'!AO15 -> 10952.522 | L36: ='monthly model engine'!AO16 -> 11054.611 | M36: ='monthly model engine'!AO17 -> 10980.943 | N36: ='monthly model engine'!AO18 -> 11198.425 | O36: ='monthly model engine'!AO19 -> 11399.85 | P36: ='monthly model engine'!AO20 -> 11363.833 | Q36: ='monthly model engine'!AO21 -> 11256.541 | R36: ='monthly model engine'!AO22 -> 11190.923 | S36: ='monthly model engine'!AO23 -> 11243.207 | T36: ='monthly model engine'!AO24 -> 11324.241 | U36: ='monthly model engine'!AO25 -> 11465.854 | V36: ='monthly model engine'!AO26 -> 11492.861 | W36: ='monthly model engine'!AO27 -> 11265.188 | X36: ='monthly model engine'!AO28 -> 11334.673 | Y36: ='monthly model engine'!AO29 -> 11214.457 | Z36: ='monthly model engine'!AO30 -> 11439.241 | AA36: ='monthly model engine'!AO31 -> 11653.593 | AB36: ='monthly model engine'!AO32 -> 11496.281 | AC36: ='monthly model engine'!AO33 -> 11380.405 | AD36: ='monthly model engine'!AO34 -> 11309.538 | AE36: ='monthly model engine'!AO35 -> 11366.005 | AF36: ='monthly model engine'!AO36 -> 11453.522 | AG36: ='monthly model engine'!AO37 -> 11606.464 | AH36: ='monthly model engine'!AO38 -> 11635.631 | AI36: ='monthly model engine'!AO39 -> 11389.744 | AJ36: ='monthly model engine'!AO40 -> 11464.788 | AK36: ='monthly model engine'!AO41 -> 11334.955 | AL36: ='monthly model engine'!AO42 -> 11577.722 | AM36: ='monthly model engine'!AO43 -> 11809.222 | AN36: ='monthly model engine'!AO44 -> 11603.564 | AO36: ='monthly model engine'!AO45 -> 11480.736 | AP36: ='monthly model engine'!AO46 -> 11405.616 | AQ36: ='monthly model engine'!AO47 -> 11465.471 | AR36: ='monthly model engine'!AO48 -> 11558.239 | AS36: ='monthly model engine'!AO49 -> 11720.358 | AT36: ='monthly model engine'!AO50 -> 11751.275 | AU36: ='monthly model engine'!AO51 -> 11490.635 | AV36: ='monthly model engine'!AO52 -> 11570.181 | AW36: ='monthly model engine'!AO53 -> 11432.558 | AX36: ='monthly model engine'!AO54 -> 11689.891 | AY36: ='monthly model engine'!AO55 -> 11935.281 | AZ36: ='monthly model engine'!AO56 -> 11660.424 | BA36: ='monthly model engine'!AO57 -> 11533.911 | BB36: ='monthly model engine'!AO58 -> 11456.538 | BC36: ='monthly model engine'!AO59 -> 11518.188 | BD36: ='monthly model engine'!AO60 -> 11613.739 | BE36: ='monthly model engine'!AO61 -> 11780.721 | BF36: ='monthly model engine'!AO62 -> 11812.566 | BG36: ='monthly model engine'!AO63 -> 11544.107 | BH36: ='monthly model engine'!AO64 -> 11626.04 | BI36: ='monthly model engine'!AO65 -> 11484.288 | BJ36: ='monthly model engine'!AO66 -> 11749.341 | BK36: ='monthly model engine'!AO67 -> 12002.093
B38: EBITDA | D38: ='monthly model engine'!AP8 -> -4288.2114 | E38: ='monthly model engine'!AP9 -> -3322.8238 | F38: ='monthly model engine'!AP10 -> -2383.3736 | G38: ='monthly model engine'!AP11 -> -1395.4598 | H38: ='monthly model engine'!AP12 -> -437.16602 | I38: ='monthly model engine'!AP13 -> 1148.6064 | J38: ='monthly model engine'!AP14 -> 2187.0069 | K38: ='monthly model engine'!AP15 -> 1799.1531 | L38: ='monthly model engine'!AP16 -> 1709.7096 | M38: ='monthly model engine'!AP17 -> 2540.2596 | N38: ='monthly model engine'!AP18 -> 2950.3445 | O38: ='monthly model engine'!AP19 -> 3885.0886 | P38: ='monthly model engine'!AP20 -> 4438.9197 | Q38: ='monthly model engine'!AP21 -> 4669.1794 | R38: ='monthly model engine'!AP22 -> 4629.2268 | S38: ='monthly model engine'!AP23 -> 4928.4488 | T38: ='monthly model engine'!AP24 -> 5198.9207 | U38: ='monthly model engine'!AP25 -> 6306.244 | V38: ='monthly model engine'!AP26 -> 6681.9234 | W38: ='monthly model engine'!AP27 -> 5244.4606 | X38: ='monthly model engine'!AP28 -> 4485.4768 | Y38: ='monthly model engine'!AP29 -> 4957.1988 | Z38: ='monthly model engine'!AP30 -> 5083.9207 | AA38: ='monthly model engine'!AP31 -> 5924.0867 | AB38: ='monthly model engine'!AP32 -> 5570.6918 | AC38: ='monthly model engine'!AP33 -> 5819.3723 | AD38: ='monthly model engine'!AP34 -> 5776.2235 | AE38: ='monthly model engine'!AP35 -> 6099.3832 | AF38: ='monthly model engine'!AP36 -> 6391.493 | AG38: ='monthly model engine'!AP37 -> 7587.4021 | AH38: ='monthly model engine'!AP38 -> 7993.1359 | AI38: ='monthly model engine'!AP39 -> 6440.676 | AJ38: ='monthly model engine'!AP40 -> 5620.9735 | AK38: ='monthly model engine'!AP41 -> 6130.4332 | AL38: ='monthly model engine'!AP42 -> 6267.293 | AM38: ='monthly model engine'!AP43 -> 7174.6722 | AN38: ='monthly model engine'!AP44 -> 6487.4273 | AO38: ='monthly model engine'!AP45 -> 6751.0286 | AP38: ='monthly model engine'!AP46 -> 6705.2908 | AQ38: ='monthly model engine'!AP47 -> 7047.8402 | AR38: ='monthly model engine'!AP48 -> 7357.4765 | AS38: ='monthly model engine'!AP49 -> 8625.1402 | AT38: ='monthly model engine'!AP50 -> 9055.218 | AU38: ='monthly model engine'!AP51 -> 7409.6105 | AV38: ='monthly model engine'!AP52 -> 6540.7258 | AW38: ='monthly model engine'!AP53 -> 7080.7532 | AX38: ='monthly model engine'!AP54 -> 7225.8245 | AY38: ='monthly model engine'!AP55 -> 8187.6465 | AZ38: ='monthly model engine'!AP56 -> 6973.2971 | BA38: ='monthly model engine'!AP57 -> 7244.8064 | BB38: ='monthly model engine'!AP58 -> 7197.6965 | BC38: ='monthly model engine'!AP59 -> 7550.5224 | BD38: ='monthly model engine'!AP60 -> 7869.4478 | BE38: ='monthly model engine'!AP61 -> 9175.1414 | BF38: ='monthly model engine'!AP62 -> 9618.1215 | BG38: ='monthly model engine'!AP63 -> 7923.1458 | BH38: ='monthly model engine'!AP64 -> 7028.1946 | BI38: ='monthly model engine'!AP65 -> 7584.4227 | BJ38: ='monthly model engine'!AP66 -> 7733.8462 | BK38: ='monthly model engine'!AP67 -> 8724.5228
A40: BELOW EBITDA
B41: Depreciation | D41: ='monthly model engine'!AQ8 -> 916.66667 | E41: ='monthly model engine'!AQ9 -> 916.66667 | F41: ='monthly model engine'!AQ10 -> 916.66667 | G41: ='monthly model engine'!AQ11 -> 916.66667 | H41: ='monthly model engine'!AQ12 -> 916.66667 | I41: ='monthly model engine'!AQ13 -> 916.66667 | J41: ='monthly model engine'!AQ14 -> 916.66667 | K41: ='monthly model engine'!AQ15 -> 916.66667 | L41: ='monthly model engine'!AQ16 -> 916.66667 | M41: ='monthly model engine'!AQ17 -> 916.66667 | N41: ='monthly model engine'!AQ18 -> 916.66667 | O41: ='monthly model engine'!AQ19 -> 916.66667 | P41: ='monthly model engine'!AQ20 -> 916.66667 | Q41: ='monthly model engine'!AQ21 -> 916.66667 | R41: ='monthly model engine'!AQ22 -> 916.66667 | S41: ='monthly model engine'!AQ23 -> 916.66667 | T41: ='monthly model engine'!AQ24 -> 916.66667 | U41: ='monthly model engine'!AQ25 -> 916.66667 | V41: ='monthly model engine'!AQ26 -> 916.66667 | W41: ='monthly model engine'!AQ27 -> 916.66667 | X41: ='monthly model engine'!AQ28 -> 916.66667 | Y41: ='monthly model engine'!AQ29 -> 916.66667 | Z41: ='monthly model engine'!AQ30 -> 916.66667 | AA41: ='monthly model engine'!AQ31 -> 916.66667 | AB41: ='monthly model engine'!AQ32 -> 916.66667 | AC41: ='monthly model engine'!AQ33 -> 916.66667 | AD41: ='monthly model engine'!AQ34 -> 916.66667 | AE41: ='monthly model engine'!AQ35 -> 916.66667 | AF41: ='monthly model engine'!AQ36 -> 916.66667 | AG41: ='monthly model engine'!AQ37 -> 916.66667 | AH41: ='monthly model engine'!AQ38 -> 916.66667 | AI41: ='monthly model engine'!AQ39 -> 916.66667 | AJ41: ='monthly model engine'!AQ40 -> 916.66667 | AK41: ='monthly model engine'!AQ41 -> 916.66667 | AL41: ='monthly model engine'!AQ42 -> 916.66667 | AM41: ='monthly model engine'!AQ43 -> 916.66667 | AN41: ='monthly model engine'!AQ44 -> 916.66667 | AO41: ='monthly model engine'!AQ45 -> 916.66667 | AP41: ='monthly model engine'!AQ46 -> 916.66667 | AQ41: ='monthly model engine'!AQ47 -> 916.66667 | AR41: ='monthly model engine'!AQ48 -> 916.66667 | AS41: ='monthly model engine'!AQ49 -> 916.66667 | AT41: ='monthly model engine'!AQ50 -> 916.66667 | AU41: ='monthly model engine'!AQ51 -> 916.66667 | AV41: ='monthly model engine'!AQ52 -> 916.66667 | AW41: ='monthly model engine'!AQ53 -> 916.66667 | AX41: ='monthly model engine'!AQ54 -> 916.66667 | AY41: ='monthly model engine'!AQ55 -> 916.66667 | AZ41: ='monthly model engine'!AQ56 -> 916.66667 | BA41: ='monthly model engine'!AQ57 -> 916.66667 | BB41: ='monthly model engine'!AQ58 -> 916.66667 | BC41: ='monthly model engine'!AQ59 -> 916.66667 | BD41: ='monthly model engine'!AQ60 -> 916.66667 | BE41: ='monthly model engine'!AQ61 -> 916.66667 | BF41: ='monthly model engine'!AQ62 -> 916.66667 | BG41: ='monthly model engine'!AQ63 -> 916.66667 | BH41: ='monthly model engine'!AQ64 -> 916.66667 | BI41: ='monthly model engine'!AQ65 -> 916.66667 | BJ41: ='monthly model engine'!AQ66 -> 916.66667 | BK41: ='monthly model engine'!AQ67 -> 916.66667
B42: Loan interest | D42: ='monthly model engine'!AR8 -> -436.56061 | E42: ='monthly model engine'!AR9 -> -430.54133 | F42: ='monthly model engine'!AR10 -> -424.48444 | G42: ='monthly model engine'!AR11 -> -418.38968 | H42: ='monthly model engine'!AR12 -> -412.25684 | I42: ='monthly model engine'!AR13 -> -406.08567 | J42: ='monthly model engine'!AR14 -> -399.87592 | K42: ='monthly model engine'!AR15 -> -393.62737 | L42: ='monthly model engine'!AR16 -> -387.33976 | M42: ='monthly model engine'!AR17 -> -381.01286 | N42: ='monthly model engine'!AR18 -> -374.64641 | O42: ='monthly model engine'!AR19 -> -368.24017 | P42: ='monthly model engine'!AR20 -> -361.79389 | Q42: ='monthly model engine'!AR21 -> -355.30732 | R42: ='monthly model engine'!AR22 -> -348.78021 | S42: ='monthly model engine'!AR23 -> -342.21231 | T42: ='monthly model engine'!AR24 -> -335.60336 | U42: ='monthly model engine'!AR25 -> -328.9531 | V42: ='monthly model engine'!AR26 -> -322.26128 | W42: ='monthly model engine'!AR27 -> -315.52763 | X42: ='monthly model engine'!AR28 -> -308.7519 | Y42: ='monthly model engine'!AR29 -> -301.93382 | Z42: ='monthly model engine'!AR30 -> -295.07313 | AA42: ='monthly model engine'!AR31 -> -288.16956 | AB42: ='monthly model engine'!AR32 -> -281.22284 | AC42: ='monthly model engine'!AR33 -> -274.2327 | AD42: ='monthly model engine'!AR34 -> -267.19888 | AE42: ='monthly model engine'!AR35 -> -260.12109 | AF42: ='monthly model engine'!AR36 -> -252.99907 | AG42: ='monthly model engine'!AR37 -> -245.83254 | AH42: ='monthly model engine'!AR38 -> -238.62121 | AI42: ='monthly model engine'!AR39 -> -231.36481 | AJ42: ='monthly model engine'!AR40 -> -224.06306 | AK42: ='monthly model engine'!AR41 -> -216.71568 | AL42: ='monthly model engine'!AR42 -> -209.32237 | AM42: ='monthly model engine'!AR43 -> -201.88286 | AN42: ='monthly model engine'!AR44 -> -194.39685 | AO42: ='monthly model engine'!AR45 -> -186.86405 | AP42: ='monthly model engine'!AR46 -> -179.28417 | AQ42: ='monthly model engine'!AR47 -> -171.65692 | AR42: ='monthly model engine'!AR48 -> -163.98199 | AS42: ='monthly model engine'!AR49 -> -156.2591 | AT42: ='monthly model engine'!AR50 -> -148.48794 | AU42: ='monthly model engine'!AR51 -> -140.66821 | AV42: ='monthly model engine'!AR52 -> -132.79961 | AW42: ='monthly model engine'!AR53 -> -124.88183 | AX42: ='monthly model engine'!AR54 -> -116.91456 | AY42: ='monthly model engine'!AR55 -> -108.8975 | AZ42: ='monthly model engine'!AR56 -> -100.83033 | BA42: ='monthly model engine'!AR57 -> -92.712741 | BB42: ='monthly model engine'!AR58 -> -84.544416 | BC42: ='monthly model engine'!AR59 -> -76.32504 | BD42: ='monthly model engine'!AR60 -> -68.054293 | BE42: ='monthly model engine'!AR61 -> -59.731853 | BF42: ='monthly model engine'!AR62 -> -51.357398 | BG42: ='monthly model engine'!AR63 -> -42.930603 | BH42: ='monthly model engine'!AR64 -> -34.45114 | BI42: ='monthly model engine'!AR65 -> -25.918681 | BJ42: ='monthly model engine'!AR66 -> -17.332893 | BK42: ='monthly model engine'!AR67 -> -8.693445
B43: Net profit before tax | D43: ='monthly model engine'!AS8 -> -5641.4387 | E43: ='monthly model engine'!AS9 -> -4670.0318 | F43: ='monthly model engine'!AS10 -> -3724.5247 | G43: ='monthly model engine'!AS11 -> -2730.5162 | H43: ='monthly model engine'!AS12 -> -1766.0895 | I43: ='monthly model engine'!AS13 -> -174.14594 | J43: ='monthly model engine'!AS14 -> 870.46427 | K43: ='monthly model engine'!AS15 -> 488.85902 | L43: ='monthly model engine'!AS16 -> 405.70318 | M43: ='monthly model engine'!AS17 -> 1242.5801 | N43: ='monthly model engine'!AS18 -> 1659.0314 | O43: ='monthly model engine'!AS19 -> 2600.1817 | P43: ='monthly model engine'!AS20 -> 3160.4591 | Q43: ='monthly model engine'!AS21 -> 3397.2054 | R43: ='monthly model engine'!AS22 -> 3363.7799 | S43: ='monthly model engine'!AS23 -> 3669.5698 | T43: ='monthly model engine'!AS24 -> 3946.6507 | U43: ='monthly model engine'!AS25 -> 5060.6242 | V43: ='monthly model engine'!AS26 -> 5442.9955 | W43: ='monthly model engine'!AS27 -> 4012.2663 | X43: ='monthly model engine'!AS28 -> 3260.0582 | Y43: ='monthly model engine'!AS29 -> 3738.5983 | Z43: ='monthly model engine'!AS30 -> 3872.1809 | AA43: ='monthly model engine'!AS31 -> 4719.2505 | AB43: ='monthly model engine'!AS32 -> 4372.8023 | AC43: ='monthly model engine'!AS33 -> 4628.4729 | AD43: ='monthly model engine'!AS34 -> 4592.358 | AE43: ='monthly model engine'!AS35 -> 4922.5955 | AF43: ='monthly model engine'!AS36 -> 5221.8272 | AG43: ='monthly model engine'!AS37 -> 6424.9029 | AH43: ='monthly model engine'!AS38 -> 6837.848 | AI43: ='monthly model engine'!AS39 -> 5292.6446 | AJ43: ='monthly model engine'!AS40 -> 4480.2438 | AK43: ='monthly model engine'!AS41 -> 4997.0509 | AL43: ='monthly model engine'!AS42 -> 5141.3039 | AM43: ='monthly model engine'!AS43 -> 6056.1227 | AN43: ='monthly model engine'!AS44 -> 5376.3638 | AO43: ='monthly model engine'!AS45 -> 5647.4979 | AP43: ='monthly model engine'!AS46 -> 5609.34 | AQ43: ='monthly model engine'!AS47 -> 5959.5166 | AR43: ='monthly model engine'!AS48 -> 6276.8278 | AS43: ='monthly model engine'!AS49 -> 7552.2144 | AT43: ='monthly model engine'!AS50 -> 7990.0634 | AU43: ='monthly model engine'!AS51 -> 6352.2757 | AV43: ='monthly model engine'!AS52 -> 5491.2596 | AW43: ='monthly model engine'!AS53 -> 6039.2047 | AX43: ='monthly model engine'!AS54 -> 6192.2433 | AY43: ='monthly model engine'!AS55 -> 7162.0823 | AZ43: ='monthly model engine'!AS56 -> 5955.8001 | BA43: ='monthly model engine'!AS57 -> 6235.427 | BB43: ='monthly model engine'!AS58 -> 6196.4855 | BC43: ='monthly model engine'!AS59 -> 6557.5306 | BD43: ='monthly model engine'!AS60 -> 6884.7268 | BE43: ='monthly model engine'!AS61 -> 8198.7429 | BF43: ='monthly model engine'!AS62 -> 8650.0974 | BG43: ='monthly model engine'!AS63 -> 6963.5486 | BH43: ='monthly model engine'!AS64 -> 6077.0768 | BI43: ='monthly model engine'!AS65 -> 6641.8374 | BJ43: ='monthly model engine'!AS66 -> 6799.8466 | BK43: ='monthly model engine'!AS67 -> 7799.1627
B44: Corporation tax | D44: ='monthly model engine'!AT8 -> 0 | E44: ='monthly model engine'!AT9 -> 0 | F44: ='monthly model engine'!AT10 -> 0 | G44: ='monthly model engine'!AT11 -> 0 | H44: ='monthly model engine'!AT12 -> 0 | I44: ='monthly model engine'!AT13 -> 0 | J44: ='monthly model engine'!AT14 -> -217.61607 | K44: ='monthly model engine'!AT15 -> -122.21475 | L44: ='monthly model engine'!AT16 -> -101.42579 | M44: ='monthly model engine'!AT17 -> -310.64503 | N44: ='monthly model engine'!AT18 -> -414.75786 | O44: ='monthly model engine'!AT19 -> -650.04543 | P44: ='monthly model engine'!AT20 -> -790.11478 | Q44: ='monthly model engine'!AT21 -> -849.30134 | R44: ='monthly model engine'!AT22 -> -840.94497 | S44: ='monthly model engine'!AT23 -> -917.39244 | T44: ='monthly model engine'!AT24 -> -986.66268 | U44: ='monthly model engine'!AT25 -> -1265.1561 | V44: ='monthly model engine'!AT26 -> -1360.7489 | W44: ='monthly model engine'!AT27 -> -1003.0666 | X44: ='monthly model engine'!AT28 -> -815.01455 | Y44: ='monthly model engine'!AT29 -> -934.64957 | Z44: ='monthly model engine'!AT30 -> -968.04523 | AA44: ='monthly model engine'!AT31 -> -1179.8126 | AB44: ='monthly model engine'!AT32 -> -1093.2006 | AC44: ='monthly model engine'!AT33 -> -1157.1182 | AD44: ='monthly model engine'!AT34 -> -1148.0895 | AE44: ='monthly model engine'!AT35 -> -1230.6489 | AF44: ='monthly model engine'!AT36 -> -1305.4568 | AG44: ='monthly model engine'!AT37 -> -1606.2257 | AH44: ='monthly model engine'!AT38 -> -1709.462 | AI44: ='monthly model engine'!AT39 -> -1323.1611 | AJ44: ='monthly model engine'!AT40 -> -1120.0609 | AK44: ='monthly model engine'!AT41 -> -1249.2627 | AL44: ='monthly model engine'!AT42 -> -1285.326 | AM44: ='monthly model engine'!AT43 -> -1514.0307 | AN44: ='monthly model engine'!AT44 -> -1344.0909 | AO44: ='monthly model engine'!AT45 -> -1411.8745 | AP44: ='monthly model engine'!AT46 -> -1402.335 | AQ44: ='monthly model engine'!AT47 -> -1489.8791 | AR44: ='monthly model engine'!AT48 -> -1569.207 | AS44: ='monthly model engine'!AT49 -> -1888.0536 | AT44: ='monthly model engine'!AT50 -> -1997.5158 | AU44: ='monthly model engine'!AT51 -> -1588.0689 | AV44: ='monthly model engine'!AT52 -> -1372.8149 | AW44: ='monthly model engine'!AT53 -> -1509.8012 | AX44: ='monthly model engine'!AT54 -> -1548.0608 | AY44: ='monthly model engine'!AT55 -> -1790.5206 | AZ44: ='monthly model engine'!AT56 -> -1488.95 | BA44: ='monthly model engine'!AT57 -> -1558.8567 | BB44: ='monthly model engine'!AT58 -> -1549.1214 | BC44: ='monthly model engine'!AT59 -> -1639.3827 | BD44: ='monthly model engine'!AT60 -> -1721.1817 | BE44: ='monthly model engine'!AT61 -> -2049.6857 | BF44: ='monthly model engine'!AT62 -> -2162.5244 | BG44: ='monthly model engine'!AT63 -> -1740.8871 | BH44: ='monthly model engine'!AT64 -> -1519.2692 | BI44: ='monthly model engine'!AT65 -> -1660.4593 | BJ44: ='monthly model engine'!AT66 -> -1699.9617 | BK44: ='monthly model engine'!AT67 -> -1949.7907
B45: NET PROFIT AFTER TAX | D45: ='monthly model engine'!AU8 -> -5641.4387 | E45: ='monthly model engine'!AU9 -> -4670.0318 | F45: ='monthly model engine'!AU10 -> -3724.5247 | G45: ='monthly model engine'!AU11 -> -2730.5162 | H45: ='monthly model engine'!AU12 -> -1766.0895 | I45: ='monthly model engine'!AU13 -> -174.14594 | J45: ='monthly model engine'!AU14 -> 652.8482 | K45: ='monthly model engine'!AU15 -> 366.64426 | L45: ='monthly model engine'!AU16 -> 304.27738 | M45: ='monthly model engine'!AU17 -> 931.93509 | N45: ='monthly model engine'!AU18 -> 1244.2736 | O45: ='monthly model engine'!AU19 -> 1950.1363 | P45: ='monthly model engine'!AU20 -> 2370.3443 | Q45: ='monthly model engine'!AU21 -> 2547.904 | R45: ='monthly model engine'!AU22 -> 2522.8349 | S45: ='monthly model engine'!AU23 -> 2752.1773 | T45: ='monthly model engine'!AU24 -> 2959.988 | U45: ='monthly model engine'!AU25 -> 3795.4682 | V45: ='monthly model engine'!AU26 -> 4082.2466 | W45: ='monthly model engine'!AU27 -> 3009.1997 | X45: ='monthly model engine'!AU28 -> 2445.0436 | Y45: ='monthly model engine'!AU29 -> 2803.9487 | Z45: ='monthly model engine'!AU30 -> 2904.1357 | AA45: ='monthly model engine'!AU31 -> 3539.4378 | AB45: ='monthly model engine'!AU32 -> 3279.6017 | AC45: ='monthly model engine'!AU33 -> 3471.3547 | AD45: ='monthly model engine'!AU34 -> 3444.2685 | AE45: ='monthly model engine'!AU35 -> 3691.9466 | AF45: ='monthly model engine'!AU36 -> 3916.3704 | AG45: ='monthly model engine'!AU37 -> 4818.6772 | AH45: ='monthly model engine'!AU38 -> 5128.386 | AI45: ='monthly model engine'!AU39 -> 3969.4834 | AJ45: ='monthly model engine'!AU40 -> 3360.1828 | AK45: ='monthly model engine'!AU41 -> 3747.7882 | AL45: ='monthly model engine'!AU42 -> 3855.978 | AM45: ='monthly model engine'!AU43 -> 4542.092 | AN45: ='monthly model engine'!AU44 -> 4032.2728 | AO45: ='monthly model engine'!AU45 -> 4235.6234 | AP45: ='monthly model engine'!AU46 -> 4207.005 | AQ45: ='monthly model engine'!AU47 -> 4469.6374 | AR45: ='monthly model engine'!AU48 -> 4707.6209 | AS45: ='monthly model engine'!AU49 -> 5664.1608 | AT45: ='monthly model engine'!AU50 -> 5992.5475 | AU45: ='monthly model engine'!AU51 -> 4764.2067 | AV45: ='monthly model engine'!AU52 -> 4118.4447 | AW45: ='monthly model engine'!AU53 -> 4529.4035 | AX45: ='monthly model engine'!AU54 -> 4644.1825 | AY45: ='monthly model engine'!AU55 -> 5371.5617 | AZ45: ='monthly model engine'!AU56 -> 4466.85 | BA45: ='monthly model engine'!AU57 -> 4676.5702 | BB45: ='monthly model engine'!AU58 -> 4647.3641 | BC45: ='monthly model engine'!AU59 -> 4918.148 | BD45: ='monthly model engine'!AU60 -> 5163.5451 | BE45: ='monthly model engine'!AU61 -> 6149.0571 | BF45: ='monthly model engine'!AU62 -> 6487.5731 | BG45: ='monthly model engine'!AU63 -> 5222.6614 | BH45: ='monthly model engine'!AU64 -> 4557.8076 | BI45: ='monthly model engine'!AU65 -> 4981.378 | BJ45: ='monthly model engine'!AU66 -> 5099.885 | BK45: ='monthly model engine'!AU67 -> 5849.3721
A47: MARGINS
B48: Gross margin % | D48: ='monthly model engine'!AZ8 -> 0.69536053 | E48: ='monthly model engine'!AZ9 -> 0.69551525 | F48: ='monthly model engine'!AZ10 -> 0.69602156 | G48: ='monthly model engine'!AZ11 -> 0.69622557 | H48: ='monthly model engine'!AZ12 -> 0.6964749 | I48: ='monthly model engine'!AZ13 -> 0.69706048 | J48: ='monthly model engine'!AZ14 -> 0.6972593 | K48: ='monthly model engine'!AZ15 -> 0.69678135 | L48: ='monthly model engine'!AZ16 -> 0.69580023 | M48: ='monthly model engine'!AZ17 -> 0.69605486 | N48: ='monthly model engine'!AZ18 -> 0.69630273 | O48: ='monthly model engine'!AZ19 -> 0.69702572 | P48: ='monthly model engine'!AZ20 -> 0.69464232 | Q48: ='monthly model engine'!AZ21 -> 0.69508948 | R48: ='monthly model engine'!AZ22 -> 0.695671 | S48: ='monthly model engine'!AZ23 -> 0.69596506 | T48: ='monthly model engine'!AZ24 -> 0.69624683 | U48: ='monthly model engine'!AZ25 -> 0.69687507 | V48: ='monthly model engine'!AZ26 -> 0.69712303 | W48: ='monthly model engine'!AZ27 -> 0.69663727 | X48: ='monthly model engine'!AZ28 -> 0.695671 | Y48: ='monthly model engine'!AZ29 -> 0.69596506 | Z48: ='monthly model engine'!AZ30 -> 0.69624683 | AA48: ='monthly model engine'!AZ31 -> 0.69702572 | AB48: ='monthly model engine'!AZ32 -> 0.69464232 | AC48: ='monthly model engine'!AZ33 -> 0.69508948 | AD48: ='monthly model engine'!AZ34 -> 0.695671 | AE48: ='monthly model engine'!AZ35 -> 0.69596506 | AF48: ='monthly model engine'!AZ36 -> 0.69624683 | AG48: ='monthly model engine'!AZ37 -> 0.69687507 | AH48: ='monthly model engine'!AZ38 -> 0.69712303 | AI48: ='monthly model engine'!AZ39 -> 0.69663727 | AJ48: ='monthly model engine'!AZ40 -> 0.695671 | AK48: ='monthly model engine'!AZ41 -> 0.69596506 | AL48: ='monthly model engine'!AZ42 -> 0.69624683 | AM48: ='monthly model engine'!AZ43 -> 0.69702572 | AN48: ='monthly model engine'!AZ44 -> 0.69464232 | AO48: ='monthly model engine'!AZ45 -> 0.69508948 | AP48: ='monthly model engine'!AZ46 -> 0.695671 | AQ48: ='monthly model engine'!AZ47 -> 0.69596506 | AR48: ='monthly model engine'!AZ48 -> 0.69624683 | AS48: ='monthly model engine'!AZ49 -> 0.69687507 | AT48: ='monthly model engine'!AZ50 -> 0.69712303 | AU48: ='monthly model engine'!AZ51 -> 0.69663727 | AV48: ='monthly model engine'!AZ52 -> 0.695671 | AW48: ='monthly model engine'!AZ53 -> 0.69596506 | AX48: ='monthly model engine'!AZ54 -> 0.69624683 | AY48: ='monthly model engine'!AZ55 -> 0.69702572 | AZ48: ='monthly model engine'!AZ56 -> 0.69464232 | BA48: ='monthly model engine'!AZ57 -> 0.69508948 | BB48: ='monthly model engine'!AZ58 -> 0.695671 | BC48: ='monthly model engine'!AZ59 -> 0.69596506 | BD48: ='monthly model engine'!AZ60 -> 0.69624683 | BE48: ='monthly model engine'!AZ61 -> 0.69687507 | BF48: ='monthly model engine'!AZ62 -> 0.69712303 | BG48: ='monthly model engine'!AZ63 -> 0.69663727 | BH48: ='monthly model engine'!AZ64 -> 0.695671 | BI48: ='monthly model engine'!AZ65 -> 0.69596506 | BJ48: ='monthly model engine'!AZ66 -> 0.69624683 | BK48: ='monthly model engine'!AZ67 -> 0.69702572
B49: EBITDA margin % | D49: ='monthly model engine'!BA8 -> -0.46928262 | E49: ='monthly model engine'!BA9 -> -0.31733395 | F49: ='monthly model engine'!BA10 -> -0.20139382 | G49: ='monthly model engine'!BA11 -> -0.10420053 | H49: ='monthly model engine'!BA12 -> -0.029260296 | I49: ='monthly model engine'!BA13 -> 0.065840093 | J49: ='monthly model engine'!BA14 -> 0.11487474 | K49: ='monthly model engine'!BA15 -> 0.098309934 | L49: ='monthly model engine'!BA16 -> 0.093198566 | M49: ='monthly model engine'!BA17 -> 0.13076944 | N49: ='monthly model engine'!BA18 -> 0.14519516 | O49: ='monthly model engine'!BA19 -> 0.1771683 | P49: ='monthly model engine'!BA20 -> 0.1951218 | Q49: ='monthly model engine'!BA21 -> 0.20378968 | R49: ='monthly model engine'!BA22 -> 0.20356437 | S49: ='monthly model engine'!BA23 -> 0.21210123 | T49: ='monthly model engine'!BA24 -> 0.21907019 | U49: ='monthly model engine'!BA25 -> 0.24727887 | V49: ='monthly model engine'!BA26 -> 0.2562959 | W49: ='monthly model engine'!BA27 -> 0.22129404 | X49: ='monthly model engine'!BA28 -> 0.19724315 | Y49: ='monthly model engine'!BA29 -> 0.21333852 | Z49: ='monthly model engine'!BA30 -> 0.21422436 | AA49: ='monthly model engine'!BA31 -> 0.23491387 | AB49: ='monthly model engine'!BA32 -> 0.22673256 | AC49: ='monthly model engine'!BA33 -> 0.23517655 | AD49: ='monthly model engine'!BA34 -> 0.23518713 | AE49: ='monthly model engine'!BA35 -> 0.24304972 | AF49: ='monthly model engine'!BA36 -> 0.24937255 | AG49: ='monthly model engine'!BA37 -> 0.27547715 | AH49: ='monthly model engine'!BA38 -> 0.28387922 | AI49: ='monthly model engine'!BA39 -> 0.25163821 | AJ49: ='monthly model engine'!BA40 -> 0.22886591 | AK49: ='monthly model engine'!BA41 -> 0.244287 | AL49: ='monthly model engine'!BA42 -> 0.24452672 | AM49: ='monthly model engine'!BA43 -> 0.2634302 | AN49: ='monthly model engine'!BA44 -> 0.24909866 | AO49: ='monthly model engine'!BA45 -> 0.25738425 | AP49: ='monthly model engine'!BA46 -> 0.25756172 | AQ49: ='monthly model engine'!BA47 -> 0.26494723 | AR49: ='monthly model engine'!BA48 -> 0.2708129 | AS49: ='monthly model engine'!BA49 -> 0.29542876 | AT49: ='monthly model engine'!BA50 -> 0.30339572 | AU49: ='monthly model engine'!BA51 -> 0.27310814 | AV49: ='monthly model engine'!BA52 -> 0.2512405 | AW49: ='monthly model engine'!BA53 -> 0.26618451 | AX49: ='monthly model engine'!BA54 -> 0.26596707 | AY49: ='monthly model engine'!BA55 -> 0.28360685 | AZ49: ='monthly model engine'!BA56 -> 0.25995599 | BA49: ='monthly model engine'!BA57 -> 0.26816468 | BB49: ='monthly model engine'!BA58 -> 0.26842317 | BC49: ='monthly model engine'!BA59 -> 0.27557709 | BD49: ='monthly model engine'!BA60 -> 0.28122083 | BE49: ='monthly model engine'!BA61 -> 0.30511401 | BF49: ='monthly model engine'!BA62 -> 0.31286975 | BG49: ='monthly model engine'!BA63 -> 0.28353044 | BH49: ='monthly model engine'!BA64 -> 0.26210195 | BI49: ='monthly model engine'!BA65 -> 0.27681437 | BJ49: ='monthly model engine'!BA66 -> 0.27637501 | BK49: ='monthly model engine'!BA67 -> 0.29340134
B50: Net margin % | D50: ='monthly model engine'!BB8 -> -0.61737374 | E50: ='monthly model engine'!BB9 -> -0.44599405 | F50: ='monthly model engine'!BB10 -> -0.31472039 | G50: ='monthly model engine'!BB11 -> -0.20389066 | H50: ='monthly model engine'!BB12 -> -0.1182075 | I50: ='monthly model engine'!BB13 -> -0.0099823445 | J50: ='monthly model engine'!BB14 -> 0.034291511 | K50: ='monthly model engine'!BB15 -> 0.020034301 | L50: ='monthly model engine'!BB16 -> 0.016586569 | M50: ='monthly model engine'!BB17 -> 0.047974871 | N50: ='monthly model engine'!BB18 -> 0.061234375 | O50: ='monthly model engine'!BB19 -> 0.088930361 | P50: ='monthly model engine'!BB20 -> 0.10419334 | Q50: ='monthly model engine'!BB21 -> 0.1112051 | R50: ='monthly model engine'!BB22 -> 0.11093846 | S50: ='monthly model engine'!BB23 -> 0.11844299 | T50: ='monthly model engine'!BB24 -> 0.12472687 | U50: ='monthly model engine'!BB25 -> 0.14882695 | V50: ='monthly model engine'!BB26 -> 0.15658112 | W50: ='monthly model engine'!BB27 -> 0.12697549 | X50: ='monthly model engine'!BB28 -> 0.10751769 | Y50: ='monthly model engine'!BB29 -> 0.12067103 | Z50: ='monthly model engine'!BB30 -> 0.12237339 | AA50: ='monthly model engine'!BB31 -> 0.14035295 | AB50: ='monthly model engine'!BB32 -> 0.13348297 | AC50: ='monthly model engine'!BB33 -> 0.14028682 | AD50: ='monthly model engine'!BB34 -> 0.14023827 | AE50: ='monthly model engine'!BB35 -> 0.14711759 | AF50: ='monthly model engine'!BB36 -> 0.15280237 | AG50: ='monthly model engine'!BB37 -> 0.17495256 | AH50: ='monthly model engine'!BB38 -> 0.18213655 | AI50: ='monthly model engine'!BB39 -> 0.15508833 | AJ50: ='monthly model engine'!BB40 -> 0.13681461 | AK50: ='monthly model engine'!BB41 -> 0.14934278 | AL50: ='monthly model engine'!BB42 -> 0.15044608 | AM50: ='monthly model engine'!BB43 -> 0.16677057 | AN50: ='monthly model engine'!BB44 -> 0.15482775 | AO50: ='monthly model engine'!BB45 -> 0.16148395 | AP50: ='monthly model engine'!BB46 -> 0.16159828 | AQ50: ='monthly model engine'!BB47 -> 0.16802567 | AR50: ='monthly model engine'!BB48 -> 0.17327741 | AS50: ='monthly model engine'!BB49 -> 0.19400914 | AT50: ='monthly model engine'!BB50 -> 0.20078073 | AU50: ='monthly model engine'!BB51 -> 0.17560216 | AV50: ='monthly model engine'!BB52 -> 0.15819652 | AW50: ='monthly model engine'!BB53 -> 0.17027243 | AX50: ='monthly model engine'!BB54 -> 0.17094237 | AY50: ='monthly model engine'!BB55 -> 0.18606222 | AZ50: ='monthly model engine'!BB56 -> 0.16651871 | BA50: ='monthly model engine'!BB57 -> 0.17310207 | BB50: ='monthly model engine'!BB58 -> 0.17331381 | BC50: ='monthly model engine'!BB59 -> 0.17950134 | BD50: ='monthly model engine'!BB60 -> 0.1845233 | BE50: ='monthly model engine'!BB61 -> 0.20448333 | BF50: ='monthly model engine'!BB62 -> 0.21103553 | BG50: ='monthly model engine'!BB63 -> 0.18689338 | BH50: ='monthly model engine'!BB64 -> 0.16997399 | BI50: ='monthly model engine'!BB65 -> 0.1818091 | BJ50: ='monthly model engine'!BB66 -> 0.18224835 | BK50: ='monthly model engine'!BB67 -> 0.19671146

Sheet Pivot Table
B1: Scenario: | C1: Base | E1: Afro Brunch and Fitness Studio Co | F1: Last Updated: | G1: =TODAY() -> 46233
A5: Pivot Table — Sum of performance by Year
A7: Row Labels | B7: Sum of TotalRevenue | C7: Sum of GrossProfit | D7: Sum of EBITDA
A8: 1 | B8: 194579.26 | C8: 135509.44 | D8: 4393.1339
A9: 2 | B9: 285569.93 | C9: 198792.62 | D9: 62548.006
A10: 3 | B10: 308415.52 | C10: 214696.03 | D10: 76871.75
A11: 4 | B11: 326920.46 | C11: 227577.79 | D11: 88473.982
A12: 5 | B12: 336728.07 | C12: 234405.12 | D12: 94623.165
A13: Grand Total | B13: 1452213.2 | C13: 1010981 | D13: 326910.04

Sheet monthly model engine
B1: Scenario: | C1: Base | E1: Afro Brunch and Fitness Studio Co | F1: Last Updated: | G1: =TODAY() -> 46233
A5: 5-Year Monthly Model (60 months, seasonality-adjusted)
BD6: FIELD REFERENCE — what each column means and how it's calculated
A7: Period | B7: Year | C7: MonthInYr | D7: MonthLabel | E7: CafeRamp | F7: FitRamp | G7: GrowthFactor | H7: CafeSeason | I7: FitSeason | J7: TradingDays | K7: EffCoversPerDay | L7: AvgSpendAdj | M7: CafeRevenue | N7: FoodCOGS | O7: Members | P7: MembershipRev | Q7: ClassesRun | R7: TotalAttend | S7: MemberCovAttend | T7: DropinAttend | U7: DropinRev | V7: InstructorCost | W7: FitnessRevenue | X7: TotalRevenue | Y7: TotalCOGS | Z7: GrossProfit | AA7: Rent | AB7: Rates | AC7: Insurance | AD7: WagesTotal | AE7: MktSocial | AF7: MktLocal | AG7: MktReferral | AH7: MktTotal | AI7: Software | AJ7: Admin | AK7: TotalFixedOpex | AL7: Utilities | AM7: CardFees | AN7: TotalVarOpex | AO7: TotalOpex | AP7: EBITDA | AQ7: Depreciation | AR7: LoanInterest | AS7: NPBT | AT7: Tax | AU7: NPAT | AV7: LoanPrincipal | AW7: NetCashFlow | AX7: OpeningCash | AY7: ClosingCash | AZ7: GrossMarginPct | BA7: EBITDAMarginPct | BB7: NetMarginPct | BD7: Column | BE7: What it is / how it's calculated
A8: 1 | B8: 1 | C8: 1 | D8: ='Seasonality Data Break down'!$B$7&" Y"&B8 -> January Y1 | E8: =IF(B8=1,INDEX(Workings!$B$27:$B$38,C8),1) -> 0.5 | F8: =IF(B8=1,INDEX(Workings!$C$27:$C$38,C8),1) -> 0.4 | G8: =INDEX(Workings!$C$19:$C$23,B8) -> 1 | H8: =INDEX('Seasonality Data Break down'!$C$7:$C$18,C8) -> 0.85 | I8: =INDEX('Seasonality Data Break down'!$D$7:$D$18,C8) -> 1.3 | J8: =Assumptions!$C$18/12 -> 26.083333 | K8: =Assumptions!$C$19*E8*H8*G8 -> 27.625 | L8: =Assumptions!$C$20+INDEX('Seasonality Data Break down'!$E$7:$E$18,C8) -> 8.5 | M8: =K8*J8*L8 -> 6124.6927 | N8: =M8*Assumptions!$C$21 -> 1837.4078 | O8: =Assumptions!$C$27*F8*I8*G8 -> 28.6 | P8: =O8*Assumptions!$C$28 -> 1287 | Q8: =Assumptions!$C$24*4.333*F8*I8*G8 -> 31.54424 | R8: =Q8*Assumptions!$C$25 -> 315.4424 | S8: =MIN(O8*Assumptions!$C$48,R8) -> 171.6 | T8: =MAX(R8-S8,0) -> 143.8424 | U8: =T8*Assumptions!$C$26 -> 1726.1088 | V8: =Q8*Assumptions!$C$29 -> 946.3272 | W8: =P8+U8 -> 3013.1088 | X8: =M8+W8 -> 9137.8015 | Y8: =N8+V8 -> 2783.735 | Z8: =X8-Y8 -> 6354.0665 | AA8: =Assumptions!$C$10*Assumptions!$C$9/12 -> 2000 | AB8: =Assumptions!$C$12/12 -> 125 | AC8: =Assumptions!$C$14/12 -> 150 | AD8: =(Assumptions!$C$32*4.333*Assumptions!$C$33+Assumptions!$C$34/12)*(1+(Assumptions!$C$35)) -> 6783.2324 | AE8: =INDEX('Seasonality Data Break down'!$F$7:$F$18,C8)*G8 -> 300 | AF8: =INDEX('Seasonality Data Break down'!$G$7:$G$18,C8)*G8 -> 150 | AG8: =INDEX('Seasonality Data Break down'!$H$7:$H$18,C8)*G8 -> 50 | AH8: =AE8+AF8+AG8 -> 500 | AI8: =Assumptions!$C$39 -> 150 | AJ8: =Assumptions!$C$40 -> 500 | AK8: =AA8+AB8+AC8+AD8+AH8+AI8+AJ8 -> 10208.232 | AL8: =X8*Assumptions!$C$13 -> 274.13405 | AM8: =X8*Assumptions!$C$15 -> 159.91153 | AN8: =AL8+AM8 -> 434.04557 | AO8: =AK8+AN8 -> 10642.278 | AP8: =Z8-AO8 -> -4288.2114 | AQ8: ='Startup Costs'!$D$24/(Assumptions!$C$54*12) -> 916.66667 | AR8: =-'Loan schedule'!$D$12 -> -436.56061 | AS8: =AP8-AQ8+AR8 -> -5641.4387 | AT8: =-MAX(AS8,0)*Assumptions!$C$41 -> 0 | AU8: =AS8+AT8 -> -5641.4387 | AV8: =-'Loan schedule'!$E$12 -> -963.08403 | AW8: =AU8+AQ8+AV8 -> -5687.8561 | AX8: =Workings!$B$46 -> 31074.697 | AY8: =AX8+AW8 -> 25386.841 | AZ8: =IFERROR(Z8/X8,0) -> 0.69536053 | BA8: =IFERROR(AP8/X8,0) -> -0.46928262 | BB8: =IFERROR(AU8/X8,0) -> -0.61737374 | BD8: Period / Year / Month-in-Yr | BE8: Which of the 60 months this row is: Period 1-60, Year 1-5, and month-in-year 1-12 (1=Jan).
A9: 2 | B9: 1 | C9: 2 | D9: ='Seasonality Data Break down'!$B$8&" Y"&B9 -> February Y1 | E9: =IF(B9=1,INDEX(Workings!$B$27:$B$38,C9),1) -> 0.55 | F9: =IF(B9=1,INDEX(Workings!$C$27:$C$38,C9),1) -> 0.48 | G9: =INDEX(Workings!$C$19:$C$23,B9) -> 1 | H9: =INDEX('Seasonality Data Break down'!$C$7:$C$18,C9) -> 0.9 | I9: =INDEX('Seasonality Data Break down'!$D$7:$D$18,C9) -> 1.2 | J9: =Assumptions!$C$18/12 -> 26.083333 | K9: =Assumptions!$C$19*E9*H9*G9 -> 32.175 | L9: =Assumptions!$C$20+INDEX('Seasonality Data Break down'!$E$7:$E$18,C9) -> 8.5 | M9: =K9*J9*L9 -> 7133.4656 | N9: =M9*Assumptions!$C$21 -> 2140.0397 | O9: =Assumptions!$C$27*F9*I9*G9 -> 31.68 | P9: =O9*Assumptions!$C$28 -> 1425.6 | Q9: =Assumptions!$C$24*4.333*F9*I9*G9 -> 34.941312 | R9: =Q9*Assumptions!$C$25 -> 349.41312 | S9: =MIN(O9*Assumptions!$C$48,R9) -> 190.08 | T9: =MAX(R9-S9,0) -> 159.33312 | U9: =T9*Assumptions!$C$26 -> 1911.9974 | V9: =Q9*Assumptions!$C$29 -> 1048.2394 | W9: =P9+U9 -> 3337.5974 | X9: =M9+W9 -> 10471.063 | Y9: =N9+V9 -> 3188.279 | Z9: =X9-Y9 -> 7282.784 | AA9: =Assumptions!$C$10*Assumptions!$C$9/12 -> 2000 | AB9: =Assumptions!$C$12/12 -> 125 | AC9: =Assumptions!$C$14/12 -> 150 | AD9: =(Assumptions!$C$32*4.333*Assumptions!$C$33+Assumptions!$C$34/12)*(1+(Assumptions!$C$35)) -> 6783.2324 | AE9: =INDEX('Seasonality Data Break down'!$F$7:$F$18,C9)*G9 -> 200 | AF9: =INDEX('Seasonality Data Break down'!$G$7:$G$18,C9)*G9 -> 150 | AG9: =INDEX('Seasonality Data Break down'!$H$7:$H$18,C9)*G9 -> 50 | AH9: =AE9+AF9+AG9 -> 400 | AI9: =Assumptions!$C$39 -> 150 | AJ9: =Assumptions!$C$40 -> 500 | AK9: =AA9+AB9+AC9+AD9+AH9+AI9+AJ9 -> 10108.232 | AL9: =X9*Assumptions!$C$13 -> 314.13189 | AM9: =X9*Assumptions!$C$15 -> 183.2436 | AN9: =AL9+AM9 -> 497.3755 | AO9: =AK9+AN9 -> 10605.608 | AP9: =Z9-AO9 -> -3322.8238 | AQ9: ='Startup Costs'!$D$24/(Assumptions!$C$54*12) -> 916.66667 | AR9: =-'Loan schedule'!$D$13 -> -430.54133 | AS9: =AP9-AQ9+AR9 -> -4670.0318 | AT9: =-MAX(AS9,0)*Assumptions!$C$41 -> 0 | AU9: =AS9+AT9 -> -4670.0318 | AV9: =-'Loan schedule'!$E$13 -> -969.10331 | AW9: =AU9+AQ9+AV9 -> -4722.4685 | AX9: =AY8 -> 25386.841 | AY9: =AX9+AW9 -> 20664.373 | AZ9: =IFERROR(Z9/X9,0) -> 0.69551525 | BA9: =IFERROR(AP9/X9,0) -> -0.31733395 | BB9: =IFERROR(AU9/X9,0) -> -0.44599405 | BD9: Cafe Ramp / Fit Ramp | BE9: How close to full capacity the business is, Year 1 only (50%->100% for cafe, 40%->100% for fitness). Locked at 100% from Year 2 on.
A10: 3 | B10: 1 | C10: 3 | D10: ='Seasonality Data Break down'!$B$9&" Y"&B10 -> March Y1 | E10: =IF(B10=1,INDEX(Workings!$B$27:$B$38,C10),1) -> 0.62 | F10: =IF(B10=1,INDEX(Workings!$C$27:$C$38,C10),1) -> 0.55 | G10: =INDEX(Workings!$C$19:$C$23,B10) -> 1 | H10: =INDEX('Seasonality Data Break down'!$C$7:$C$18,C10) -> 0.95 | I10: =INDEX('Seasonality Data Break down'!$D$7:$D$18,C10) -> 1.05 | J10: =Assumptions!$C$18/12 -> 26.083333 | K10: =Assumptions!$C$19*E10*H10*G10 -> 38.285 | L10: =Assumptions!$C$20+INDEX('Seasonality Data Break down'!$E$7:$E$18,C10) -> 8.5 | M10: =K10*J10*L10 -> 8488.1035 | N10: =M10*Assumptions!$C$21 -> 2546.4311 | O10: =Assumptions!$C$27*F10*I10*G10 -> 31.7625 | P10: =O10*Assumptions!$C$28 -> 1429.3125 | Q10: =Assumptions!$C$24*4.333*F10*I10*G10 -> 35.032305 | R10: =Q10*Assumptions!$C$25 -> 350.32305 | S10: =MIN(O10*Assumptions!$C$48,R10) -> 190.575 | T10: =MAX(R10-S10,0) -> 159.74805 | U10: =T10*Assumptions!$C$26 -> 1916.9766 | V10: =Q10*Assumptions!$C$29 -> 1050.9692 | W10: =P10+U10 -> 3346.2891 | X10: =M10+W10 -> 11834.393 | Y10: =N10+V10 -> 3597.4002 | Z10: =X10-Y10 -> 8236.9924 | AA10: =Assumptions!$C$10*Assumptions!$C$9/12 -> 2000 | AB10: =Assumptions!$C$12/12 -> 125 | AC10: =Assumptions!$C$14/12 -> 150 | AD10: =(Assumptions!$C$32*4.333*Assumptions!$C$33+Assumptions!$C$34/12)*(1+(Assumptions!$C$35)) -> 6783.2324 | AE10: =INDEX('Seasonality Data Break down'!$F$7:$F$18,C10)*G10 -> 150 | AF10: =INDEX('Seasonality Data Break down'!$G$7:$G$18,C10)*G10 -> 150 | AG10: =INDEX('Seasonality Data Break down'!$H$7:$H$18,C10)*G10 -> 50 | AH10: =AE10+AF10+AG10 -> 350 | AI10: =Assumptions!$C$39 -> 150 | AJ10: =Assumptions!$C$40 -> 500 | AK10: =AA10+AB10+AC10+AD10+AH10+AI10+AJ10 -> 10058.232 | AL10: =X10*Assumptions!$C$13 -> 355.03178 | AM10: =X10*Assumptions!$C$15 -> 207.10187 | AN10: =AL10+AM10 -> 562.13365 | AO10: =AK10+AN10 -> 10620.366 | AP10: =Z10-AO10 -> -2383.3736 | AQ10: ='Startup Costs'!$D$24/(Assumptions!$C$54*12) -> 916.66667 | AR10: =-'Loan schedule'!$D$14 -> -424.48444 | AS10: =AP10-AQ10+AR10 -> -3724.5247 | AT10: =-MAX(AS10,0)*Assumptions!$C$41 -> 0 | AU10: =AS10+AT10 -> -3724.5247 | AV10: =-'Loan schedule'!$E$14 -> -975.1602 | AW10: =AU10+AQ10+AV10 -> -3783.0182 | AX10: =AY9 -> 20664.373 | AY10: =AX10+AW10 -> 16881.354 | AZ10: =IFERROR(Z10/X10,0) -> 0.69602156 | BA10: =IFERROR(AP10/X10,0) -> -0.20139382 | BB10: =IFERROR(AU10/X10,0) -> -0.31472039 | BD10: Cafe Season / Fit Season | BE10: This month's seasonality multiplier vs an average month (e.g. July cafe = 1.15, i.e. +15%). From the Seasonality & Marketing tab.
A11: 4 | B11: 1 | C11: 4 | D11: ='Seasonality Data Break down'!$B$10&" Y"&B11 -> April Y1 | E11: =IF(B11=1,INDEX(Workings!$B$27:$B$38,C11),1) -> 0.68 | F11: =IF(B11=1,INDEX(Workings!$C$27:$C$38,C11),1) -> 0.62 | G11: =INDEX(Workings!$C$19:$C$23,B11) -> 1 | H11: =INDEX('Seasonality Data Break down'!$C$7:$C$18,C11) -> 1 | I11: =INDEX('Seasonality Data Break down'!$D$7:$D$18,C11) -> 1 | J11: =Assumptions!$C$18/12 -> 26.083333 | K11: =Assumptions!$C$19*E11*H11*G11 -> 44.2 | L11: =Assumptions!$C$20+INDEX('Seasonality Data Break down'!$E$7:$E$18,C11) -> 8.5 | M11: =K11*J11*L11 -> 9799.5083 | N11: =M11*Assumptions!$C$21 -> 2939.8525 | O11: =Assumptions!$C$27*F11*I11*G11 -> 34.1 | P11: =O11*Assumptions!$C$28 -> 1534.5 | Q11: =Assumptions!$C$24*4.333*F11*I11*G11 -> 37.61044 | R11: =Q11*Assumptions!$C$25 -> 376.1044 | S11: =MIN(O11*Assumptions!$C$48,R11) -> 204.6 | T11: =MAX(R11-S11,0) -> 171.5044 | U11: =T11*Assumptions!$C$26 -> 2058.0528 | V11: =Q11*Assumptions!$C$29 -> 1128.3132 | W11: =P11+U11 -> 3592.5528 | X11: =M11+W11 -> 13392.061 | Y11: =N11+V11 -> 4068.1657 | Z11: =X11-Y11 -> 9323.8954 | AA11: =Assumptions!$C$10*Assumptions!$C$9/12 -> 2000 | AB11: =Assumptions!$C$12/12 -> 125 | AC11: =Assumptions!$C$14/12 -> 150 | AD11: =(Assumptions!$C$32*4.333*Assumptions!$C$33+Assumptions!$C$34/12)*(1+(Assumptions!$C$35)) -> 6783.2324 | AE11: =INDEX('Seasonality Data Break down'!$F$7:$F$18,C11)*G11 -> 150 | AF11: =INDEX('Seasonality Data Break down'!$G$7:$G$18,C11)*G11 -> 150 | AG11: =INDEX('Seasonality Data Break down'!$H$7:$H$18,C11)*G11 -> 75 | AH11: =AE11+AF11+AG11 -> 375 | AI11: =Assumptions!$C$39 -> 150 | AJ11: =Assumptions!$C$40 -> 500 | AK11: =AA11+AB11+AC11+AD11+AH11+AI11+AJ11 -> 10083.232 | AL11: =X11*Assumptions!$C$13 -> 401.76183 | AM11: =X11*Assumptions!$C$15 -> 234.36107 | AN11: =AL11+AM11 -> 636.1229 | AO11: =AK11+AN11 -> 10719.355 | AP11: =Z11-AO11 -> -1395.4598 | AQ11: ='Startup Costs'!$D$24/(Assumptions!$C$54*12) -> 916.66667 | AR11: =-'Loan schedule'!$D$15 -> -418.38968 | AS11: =AP11-AQ11+AR11 -> -2730.5162 | AT11: =-MAX(AS11,0)*Assumptions!$C$41 -> 0 | AU11: =AS11+AT11 -> -2730.5162 | AV11: =-'Loan schedule'!$E$15 -> -981.25495 | AW11: =AU11+AQ11+AV11 -> -2795.1045 | AX11: =AY10 -> 16881.354 | AY11: =AX11+AW11 -> 14086.25 | AZ11: =IFERROR(Z11/X11,0) -> 0.69622557 | BA11: =IFERROR(AP11/X11,0) -> -0.10420053 | BB11: =IFERROR(AU11/X11,0) -> -0.20389066 | BD11: Growth Factor | BE11: Cumulative year-on-year growth applied from Year 2 onward (compounds each year using the Scenarios-linked growth rates).
A12: 5 | B12: 1 | C12: 5 | D12: ='Seasonality Data Break down'!$B$11&" Y"&B12 -> May Y1 | E12: =IF(B12=1,INDEX(Workings!$B$27:$B$38,C12),1) -> 0.74 | F12: =IF(B12=1,INDEX(Workings!$C$27:$C$38,C12),1) -> 0.68 | G12: =INDEX(Workings!$C$19:$C$23,B12) -> 1 | H12: =INDEX('Seasonality Data Break down'!$C$7:$C$18,C12) -> 1.05 | I12: =INDEX('Seasonality Data Break down'!$D$7:$D$18,C12) -> 0.95 | J12: =Assumptions!$C$18/12 -> 26.083333 | K12: =Assumptions!$C$19*E12*H12*G12 -> 50.505 | L12: =Assumptions!$C$20+INDEX('Seasonality Data Break down'!$E$7:$E$18,C12) -> 8.5 | M12: =K12*J12*L12 -> 11197.379 | N12: =M12*Assumptions!$C$21 -> 3359.2138 | O12: =Assumptions!$C$27*F12*I12*G12 -> 35.53 | P12: =O12*Assumptions!$C$28 -> 1598.85 | Q12: =Assumptions!$C$24*4.333*F12*I12*G12 -> 39.187652 | R12: =Q12*Assumptions!$C$25 -> 391.87652 | S12: =MIN(O12*Assumptions!$C$48,R12) -> 213.18 | T12: =MAX(R12-S12,0) -> 178.69652 | U12: =T12*Assumptions!$C$26 -> 2144.3582 | V12: =Q12*Assumptions!$C$29 -> 1175.6296 | W12: =P12+U12 -> 3743.2082 | X12: =M12+W12 -> 14940.588 | Y12: =N12+V12 -> 4534.8434 | Z12: =X12-Y12 -> 10405.744 | AA12: =Assumptions!$C$10*Assumptions!$C$9/12 -> 2000 | AB12: =Assumptions!$C$12/12 -> 125 | AC12: =Assumptions!$C$14/12 -> 150 | AD12: =(Assumptions!$C$32*4.333*Assumptions!$C$33+Assumptions!$C$34/12)*(1+(Assumptions!$C$35)) -> 6783.2324 | AE12: =INDEX('Seasonality Data Break down'!$F$7:$F$18,C12)*G12 -> 150 | AF12: =INDEX('Seasonality Data Break down'!$G$7:$G$18,C12)*G12 -> 200 | AG12: =INDEX('Seasonality Data Break down'!$H$7:$H$18,C12)*G12 -> 75 | AH12: =AE12+AF12+AG12 -> 425 | AI12: =Assumptions!$C$39 -> 150 | AJ12: =Assumptions!$C$40 -> 500 | AK12: =AA12+AB12+AC12+AD12+AH12+AI12+AJ12 -> 10133.232 | AL12: =X12*Assumptions!$C$13 -> 448.21763 | AM12: =X12*Assumptions!$C$15 -> 261.46028 | AN12: =AL12+AM12 -> 709.67791 | AO12: =AK12+AN12 -> 10842.91 | AP12: =Z12-AO12 -> -437.16602 | AQ12: ='Startup Costs'!$D$24/(Assumptions!$C$54*12) -> 916.66667 | AR12: =-'Loan schedule'!$D$16 -> -412.25684 | AS12: =AP12-AQ12+AR12 -> -1766.0895 | AT12: =-MAX(AS12,0)*Assumptions!$C$41 -> 0 | AU12: =AS12+AT12 -> -1766.0895 | AV12: =-'Loan schedule'!$E$16 -> -987.3878 | AW12: =AU12+AQ12+AV12 -> -1836.8107 | AX12: =AY11 -> 14086.25 | AY12: =AX12+AW12 -> 12249.439 | AZ12: =IFERROR(Z12/X12,0) -> 0.6964749 | BA12: =IFERROR(AP12/X12,0) -> -0.029260296 | BB12: =IFERROR(AU12/X12,0) -> -0.1182075 | BD12: Effective Covers/Day | BE12: Base covers/day (Assumptions) x Cafe Ramp x Cafe Season x Growth Factor.
A13: 6 | B13: 1 | C13: 6 | D13: ='Seasonality Data Break down'!$B$12&" Y"&B13 -> June Y1 | E13: =IF(B13=1,INDEX(Workings!$B$27:$B$38,C13),1) -> 0.8 | F13: =IF(B13=1,INDEX(Workings!$C$27:$C$38,C13),1) -> 0.74 | G13: =INDEX(Workings!$C$19:$C$23,B13) -> 1 | H13: =INDEX('Seasonality Data Break down'!$C$7:$C$18,C13) -> 1.1 | I13: =INDEX('Seasonality Data Break down'!$D$7:$D$18,C13) -> 0.85 | J13: =Assumptions!$C$18/12 -> 26.083333 | K13: =Assumptions!$C$19*E13*H13*G13 -> 57.2 | L13: =Assumptions!$C$20+INDEX('Seasonality Data Break down'!$E$7:$E$18,C13) -> 9.25 | M13: =K13*J13*L13 -> 13800.692 | N13: =M13*Assumptions!$C$21 -> 4140.2075 | O13: =Assumptions!$C$27*F13*I13*G13 -> 34.595 | P13: =O13*Assumptions!$C$28 -> 1556.775 | Q13: =Assumptions!$C$24*4.333*F13*I13*G13 -> 38.156398 | R13: =Q13*Assumptions!$C$25 -> 381.56398 | S13: =MIN(O13*Assumptions!$C$48,R13) -> 207.57 | T13: =MAX(R13-S13,0) -> 173.99398 | U13: =T13*Assumptions!$C$26 -> 2087.9278 | V13: =Q13*Assumptions!$C$29 -> 1144.6919 | W13: =P13+U13 -> 3644.7028 | X13: =M13+W13 -> 17445.394 | Y13: =N13+V13 -> 5284.8994 | Z13: =X13-Y13 -> 12160.495 | AA13: =Assumptions!$C$10*Assumptions!$C$9/12 -> 2000 | AB13: =Assumptions!$C$12/12 -> 125 | AC13: =Assumptions!$C$14/12 -> 150 | AD13: =(Assumptions!$C$32*4.333*Assumptions!$C$33+Assumptions!$C$34/12)*(1+(Assumptions!$C$35)) -> 6783.2324 | AE13: =INDEX('Seasonality Data Break down'!$F$7:$F$18,C13)*G13 -> 250 | AF13: =INDEX('Seasonality Data Break down'!$G$7:$G$18,C13)*G13 -> 150 | AG13: =INDEX('Seasonality Data Break down'!$H$7:$H$18,C13)*G13 -> 75 | AH13: =AE13+AF13+AG13 -> 475 | AI13: =Assumptions!$C$39 -> 150 | AJ13: =Assumptions!$C$40 -> 500 | AK13: =AA13+AB13+AC13+AD13+AH13+AI13+AJ13 -> 10183.232 | AL13: =X13*Assumptions!$C$13 -> 523.36183 | AM13: =X13*Assumptions!$C$15 -> 305.2944 | AN13: =AL13+AM13 -> 828.65624 | AO13: =AK13+AN13 -> 11011.889 | AP13: =Z13-AO13 -> 1148.6064 | AQ13: ='Startup Costs'!$D$24/(Assumptions!$C$54*12) -> 916.66667 | AR13: =-'Loan schedule'!$D$17 -> -406.08567 | AS13: =AP13-AQ13+AR13 -> -174.14594 | AT13: =-MAX(AS13,0)*Assumptions!$C$41 -> 0 | AU13: =AS13+AT13 -> -174.14594 | AV13: =-'Loan schedule'!$E$17 -> -993.55897 | AW13: =AU13+AQ13+AV13 -> -251.03824 | AX13: =AY12 -> 12249.439 | AY13: =AX13+AW13 -> 11998.401 | AZ13: =IFERROR(Z13/X13,0) -> 0.69706048 | BA13: =IFERROR(AP13/X13,0) -> 0.065840093 | BB13: =IFERROR(AU13/X13,0) -> -0.0099823445 | BD13: Cafe Revenue | BE13: Effective Covers/Day x Trading Days in month x Average Spend (spend includes the summer iced-drink uplift in Jun-Aug).
A14: 7 | B14: 1 | C14: 7 | D14: ='Seasonality Data Break down'!$B$13&" Y"&B14 -> July Y1 | E14: =IF(B14=1,INDEX(Workings!$B$27:$B$38,C14),1) -> 0.85 | F14: =IF(B14=1,INDEX(Workings!$C$27:$C$38,C14),1) -> 0.8 | G14: =INDEX(Workings!$C$19:$C$23,B14) -> 1 | H14: =INDEX('Seasonality Data Break down'!$C$7:$C$18,C14) -> 1.15 | I14: =INDEX('Seasonality Data Break down'!$D$7:$D$18,C14) -> 0.8 | J14: =Assumptions!$C$18/12 -> 26.083333 | K14: =Assumptions!$C$19*E14*H14*G14 -> 63.5375 | L14: =Assumptions!$C$20+INDEX('Seasonality Data Break down'!$E$7:$E$18,C14) -> 9.25 | M14: =K14*J14*L14 -> 15329.746 | N14: =M14*Assumptions!$C$21 -> 4598.9237 | O14: =Assumptions!$C$27*F14*I14*G14 -> 35.2 | P14: =O14*Assumptions!$C$28 -> 1584 | Q14: =Assumptions!$C$24*4.333*F14*I14*G14 -> 38.82368 | R14: =Q14*Assumptions!$C$25 -> 388.2368 | S14: =MIN(O14*Assumptions!$C$48,R14) -> 211.2 | T14: =MAX(R14-S14,0) -> 177.0368 | U14: =T14*Assumptions!$C$26 -> 2124.4416 | V14: =Q14*Assumptions!$C$29 -> 1164.7104 | W14: =P14+U14 -> 3708.4416 | X14: =M14+W14 -> 19038.187 | Y14: =N14+V14 -> 5763.6341 | Z14: =X14-Y14 -> 13274.553 | AA14: =Assumptions!$C$10*Assumptions!$C$9/12 -> 2000 | AB14: =Assumptions!$C$12/12 -> 125 | AC14: =Assumptions!$C$14/12 -> 150 | AD14: =(Assumptions!$C$32*4.333*Assumptions!$C$33+Assumptions!$C$34/12)*(1+(Assumptions!$C$35)) -> 6783.2324 | AE14: =INDEX('Seasonality Data Break down'!$F$7:$F$18,C14)*G14 -> 250 | AF14: =INDEX('Seasonality Data Break down'!$G$7:$G$18,C14)*G14 -> 150 | AG14: =INDEX('Seasonality Data Break down'!$H$7:$H$18,C14)*G14 -> 75 | AH14: =AE14+AF14+AG14 -> 475 | AI14: =Assumptions!$C$39 -> 150 | AJ14: =Assumptions!$C$40 -> 500 | AK14: =AA14+AB14+AC14+AD14+AH14+AI14+AJ14 -> 10183.232 | AL14: =X14*Assumptions!$C$13 -> 571.14562 | AM14: =X14*Assumptions!$C$15 -> 333.16828 | AN14: =AL14+AM14 -> 904.31389 | AO14: =AK14+AN14 -> 11087.546 | AP14: =Z14-AO14 -> 2187.0069 | AQ14: ='Startup Costs'!$D$24/(Assumptions!$C$54*12) -> 916.66667 | AR14: =-'Loan schedule'!$D$18 -> -399.87592 | AS14: =AP14-AQ14+AR14 -> 870.46427 | AT14: =-MAX(AS14,0)*Assumptions!$C$41 -> -217.61607 | AU14: =AS14+AT14 -> 652.8482 | AV14: =-'Loan schedule'!$E$18 -> -999.76872 | AW14: =AU14+AQ14+AV14 -> 569.74615 | AX14: =AY13 -> 11998.401 | AY14: =AX14+AW14 -> 12568.147 | AZ14: =IFERROR(Z14/X14,0) -> 0.6972593 | BA14: =IFERROR(AP14/X14,0) -> 0.11487474 | BB14: =IFERROR(AU14/X14,0) -> 0.034291511 | BD14: Members | BE14: Base members (Assumptions) x Fit Ramp x Fit Season x Growth Factor.
A15: 8 | B15: 1 | C15: 8 | D15: ='Seasonality Data Break down'!$B$14&" Y"&B15 -> August Y1 | E15: =IF(B15=1,INDEX(Workings!$B$27:$B$38,C15),1) -> 0.9 | F15: =IF(B15=1,INDEX(Workings!$C$27:$C$38,C15),1) -> 0.85 | G15: =INDEX(Workings!$C$19:$C$23,B15) -> 1 | H15: =INDEX('Seasonality Data Break down'!$C$7:$C$18,C15) -> 1 | I15: =INDEX('Seasonality Data Break down'!$D$7:$D$18,C15) -> 0.85 | J15: =Assumptions!$C$18/12 -> 26.083333 | K15: =Assumptions!$C$19*E15*H15*G15 -> 58.5 | L15: =Assumptions!$C$20+INDEX('Seasonality Data Break down'!$E$7:$E$18,C15) -> 9.25 | M15: =K15*J15*L15 -> 14114.344 | N15: =M15*Assumptions!$C$21 -> 4234.3031 | O15: =Assumptions!$C$27*F15*I15*G15 -> 39.7375 | P15: =O15*Assumptions!$C$28 -> 1788.1875 | Q15: =Assumptions!$C$24*4.333*F15*I15*G15 -> 43.828295 | R15: =Q15*Assumptions!$C$25 -> 438.28295 | S15: =MIN(O15*Assumptions!$C$48,R15) -> 238.425 | T15: =MAX(R15-S15,0) -> 199.85795 | U15: =T15*Assumptions!$C$26 -> 2398.2954 | V15: =Q15*Assumptions!$C$29 -> 1314.8489 | W15: =P15+U15 -> 4186.4829 | X15: =M15+W15 -> 18300.827 | Y15: =N15+V15 -> 5549.152 | Z15: =X15-Y15 -> 12751.675 | AA15: =Assumptions!$C$10*Assumptions!$C$9/12 -> 2000 | AB15: =Assumptions!$C$12/12 -> 125 | AC15: =Assumptions!$C$14/12 -> 150 | AD15: =(Assumptions!$C$32*4.333*Assumptions!$C$33+Assumptions!$C$34/12)*(1+(Assumptions!$C$35)) -> 6783.2324 | AE15: =INDEX('Seasonality Data Break down'!$F$7:$F$18,C15)*G15 -> 150 | AF15: =INDEX('Seasonality Data Break down'!$G$7:$G$18,C15)*G15 -> 150 | AG15: =INDEX('Seasonality Data Break down'!$H$7:$H$18,C15)*G15 -> 75 | AH15: =AE15+AF15+AG15 -> 375 | AI15: =Assumptions!$C$39 -> 150 | AJ15: =Assumptions!$C$40 -> 500 | AK15: =AA15+AB15+AC15+AD15+AH15+AI15+AJ15 -> 10083.232 | AL15: =X15*Assumptions!$C$13 -> 549.0248 | AM15: =X15*Assumptions!$C$15 -> 320.26447 | AN15: =AL15+AM15 -> 869.28927 | AO15: =AK15+AN15 -> 10952.522 | AP15: =Z15-AO15 -> 1799.1531 | AQ15: ='Startup Costs'!$D$24/(Assumptions!$C$54*12) -> 916.66667 | AR15: =-'Loan schedule'!$D$19 -> -393.62737 | AS15: =AP15-AQ15+AR15 -> 488.85902 | AT15: =-MAX(AS15,0)*Assumptions!$C$41 -> -122.21475 | AU15: =AS15+AT15 -> 366.64426 | AV15: =-'Loan schedule'!$E$19 -> -1006.0173 | AW15: =AU15+AQ15+AV15 -> 277.29366 | AX15: =AY14 -> 12568.147 | AY15: =AX15+AW15 -> 12845.441 | AZ15: =IFERROR(Z15/X15,0) -> 0.69678135 | BA15: =IFERROR(AP15/X15,0) -> 0.098309934 | BB15: =IFERROR(AU15/X15,0) -> 0.020034301 | BD15: Membership Revenue | BE15: Members x monthly membership price.
A16: 9 | B16: 1 | C16: 9 | D16: ='Seasonality Data Break down'!$B$15&" Y"&B16 -> September Y1 | E16: =IF(B16=1,INDEX(Workings!$B$27:$B$38,C16),1) -> 0.94 | F16: =IF(B16=1,INDEX(Workings!$C$27:$C$38,C16),1) -> 0.9 | G16: =INDEX(Workings!$C$19:$C$23,B16) -> 1 | H16: =INDEX('Seasonality Data Break down'!$C$7:$C$18,C16) -> 0.95 | I16: =INDEX('Seasonality Data Break down'!$D$7:$D$18,C16) -> 1.05 | J16: =Assumptions!$C$18/12 -> 26.083333 | K16: =Assumptions!$C$19*E16*H16*G16 -> 58.045 | L16: =Assumptions!$C$20+INDEX('Seasonality Data Break down'!$E$7:$E$18,C16) -> 8.5 | M16: =K16*J16*L16 -> 12869.06 | N16: =M16*Assumptions!$C$21 -> 3860.7181 | O16: =Assumptions!$C$27*F16*I16*G16 -> 51.975 | P16: =O16*Assumptions!$C$28 -> 2338.875 | Q16: =Assumptions!$C$24*4.333*F16*I16*G16 -> 57.32559 | R16: =Q16*Assumptions!$C$25 -> 573.2559 | S16: =MIN(O16*Assumptions!$C$48,R16) -> 311.85 | T16: =MAX(R16-S16,0) -> 261.4059 | U16: =T16*Assumptions!$C$26 -> 3136.8708 | V16: =Q16*Assumptions!$C$29 -> 1719.7677 | W16: =P16+U16 -> 5475.7458 | X16: =M16+W16 -> 18344.806 | Y16: =N16+V16 -> 5580.4858 | Z16: =X16-Y16 -> 12764.32 | AA16: =Assumptions!$C$10*Assumptions!$C$9/12 -> 2000 | AB16: =Assumptions!$C$12/12 -> 125 | AC16: =Assumptions!$C$14/12 -> 150 | AD16: =(Assumptions!$C$32*4.333*Assumptions!$C$33+Assumptions!$C$34/12)*(1+(Assumptions!$C$35)) -> 6783.2324 | AE16: =INDEX('Seasonality Data Break down'!$F$7:$F$18,C16)*G16 -> 200 | AF16: =INDEX('Seasonality Data Break down'!$G$7:$G$18,C16)*G16 -> 200 | AG16: =INDEX('Seasonality Data Break down'!$H$7:$H$18,C16)*G16 -> 75 | AH16: =AE16+AF16+AG16 -> 475 | AI16: =Assumptions!$C$39 -> 150 | AJ16: =Assumptions!$C$40 -> 500 | AK16: =AA16+AB16+AC16+AD16+AH16+AI16+AJ16 -> 10183.232 | AL16: =X16*Assumptions!$C$13 -> 550.34418 | AM16: =X16*Assumptions!$C$15 -> 321.03411 | AN16: =AL16+AM16 -> 871.37829 | AO16: =AK16+AN16 -> 11054.611 | AP16: =Z16-AO16 -> 1709.7096 | AQ16: ='Startup Costs'!$D$24/(Assumptions!$C$54*12) -> 916.66667 | AR16: =-'Loan schedule'!$D$20 -> -387.33976 | AS16: =AP16-AQ16+AR16 -> 405.70318 | AT16: =-MAX(AS16,0)*Assumptions!$C$41 -> -101.42579 | AU16: =AS16+AT16 -> 304.27738 | AV16: =-'Loan schedule'!$E$20 -> -1012.3049 | AW16: =AU16+AQ16+AV16 -> 208.63917 | AX16: =AY15 -> 12845.441 | AY16: =AX16+AW16 -> 13054.08 | AZ16: =IFERROR(Z16/X16,0) -> 0.69580023 | BA16: =IFERROR(AP16/X16,0) -> 0.093198566 | BB16: =IFERROR(AU16/X16,0) -> 0.016586569 | BD16: Classes Run | BE16: Base classes/week x 4.333 x Fit Ramp x Fit Season x Growth Factor.
A17: 10 | B17: 1 | C17: 10 | D17: ='Seasonality Data Break down'!$B$16&" Y"&B17 -> October Y1 | E17: =IF(B17=1,INDEX(Workings!$B$27:$B$38,C17),1) -> 0.97 | F17: =IF(B17=1,INDEX(Workings!$C$27:$C$38,C17),1) -> 0.94 | G17: =INDEX(Workings!$C$19:$C$23,B17) -> 1 | H17: =INDEX('Seasonality Data Break down'!$C$7:$C$18,C17) -> 1 | I17: =INDEX('Seasonality Data Break down'!$D$7:$D$18,C17) -> 1 | J17: =Assumptions!$C$18/12 -> 26.083333 | K17: =Assumptions!$C$19*E17*H17*G17 -> 63.05 | L17: =Assumptions!$C$20+INDEX('Seasonality Data Break down'!$E$7:$E$18,C17) -> 8.5 | M17: =K17*J17*L17 -> 13978.71 | N17: =M17*Assumptions!$C$21 -> 4193.6131 | O17: =Assumptions!$C$27*F17*I17*G17 -> 51.7 | P17: =O17*Assumptions!$C$28 -> 2326.5 | Q17: =Assumptions!$C$24*4.333*F17*I17*G17 -> 57.02228 | R17: =Q17*Assumptions!$C$25 -> 570.2228 | S17: =MIN(O17*Assumptions!$C$48,R17) -> 310.2 | T17: =MAX(R17-S17,0) -> 260.0228 | U17: =T17*Assumptions!$C$26 -> 3120.2736 | V17: =Q17*Assumptions!$C$29 -> 1710.6684 | W17: =P17+U17 -> 5446.7736 | X17: =M17+W17 -> 19425.484 | Y17: =N17+V17 -> 5904.2815 | Z17: =X17-Y17 -> 13521.202 | AA17: =Assumptions!$C$10*Assumptions!$C$9/12 -> 2000 | AB17: =Assumptions!$C$12/12 -> 125 | AC17: =Assumptions!$C$14/12 -> 150 | AD17: =(Assumptions!$C$32*4.333*Assumptions!$C$33+Assumptions!$C$34/12)*(1+(Assumptions!$C$35)) -> 6783.2324 | AE17: =INDEX('Seasonality Data Break down'!$F$7:$F$18,C17)*G17 -> 150 | AF17: =INDEX('Seasonality Data Break down'!$G$7:$G$18,C17)*G17 -> 150 | AG17: =INDEX('Seasonality Data Break down'!$H$7:$H$18,C17)*G17 -> 50 | AH17: =AE17+AF17+AG17 -> 350 | AI17: =Assumptions!$C$39 -> 150 | AJ17: =Assumptions!$C$40 -> 500 | AK17: =AA17+AB17+AC17+AD17+AH17+AI17+AJ17 -> 10058.232 | AL17: =X17*Assumptions!$C$13 -> 582.76452 | AM17: =X17*Assumptions!$C$15 -> 339.94597 | AN17: =AL17+AM17 -> 922.71049 | AO17: =AK17+AN17 -> 10980.943 | AP17: =Z17-AO17 -> 2540.2596 | AQ17: ='Startup Costs'!$D$24/(Assumptions!$C$54*12) -> 916.66667 | AR17: =-'Loan schedule'!$D$21 -> -381.01286 | AS17: =AP17-AQ17+AR17 -> 1242.5801 | AT17: =-MAX(AS17,0)*Assumptions!$C$41 -> -310.64503 | AU17: =AS17+AT17 -> 931.93509 | AV17: =-'Loan schedule'!$E$21 -> -1018.6318 | AW17: =AU17+AQ17+AV17 -> 829.96998 | AX17: =AY16 -> 13054.08 | AY17: =AX17+AW17 -> 13884.05 | AZ17: =IFERROR(Z17/X17,0) -> 0.69605486 | BA17: =IFERROR(AP17/X17,0) -> 0.13076944 | BB17: =IFERROR(AU17/X17,0) -> 0.047974871 | BD17: Drop-in Revenue | BE17: (Total class attendances - attendances covered by memberships) x drop-in price.
A18: 11 | B18: 1 | C18: 11 | D18: ='Seasonality Data Break down'!$B$17&" Y"&B18 -> November Y1 | E18: =IF(B18=1,INDEX(Workings!$B$27:$B$38,C18),1) -> 0.99 | F18: =IF(B18=1,INDEX(Workings!$C$27:$C$38,C18),1) -> 0.97 | G18: =INDEX(Workings!$C$19:$C$23,B18) -> 1 | H18: =INDEX('Seasonality Data Break down'!$C$7:$C$18,C18) -> 1.05 | I18: =INDEX('Seasonality Data Break down'!$D$7:$D$18,C18) -> 0.95 | J18: =Assumptions!$C$18/12 -> 26.083333 | K18: =Assumptions!$C$19*E18*H18*G18 -> 67.5675 | L18: =Assumptions!$C$20+INDEX('Seasonality Data Break down'!$E$7:$E$18,C18) -> 8.5 | M18: =K18*J18*L18 -> 14980.278 | N18: =M18*Assumptions!$C$21 -> 4494.0833 | O18: =Assumptions!$C$27*F18*I18*G18 -> 50.6825 | P18: =O18*Assumptions!$C$28 -> 2280.7125 | Q18: =Assumptions!$C$24*4.333*F18*I18*G18 -> 55.900033 | R18: =Q18*Assumptions!$C$25 -> 559.00033 | S18: =MIN(O18*Assumptions!$C$48,R18) -> 304.095 | T18: =MAX(R18-S18,0) -> 254.90533 | U18: =T18*Assumptions!$C$26 -> 3058.864 | V18: =Q18*Assumptions!$C$29 -> 1677.001 | W18: =P18+U18 -> 5339.5765 | X18: =M18+W18 -> 20319.854 | Y18: =N18+V18 -> 6171.0843 | Z18: =X18-Y18 -> 14148.77 | AA18: =Assumptions!$C$10*Assumptions!$C$9/12 -> 2000 | AB18: =Assumptions!$C$12/12 -> 125 | AC18: =Assumptions!$C$14/12 -> 150 | AD18: =(Assumptions!$C$32*4.333*Assumptions!$C$33+Assumptions!$C$34/12)*(1+(Assumptions!$C$35)) -> 6783.2324 | AE18: =INDEX('Seasonality Data Break down'!$F$7:$F$18,C18)*G18 -> 250 | AF18: =INDEX('Seasonality Data Break down'!$G$7:$G$18,C18)*G18 -> 200 | AG18: =INDEX('Seasonality Data Break down'!$H$7:$H$18,C18)*G18 -> 75 | AH18: =AE18+AF18+AG18 -> 525 | AI18: =Assumptions!$C$39 -> 150 | AJ18: =Assumptions!$C$40 -> 500 | AK18: =AA18+AB18+AC18+AD18+AH18+AI18+AJ18 -> 10233.232 | AL18: =X18*Assumptions!$C$13 -> 609.59563 | AM18: =X18*Assumptions!$C$15 -> 355.59745 | AN18: =AL18+AM18 -> 965.19308 | AO18: =AK18+AN18 -> 11198.425 | AP18: =Z18-AO18 -> 2950.3445 | AQ18: ='Startup Costs'!$D$24/(Assumptions!$C$54*12) -> 916.66667 | AR18: =-'Loan schedule'!$D$22 -> -374.64641 | AS18: =AP18-AQ18+AR18 -> 1659.0314 | AT18: =-MAX(AS18,0)*Assumptions!$C$41 -> -414.75786 | AU18: =AS18+AT18 -> 1244.2736 | AV18: =-'Loan schedule'!$E$22 -> -1024.9982 | AW18: =AU18+AQ18+AV18 -> 1135.942 | AX18: =AY17 -> 13884.05 | AY18: =AX18+AW18 -> 15019.992 | AZ18: =IFERROR(Z18/X18,0) -> 0.69630273 | BA18: =IFERROR(AP18/X18,0) -> 0.14519516 | BB18: =IFERROR(AU18/X18,0) -> 0.061234375 | BD18: Fitness Revenue | BE18: Membership Revenue + Drop-in Revenue.
A19: 12 | B19: 1 | C19: 12 | D19: ='Seasonality Data Break down'!$B$18&" Y"&B19 -> December Y1 | E19: =IF(B19=1,INDEX(Workings!$B$27:$B$38,C19),1) -> 1 | F19: =IF(B19=1,INDEX(Workings!$C$27:$C$38,C19),1) -> 1 | G19: =INDEX(Workings!$C$19:$C$23,B19) -> 1 | H19: =INDEX('Seasonality Data Break down'!$C$7:$C$18,C19) -> 1.2 | I19: =INDEX('Seasonality Data Break down'!$D$7:$D$18,C19) -> 0.8 | J19: =Assumptions!$C$18/12 -> 26.083333 | K19: =Assumptions!$C$19*E19*H19*G19 -> 78 | L19: =Assumptions!$C$20+INDEX('Seasonality Data Break down'!$E$7:$E$18,C19) -> 8.5 | M19: =K19*J19*L19 -> 17293.25 | N19: =M19*Assumptions!$C$21 -> 5187.975 | O19: =Assumptions!$C$27*F19*I19*G19 -> 44 | P19: =O19*Assumptions!$C$28 -> 1980 | Q19: =Assumptions!$C$24*4.333*F19*I19*G19 -> 48.5296 | R19: =Q19*Assumptions!$C$25 -> 485.296 | S19: =MIN(O19*Assumptions!$C$48,R19) -> 264 | T19: =MAX(R19-S19,0) -> 221.296 | U19: =T19*Assumptions!$C$26 -> 2655.552 | V19: =Q19*Assumptions!$C$29 -> 1455.888 | W19: =P19+U19 -> 4635.552 | X19: =M19+W19 -> 21928.802 | Y19: =N19+V19 -> 6643.863 | Z19: =X19-Y19 -> 15284.939 | AA19: =Assumptions!$C$10*Assumptions!$C$9/12 -> 2000 | AB19: =Assumptions!$C$12/12 -> 125 | AC19: =Assumptions!$C$14/12 -> 150 | AD19: =(Assumptions!$C$32*4.333*Assumptions!$C$33+Assumptions!$C$34/12)*(1+(Assumptions!$C$35)) -> 6783.2324 | AE19: =INDEX('Seasonality Data Break down'!$F$7:$F$18,C19)*G19 -> 300 | AF19: =INDEX('Seasonality Data Break down'!$G$7:$G$18,C19)*G19 -> 250 | AG19: =INDEX('Seasonality Data Break down'!$H$7:$H$18,C19)*G19 -> 100 | AH19: =AE19+AF19+AG19 -> 650 | AI19: =Assumptions!$C$39 -> 150 | AJ19: =Assumptions!$C$40 -> 500 | AK19: =AA19+AB19+AC19+AD19+AH19+AI19+AJ19 -> 10358.232 | AL19: =X19*Assumptions!$C$13 -> 657.86406 | AM19: =X19*Assumptions!$C$15 -> 383.75404 | AN19: =AL19+AM19 -> 1041.6181 | AO19: =AK19+AN19 -> 11399.85 | AP19: =Z19-AO19 -> 3885.0886 | AQ19: ='Startup Costs'!$D$24/(Assumptions!$C$54*12) -> 916.66667 | AR19: =-'Loan schedule'!$D$23 -> -368.24017 | AS19: =AP19-AQ19+AR19 -> 2600.1817 | AT19: =-MAX(AS19,0)*Assumptions!$C$41 -> -650.04543 | AU19: =AS19+AT19 -> 1950.1363 | AV19: =-'Loan schedule'!$E$23 -> -1031.4045 | AW19: =AU19+AQ19+AV19 -> 1835.3985 | AX19: =AY18 -> 15019.992 | AY19: =AX19+AW19 -> 16855.39 | AZ19: =IFERROR(Z19/X19,0) -> 0.69702572 | BA19: =IFERROR(AP19/X19,0) -> 0.1771683 | BB19: =IFERROR(AU19/X19,0) -> 0.088930361 | BD19: TOTAL REVENUE | BE19: Cafe Revenue + Fitness Revenue. This is what the Income Statement sums by year.
A20: 13 | B20: 2 | C20: 1 | D20: ='Seasonality Data Break down'!$B$7&" Y"&B20 -> January Y2 | E20: =IF(B20=1,INDEX(Workings!$B$27:$B$38,C20),1) -> 1 | F20: =IF(B20=1,INDEX(Workings!$C$27:$C$38,C20),1) -> 1 | G20: =INDEX(Workings!$C$19:$C$23,B20) -> 1.15 | H20: =INDEX('Seasonality Data Break down'!$C$7:$C$18,C20) -> 0.85 | I20: =INDEX('Seasonality Data Break down'!$D$7:$D$18,C20) -> 1.3 | J20: =Assumptions!$C$18/12 -> 26.083333 | K20: =Assumptions!$C$19*E20*H20*G20 -> 63.5375 | L20: =Assumptions!$C$20+INDEX('Seasonality Data Break down'!$E$7:$E$18,C20) -> 8.5 | M20: =K20*J20*L20 -> 14086.793 | N20: =M20*Assumptions!$C$21 -> 4226.038 | O20: =Assumptions!$C$27*F20*I20*G20 -> 82.225 | P20: =O20*Assumptions!$C$28 -> 3700.125 | Q20: =Assumptions!$C$24*4.333*F20*I20*G20 -> 90.68969 | R20: =Q20*Assumptions!$C$25 -> 906.8969 | S20: =MIN(O20*Assumptions!$C$48,R20) -> 493.35 | T20: =MAX(R20-S20,0) -> 413.5469 | U20: =T20*Assumptions!$C$26 -> 4962.5628 | V20: =Q20*Assumptions!$C$29 -> 2720.6907 | W20: =P20+U20 -> 8662.6878 | X20: =M20+W20 -> 22749.481 | Y20: =N20+V20 -> 6946.7287 | Z20: =X20-Y20 -> 15802.752 | AA20: =Assumptions!$C$10*Assumptions!$C$9/12 -> 2000 | AB20: =Assumptions!$C$12/12 -> 125 | AC20: =Assumptions!$C$14/12 -> 150 | AD20: =(Assumptions!$C$32*4.333*Assumptions!$C$33+Assumptions!$C$34/12)*(1+(Assumptions!$C$35)) -> 6783.2324 | AE20: =INDEX('Seasonality Data Break down'!$F$7:$F$18,C20)*G20 -> 345 | AF20: =INDEX('Seasonality Data Break down'!$G$7:$G$18,C20)*G20 -> 172.5 | AG20: =INDEX('Seasonality Data Break down'!$H$7:$H$18,C20)*G20 -> 57.5 | AH20: =AE20+AF20+AG20 -> 575 | AI20: =Assumptions!$C$39 -> 150 | AJ20: =Assumptions!$C$40 -> 500 | AK20: =AA20+AB20+AC20+AD20+AH20+AI20+AJ20 -> 10283.232 | AL20: =X20*Assumptions!$C$13 -> 682.48443 | AM20: =X20*Assumptions!$C$15 -> 398.11592 | AN20: =AL20+AM20 -> 1080.6003 | AO20: =AK20+AN20 -> 11363.833 | AP20: =Z20-AO20 -> 4438.9197 | AQ20: ='Startup Costs'!$D$24/(Assumptions!$C$54*12) -> 916.66667 | AR20: =-'Loan schedule'!$D$24 -> -361.79389 | AS20: =AP20-AQ20+AR20 -> 3160.4591 | AT20: =-MAX(AS20,0)*Assumptions!$C$41 -> -790.11478 | AU20: =AS20+AT20 -> 2370.3443 | AV20: =-'Loan schedule'!$E$24 -> -1037.8507 | AW20: =AU20+AQ20+AV20 -> 2249.1602 | AX20: =AY19 -> 16855.39 | AY20: =AX20+AW20 -> 19104.551 | AZ20: =IFERROR(Z20/X20,0) -> 0.69464232 | BA20: =IFERROR(AP20/X20,0) -> 0.1951218 | BB20: =IFERROR(AU20/X20,0) -> 0.10419334 | BD20: Total COGS | BE20: Food & drink cost of sales + freelance instructor costs.
A21: 14 | B21: 2 | C21: 2 | D21: ='Seasonality Data Break down'!$B$8&" Y"&B21 -> February Y2 | E21: =IF(B21=1,INDEX(Workings!$B$27:$B$38,C21),1) -> 1 | F21: =IF(B21=1,INDEX(Workings!$C$27:$C$38,C21),1) -> 1 | G21: =INDEX(Workings!$C$19:$C$23,B21) -> 1.15 | H21: =INDEX('Seasonality Data Break down'!$C$7:$C$18,C21) -> 0.9 | I21: =INDEX('Seasonality Data Break down'!$D$7:$D$18,C21) -> 1.2 | J21: =Assumptions!$C$18/12 -> 26.083333 | K21: =Assumptions!$C$19*E21*H21*G21 -> 67.275 | L21: =Assumptions!$C$20+INDEX('Seasonality Data Break down'!$E$7:$E$18,C21) -> 8.5 | M21: =K21*J21*L21 -> 14915.428 | N21: =M21*Assumptions!$C$21 -> 4474.6284 | O21: =Assumptions!$C$27*F21*I21*G21 -> 75.9 | P21: =O21*Assumptions!$C$28 -> 3415.5 | Q21: =Assumptions!$C$24*4.333*F21*I21*G21 -> 83.71356 | R21: =Q21*Assumptions!$C$25 -> 837.1356 | S21: =MIN(O21*Assumptions!$C$48,R21) -> 455.4 | T21: =MAX(R21-S21,0) -> 381.7356 | U21: =T21*Assumptions!$C$26 -> 4580.8272 | V21: =Q21*Assumptions!$C$29 -> 2511.4068 | W21: =P21+U21 -> 7996.3272 | X21: =M21+W21 -> 22911.755 | Y21: =N21+V21 -> 6986.0352 | Z21: =X21-Y21 -> 15925.72 | AA21: =Assumptions!$C$10*Assumptions!$C$9/12 -> 2000 | AB21: =Assumptions!$C$12/12 -> 125 | AC21: =Assumptions!$C$14/12 -> 150 | AD21: =(Assumptions!$C$32*4.333*Assumptions!$C$33+Assumptions!$C$34/12)*(1+(Assumptions!$C$35)) -> 6783.2324 | AE21: =INDEX('Seasonality Data Break down'!$F$7:$F$18,C21)*G21 -> 230 | AF21: =INDEX('Seasonality Data Break down'!$G$7:$G$18,C21)*G21 -> 172.5 | AG21: =INDEX('Seasonality Data Break down'!$H$7:$H$18,C21)*G21 -> 57.5 | AH21: =AE21+AF21+AG21 -> 460 | AI21: =Assumptions!$C$39 -> 150 | AJ21: =Assumptions!$C$40 -> 500 | AK21: =AA21+AB21+AC21+AD21+AH21+AI21+AJ21 -> 10168.232 | AL21: =X21*Assumptions!$C$13 -> 687.35266 | AM21: =X21*Assumptions!$C$15 -> 400.95572 | AN21: =AL21+AM21 -> 1088.3084 | AO21: =AK21+AN21 -> 11256.541 | AP21: =Z21-AO21 -> 4669.1794 | AQ21: ='Startup Costs'!$D$24/(Assumptions!$C$54*12) -> 916.66667 | AR21: =-'Loan schedule'!$D$25 -> -355.30732 | AS21: =AP21-AQ21+AR21 -> 3397.2054 | AT21: =-MAX(AS21,0)*Assumptions!$C$41 -> -849.30134 | AU21: =AS21+AT21 -> 2547.904 | AV21: =-'Loan schedule'!$E$25 -> -1044.3373 | AW21: =AU21+AQ21+AV21 -> 2420.2334 | AX21: =AY20 -> 19104.551 | AY21: =AX21+AW21 -> 21524.784 | AZ21: =IFERROR(Z21/X21,0) -> 0.69508948 | BA21: =IFERROR(AP21/X21,0) -> 0.20378968 | BB21: =IFERROR(AU21/X21,0) -> 0.1112051 | BD21: GROSS PROFIT | BE21: Total Revenue - Total COGS.
A22: 15 | B22: 2 | C22: 3 | D22: ='Seasonality Data Break down'!$B$9&" Y"&B22 -> March Y2 | E22: =IF(B22=1,INDEX(Workings!$B$27:$B$38,C22),1) -> 1 | F22: =IF(B22=1,INDEX(Workings!$C$27:$C$38,C22),1) -> 1 | G22: =INDEX(Workings!$C$19:$C$23,B22) -> 1.15 | H22: =INDEX('Seasonality Data Break down'!$C$7:$C$18,C22) -> 0.95 | I22: =INDEX('Seasonality Data Break down'!$D$7:$D$18,C22) -> 1.05 | J22: =Assumptions!$C$18/12 -> 26.083333 | K22: =Assumptions!$C$19*E22*H22*G22 -> 71.0125 | L22: =Assumptions!$C$20+INDEX('Seasonality Data Break down'!$E$7:$E$18,C22) -> 8.5 | M22: =K22*J22*L22 -> 15744.063 | N22: =M22*Assumptions!$C$21 -> 4723.2189 | O22: =Assumptions!$C$27*F22*I22*G22 -> 66.4125 | P22: =O22*Assumptions!$C$28 -> 2988.5625 | Q22: =Assumptions!$C$24*4.333*F22*I22*G22 -> 73.249365 | R22: =Q22*Assumptions!$C$25 -> 732.49365 | S22: =MIN(O22*Assumptions!$C$48,R22) -> 398.475 | T22: =MAX(R22-S22,0) -> 334.01865 | U22: =T22*Assumptions!$C$26 -> 4008.2238 | V22: =Q22*Assumptions!$C$29 -> 2197.481 | W22: =P22+U22 -> 6996.7863 | X22: =M22+W22 -> 22740.849 | Y22: =N22+V22 -> 6920.6999 | Z22: =X22-Y22 -> 15820.149 | AA22: =Assumptions!$C$10*Assumptions!$C$9/12 -> 2000 | AB22: =Assumptions!$C$12/12 -> 125 | AC22: =Assumptions!$C$14/12 -> 150 | AD22: =(Assumptions!$C$32*4.333*Assumptions!$C$33+Assumptions!$C$34/12)*(1+(Assumptions!$C$35)) -> 6783.2324 | AE22: =INDEX('Seasonality Data Break down'!$F$7:$F$18,C22)*G22 -> 172.5 | AF22: =INDEX('Seasonality Data Break down'!$G$7:$G$18,C22)*G22 -> 172.5 | AG22: =INDEX('Seasonality Data Break down'!$H$7:$H$18,C22)*G22 -> 57.5 | AH22: =AE22+AF22+AG22 -> 402.5 | AI22: =Assumptions!$C$39 -> 150 | AJ22: =Assumptions!$C$40 -> 500 | AK22: =AA22+AB22+AC22+AD22+AH22+AI22+AJ22 -> 10110.732 | AL22: =X22*Assumptions!$C$13 -> 682.22548 | AM22: =X22*Assumptions!$C$15 -> 397.96486 | AN22: =AL22+AM22 -> 1080.1903 | AO22: =AK22+AN22 -> 11190.923 | AP22: =Z22-AO22 -> 4629.2268 | AQ22: ='Startup Costs'!$D$24/(Assumptions!$C$54*12) -> 916.66667 | AR22: =-'Loan schedule'!$D$26 -> -348.78021 | AS22: =AP22-AQ22+AR22 -> 3363.7799 | AT22: =-MAX(AS22,0)*Assumptions!$C$41 -> -840.94497 | AU22: =AS22+AT22 -> 2522.8349 | AV22: =-'Loan schedule'!$E$26 -> -1050.8644 | AW22: =AU22+AQ22+AV22 -> 2388.6372 | AX22: =AY21 -> 21524.784 | AY22: =AX22+AW22 -> 23913.421 | AZ22: =IFERROR(Z22/X22,0) -> 0.695671 | BA22: =IFERROR(AP22/X22,0) -> 0.20356437 | BB22: =IFERROR(AU22/X22,0) -> 0.11093846 | BD22: Rent / Rates / Insurance | BE22: Fixed monthly costs, pulled straight from the Assumptions tab (annual figures / 12).
A23: 16 | B23: 2 | C23: 4 | D23: ='Seasonality Data Break down'!$B$10&" Y"&B23 -> April Y2 | E23: =IF(B23=1,INDEX(Workings!$B$27:$B$38,C23),1) -> 1 | F23: =IF(B23=1,INDEX(Workings!$C$27:$C$38,C23),1) -> 1 | G23: =INDEX(Workings!$C$19:$C$23,B23) -> 1.15 | H23: =INDEX('Seasonality Data Break down'!$C$7:$C$18,C23) -> 1 | I23: =INDEX('Seasonality Data Break down'!$D$7:$D$18,C23) -> 1 | J23: =Assumptions!$C$18/12 -> 26.083333 | K23: =Assumptions!$C$19*E23*H23*G23 -> 74.75 | L23: =Assumptions!$C$20+INDEX('Seasonality Data Break down'!$E$7:$E$18,C23) -> 8.5 | M23: =K23*J23*L23 -> 16572.698 | N23: =M23*Assumptions!$C$21 -> 4971.8094 | O23: =Assumptions!$C$27*F23*I23*G23 -> 63.25 | P23: =O23*Assumptions!$C$28 -> 2846.25 | Q23: =Assumptions!$C$24*4.333*F23*I23*G23 -> 69.7613 | R23: =Q23*Assumptions!$C$25 -> 697.613 | S23: =MIN(O23*Assumptions!$C$48,R23) -> 379.5 | T23: =MAX(R23-S23,0) -> 318.113 | U23: =T23*Assumptions!$C$26 -> 3817.356 | V23: =Q23*Assumptions!$C$29 -> 2092.839 | W23: =P23+U23 -> 6663.606 | X23: =M23+W23 -> 23236.304 | Y23: =N23+V23 -> 7064.6484 | Z23: =X23-Y23 -> 16171.656 | AA23: =Assumptions!$C$10*Assumptions!$C$9/12 -> 2000 | AB23: =Assumptions!$C$12/12 -> 125 | AC23: =Assumptions!$C$14/12 -> 150 | AD23: =(Assumptions!$C$32*4.333*Assumptions!$C$33+Assumptions!$C$34/12)*(1+(Assumptions!$C$35)) -> 6783.2324 | AE23: =INDEX('Seasonality Data Break down'!$F$7:$F$18,C23)*G23 -> 172.5 | AF23: =INDEX('Seasonality Data Break down'!$G$7:$G$18,C23)*G23 -> 172.5 | AG23: =INDEX('Seasonality Data Break down'!$H$7:$H$18,C23)*G23 -> 86.25 | AH23: =AE23+AF23+AG23 -> 431.25 | AI23: =Assumptions!$C$39 -> 150 | AJ23: =Assumptions!$C$40 -> 500 | AK23: =AA23+AB23+AC23+AD23+AH23+AI23+AJ23 -> 10139.482 | AL23: =X23*Assumptions!$C$13 -> 697.08912 | AM23: =X23*Assumptions!$C$15 -> 406.63532 | AN23: =AL23+AM23 -> 1103.7244 | AO23: =AK23+AN23 -> 11243.207 | AP23: =Z23-AO23 -> 4928.4488 | AQ23: ='Startup Costs'!$D$24/(Assumptions!$C$54*12) -> 916.66667 | AR23: =-'Loan schedule'!$D$27 -> -342.21231 | AS23: =AP23-AQ23+AR23 -> 3669.5698 | AT23: =-MAX(AS23,0)*Assumptions!$C$41 -> -917.39244 | AU23: =AS23+AT23 -> 2752.1773 | AV23: =-'Loan schedule'!$E$27 -> -1057.4323 | AW23: =AU23+AQ23+AV23 -> 2611.4117 | AX23: =AY22 -> 23913.421 | AY23: =AX23+AW23 -> 26524.833 | AZ23: =IFERROR(Z23/X23,0) -> 0.69596506 | BA23: =IFERROR(AP23/X23,0) -> 0.21210123 | BB23: =IFERROR(AU23/X23,0) -> 0.11844299 | BD23: Wages Total | BE23: Front-of-house wages + manager salary, grossed up for employer NI and pension (Assumptions).
A24: 17 | B24: 2 | C24: 5 | D24: ='Seasonality Data Break down'!$B$11&" Y"&B24 -> May Y2 | E24: =IF(B24=1,INDEX(Workings!$B$27:$B$38,C24),1) -> 1 | F24: =IF(B24=1,INDEX(Workings!$C$27:$C$38,C24),1) -> 1 | G24: =INDEX(Workings!$C$19:$C$23,B24) -> 1.15 | H24: =INDEX('Seasonality Data Break down'!$C$7:$C$18,C24) -> 1.05 | I24: =INDEX('Seasonality Data Break down'!$D$7:$D$18,C24) -> 0.95 | J24: =Assumptions!$C$18/12 -> 26.083333 | K24: =Assumptions!$C$19*E24*H24*G24 -> 78.4875 | L24: =Assumptions!$C$20+INDEX('Seasonality Data Break down'!$E$7:$E$18,C24) -> 8.5 | M24: =K24*J24*L24 -> 17401.333 | N24: =M24*Assumptions!$C$21 -> 5220.3998 | O24: =Assumptions!$C$27*F24*I24*G24 -> 60.0875 | P24: =O24*Assumptions!$C$28 -> 2703.9375 | Q24: =Assumptions!$C$24*4.333*F24*I24*G24 -> 66.273235 | R24: =Q24*Assumptions!$C$25 -> 662.73235 | S24: =MIN(O24*Assumptions!$C$48,R24) -> 360.525 | T24: =MAX(R24-S24,0) -> 302.20735 | U24: =T24*Assumptions!$C$26 -> 3626.4882 | V24: =Q24*Assumptions!$C$29 -> 1988.197 | W24: =P24+U24 -> 6330.4257 | X24: =M24+W24 -> 23731.759 | Y24: =N24+V24 -> 7208.5969 | Z24: =X24-Y24 -> 16523.162 | AA24: =Assumptions!$C$10*Assumptions!$C$9/12 -> 2000 | AB24: =Assumptions!$C$12/12 -> 125 | AC24: =Assumptions!$C$14/12 -> 150 | AD24: =(Assumptions!$C$32*4.333*Assumptions!$C$33+Assumptions!$C$34/12)*(1+(Assumptions!$C$35)) -> 6783.2324 | AE24: =INDEX('Seasonality Data Break down'!$F$7:$F$18,C24)*G24 -> 172.5 | AF24: =INDEX('Seasonality Data Break down'!$G$7:$G$18,C24)*G24 -> 230 | AG24: =INDEX('Seasonality Data Break down'!$H$7:$H$18,C24)*G24 -> 86.25 | AH24: =AE24+AF24+AG24 -> 488.75 | AI24: =Assumptions!$C$39 -> 150 | AJ24: =Assumptions!$C$40 -> 500 | AK24: =AA24+AB24+AC24+AD24+AH24+AI24+AJ24 -> 10196.982 | AL24: =X24*Assumptions!$C$13 -> 711.95276 | AM24: =X24*Assumptions!$C$15 -> 415.30577 | AN24: =AL24+AM24 -> 1127.2585 | AO24: =AK24+AN24 -> 11324.241 | AP24: =Z24-AO24 -> 5198.9207 | AQ24: ='Startup Costs'!$D$24/(Assumptions!$C$54*12) -> 916.66667 | AR24: =-'Loan schedule'!$D$28 -> -335.60336 | AS24: =AP24-AQ24+AR24 -> 3946.6507 | AT24: =-MAX(AS24,0)*Assumptions!$C$41 -> -986.66268 | AU24: =AS24+AT24 -> 2959.988 | AV24: =-'Loan schedule'!$E$28 -> -1064.0413 | AW24: =AU24+AQ24+AV24 -> 2812.6134 | AX24: =AY23 -> 26524.833 | AY24: =AX24+AW24 -> 29337.446 | AZ24: =IFERROR(Z24/X24,0) -> 0.69624683 | BA24: =IFERROR(AP24/X24,0) -> 0.21907019 | BB24: =IFERROR(AU24/X24,0) -> 0.12472687 | BD24: Mkt Social / Local / Referral | BE24: This month's spend per channel (Seasonality & Marketing tab), scaled up by the Growth Factor as the business grows.
A25: 18 | B25: 2 | C25: 6 | D25: ='Seasonality Data Break down'!$B$12&" Y"&B25 -> June Y2 | E25: =IF(B25=1,INDEX(Workings!$B$27:$B$38,C25),1) -> 1 | F25: =IF(B25=1,INDEX(Workings!$C$27:$C$38,C25),1) -> 1 | G25: =INDEX(Workings!$C$19:$C$23,B25) -> 1.15 | H25: =INDEX('Seasonality Data Break down'!$C$7:$C$18,C25) -> 1.1 | I25: =INDEX('Seasonality Data Break down'!$D$7:$D$18,C25) -> 0.85 | J25: =Assumptions!$C$18/12 -> 26.083333 | K25: =Assumptions!$C$19*E25*H25*G25 -> 82.225 | L25: =Assumptions!$C$20+INDEX('Seasonality Data Break down'!$E$7:$E$18,C25) -> 9.25 | M25: =K25*J25*L25 -> 19838.494 | N25: =M25*Assumptions!$C$21 -> 5951.5483 | O25: =Assumptions!$C$27*F25*I25*G25 -> 53.7625 | P25: =O25*Assumptions!$C$28 -> 2419.3125 | Q25: =Assumptions!$C$24*4.333*F25*I25*G25 -> 59.297105 | R25: =Q25*Assumptions!$C$25 -> 592.97105 | S25: =MIN(O25*Assumptions!$C$48,R25) -> 322.575 | T25: =MAX(R25-S25,0) -> 270.39605 | U25: =T25*Assumptions!$C$26 -> 3244.7526 | V25: =Q25*Assumptions!$C$29 -> 1778.9132 | W25: =P25+U25 -> 5664.0651 | X25: =M25+W25 -> 25502.559 | Y25: =N25+V25 -> 7730.4614 | Z25: =X25-Y25 -> 17772.098 | AA25: =Assumptions!$C$10*Assumptions!$C$9/12 -> 2000 | AB25: =Assumptions!$C$12/12 -> 125 | AC25: =Assumptions!$C$14/12 -> 150 | AD25: =(Assumptions!$C$32*4.333*Assumptions!$C$33+Assumptions!$C$34/12)*(1+(Assumptions!$C$35)) -> 6783.2324 | AE25: =INDEX('Seasonality Data Break down'!$F$7:$F$18,C25)*G25 -> 287.5 | AF25: =INDEX('Seasonality Data Break down'!$G$7:$G$18,C25)*G25 -> 172.5 | AG25: =INDEX('Seasonality Data Break down'!$H$7:$H$18,C25)*G25 -> 86.25 | AH25: =AE25+AF25+AG25 -> 546.25 | AI25: =Assumptions!$C$39 -> 150 | AJ25: =Assumptions!$C$40 -> 500 | AK25: =AA25+AB25+AC25+AD25+AH25+AI25+AJ25 -> 10254.482 | AL25: =X25*Assumptions!$C$13 -> 765.07678 | AM25: =X25*Assumptions!$C$15 -> 446.29479 | AN25: =AL25+AM25 -> 1211.3716 | AO25: =AK25+AN25 -> 11465.854 | AP25: =Z25-AO25 -> 6306.244 | AQ25: ='Startup Costs'!$D$24/(Assumptions!$C$54*12) -> 916.66667 | AR25: =-'Loan schedule'!$D$29 -> -328.9531 | AS25: =AP25-AQ25+AR25 -> 5060.6242 | AT25: =-MAX(AS25,0)*Assumptions!$C$41 -> -1265.1561 | AU25: =AS25+AT25 -> 3795.4682 | AV25: =-'Loan schedule'!$E$29 -> -1070.6915 | AW25: =AU25+AQ25+AV25 -> 3641.4433 | AX25: =AY24 -> 29337.446 | AY25: =AX25+AW25 -> 32978.89 | AZ25: =IFERROR(Z25/X25,0) -> 0.69687507 | BA25: =IFERROR(AP25/X25,0) -> 0.24727887 | BB25: =IFERROR(AU25/X25,0) -> 0.14882695 | BD25: Total Fixed Opex | BE25: Rent + Rates + Insurance + Wages + all 3 marketing channels + Software + Admin.
A26: 19 | B26: 2 | C26: 7 | D26: ='Seasonality Data Break down'!$B$13&" Y"&B26 -> July Y2 | E26: =IF(B26=1,INDEX(Workings!$B$27:$B$38,C26),1) -> 1 | F26: =IF(B26=1,INDEX(Workings!$C$27:$C$38,C26),1) -> 1 | G26: =INDEX(Workings!$C$19:$C$23,B26) -> 1.15 | H26: =INDEX('Seasonality Data Break down'!$C$7:$C$18,C26) -> 1.15 | I26: =INDEX('Seasonality Data Break down'!$D$7:$D$18,C26) -> 0.8 | J26: =Assumptions!$C$18/12 -> 26.083333 | K26: =Assumptions!$C$19*E26*H26*G26 -> 85.9625 | L26: =Assumptions!$C$20+INDEX('Seasonality Data Break down'!$E$7:$E$18,C26) -> 9.25 | M26: =K26*J26*L26 -> 20740.244 | N26: =M26*Assumptions!$C$21 -> 6222.0732 | O26: =Assumptions!$C$27*F26*I26*G26 -> 50.6 | P26: =O26*Assumptions!$C$28 -> 2277 | Q26: =Assumptions!$C$24*4.333*F26*I26*G26 -> 55.80904 | R26: =Q26*Assumptions!$C$25 -> 558.0904 | S26: =MIN(O26*Assumptions!$C$48,R26) -> 303.6 | T26: =MAX(R26-S26,0) -> 254.4904 | U26: =T26*Assumptions!$C$26 -> 3053.8848 | V26: =Q26*Assumptions!$C$29 -> 1674.2712 | W26: =P26+U26 -> 5330.8848 | X26: =M26+W26 -> 26071.129 | Y26: =N26+V26 -> 7896.3444 | Z26: =X26-Y26 -> 18174.784 | AA26: =Assumptions!$C$10*Assumptions!$C$9/12 -> 2000 | AB26: =Assumptions!$C$12/12 -> 125 | AC26: =Assumptions!$C$14/12 -> 150 | AD26: =(Assumptions!$C$32*4.333*Assumptions!$C$33+Assumptions!$C$34/12)*(1+(Assumptions!$C$35)) -> 6783.2324 | AE26: =INDEX('Seasonality Data Break down'!$F$7:$F$18,C26)*G26 -> 287.5 | AF26: =INDEX('Seasonality Data Break down'!$G$7:$G$18,C26)*G26 -> 172.5 | AG26: =INDEX('Seasonality Data Break down'!$H$7:$H$18,C26)*G26 -> 86.25 | AH26: =AE26+AF26+AG26 -> 546.25 | AI26: =Assumptions!$C$39 -> 150 | AJ26: =Assumptions!$C$40 -> 500 | AK26: =AA26+AB26+AC26+AD26+AH26+AI26+AJ26 -> 10254.482 | AL26: =X26*Assumptions!$C$13 -> 782.13386 | AM26: =X26*Assumptions!$C$15 -> 456.24475 | AN26: =AL26+AM26 -> 1238.3786 | AO26: =AK26+AN26 -> 11492.861 | AP26: =Z26-AO26 -> 6681.9234 | AQ26: ='Startup Costs'!$D$24/(Assumptions!$C$54*12) -> 916.66667 | AR26: =-'Loan schedule'!$D$30 -> -322.26128 | AS26: =AP26-AQ26+AR26 -> 5442.9955 | AT26: =-MAX(AS26,0)*Assumptions!$C$41 -> -1360.7489 | AU26: =AS26+AT26 -> 4082.2466 | AV26: =-'Loan schedule'!$E$30 -> -1077.3834 | AW26: =AU26+AQ26+AV26 -> 3921.5299 | AX26: =AY25 -> 32978.89 | AY26: =AX26+AW26 -> 36900.419 | AZ26: =IFERROR(Z26/X26,0) -> 0.69712303 | BA26: =IFERROR(AP26/X26,0) -> 0.2562959 | BB26: =IFERROR(AU26/X26,0) -> 0.15658112 | BD26: Utilities / Card Fees | BE26: Both calculated as a % of Total Revenue (Assumptions).
A27: 20 | B27: 2 | C27: 8 | D27: ='Seasonality Data Break down'!$B$14&" Y"&B27 -> August Y2 | E27: =IF(B27=1,INDEX(Workings!$B$27:$B$38,C27),1) -> 1 | F27: =IF(B27=1,INDEX(Workings!$C$27:$C$38,C27),1) -> 1 | G27: =INDEX(Workings!$C$19:$C$23,B27) -> 1.15 | H27: =INDEX('Seasonality Data Break down'!$C$7:$C$18,C27) -> 1 | I27: =INDEX('Seasonality Data Break down'!$D$7:$D$18,C27) -> 0.85 | J27: =Assumptions!$C$18/12 -> 26.083333 | K27: =Assumptions!$C$19*E27*H27*G27 -> 74.75 | L27: =Assumptions!$C$20+INDEX('Seasonality Data Break down'!$E$7:$E$18,C27) -> 9.25 | M27: =K27*J27*L27 -> 18034.995 | N27: =M27*Assumptions!$C$21 -> 5410.4984 | O27: =Assumptions!$C$27*F27*I27*G27 -> 53.7625 | P27: =O27*Assumptions!$C$28 -> 2419.3125 | Q27: =Assumptions!$C$24*4.333*F27*I27*G27 -> 59.297105 | R27: =Q27*Assumptions!$C$25 -> 592.97105 | S27: =MIN(O27*Assumptions!$C$48,R27) -> 322.575 | T27: =MAX(R27-S27,0) -> 270.39605 | U27: =T27*Assumptions!$C$26 -> 3244.7526 | V27: =Q27*Assumptions!$C$29 -> 1778.9132 | W27: =P27+U27 -> 5664.0651 | X27: =M27+W27 -> 23699.06 | Y27: =N27+V27 -> 7189.4116 | Z27: =X27-Y27 -> 16509.648 | AA27: =Assumptions!$C$10*Assumptions!$C$9/12 -> 2000 | AB27: =Assumptions!$C$12/12 -> 125 | AC27: =Assumptions!$C$14/12 -> 150 | AD27: =(Assumptions!$C$32*4.333*Assumptions!$C$33+Assumptions!$C$34/12)*(1+(Assumptions!$C$35)) -> 6783.2324 | AE27: =INDEX('Seasonality Data Break down'!$F$7:$F$18,C27)*G27 -> 172.5 | AF27: =INDEX('Seasonality Data Break down'!$G$7:$G$18,C27)*G27 -> 172.5 | AG27: =INDEX('Seasonality Data Break down'!$H$7:$H$18,C27)*G27 -> 86.25 | AH27: =AE27+AF27+AG27 -> 431.25 | AI27: =Assumptions!$C$39 -> 150 | AJ27: =Assumptions!$C$40 -> 500 | AK27: =AA27+AB27+AC27+AD27+AH27+AI27+AJ27 -> 10139.482 | AL27: =X27*Assumptions!$C$13 -> 710.9718 | AM27: =X27*Assumptions!$C$15 -> 414.73355 | AN27: =AL27+AM27 -> 1125.7053 | AO27: =AK27+AN27 -> 11265.188 | AP27: =Z27-AO27 -> 5244.4606 | AQ27: ='Startup Costs'!$D$24/(Assumptions!$C$54*12) -> 916.66667 | AR27: =-'Loan schedule'!$D$31 -> -315.52763 | AS27: =AP27-AQ27+AR27 -> 4012.2663 | AT27: =-MAX(AS27,0)*Assumptions!$C$41 -> -1003.0666 | AU27: =AS27+AT27 -> 3009.1997 | AV27: =-'Loan schedule'!$E$31 -> -1084.117 | AW27: =AU27+AQ27+AV27 -> 2841.7494 | AX27: =AY26 -> 36900.419 | AY27: =AX27+AW27 -> 39742.169 | AZ27: =IFERROR(Z27/X27,0) -> 0.69663727 | BA27: =IFERROR(AP27/X27,0) -> 0.22129404 | BB27: =IFERROR(AU27/X27,0) -> 0.12697549 | BD27: TOTAL OPEX | BE27: Total Fixed Opex + Total Variable Opex (Utilities + Card Fees).
A28: 21 | B28: 2 | C28: 9 | D28: ='Seasonality Data Break down'!$B$15&" Y"&B28 -> September Y2 | E28: =IF(B28=1,INDEX(Workings!$B$27:$B$38,C28),1) -> 1 | F28: =IF(B28=1,INDEX(Workings!$C$27:$C$38,C28),1) -> 1 | G28: =INDEX(Workings!$C$19:$C$23,B28) -> 1.15 | H28: =INDEX('Seasonality Data Break down'!$C$7:$C$18,C28) -> 0.95 | I28: =INDEX('Seasonality Data Break down'!$D$7:$D$18,C28) -> 1.05 | J28: =Assumptions!$C$18/12 -> 26.083333 | K28: =Assumptions!$C$19*E28*H28*G28 -> 71.0125 | L28: =Assumptions!$C$20+INDEX('Seasonality Data Break down'!$E$7:$E$18,C28) -> 8.5 | M28: =K28*J28*L28 -> 15744.063 | N28: =M28*Assumptions!$C$21 -> 4723.2189 | O28: =Assumptions!$C$27*F28*I28*G28 -> 66.4125 | P28: =O28*Assumptions!$C$28 -> 2988.5625 | Q28: =Assumptions!$C$24*4.333*F28*I28*G28 -> 73.249365 | R28: =Q28*Assumptions!$C$25 -> 732.49365 | S28: =MIN(O28*Assumptions!$C$48,R28) -> 398.475 | T28: =MAX(R28-S28,0) -> 334.01865 | U28: =T28*Assumptions!$C$26 -> 4008.2238 | V28: =Q28*Assumptions!$C$29 -> 2197.481 | W28: =P28+U28 -> 6996.7863 | X28: =M28+W28 -> 22740.849 | Y28: =N28+V28 -> 6920.6999 | Z28: =X28-Y28 -> 15820.149 | AA28: =Assumptions!$C$10*Assumptions!$C$9/12 -> 2000 | AB28: =Assumptions!$C$12/12 -> 125 | AC28: =Assumptions!$C$14/12 -> 150 | AD28: =(Assumptions!$C$32*4.333*Assumptions!$C$33+Assumptions!$C$34/12)*(1+(Assumptions!$C$35)) -> 6783.2324 | AE28: =INDEX('Seasonality Data Break down'!$F$7:$F$18,C28)*G28 -> 230 | AF28: =INDEX('Seasonality Data Break down'!$G$7:$G$18,C28)*G28 -> 230 | AG28: =INDEX('Seasonality Data Break down'!$H$7:$H$18,C28)*G28 -> 86.25 | AH28: =AE28+AF28+AG28 -> 546.25 | AI28: =Assumptions!$C$39 -> 150 | AJ28: =Assumptions!$C$40 -> 500 | AK28: =AA28+AB28+AC28+AD28+AH28+AI28+AJ28 -> 10254.482 | AL28: =X28*Assumptions!$C$13 -> 682.22548 | AM28: =X28*Assumptions!$C$15 -> 397.96486 | AN28: =AL28+AM28 -> 1080.1903 | AO28: =AK28+AN28 -> 11334.673 | AP28: =Z28-AO28 -> 4485.4768 | AQ28: ='Startup Costs'!$D$24/(Assumptions!$C$54*12) -> 916.66667 | AR28: =-'Loan schedule'!$D$32 -> -308.7519 | AS28: =AP28-AQ28+AR28 -> 3260.0582 | AT28: =-MAX(AS28,0)*Assumptions!$C$41 -> -815.01455 | AU28: =AS28+AT28 -> 2445.0436 | AV28: =-'Loan schedule'!$E$32 -> -1090.8927 | AW28: =AU28+AQ28+AV28 -> 2270.8176 | AX28: =AY27 -> 39742.169 | AY28: =AX28+AW28 -> 42012.986 | AZ28: =IFERROR(Z28/X28,0) -> 0.695671 | BA28: =IFERROR(AP28/X28,0) -> 0.19724315 | BB28: =IFERROR(AU28/X28,0) -> 0.10751769 | BD28: EBITDA | BE28: Gross Profit - Total Opex. Earnings before interest, tax, depreciation, amortisation.
A29: 22 | B29: 2 | C29: 10 | D29: ='Seasonality Data Break down'!$B$16&" Y"&B29 -> October Y2 | E29: =IF(B29=1,INDEX(Workings!$B$27:$B$38,C29),1) -> 1 | F29: =IF(B29=1,INDEX(Workings!$C$27:$C$38,C29),1) -> 1 | G29: =INDEX(Workings!$C$19:$C$23,B29) -> 1.15 | H29: =INDEX('Seasonality Data Break down'!$C$7:$C$18,C29) -> 1 | I29: =INDEX('Seasonality Data Break down'!$D$7:$D$18,C29) -> 1 | J29: =Assumptions!$C$18/12 -> 26.083333 | K29: =Assumptions!$C$19*E29*H29*G29 -> 74.75 | L29: =Assumptions!$C$20+INDEX('Seasonality Data Break down'!$E$7:$E$18,C29) -> 8.5 | M29: =K29*J29*L29 -> 16572.698 | N29: =M29*Assumptions!$C$21 -> 4971.8094 | O29: =Assumptions!$C$27*F29*I29*G29 -> 63.25 | P29: =O29*Assumptions!$C$28 -> 2846.25 | Q29: =Assumptions!$C$24*4.333*F29*I29*G29 -> 69.7613 | R29: =Q29*Assumptions!$C$25 -> 697.613 | S29: =MIN(O29*Assumptions!$C$48,R29) -> 379.5 | T29: =MAX(R29-S29,0) -> 318.113 | U29: =T29*Assumptions!$C$26 -> 3817.356 | V29: =Q29*Assumptions!$C$29 -> 2092.839 | W29: =P29+U29 -> 6663.606 | X29: =M29+W29 -> 23236.304 | Y29: =N29+V29 -> 7064.6484 | Z29: =X29-Y29 -> 16171.656 | AA29: =Assumptions!$C$10*Assumptions!$C$9/12 -> 2000 | AB29: =Assumptions!$C$12/12 -> 125 | AC29: =Assumptions!$C$14/12 -> 150 | AD29: =(Assumptions!$C$32*4.333*Assumptions!$C$33+Assumptions!$C$34/12)*(1+(Assumptions!$C$35)) -> 6783.2324 | AE29: =INDEX('Seasonality Data Break down'!$F$7:$F$18,C29)*G29 -> 172.5 | AF29: =INDEX('Seasonality Data Break down'!$G$7:$G$18,C29)*G29 -> 172.5 | AG29: =INDEX('Seasonality Data Break down'!$H$7:$H$18,C29)*G29 -> 57.5 | AH29: =AE29+AF29+AG29 -> 402.5 | AI29: =Assumptions!$C$39 -> 150 | AJ29: =Assumptions!$C$40 -> 500 | AK29: =AA29+AB29+AC29+AD29+AH29+AI29+AJ29 -> 10110.732 | AL29: =X29*Assumptions!$C$13 -> 697.08912 | AM29: =X29*Assumptions!$C$15 -> 406.63532 | AN29: =AL29+AM29 -> 1103.7244 | AO29: =AK29+AN29 -> 11214.457 | AP29: =Z29-AO29 -> 4957.1988 | AQ29: ='Startup Costs'!$D$24/(Assumptions!$C$54*12) -> 916.66667 | AR29: =-'Loan schedule'!$D$33 -> -301.93382 | AS29: =AP29-AQ29+AR29 -> 3738.5983 | AT29: =-MAX(AS29,0)*Assumptions!$C$41 -> -934.64957 | AU29: =AS29+AT29 -> 2803.9487 | AV29: =-'Loan schedule'!$E$33 -> -1097.7108 | AW29: =AU29+AQ29+AV29 -> 2622.9045 | AX29: =AY28 -> 42012.986 | AY29: =AX29+AW29 -> 44635.891 | AZ29: =IFERROR(Z29/X29,0) -> 0.69596506 | BA29: =IFERROR(AP29/X29,0) -> 0.21333852 | BB29: =IFERROR(AU29/X29,0) -> 0.12067103 | BD29: Depreciation | BE29: Capitalised startup fixed assets (Startup Costs tab) spread evenly over their useful life (Assumptions).
A30: 23 | B30: 2 | C30: 11 | D30: ='Seasonality Data Break down'!$B$17&" Y"&B30 -> November Y2 | E30: =IF(B30=1,INDEX(Workings!$B$27:$B$38,C30),1) -> 1 | F30: =IF(B30=1,INDEX(Workings!$C$27:$C$38,C30),1) -> 1 | G30: =INDEX(Workings!$C$19:$C$23,B30) -> 1.15 | H30: =INDEX('Seasonality Data Break down'!$C$7:$C$18,C30) -> 1.05 | I30: =INDEX('Seasonality Data Break down'!$D$7:$D$18,C30) -> 0.95 | J30: =Assumptions!$C$18/12 -> 26.083333 | K30: =Assumptions!$C$19*E30*H30*G30 -> 78.4875 | L30: =Assumptions!$C$20+INDEX('Seasonality Data Break down'!$E$7:$E$18,C30) -> 8.5 | M30: =K30*J30*L30 -> 17401.333 | N30: =M30*Assumptions!$C$21 -> 5220.3998 | O30: =Assumptions!$C$27*F30*I30*G30 -> 60.0875 | P30: =O30*Assumptions!$C$28 -> 2703.9375 | Q30: =Assumptions!$C$24*4.333*F30*I30*G30 -> 66.273235 | R30: =Q30*Assumptions!$C$25 -> 662.73235 | S30: =MIN(O30*Assumptions!$C$48,R30) -> 360.525 | T30: =MAX(R30-S30,0) -> 302.20735 | U30: =T30*Assumptions!$C$26 -> 3626.4882 | V30: =Q30*Assumptions!$C$29 -> 1988.197 | W30: =P30+U30 -> 6330.4257 | X30: =M30+W30 -> 23731.759 | Y30: =N30+V30 -> 7208.5969 | Z30: =X30-Y30 -> 16523.162 | AA30: =Assumptions!$C$10*Assumptions!$C$9/12 -> 2000 | AB30: =Assumptions!$C$12/12 -> 125 | AC30: =Assumptions!$C$14/12 -> 150 | AD30: =(Assumptions!$C$32*4.333*Assumptions!$C$33+Assumptions!$C$34/12)*(1+(Assumptions!$C$35)) -> 6783.2324 | AE30: =INDEX('Seasonality Data Break down'!$F$7:$F$18,C30)*G30 -> 287.5 | AF30: =INDEX('Seasonality Data Break down'!$G$7:$G$18,C30)*G30 -> 230 | AG30: =INDEX('Seasonality Data Break down'!$H$7:$H$18,C30)*G30 -> 86.25 | AH30: =AE30+AF30+AG30 -> 603.75 | AI30: =Assumptions!$C$39 -> 150 | AJ30: =Assumptions!$C$40 -> 500 | AK30: =AA30+AB30+AC30+AD30+AH30+AI30+AJ30 -> 10311.982 | AL30: =X30*Assumptions!$C$13 -> 711.95276 | AM30: =X30*Assumptions!$C$15 -> 415.30577 | AN30: =AL30+AM30 -> 1127.2585 | AO30: =AK30+AN30 -> 11439.241 | AP30: =Z30-AO30 -> 5083.9207 | AQ30: ='Startup Costs'!$D$24/(Assumptions!$C$54*12) -> 916.66667 | AR30: =-'Loan schedule'!$D$34 -> -295.07313 | AS30: =AP30-AQ30+AR30 -> 3872.1809 | AT30: =-MAX(AS30,0)*Assumptions!$C$41 -> -968.04523 | AU30: =AS30+AT30 -> 2904.1357 | AV30: =-'Loan schedule'!$E$34 -> -1104.5715 | AW30: =AU30+AQ30+AV30 -> 2716.2309 | AX30: =AY29 -> 44635.891 | AY30: =AX30+AW30 -> 47352.122 | AZ30: =IFERROR(Z30/X30,0) -> 0.69624683 | BA30: =IFERROR(AP30/X30,0) -> 0.21422436 | BB30: =IFERROR(AU30/X30,0) -> 0.12237339 | BD30: Loan Interest / Principal | BE30: This month's split of the loan repayment, pulled from the Loan Schedule tab.
A31: 24 | B31: 2 | C31: 12 | D31: ='Seasonality Data Break down'!$B$18&" Y"&B31 -> December Y2 | E31: =IF(B31=1,INDEX(Workings!$B$27:$B$38,C31),1) -> 1 | F31: =IF(B31=1,INDEX(Workings!$C$27:$C$38,C31),1) -> 1 | G31: =INDEX(Workings!$C$19:$C$23,B31) -> 1.15 | H31: =INDEX('Seasonality Data Break down'!$C$7:$C$18,C31) -> 1.2 | I31: =INDEX('Seasonality Data Break down'!$D$7:$D$18,C31) -> 0.8 | J31: =Assumptions!$C$18/12 -> 26.083333 | K31: =Assumptions!$C$19*E31*H31*G31 -> 89.7 | L31: =Assumptions!$C$20+INDEX('Seasonality Data Break down'!$E$7:$E$18,C31) -> 8.5 | M31: =K31*J31*L31 -> 19887.237 | N31: =M31*Assumptions!$C$21 -> 5966.1712 | O31: =Assumptions!$C$27*F31*I31*G31 -> 50.6 | P31: =O31*Assumptions!$C$28 -> 2277 | Q31: =Assumptions!$C$24*4.333*F31*I31*G31 -> 55.80904 | R31: =Q31*Assumptions!$C$25 -> 558.0904 | S31: =MIN(O31*Assumptions!$C$48,R31) -> 303.6 | T31: =MAX(R31-S31,0) -> 254.4904 | U31: =T31*Assumptions!$C$26 -> 3053.8848 | V31: =Q31*Assumptions!$C$29 -> 1674.2712 | W31: =P31+U31 -> 5330.8848 | X31: =M31+W31 -> 25218.122 | Y31: =N31+V31 -> 7640.4424 | Z31: =X31-Y31 -> 17577.68 | AA31: =Assumptions!$C$10*Assumptions!$C$9/12 -> 2000 | AB31: =Assumptions!$C$12/12 -> 125 | AC31: =Assumptions!$C$14/12 -> 150 | AD31: =(Assumptions!$C$32*4.333*Assumptions!$C$33+Assumptions!$C$34/12)*(1+(Assumptions!$C$35)) -> 6783.2324 | AE31: =INDEX('Seasonality Data Break down'!$F$7:$F$18,C31)*G31 -> 345 | AF31: =INDEX('Seasonality Data Break down'!$G$7:$G$18,C31)*G31 -> 287.5 | AG31: =INDEX('Seasonality Data Break down'!$H$7:$H$18,C31)*G31 -> 115 | AH31: =AE31+AF31+AG31 -> 747.5 | AI31: =Assumptions!$C$39 -> 150 | AJ31: =Assumptions!$C$40 -> 500 | AK31: =AA31+AB31+AC31+AD31+AH31+AI31+AJ31 -> 10455.732 | AL31: =X31*Assumptions!$C$13 -> 756.54367 | AM31: =X31*Assumptions!$C$15 -> 441.31714 | AN31: =AL31+AM31 -> 1197.8608 | AO31: =AK31+AN31 -> 11653.593 | AP31: =Z31-AO31 -> 5924.0867 | AQ31: ='Startup Costs'!$D$24/(Assumptions!$C$54*12) -> 916.66667 | AR31: =-'Loan schedule'!$D$35 -> -288.16956 | AS31: =AP31-AQ31+AR31 -> 4719.2505 | AT31: =-MAX(AS31,0)*Assumptions!$C$41 -> -1179.8126 | AU31: =AS31+AT31 -> 3539.4378 | AV31: =-'Loan schedule'!$E$35 -> -1111.4751 | AW31: =AU31+AQ31+AV31 -> 3344.6294 | AX31: =AY30 -> 47352.122 | AY31: =AX31+AW31 -> 50696.751 | AZ31: =IFERROR(Z31/X31,0) -> 0.69702572 | BA31: =IFERROR(AP31/X31,0) -> 0.23491387 | BB31: =IFERROR(AU31/X31,0) -> 0.14035295 | BD31: NPBT / Tax / NPAT | BE31: EBITDA - Depreciation + Interest = profit before tax; tax = profit x corporation tax rate (if positive); NPAT = profit after tax.
A32: 25 | B32: 3 | C32: 1 | D32: ='Seasonality Data Break down'!$B$7&" Y"&B32 -> January Y3 | E32: =IF(B32=1,INDEX(Workings!$B$27:$B$38,C32),1) -> 1 | F32: =IF(B32=1,INDEX(Workings!$C$27:$C$38,C32),1) -> 1 | G32: =INDEX(Workings!$C$19:$C$23,B32) -> 1.242 | H32: =INDEX('Seasonality Data Break down'!$C$7:$C$18,C32) -> 0.85 | I32: =INDEX('Seasonality Data Break down'!$D$7:$D$18,C32) -> 1.3 | J32: =Assumptions!$C$18/12 -> 26.083333 | K32: =Assumptions!$C$19*E32*H32*G32 -> 68.6205 | L32: =Assumptions!$C$20+INDEX('Seasonality Data Break down'!$E$7:$E$18,C32) -> 8.5 | M32: =K32*J32*L32 -> 15213.737 | N32: =M32*Assumptions!$C$21 -> 4564.121 | O32: =Assumptions!$C$27*F32*I32*G32 -> 88.803 | P32: =O32*Assumptions!$C$28 -> 3996.135 | Q32: =Assumptions!$C$24*4.333*F32*I32*G32 -> 97.944865 | R32: =Q32*Assumptions!$C$25 -> 979.44865 | S32: =MIN(O32*Assumptions!$C$48,R32) -> 532.818 | T32: =MAX(R32-S32,0) -> 446.63065 | U32: =T32*Assumptions!$C$26 -> 5359.5678 | V32: =Q32*Assumptions!$C$29 -> 2938.346 | W32: =P32+U32 -> 9355.7028 | X32: =M32+W32 -> 24569.44 | Y32: =N32+V32 -> 7502.467 | Z32: =X32-Y32 -> 17066.973 | AA32: =Assumptions!$C$10*Assumptions!$C$9/12 -> 2000 | AB32: =Assumptions!$C$12/12 -> 125 | AC32: =Assumptions!$C$14/12 -> 150 | AD32: =(Assumptions!$C$32*4.333*Assumptions!$C$33+Assumptions!$C$34/12)*(1+(Assumptions!$C$35)) -> 6783.2324 | AE32: =INDEX('Seasonality Data Break down'!$F$7:$F$18,C32)*G32 -> 372.6 | AF32: =INDEX('Seasonality Data Break down'!$G$7:$G$18,C32)*G32 -> 186.3 | AG32: =INDEX('Seasonality Data Break down'!$H$7:$H$18,C32)*G32 -> 62.1 | AH32: =AE32+AF32+AG32 -> 621 | AI32: =Assumptions!$C$39 -> 150 | AJ32: =Assumptions!$C$40 -> 500 | AK32: =AA32+AB32+AC32+AD32+AH32+AI32+AJ32 -> 10329.232 | AL32: =X32*Assumptions!$C$13 -> 737.08319 | AM32: =X32*Assumptions!$C$15 -> 429.96519 | AN32: =AL32+AM32 -> 1167.0484 | AO32: =AK32+AN32 -> 11496.281 | AP32: =Z32-AO32 -> 5570.6918 | AQ32: ='Startup Costs'!$D$24/(Assumptions!$C$54*12) -> 916.66667 | AR32: =-'Loan schedule'!$D$36 -> -281.22284 | AS32: =AP32-AQ32+AR32 -> 4372.8023 | AT32: =-MAX(AS32,0)*Assumptions!$C$41 -> -1093.2006 | AU32: =AS32+AT32 -> 3279.6017 | AV32: =-'Loan schedule'!$E$36 -> -1118.4218 | AW32: =AU32+AQ32+AV32 -> 3077.8466 | AX32: =AY31 -> 50696.751 | AY32: =AX32+AW32 -> 53774.598 | AZ32: =IFERROR(Z32/X32,0) -> 0.69464232 | BA32: =IFERROR(AP32/X32,0) -> 0.22673256 | BB32: =IFERROR(AU32/X32,0) -> 0.13348297 | BD32: Net Cash Flow | BE32: NPAT + Depreciation (added back, it's non-cash) + Loan Principal (cash out, not in NPAT).
A33: 26 | B33: 3 | C33: 2 | D33: ='Seasonality Data Break down'!$B$8&" Y"&B33 -> February Y3 | E33: =IF(B33=1,INDEX(Workings!$B$27:$B$38,C33),1) -> 1 | F33: =IF(B33=1,INDEX(Workings!$C$27:$C$38,C33),1) -> 1 | G33: =INDEX(Workings!$C$19:$C$23,B33) -> 1.242 | H33: =INDEX('Seasonality Data Break down'!$C$7:$C$18,C33) -> 0.9 | I33: =INDEX('Seasonality Data Break down'!$D$7:$D$18,C33) -> 1.2 | J33: =Assumptions!$C$18/12 -> 26.083333 | K33: =Assumptions!$C$19*E33*H33*G33 -> 72.657 | L33: =Assumptions!$C$20+INDEX('Seasonality Data Break down'!$E$7:$E$18,C33) -> 8.5 | M33: =K33*J33*L33 -> 16108.662 | N33: =M33*Assumptions!$C$21 -> 4832.5987 | O33: =Assumptions!$C$27*F33*I33*G33 -> 81.972 | P33: =O33*Assumptions!$C$28 -> 3688.74 | Q33: =Assumptions!$C$24*4.333*F33*I33*G33 -> 90.410645 | R33: =Q33*Assumptions!$C$25 -> 904.10645 | S33: =MIN(O33*Assumptions!$C$48,R33) -> 491.832 | T33: =MAX(R33-S33,0) -> 412.27445 | U33: =T33*Assumptions!$C$26 -> 4947.2934 | V33: =Q33*Assumptions!$C$29 -> 2712.3193 | W33: =P33+U33 -> 8636.0334 | X33: =M33+W33 -> 24744.696 | Y33: =N33+V33 -> 7544.9181 | Z33: =X33-Y33 -> 17199.778 | AA33: =Assumptions!$C$10*Assumptions!$C$9/12 -> 2000 | AB33: =Assumptions!$C$12/12 -> 125 | AC33: =Assumptions!$C$14/12 -> 150 | AD33: =(Assumptions!$C$32*4.333*Assumptions!$C$33+Assumptions!$C$34/12)*(1+(Assumptions!$C$35)) -> 6783.2324 | AE33: =INDEX('Seasonality Data Break down'!$F$7:$F$18,C33)*G33 -> 248.4 | AF33: =INDEX('Seasonality Data Break down'!$G$7:$G$18,C33)*G33 -> 186.3 | AG33: =INDEX('Seasonality Data Break down'!$H$7:$H$18,C33)*G33 -> 62.1 | AH33: =AE33+AF33+AG33 -> 496.8 | AI33: =Assumptions!$C$39 -> 150 | AJ33: =Assumptions!$C$40 -> 500 | AK33: =AA33+AB33+AC33+AD33+AH33+AI33+AJ33 -> 10205.032 | AL33: =X33*Assumptions!$C$13 -> 742.34087 | AM33: =X33*Assumptions!$C$15 -> 433.03218 | AN33: =AL33+AM33 -> 1175.373 | AO33: =AK33+AN33 -> 11380.405 | AP33: =Z33-AO33 -> 5819.3723 | AQ33: ='Startup Costs'!$D$24/(Assumptions!$C$54*12) -> 916.66667 | AR33: =-'Loan schedule'!$D$37 -> -274.2327 | AS33: =AP33-AQ33+AR33 -> 4628.4729 | AT33: =-MAX(AS33,0)*Assumptions!$C$41 -> -1157.1182 | AU33: =AS33+AT33 -> 3471.3547 | AV33: =-'Loan schedule'!$E$37 -> -1125.4119 | AW33: =AU33+AQ33+AV33 -> 3262.6094 | AX33: =AY32 -> 53774.598 | AY33: =AX33+AW33 -> 57037.207 | AZ33: =IFERROR(Z33/X33,0) -> 0.69508948 | BA33: =IFERROR(AP33/X33,0) -> 0.23517655 | BB33: =IFERROR(AU33/X33,0) -> 0.14028682 | BD33: Opening / Closing Cash | BE33: Running cash balance: this month's opening = last month's closing; closing = opening + Net Cash Flow.
A34: 27 | B34: 3 | C34: 3 | D34: ='Seasonality Data Break down'!$B$9&" Y"&B34 -> March Y3 | E34: =IF(B34=1,INDEX(Workings!$B$27:$B$38,C34),1) -> 1 | F34: =IF(B34=1,INDEX(Workings!$C$27:$C$38,C34),1) -> 1 | G34: =INDEX(Workings!$C$19:$C$23,B34) -> 1.242 | H34: =INDEX('Seasonality Data Break down'!$C$7:$C$18,C34) -> 0.95 | I34: =INDEX('Seasonality Data Break down'!$D$7:$D$18,C34) -> 1.05 | J34: =Assumptions!$C$18/12 -> 26.083333 | K34: =Assumptions!$C$19*E34*H34*G34 -> 76.6935 | L34: =Assumptions!$C$20+INDEX('Seasonality Data Break down'!$E$7:$E$18,C34) -> 8.5 | M34: =K34*J34*L34 -> 17003.588 | N34: =M34*Assumptions!$C$21 -> 5101.0764 | O34: =Assumptions!$C$27*F34*I34*G34 -> 71.7255 | P34: =O34*Assumptions!$C$28 -> 3227.6475 | Q34: =Assumptions!$C$24*4.333*F34*I34*G34 -> 79.109314 | R34: =Q34*Assumptions!$C$25 -> 791.09314 | S34: =MIN(O34*Assumptions!$C$48,R34) -> 430.353 | T34: =MAX(R34-S34,0) -> 360.74014 | U34: =T34*Assumptions!$C$26 -> 4328.8817 | V34: =Q34*Assumptions!$C$29 -> 2373.2794 | W34: =P34+U34 -> 7556.5292 | X34: =M34+W34 -> 24560.117 | Y34: =N34+V34 -> 7474.3558 | Z34: =X34-Y34 -> 17085.761 | AA34: =Assumptions!$C$10*Assumptions!$C$9/12 -> 2000 | AB34: =Assumptions!$C$12/12 -> 125 | AC34: =Assumptions!$C$14/12 -> 150 | AD34: =(Assumptions!$C$32*4.333*Assumptions!$C$33+Assumptions!$C$34/12)*(1+(Assumptions!$C$35)) -> 6783.2324 | AE34: =INDEX('Seasonality Data Break down'!$F$7:$F$18,C34)*G34 -> 186.3 | AF34: =INDEX('Seasonality Data Break down'!$G$7:$G$18,C34)*G34 -> 186.3 | AG34: =INDEX('Seasonality Data Break down'!$H$7:$H$18,C34)*G34 -> 62.1 | AH34: =AE34+AF34+AG34 -> 434.7 | AI34: =Assumptions!$C$39 -> 150 | AJ34: =Assumptions!$C$40 -> 500 | AK34: =AA34+AB34+AC34+AD34+AH34+AI34+AJ34 -> 10142.932 | AL34: =X34*Assumptions!$C$13 -> 736.80352 | AM34: =X34*Assumptions!$C$15 -> 429.80205 | AN34: =AL34+AM34 -> 1166.6056 | AO34: =AK34+AN34 -> 11309.538 | AP34: =Z34-AO34 -> 5776.2235 | AQ34: ='Startup Costs'!$D$24/(Assumptions!$C$54*12) -> 916.66667 | AR34: =-'Loan schedule'!$D$38 -> -267.19888 | AS34: =AP34-AQ34+AR34 -> 4592.358 | AT34: =-MAX(AS34,0)*Assumptions!$C$41 -> -1148.0895 | AU34: =AS34+AT34 -> 3444.2685 | AV34: =-'Loan schedule'!$E$38 -> -1132.4458 | AW34: =AU34+AQ34+AV34 -> 3228.4894 | AX34: =AY33 -> 57037.207 | AY34: =AX34+AW34 -> 60265.697 | AZ34: =IFERROR(Z34/X34,0) -> 0.695671 | BA34: =IFERROR(AP34/X34,0) -> 0.23518713 | BB34: =IFERROR(AU34/X34,0) -> 0.14023827 | BD34: Margin % columns | BE34: Gross Profit, EBITDA, or NPAT divided by Total Revenue, as a percentage.
A35: 28 | B35: 3 | C35: 4 | D35: ='Seasonality Data Break down'!$B$10&" Y"&B35 -> April Y3 | E35: =IF(B35=1,INDEX(Workings!$B$27:$B$38,C35),1) -> 1 | F35: =IF(B35=1,INDEX(Workings!$C$27:$C$38,C35),1) -> 1 | G35: =INDEX(Workings!$C$19:$C$23,B35) -> 1.242 | H35: =INDEX('Seasonality Data Break down'!$C$7:$C$18,C35) -> 1 | I35: =INDEX('Seasonality Data Break down'!$D$7:$D$18,C35) -> 1 | J35: =Assumptions!$C$18/12 -> 26.083333 | K35: =Assumptions!$C$19*E35*H35*G35 -> 80.73 | L35: =Assumptions!$C$20+INDEX('Seasonality Data Break down'!$E$7:$E$18,C35) -> 8.5 | M35: =K35*J35*L35 -> 17898.514 | N35: =M35*Assumptions!$C$21 -> 5369.5541 | O35: =Assumptions!$C$27*F35*I35*G35 -> 68.31 | P35: =O35*Assumptions!$C$28 -> 3073.95 | Q35: =Assumptions!$C$24*4.333*F35*I35*G35 -> 75.342204 | R35: =Q35*Assumptions!$C$25 -> 753.42204 | S35: =MIN(O35*Assumptions!$C$48,R35) -> 409.86 | T35: =MAX(R35-S35,0) -> 343.56204 | U35: =T35*Assumptions!$C$26 -> 4122.7445 | V35: =Q35*Assumptions!$C$29 -> 2260.2661 | W35: =P35+U35 -> 7196.6945 | X35: =M35+W35 -> 25095.208 | Y35: =N35+V35 -> 7629.8202 | Z35: =X35-Y35 -> 17465.388 | AA35: =Assumptions!$C$10*Assumptions!$C$9/12 -> 2000 | AB35: =Assumptions!$C$12/12 -> 125 | AC35: =Assumptions!$C$14/12 -> 150 | AD35: =(Assumptions!$C$32*4.333*Assumptions!$C$33+Assumptions!$C$34/12)*(1+(Assumptions!$C$35)) -> 6783.2324 | AE35: =INDEX('Seasonality Data Break down'!$F$7:$F$18,C35)*G35 -> 186.3 | AF35: =INDEX('Seasonality Data Break down'!$G$7:$G$18,C35)*G35 -> 186.3 | AG35: =INDEX('Seasonality Data Break down'!$H$7:$H$18,C35)*G35 -> 93.15 | AH35: =AE35+AF35+AG35 -> 465.75 | AI35: =Assumptions!$C$39 -> 150 | AJ35: =Assumptions!$C$40 -> 500 | AK35: =AA35+AB35+AC35+AD35+AH35+AI35+AJ35 -> 10173.982 | AL35: =X35*Assumptions!$C$13 -> 752.85625 | AM35: =X35*Assumptions!$C$15 -> 439.16614 | AN35: =AL35+AM35 -> 1192.0224 | AO35: =AK35+AN35 -> 11366.005 | AP35: =Z35-AO35 -> 6099.3832 | AQ35: ='Startup Costs'!$D$24/(Assumptions!$C$54*12) -> 916.66667 | AR35: =-'Loan schedule'!$D$39 -> -260.12109 | AS35: =AP35-AQ35+AR35 -> 4922.5955 | AT35: =-MAX(AS35,0)*Assumptions!$C$41 -> -1230.6489 | AU35: =AS35+AT35 -> 3691.9466 | AV35: =-'Loan schedule'!$E$39 -> -1139.5235 | AW35: =AU35+AQ35+AV35 -> 3469.0897 | AX35: =AY34 -> 60265.697 | AY35: =AX35+AW35 -> 63734.786 | AZ35: =IFERROR(Z35/X35,0) -> 0.69596506 | BA35: =IFERROR(AP35/X35,0) -> 0.24304972 | BB35: =IFERROR(AU35/X35,0) -> 0.14711759
A36: 29 | B36: 3 | C36: 5 | D36: ='Seasonality Data Break down'!$B$11&" Y"&B36 -> May Y3 | E36: =IF(B36=1,INDEX(Workings!$B$27:$B$38,C36),1) -> 1 | F36: =IF(B36=1,INDEX(Workings!$C$27:$C$38,C36),1) -> 1 | G36: =INDEX(Workings!$C$19:$C$23,B36) -> 1.242 | H36: =INDEX('Seasonality Data Break down'!$C$7:$C$18,C36) -> 1.05 | I36: =INDEX('Seasonality Data Break down'!$D$7:$D$18,C36) -> 0.95 | J36: =Assumptions!$C$18/12 -> 26.083333 | K36: =Assumptions!$C$19*E36*H36*G36 -> 84.7665 | L36: =Assumptions!$C$20+INDEX('Seasonality Data Break down'!$E$7:$E$18,C36) -> 8.5 | M36: =K36*J36*L36 -> 18793.439 | N36: =M36*Assumptions!$C$21 -> 5638.0318 | O36: =Assumptions!$C$27*F36*I36*G36 -> 64.8945 | P36: =O36*Assumptions!$C$28 -> 2920.2525 | Q36: =Assumptions!$C$24*4.333*F36*I36*G36 -> 71.575094 | R36: =Q36*Assumptions!$C$25 -> 715.75094 | S36: =MIN(O36*Assumptions!$C$48,R36) -> 389.367 | T36: =MAX(R36-S36,0) -> 326.38394 | U36: =T36*Assumptions!$C$26 -> 3916.6073 | V36: =Q36*Assumptions!$C$29 -> 2147.2528 | W36: =P36+U36 -> 6836.8598 | X36: =M36+W36 -> 25630.299 | Y36: =N36+V36 -> 7785.2846 | Z36: =X36-Y36 -> 17845.015 | AA36: =Assumptions!$C$10*Assumptions!$C$9/12 -> 2000 | AB36: =Assumptions!$C$12/12 -> 125 | AC36: =Assumptions!$C$14/12 -> 150 | AD36: =(Assumptions!$C$32*4.333*Assumptions!$C$33+Assumptions!$C$34/12)*(1+(Assumptions!$C$35)) -> 6783.2324 | AE36: =INDEX('Seasonality Data Break down'!$F$7:$F$18,C36)*G36 -> 186.3 | AF36: =INDEX('Seasonality Data Break down'!$G$7:$G$18,C36)*G36 -> 248.4 | AG36: =INDEX('Seasonality Data Break down'!$H$7:$H$18,C36)*G36 -> 93.15 | AH36: =AE36+AF36+AG36 -> 527.85 | AI36: =Assumptions!$C$39 -> 150 | AJ36: =Assumptions!$C$40 -> 500 | AK36: =AA36+AB36+AC36+AD36+AH36+AI36+AJ36 -> 10236.082 | AL36: =X36*Assumptions!$C$13 -> 768.90898 | AM36: =X36*Assumptions!$C$15 -> 448.53024 | AN36: =AL36+AM36 -> 1217.4392 | AO36: =AK36+AN36 -> 11453.522 | AP36: =Z36-AO36 -> 6391.493 | AQ36: ='Startup Costs'!$D$24/(Assumptions!$C$54*12) -> 916.66667 | AR36: =-'Loan schedule'!$D$40 -> -252.99907 | AS36: =AP36-AQ36+AR36 -> 5221.8272 | AT36: =-MAX(AS36,0)*Assumptions!$C$41 -> -1305.4568 | AU36: =AS36+AT36 -> 3916.3704 | AV36: =-'Loan schedule'!$E$40 -> -1146.6456 | AW36: =AU36+AQ36+AV36 -> 3686.3915 | AX36: =AY35 -> 63734.786 | AY36: =AX36+AW36 -> 67421.178 | AZ36: =IFERROR(Z36/X36,0) -> 0.69624683 | BA36: =IFERROR(AP36/X36,0) -> 0.24937255 | BB36: =IFERROR(AU36/X36,0) -> 0.15280237
A37: 30 | B37: 3 | C37: 6 | D37: ='Seasonality Data Break down'!$B$12&" Y"&B37 -> June Y3 | E37: =IF(B37=1,INDEX(Workings!$B$27:$B$38,C37),1) -> 1 | F37: =IF(B37=1,INDEX(Workings!$C$27:$C$38,C37),1) -> 1 | G37: =INDEX(Workings!$C$19:$C$23,B37) -> 1.242 | H37: =INDEX('Seasonality Data Break down'!$C$7:$C$18,C37) -> 1.1 | I37: =INDEX('Seasonality Data Break down'!$D$7:$D$18,C37) -> 0.85 | J37: =Assumptions!$C$18/12 -> 26.083333 | K37: =Assumptions!$C$19*E37*H37*G37 -> 88.803 | L37: =Assumptions!$C$20+INDEX('Seasonality Data Break down'!$E$7:$E$18,C37) -> 9.25 | M37: =K37*J37*L37 -> 21425.574 | N37: =M37*Assumptions!$C$21 -> 6427.6721 | O37: =Assumptions!$C$27*F37*I37*G37 -> 58.0635 | P37: =O37*Assumptions!$C$28 -> 2612.8575 | Q37: =Assumptions!$C$24*4.333*F37*I37*G37 -> 64.040873 | R37: =Q37*Assumptions!$C$25 -> 640.40873 | S37: =MIN(O37*Assumptions!$C$48,R37) -> 348.381 | T37: =MAX(R37-S37,0) -> 292.02773 | U37: =T37*Assumptions!$C$26 -> 3504.3328 | V37: =Q37*Assumptions!$C$29 -> 1921.2262 | W37: =P37+U37 -> 6117.1903 | X37: =M37+W37 -> 27542.764 | Y37: =N37+V37 -> 8348.8983 | Z37: =X37-Y37 -> 19193.866 | AA37: =Assumptions!$C$10*Assumptions!$C$9/12 -> 2000 | AB37: =Assumptions!$C$12/12 -> 125 | AC37: =Assumptions!$C$14/12 -> 150 | AD37: =(Assumptions!$C$32*4.333*Assumptions!$C$33+Assumptions!$C$34/12)*(1+(Assumptions!$C$35)) -> 6783.2324 | AE37: =INDEX('Seasonality Data Break down'!$F$7:$F$18,C37)*G37 -> 310.5 | AF37: =INDEX('Seasonality Data Break down'!$G$7:$G$18,C37)*G37 -> 186.3 | AG37: =INDEX('Seasonality Data Break down'!$H$7:$H$18,C37)*G37 -> 93.15 | AH37: =AE37+AF37+AG37 -> 589.95 | AI37: =Assumptions!$C$39 -> 150 | AJ37: =Assumptions!$C$40 -> 500 | AK37: =AA37+AB37+AC37+AD37+AH37+AI37+AJ37 -> 10298.182 | AL37: =X37*Assumptions!$C$13 -> 826.28292 | AM37: =X37*Assumptions!$C$15 -> 481.99837 | AN37: =AL37+AM37 -> 1308.2813 | AO37: =AK37+AN37 -> 11606.464 | AP37: =Z37-AO37 -> 7587.4021 | AQ37: ='Startup Costs'!$D$24/(Assumptions!$C$54*12) -> 916.66667 | AR37: =-'Loan schedule'!$D$41 -> -245.83254 | AS37: =AP37-AQ37+AR37 -> 6424.9029 | AT37: =-MAX(AS37,0)*Assumptions!$C$41 -> -1606.2257 | AU37: =AS37+AT37 -> 4818.6772 | AV37: =-'Loan schedule'!$E$41 -> -1153.8121 | AW37: =AU37+AQ37+AV37 -> 4581.5318 | AX37: =AY36 -> 67421.178 | AY37: =AX37+AW37 -> 72002.71 | AZ37: =IFERROR(Z37/X37,0) -> 0.69687507 | BA37: =IFERROR(AP37/X37,0) -> 0.27547715 | BB37: =IFERROR(AU37/X37,0) -> 0.17495256
A38: 31 | B38: 3 | C38: 7 | D38: ='Seasonality Data Break down'!$B$13&" Y"&B38 -> July Y3 | E38: =IF(B38=1,INDEX(Workings!$B$27:$B$38,C38),1) -> 1 | F38: =IF(B38=1,INDEX(Workings!$C$27:$C$38,C38),1) -> 1 | G38: =INDEX(Workings!$C$19:$C$23,B38) -> 1.242 | H38: =INDEX('Seasonality Data Break down'!$C$7:$C$18,C38) -> 1.15 | I38: =INDEX('Seasonality Data Break down'!$D$7:$D$18,C38) -> 0.8 | J38: =Assumptions!$C$18/12 -> 26.083333 | K38: =Assumptions!$C$19*E38*H38*G38 -> 92.8395 | L38: =Assumptions!$C$20+INDEX('Seasonality Data Break down'!$E$7:$E$18,C38) -> 9.25 | M38: =K38*J38*L38 -> 22399.464 | N38: =M38*Assumptions!$C$21 -> 6719.8391 | O38: =Assumptions!$C$27*F38*I38*G38 -> 54.648 | P38: =O38*Assumptions!$C$28 -> 2459.16 | Q38: =Assumptions!$C$24*4.333*F38*I38*G38 -> 60.273763 | R38: =Q38*Assumptions!$C$25 -> 602.73763 | S38: =MIN(O38*Assumptions!$C$48,R38) -> 327.888 | T38: =MAX(R38-S38,0) -> 274.84963 | U38: =T38*Assumptions!$C$26 -> 3298.1956 | V38: =Q38*Assumptions!$C$29 -> 1808.2129 | W38: =P38+U38 -> 5757.3556 | X38: =M38+W38 -> 28156.819 | Y38: =N38+V38 -> 8528.052 | Z38: =X38-Y38 -> 19628.767 | AA38: =Assumptions!$C$10*Assumptions!$C$9/12 -> 2000 | AB38: =Assumptions!$C$12/12 -> 125 | AC38: =Assumptions!$C$14/12 -> 150 | AD38: =(Assumptions!$C$32*4.333*Assumptions!$C$33+Assumptions!$C$34/12)*(1+(Assumptions!$C$35)) -> 6783.2324 | AE38: =INDEX('Seasonality Data Break down'!$F$7:$F$18,C38)*G38 -> 310.5 | AF38: =INDEX('Seasonality Data Break down'!$G$7:$G$18,C38)*G38 -> 186.3 | AG38: =INDEX('Seasonality Data Break down'!$H$7:$H$18,C38)*G38 -> 93.15 | AH38: =AE38+AF38+AG38 -> 589.95 | AI38: =Assumptions!$C$39 -> 150 | AJ38: =Assumptions!$C$40 -> 500 | AK38: =AA38+AB38+AC38+AD38+AH38+AI38+AJ38 -> 10298.182 | AL38: =X38*Assumptions!$C$13 -> 844.70457 | AM38: =X38*Assumptions!$C$15 -> 492.74433 | AN38: =AL38+AM38 -> 1337.4489 | AO38: =AK38+AN38 -> 11635.631 | AP38: =Z38-AO38 -> 7993.1359 | AQ38: ='Startup Costs'!$D$24/(Assumptions!$C$54*12) -> 916.66667 | AR38: =-'Loan schedule'!$D$42 -> -238.62121 | AS38: =AP38-AQ38+AR38 -> 6837.848 | AT38: =-MAX(AS38,0)*Assumptions!$C$41 -> -1709.462 | AU38: =AS38+AT38 -> 5128.386 | AV38: =-'Loan schedule'!$E$42 -> -1161.0234 | AW38: =AU38+AQ38+AV38 -> 4884.0293 | AX38: =AY37 -> 72002.71 | AY38: =AX38+AW38 -> 76886.739 | AZ38: =IFERROR(Z38/X38,0) -> 0.69712303 | BA38: =IFERROR(AP38/X38,0) -> 0.28387922 | BB38: =IFERROR(AU38/X38,0) -> 0.18213655
A39: 32 | B39: 3 | C39: 8 | D39: ='Seasonality Data Break down'!$B$14&" Y"&B39 -> August Y3 | E39: =IF(B39=1,INDEX(Workings!$B$27:$B$38,C39),1) -> 1 | F39: =IF(B39=1,INDEX(Workings!$C$27:$C$38,C39),1) -> 1 | G39: =INDEX(Workings!$C$19:$C$23,B39) -> 1.242 | H39: =INDEX('Seasonality Data Break down'!$C$7:$C$18,C39) -> 1 | I39: =INDEX('Seasonality Data Break down'!$D$7:$D$18,C39) -> 0.85 | J39: =Assumptions!$C$18/12 -> 26.083333 | K39: =Assumptions!$C$19*E39*H39*G39 -> 80.73 | L39: =Assumptions!$C$20+INDEX('Seasonality Data Break down'!$E$7:$E$18,C39) -> 9.25 | M39: =K39*J39*L39 -> 19477.794 | N39: =M39*Assumptions!$C$21 -> 5843.3383 | O39: =Assumptions!$C$27*F39*I39*G39 -> 58.0635 | P39: =O39*Assumptions!$C$28 -> 2612.8575 | Q39: =Assumptions!$C$24*4.333*F39*I39*G39 -> 64.040873 | R39: =Q39*Assumptions!$C$25 -> 640.40873 | S39: =MIN(O39*Assumptions!$C$48,R39) -> 348.381 | T39: =MAX(R39-S39,0) -> 292.02773 | U39: =T39*Assumptions!$C$26 -> 3504.3328 | V39: =Q39*Assumptions!$C$29 -> 1921.2262 | W39: =P39+U39 -> 6117.1903 | X39: =M39+W39 -> 25594.985 | Y39: =N39+V39 -> 7764.5645 | Z39: =X39-Y39 -> 17830.42 | AA39: =Assumptions!$C$10*Assumptions!$C$9/12 -> 2000 | AB39: =Assumptions!$C$12/12 -> 125 | AC39: =Assumptions!$C$14/12 -> 150 | AD39: =(Assumptions!$C$32*4.333*Assumptions!$C$33+Assumptions!$C$34/12)*(1+(Assumptions!$C$35)) -> 6783.2324 | AE39: =INDEX('Seasonality Data Break down'!$F$7:$F$18,C39)*G39 -> 186.3 | AF39: =INDEX('Seasonality Data Break down'!$G$7:$G$18,C39)*G39 -> 186.3 | AG39: =INDEX('Seasonality Data Break down'!$H$7:$H$18,C39)*G39 -> 93.15 | AH39: =AE39+AF39+AG39 -> 465.75 | AI39: =Assumptions!$C$39 -> 150 | AJ39: =Assumptions!$C$40 -> 500 | AK39: =AA39+AB39+AC39+AD39+AH39+AI39+AJ39 -> 10173.982 | AL39: =X39*Assumptions!$C$13 -> 767.84954 | AM39: =X39*Assumptions!$C$15 -> 447.91223 | AN39: =AL39+AM39 -> 1215.7618 | AO39: =AK39+AN39 -> 11389.744 | AP39: =Z39-AO39 -> 6440.676 | AQ39: ='Startup Costs'!$D$24/(Assumptions!$C$54*12) -> 916.66667 | AR39: =-'Loan schedule'!$D$43 -> -231.36481 | AS39: =AP39-AQ39+AR39 -> 5292.6446 | AT39: =-MAX(AS39,0)*Assumptions!$C$41 -> -1323.1611 | AU39: =AS39+AT39 -> 3969.4834 | AV39: =-'Loan schedule'!$E$43 -> -1168.2798 | AW39: =AU39+AQ39+AV39 -> 3717.8703 | AX39: =AY38 -> 76886.739 | AY39: =AX39+AW39 -> 80604.609 | AZ39: =IFERROR(Z39/X39,0) -> 0.69663727 | BA39: =IFERROR(AP39/X39,0) -> 0.25163821 | BB39: =IFERROR(AU39/X39,0) -> 0.15508833
A40: 33 | B40: 3 | C40: 9 | D40: ='Seasonality Data Break down'!$B$15&" Y"&B40 -> September Y3 | E40: =IF(B40=1,INDEX(Workings!$B$27:$B$38,C40),1) -> 1 | F40: =IF(B40=1,INDEX(Workings!$C$27:$C$38,C40),1) -> 1 | G40: =INDEX(Workings!$C$19:$C$23,B40) -> 1.242 | H40: =INDEX('Seasonality Data Break down'!$C$7:$C$18,C40) -> 0.95 | I40: =INDEX('Seasonality Data Break down'!$D$7:$D$18,C40) -> 1.05 | J40: =Assumptions!$C$18/12 -> 26.083333 | K40: =Assumptions!$C$19*E40*H40*G40 -> 76.6935 | L40: =Assumptions!$C$20+INDEX('Seasonality Data Break down'!$E$7:$E$18,C40) -> 8.5 | M40: =K40*J40*L40 -> 17003.588 | N40: =M40*Assumptions!$C$21 -> 5101.0764 | O40: =Assumptions!$C$27*F40*I40*G40 -> 71.7255 | P40: =O40*Assumptions!$C$28 -> 3227.6475 | Q40: =Assumptions!$C$24*4.333*F40*I40*G40 -> 79.109314 | R40: =Q40*Assumptions!$C$25 -> 791.09314 | S40: =MIN(O40*Assumptions!$C$48,R40) -> 430.353 | T40: =MAX(R40-S40,0) -> 360.74014 | U40: =T40*Assumptions!$C$26 -> 4328.8817 | V40: =Q40*Assumptions!$C$29 -> 2373.2794 | W40: =P40+U40 -> 7556.5292 | X40: =M40+W40 -> 24560.117 | Y40: =N40+V40 -> 7474.3558 | Z40: =X40-Y40 -> 17085.761 | AA40: =Assumptions!$C$10*Assumptions!$C$9/12 -> 2000 | AB40: =Assumptions!$C$12/12 -> 125 | AC40: =Assumptions!$C$14/12 -> 150 | AD40: =(Assumptions!$C$32*4.333*Assumptions!$C$33+Assumptions!$C$34/12)*(1+(Assumptions!$C$35)) -> 6783.2324 | AE40: =INDEX('Seasonality Data Break down'!$F$7:$F$18,C40)*G40 -> 248.4 | AF40: =INDEX('Seasonality Data Break down'!$G$7:$G$18,C40)*G40 -> 248.4 | AG40: =INDEX('Seasonality Data Break down'!$H$7:$H$18,C40)*G40 -> 93.15 | AH40: =AE40+AF40+AG40 -> 589.95 | AI40: =Assumptions!$C$39 -> 150 | AJ40: =Assumptions!$C$40 -> 500 | AK40: =AA40+AB40+AC40+AD40+AH40+AI40+AJ40 -> 10298.182 | AL40: =X40*Assumptions!$C$13 -> 736.80352 | AM40: =X40*Assumptions!$C$15 -> 429.80205 | AN40: =AL40+AM40 -> 1166.6056 | AO40: =AK40+AN40 -> 11464.788 | AP40: =Z40-AO40 -> 5620.9735 | AQ40: ='Startup Costs'!$D$24/(Assumptions!$C$54*12) -> 916.66667 | AR40: =-'Loan schedule'!$D$44 -> -224.06306 | AS40: =AP40-AQ40+AR40 -> 4480.2438 | AT40: =-MAX(AS40,0)*Assumptions!$C$41 -> -1120.0609 | AU40: =AS40+AT40 -> 3360.1828 | AV40: =-'Loan schedule'!$E$44 -> -1175.5816 | AW40: =AU40+AQ40+AV40 -> 3101.2679 | AX40: =AY39 -> 80604.609 | AY40: =AX40+AW40 -> 83705.877 | AZ40: =IFERROR(Z40/X40,0) -> 0.695671 | BA40: =IFERROR(AP40/X40,0) -> 0.22886591 | BB40: =IFERROR(AU40/X40,0) -> 0.13681461
A41: 34 | B41: 3 | C41: 10 | D41: ='Seasonality Data Break down'!$B$16&" Y"&B41 -> October Y3 | E41: =IF(B41=1,INDEX(Workings!$B$27:$B$38,C41),1) -> 1 | F41: =IF(B41=1,INDEX(Workings!$C$27:$C$38,C41),1) -> 1 | G41: =INDEX(Workings!$C$19:$C$23,B41) -> 1.242 | H41: =INDEX('Seasonality Data Break down'!$C$7:$C$18,C41) -> 1 | I41: =INDEX('Seasonality Data Break down'!$D$7:$D$18,C41) -> 1 | J41: =Assumptions!$C$18/12 -> 26.083333 | K41: =Assumptions!$C$19*E41*H41*G41 -> 80.73 | L41: =Assumptions!$C$20+INDEX('Seasonality Data Break down'!$E$7:$E$18,C41) -> 8.5 | M41: =K41*J41*L41 -> 17898.514 | N41: =M41*Assumptions!$C$21 -> 5369.5541 | O41: =Assumptions!$C$27*F41*I41*G41 -> 68.31 | P41: =O41*Assumptions!$C$28 -> 3073.95 | Q41: =Assumptions!$C$24*4.333*F41*I41*G41 -> 75.342204 | R41: =Q41*Assumptions!$C$25 -> 753.42204 | S41: =MIN(O41*Assumptions!$C$48,R41) -> 409.86 | T41: =MAX(R41-S41,0) -> 343.56204 | U41: =T41*Assumptions!$C$26 -> 4122.7445 | V41: =Q41*Assumptions!$C$29 -> 2260.2661 | W41: =P41+U41 -> 7196.6945 | X41: =M41+W41 -> 25095.208 | Y41: =N41+V41 -> 7629.8202 | Z41: =X41-Y41 -> 17465.388 | AA41: =Assumptions!$C$10*Assumptions!$C$9/12 -> 2000 | AB41: =Assumptions!$C$12/12 -> 125 | AC41: =Assumptions!$C$14/12 -> 150 | AD41: =(Assumptions!$C$32*4.333*Assumptions!$C$33+Assumptions!$C$34/12)*(1+(Assumptions!$C$35)) -> 6783.2324 | AE41: =INDEX('Seasonality Data Break down'!$F$7:$F$18,C41)*G41 -> 186.3 | AF41: =INDEX('Seasonality Data Break down'!$G$7:$G$18,C41)*G41 -> 186.3 | AG41: =INDEX('Seasonality Data Break down'!$H$7:$H$18,C41)*G41 -> 62.1 | AH41: =AE41+AF41+AG41 -> 434.7 | AI41: =Assumptions!$C$39 -> 150 | AJ41: =Assumptions!$C$40 -> 500 | AK41: =AA41+AB41+AC41+AD41+AH41+AI41+AJ41 -> 10142.932 | AL41: =X41*Assumptions!$C$13 -> 752.85625 | AM41: =X41*Assumptions!$C$15 -> 439.16614 | AN41: =AL41+AM41 -> 1192.0224 | AO41: =AK41+AN41 -> 11334.955 | AP41: =Z41-AO41 -> 6130.4332 | AQ41: ='Startup Costs'!$D$24/(Assumptions!$C$54*12) -> 916.66667 | AR41: =-'Loan schedule'!$D$45 -> -216.71568 | AS41: =AP41-AQ41+AR41 -> 4997.0509 | AT41: =-MAX(AS41,0)*Assumptions!$C$41 -> -1249.2627 | AU41: =AS41+AT41 -> 3747.7882 | AV41: =-'Loan schedule'!$E$45 -> -1182.929 | AW41: =AU41+AQ41+AV41 -> 3481.5259 | AX41: =AY40 -> 83705.877 | AY41: =AX41+AW41 -> 87187.403 | AZ41: =IFERROR(Z41/X41,0) -> 0.69596506 | BA41: =IFERROR(AP41/X41,0) -> 0.244287 | BB41: =IFERROR(AU41/X41,0) -> 0.14934278
