Workbook

Sheet Student Headcount
A1: Vector University: Historical Student Headcount (Monthly Actuals)
A4: Month | B4: FY | C4: UK Undergraduate | D4: MOM Changes | E4: International Undergraduate | F4: MOM Changes | G4: UK Postgraduate | H4: MOM Changes | I4: International Postgraduate | J4: MOM Changes | K4: Postgraduate Research (PGR) | L4: MOM Changes | M4: Total Students
A5: 45139 | B5: FY23/24 | C5: 6000 | D5: =C6-C5 -> 3007 | E5: 1400 | F5: =E6-E5 -> 707 | G5: 184 | H5: =G6-G5 -> 6715 | I5: 192 | J5: =I6-I5 -> 6057 | K5: 748 | L5: =K6-K5 -> 251 | M5: =SUM(C5:K5) -> 25010
A6: 45170 | B6: FY23/24 | C6: 9007 | D6: =C7-C6 -> -44 | E6: 2107 | F6: =E7-E6 -> -24 | G6: 6899 | H6: =G7-G6 -> -1350 | I6: 6249 | J6: =I7-I6 -> -1205 | K6: 999 | L6: =K7-K6 -> 7 | M6: =SUM(C6:K6) -> 22638
A7: 45200 | B7: FY23/24 | C7: 8963 | D7: =C8-C7 -> -47 | E7: 2083 | F7: =E8-E7 -> 0 | G7: 5549 | H7: =G8-G7 -> -1114 | I7: 5044 | J7: =I8-I7 -> -1067 | K7: 1006 | L7: =K8-K7 -> -5 | M7: =SUM(C7:K7) -> 20417
A8: 45231 | B8: FY23/24 | C8: 8916 | D8: =C9-C8 -> 10 | E8: 2083 | F8: =E9-E8 -> -3 | G8: 4435 | H8: =G9-G8 -> -920 | I8: 3977 | J8: =I9-I8 -> -794 | K8: 1001 | L8: =K9-K8 -> -7 | M8: =SUM(C8:K8) -> 18705
A9: 45261 | B9: FY23/24 | C9: 8926 | D9: =C10-C9 -> -42 | E9: 2080 | F9: =E10-E9 -> -7 | G9: 3515 | H9: =G10-G9 -> -220 | I9: 3183 | J9: =I10-I9 -> -270 | K9: 994 | L9: =K10-K9 -> 69 | M9: =SUM(C9:K9) -> 18159
A10: 45292 | B10: FY23/24 | C10: 8884 | D10: =C11-C10 -> 43 | E10: 2073 | F10: =E11-E10 -> -21 | G10: 3295 | H10: =G11-G10 -> -657 | I10: 2913 | J10: =I11-I10 -> -607 | K10: 1063 | L10: =K11-K10 -> 0 | M10: =SUM(C10:K10) -> 16986
A11: 45323 | B11: FY23/24 | C11: 8927 | D11: =C12-C11 -> 55 | E11: 2052 | F11: =E12-E11 -> 10 | G11: 2638 | H11: =G12-G11 -> -542 | I11: 2306 | J11: =I12-I11 -> -468 | K11: 1063 | L11: =K12-K11 -> 10 | M11: =SUM(C11:K11) -> 16041
A12: 45352 | B12: FY23/24 | C12: 8982 | D12: =C13-C12 -> -111 | E12: 2062 | F12: =E13-E12 -> 10 | G12: 2096 | H12: =G13-G12 -> -406 | I12: 1838 | J12: =I13-I12 -> -379 | K12: 1073 | L12: =K13-K12 -> -14 | M12: =SUM(C12:K12) -> 15165
A13: 45383 | B13: FY23/24 | C13: 8871 | D13: =C14-C13 -> -20 | E13: 2072 | F13: =E14-E13 -> -41 | G13: 1690 | H13: =G14-G13 -> -347 | I13: 1459 | J13: =I14-I13 -> -295 | K13: 1059 | L13: =K14-K13 -> 0 | M13: =SUM(C13:K13) -> 14448
A14: 45413 | B14: FY23/24 | C14: 8851 | D14: =C15-C14 -> 45 | E14: 2031 | F14: =E15-E14 -> 23 | G14: 1343 | H14: =G15-G14 -> -257 | I14: 1164 | J14: =I15-I14 -> -241 | K14: 1059 | L14: =K15-K14 -> 3 | M14: =SUM(C14:K14) -> 14018
A15: 45444 | B15: FY23/24 | C15: 8896 | D15: =C16-C15 -> -2793 | E15: 2054 | F15: =E16-E15 -> -639 | G15: 1086 | H15: =G16-G15 -> -221 | I15: 923 | J15: =I16-I15 -> -189 | K15: 1062 | L15: =K16-K15 -> -244 | M15: =SUM(C15:K15) -> 10179
A16: 45474 | B16: FY23/24 | C16: 6103 | D16: =C17-C16 -> -18 | E16: 1415 | F16: =E17-E16 -> -10 | G16: 865 | H16: =G17-G16 -> -173 | I16: 734 | J16: =I17-I16 -> -154 | K16: 818 | L16: =K17-K16 -> -1 | M16: =SUM(C16:K16) -> 9580
... A40: 46204 | B40: FY25/26 | C40: 6242 | D40: =C41-C40 -> 2308.1389 | E40: 1392 | F40: =E41-E40 -> 583.08333 | G40: 943 | H40: =G41-G40 -> 2045.8056 | I40: 689 | J40: =I41-I40 -> 1860.2778 | K40: 934 | L40: =K41-K40 -> 132.08333 | M40: =SUM(C40:K40) -> 16997.306
B41: Average | C41: =AVERAGE(C5:C40) -> 8550.1389 | E41: =AVERAGE(E5:E40) -> 1975.0833 | G41: =AVERAGE(G5:G40) -> 2988.8056 | I41: =AVERAGE(I5:I40) -> 2549.2778 | K41: =AVERAGE(K5:K40) -> 1066.0833 | M41: =AVERAGE(M5:M40) -> 17359.592

Sheet Student Flow Summary
A1: Vector University — Annual Student Flow Summary
A4: Category | B4: FY | C4: Opening Population | D4: New Enrolments | E4: Withdrawals | F4: Graduates / Completions | G4: Closing Population | H4: Retention Rate %
A5: UK Undergraduate | B5: FY23/24 | C5: 6000 | D5: 3000 | E5: 143 | F5: 2767 | G5: =C5+D5-E5-F5 -> 6090 | H5: =1-E5/(C5+D5) -> 0.98411111
A6: UK Undergraduate | B6: FY24/25 | C6: 6090 | D6: 3050 | E6: 154 | F6: 2807 | G6: =C6+D6-E6-F6 -> 6179 | H6: =1-E6/(C6+D6) -> 0.98315098
A7: UK Undergraduate | B7: FY25/26 | C7: 6179 | D7: 3100 | E7: 156 | F7: 2850 | G7: =C7+D7-E7-F7 -> 6273 | H7: =1-E7/(C7+D7) -> 0.98318784
A8: International Undergraduate | B8: FY23/24 | C8: 1400 | D8: 700 | E8: 62 | F8: 624 | G8: =C8+D8-E8-F8 -> 1414 | H8: =1-E8/(C8+D8) -> 0.97047619
A9: International Undergraduate | B9: FY24/25 | C9: 1414 | D9: 745 | E9: 67 | F9: 641 | G9: =C9+D9-E9-F9 -> 1451 | H9: =1-E9/(C9+D9) -> 0.96896711
A10: International Undergraduate | B10: FY25/26 | C10: 1451 | D10: 645 | E10: 66 | F10: 622 | G10: =C10+D10-E10-F10 -> 1408 | H10: =1-E10/(C10+D10) -> 0.96851145
A11: UK Postgraduate | B11: FY23/24 | C11: 184 | D11: 7227 | E11: 524 | F11: 6023 | G11: =C11+D11-E11-F11 -> 864 | H11: =1-E11/(C11+D11) -> 0.92929429
A12: UK Postgraduate | B12: FY24/25 | C12: 864 | D12: 7374 | E12: 585 | F12: 6728 | G12: =C12+D12-E12-F12 -> 925 | H12: =1-E12/(C12+D12) -> 0.92898762
A13: UK Postgraduate | B13: FY25/26 | C13: 925 | D13: 7522 | E13: 600 | F13: 6900 | G13: =C13+D13-E13-F13 -> 947 | H13: =1-E13/(C13+D13) -> 0.92896886
A14: International Postgraduate | B14: FY23/24 | C14: 193 | D14: 6542 | E14: 480 | F14: 5519 | G14: =C14+D14-E14-F14 -> 736 | H14: =1-E14/(C14+D14) -> 0.92873051
A15: International Postgraduate | B15: FY24/25 | C15: 735 | D15: 6861 | E15: 544 | F15: 6252 | G15: =C15+D15-E15-F15 -> 800 | H15: =1-E15/(C15+D15) -> 0.92838336
A16: International Postgraduate | B16: FY25/26 | C16: 801 | D16: 5783 | E16: 472 | F16: 5423 | G16: =C16+D16-E16-F16 -> 689 | H16: =1-E16/(C16+D16) -> 0.92831106
... A19: Postgraduate Research (PGR) | B19: FY25/26 | C19: 878 | D19: 339 | E19: 14 | F19: 273 | G19: =C19+D19-E19-F19 -> 930 | H19: =1-E19/(C19+D19) -> 0.9884963

Sheet Tuition Fee Rates
A1: Vector University — Tuition Fee Rates
A3: Approved annual tuition fee per student (£), by category and financial year.
A5: Student Category | B5: FY23/24 | C5: FY24/25 | D5: FY25/26
A6: UK Undergraduate | B6: 9250 | C6: 9250 | D6: 9535
A7: International Undergraduate | B7: 19000 | C7: 19950 | D7: 20950
A8: UK Postgraduate | B8: 9750 | C8: 10050 | D8: 10350
A9: International Postgraduate | B9: 19500 | C9: 20500 | D9: 21500
A10: Postgraduate Research (PGR) | B10: 6500 | C10: 6700 | D10: 6950

Sheet Income
A1: Vector University — Income (Monthly Actuals)
A4: Month | B4: FY | C4: UK Undergraduate Tuition | D4: International Undergraduate Tuition | E4: UK Postgraduate Tuition | F4: International Postgraduate Tuition | G4: Postgraduate Research (PGR) Tuition | H4: Research Grants & Contracts | I4: Government & Funding Body Grants | J4: Student Accommodation Income | K4: Commercial & Professional Services | L4: Other Operating Income | M4: Total Income
A5: 45139 | B5: FY23/24 | C5: ='Student Headcount'!C5*'Tuition Fee Rates'!B6/12 -> 4625000 | D5: ='Student Headcount'!E5*'Tuition Fee Rates'!B7/12 -> 2216666.7 | E5: ='Student Headcount'!G5*'Tuition Fee Rates'!B8/12 -> 149500 | F5: ='Student Headcount'!I5*'Tuition Fee Rates'!B9/12 -> 312000 | G5: ='Student Headcount'!K5*'Tuition Fee Rates'!B10/12 -> 405166.67 | H5: 2400000 | I5: 3653846 | J5: 1200000 | K5: 675000 | L5: 500000 | M5: =SUM(C5:L5) -> 16137179
A6: 45170 | B6: FY23/24 | C6: ='Student Headcount'!C6*'Tuition Fee Rates'!B6/12 -> 6942895.8 | D6: ='Student Headcount'!E6*'Tuition Fee Rates'!B7/12 -> 3336083.3 | E6: ='Student Headcount'!G6*'Tuition Fee Rates'!B8/12 -> 5605437.5 | F6: ='Student Headcount'!I6*'Tuition Fee Rates'!B9/12 -> 10154625 | G6: ='Student Headcount'!K6*'Tuition Fee Rates'!B10/12 -> 541125 | H6: 2533333 | I6: 548077 | J6: 2600000 | K6: 825000 | L6: 500000 | M6: =SUM(C6:L6) -> 33586577
A7: 45200 | B7: FY23/24 | C7: ='Student Headcount'!C7*'Tuition Fee Rates'!B6/12 -> 6908979.2 | D7: ='Student Headcount'!E7*'Tuition Fee Rates'!B7/12 -> 3298083.3 | E7: ='Student Headcount'!G7*'Tuition Fee Rates'!B8/12 -> 4508562.5 | F7: ='Student Headcount'!I7*'Tuition Fee Rates'!B9/12 -> 8196500 | G7: ='Student Headcount'!K7*'Tuition Fee Rates'!B10/12 -> 544916.67 | H7: 2666667 | I7: 548077 | J7: 2600000 | K7: 825000 | L7: 500000 | M7: =SUM(C7:L7) -> 30596786
A8: 45231 | B8: FY23/24 | C8: ='Student Headcount'!C8*'Tuition Fee Rates'!B6/12 -> 6872750 | D8: ='Student Headcount'!E8*'Tuition Fee Rates'!B7/12 -> 3298083.3 | E8: ='Student Headcount'!G8*'Tuition Fee Rates'!B8/12 -> 3603437.5 | F8: ='Student Headcount'!I8*'Tuition Fee Rates'!B9/12 -> 6462625 | G8: ='Student Headcount'!K8*'Tuition Fee Rates'!B10/12 -> 542208.33 | H8: 2666667 | I8: 3653846 | J8: 2500000 | K8: 750000 | L8: 500000 | M8: =SUM(C8:L8) -> 30849617
A9: 45261 | B9: FY23/24 | C9: ='Student Headcount'!C9*'Tuition Fee Rates'!B6/12 -> 6880458.3 | D9: ='Student Headcount'!E9*'Tuition Fee Rates'!B7/12 -> 3293333.3 | E9: ='Student Headcount'!G9*'Tuition Fee Rates'!B8/12 -> 2855937.5 | F9: ='Student Headcount'!I9*'Tuition Fee Rates'!B9/12 -> 5172375 | G9: ='Student Headcount'!K9*'Tuition Fee Rates'!B10/12 -> 538416.67 | H9: 2800000 | I9: 548077 | J9: 2300000 | K9: 675000 | L9: 500000 | M9: =SUM(C9:L9) -> 25563598
A10: 45292 | B10: FY23/24 | C10: ='Student Headcount'!C10*'Tuition Fee Rates'!B6/12 -> 6848083.3 | D10: ='Student Headcount'!E10*'Tuition Fee Rates'!B7/12 -> 3282250 | E10: ='Student Headcount'!G10*'Tuition Fee Rates'!B8/12 -> 2677187.5 | F10: ='Student Headcount'!I10*'Tuition Fee Rates'!B9/12 -> 4733625 | G10: ='Student Headcount'!K10*'Tuition Fee Rates'!B10/12 -> 575791.67 | H10: 2800000 | I10: 548077 | J10: 2200000 | K10: 750000 | L10: 500000 | M10: =SUM(C10:L10) -> 24915014
A11: 45323 | B11: FY23/24 | C11: ='Student Headcount'!C11*'Tuition Fee Rates'!B6/12 -> 6881229.2 | D11: ='Student Headcount'!E11*'Tuition Fee Rates'!B7/12 -> 3249000 | E11: ='Student Headcount'!G11*'Tuition Fee Rates'!B8/12 -> 2143375 | F11: ='Student Headcount'!I11*'Tuition Fee Rates'!B9/12 -> 3747250 | G11: ='Student Headcount'!K11*'Tuition Fee Rates'!B10/12 -> 575791.67 | H11: 2800000 | I11: 3653846 | J11: 2200000 | K11: 825000 | L11: 500000 | M11: =SUM(C11:L11) -> 26575492
A12: 45352 | B12: FY23/24 | C12: ='Student Headcount'!C12*'Tuition Fee Rates'!B6/12 -> 6923625 | D12: ='Student Headcount'!E12*'Tuition Fee Rates'!B7/12 -> 3264833.3 | E12: ='Student Headcount'!G12*'Tuition Fee Rates'!B8/12 -> 1703000 | F12: ='Student Headcount'!I12*'Tuition Fee Rates'!B9/12 -> 2986750 | G12: ='Student Headcount'!K12*'Tuition Fee Rates'!B10/12 -> 581208.33 | H12: 2666667 | I12: 548077 | J12: 2200000 | K12: 825000 | L12: 500000 | M12: =SUM(C12:L12) -> 22199161
A13: 45383 | B13: FY23/24 | C13: ='Student Headcount'!C13*'Tuition Fee Rates'!B6/12 -> 6838062.5 | D13: ='Student Headcount'!E13*'Tuition Fee Rates'!B7/12 -> 3280666.7 | E13: ='Student Headcount'!G13*'Tuition Fee Rates'!B8/12 -> 1373125 | F13: ='Student Headcount'!I13*'Tuition Fee Rates'!B9/12 -> 2370875 | G13: ='Student Headcount'!K13*'Tuition Fee Rates'!B10/12 -> 573625 | H13: 2666667 | I13: 548077 | J13: 2200000 | K13: 750000 | L13: 500000 | M13: =SUM(C13:L13) -> 21101098
A14: 45413 | B14: FY23/24 | C14: ='Student Headcount'!C14*'Tuition Fee Rates'!B6/12 -> 6822645.8 | D14: ='Student Headcount'!E14*'Tuition Fee Rates'!B7/12 -> 3215750 | E14: ='Student Headcount'!G14*'Tuition Fee Rates'!B8/12 -> 1091187.5 | F14: ='Student Headcount'!I14*'Tuition Fee Rates'!B9/12 -> 1891500 | G14: ='Student Headcount'!K14*'Tuition Fee Rates'!B10/12 -> 573625 | H14: 2533333 | I14: 3653846 | J14: 2000000 | K14: 675000 | L14: 500000 | M14: =SUM(C14:L14) -> 22956887
A15: 45444 | B15: FY23/24 | C15: ='Student Headcount'!C15*'Tuition Fee Rates'!B6/12 -> 6857333.3 | D15: ='Student Headcount'!E15*'Tuition Fee Rates'!B7/12 -> 3252166.7 | E15: ='Student Headcount'!G15*'Tuition Fee Rates'!B8/12 -> 882375 | F15: ='Student Headcount'!I15*'Tuition Fee Rates'!B9/12 -> 1499875 | G15: ='Student Headcount'!K15*'Tuition Fee Rates'!B10/12 -> 575250 | H15: 2533333 | I15: 548077 | J15: 1000000 | K15: 675000 | L15: 500000 | M15: =SUM(C15:L15) -> 18323410
A16: 45474 | B16: FY23/24 | C16: ='Student Headcount'!C16*'Tuition Fee Rates'!B6/12 -> 4704395.8 | D16: ='Student Headcount'!E16*'Tuition Fee Rates'!B7/12 -> 2240416.7 | E16: ='Student Headcount'!G16*'Tuition Fee Rates'!B8/12 -> 702812.5 | F16: ='Student Headcount'!I16*'Tuition Fee Rates'!B9/12 -> 1192750 | G16: ='Student Headcount'!K16*'Tuition Fee Rates'!B10/12 -> 443083.33 | H16: 2933333 | I16: 548077 | J16: 1000000 | K16: 750000 | L16: 500000 | M16: =SUM(C16:L16) -> 15014868
A17: 45505 | B17: FY24/25 | C17: ='Student Headcount'!C17*'Tuition Fee Rates'!C6/12 -> 4690520.8 | D17: ='Student Headcount'!E17*'Tuition Fee Rates'!C7/12 -> 2335812.5 | E17: ='Student Headcount'!G17*'Tuition Fee Rates'!C8/12 -> 579550 | F17: ='Student Headcount'!I17*'Tuition Fee Rates'!C9/12 -> 990833.33 | G17: ='Student Headcount'!K17*'Tuition Fee Rates'!C10/12 -> 456158.33 | H17: 2512500 | I17: 3692308 | J17: 1255000 | K17: 712500 | L17: 516667 | M17: =SUM(C17:L17) -> 17741850
A18: 45536 | B18: FY24/25 | C18: ='Student Headcount'!C18*'Tuition Fee Rates'!C6/12 -> 6992229.2 | D18: ='Student Headcount'!E18*'Tuition Fee Rates'!C7/12 -> 3619262.5 | E18: ='Student Headcount'!G18*'Tuition Fee Rates'!C8/12 -> 6215925 | F18: ='Student Headcount'!I18*'Tuition Fee Rates'!C9/12 -> 11758458 | G18: ='Student Headcount'!K18*'Tuition Fee Rates'!C10/12 -> 596300 | H18: 2652083 | I18: 553846 | J18: 2719167 | K18: 870833 | L18: 516667 | M18: =SUM(C18:L18) -> 36494771
A19: 45566 | B19: FY24/25 | C19: ='Student Headcount'!C19*'Tuition Fee Rates'!C6/12 -> 7019208.3 | D19: ='Student Headcount'!E19*'Tuition Fee Rates'!C7/12 -> 3582687.5 | E19: ='Student Headcount'!G19*'Tuition Fee Rates'!C8/12 -> 4986475 | F19: ='Student Headcount'!I19*'Tuition Fee Rates'!C9/12 -> 9486375 | G19: ='Student Headcount'!K19*'Tuition Fee Rates'!C10/12 -> 599650 | H19: 2791667 | I19: 553846 | J19: 2719167 | K19: 870833 | L19: 516667 | M19: =SUM(C19:L19) -> 33126576
A20: 45597 | B20: FY24/25 | C20: ='Student Headcount'!C20*'Tuition Fee Rates'!C6/12 -> 7039250 | D20: ='Student Headcount'!E20*'Tuition Fee Rates'!C7/12 -> 3531150 | E20: ='Student Headcount'!G20*'Tuition Fee Rates'!C8/12 -> 3944625 | F20: ='Student Headcount'!I20*'Tuition Fee Rates'!C9/12 -> 7438083.3 | G20: ='Student Headcount'!K20*'Tuition Fee Rates'!C10/12 -> 597416.67 | H20: 2791667 | I20: 3692308 | J20: 2614583 | K20: 791667 | L20: 516667 | M20: =SUM(C20:L20) -> 32957417
A21: 45627 | B21: FY24/25 | C21: ='Student Headcount'!C21*'Tuition Fee Rates'!C6/12 -> 6943666.7 | D21: ='Student Headcount'!E21*'Tuition Fee Rates'!C7/12 -> 3547775 | E21: ='Student Headcount'!G21*'Tuition Fee Rates'!C8/12 -> 3172450 | F21: ='Student Headcount'!I21*'Tuition Fee Rates'!C9/12 -> 5898875 | G21: ='Student Headcount'!K21*'Tuition Fee Rates'!C10/12 -> 602441.67 | H21: 2931250 | I21: 553846 | J21: 2405417 | K21: 712500 | L21: 516667 | M21: =SUM(C21:L21) -> 27284888
A22: 45658 | B22: FY24/25 | C22: ='Student Headcount'!C22*'Tuition Fee Rates'!C6/12 -> 6969875 | D22: ='Student Headcount'!E22*'Tuition Fee Rates'!C7/12 -> 3547775 | E22: ='Student Headcount'!G22*'Tuition Fee Rates'!C8/12 -> 2963075 | F22: ='Student Headcount'!I22*'Tuition Fee Rates'!C9/12 -> 5430791.7 | G22: ='Student Headcount'!K22*'Tuition Fee Rates'!C10/12 -> 640408.33 | H22: 2931250 | I22: 553846 | J22: 2300833 | K22: 791667 | L22: 516667 | M22: =SUM(C22:L22) -> 26646188
A23: 45689 | B23: FY24/25 | C23: ='Student Headcount'!C23*'Tuition Fee Rates'!C6/12 -> 6898958.3 | D23: ='Student Headcount'!E23*'Tuition Fee Rates'!C7/12 -> 3522837.5 | E23: ='Student Headcount'!G23*'Tuition Fee Rates'!C8/12 -> 2334950 | F23: ='Student Headcount'!I23*'Tuition Fee Rates'!C9/12 -> 4344291.7 | G23: ='Student Headcount'!K23*'Tuition Fee Rates'!C10/12 -> 637616.67 | H23: 2931250 | I23: 3692308 | J23: 2300833 | K23: 870833 | L23: 516667 | M23: =SUM(C23:L23) -> 28050545
A24: 45717 | B24: FY24/25 | C24: ='Student Headcount'!C24*'Tuition Fee Rates'!C6/12 -> 6914375 | D24: ='Student Headcount'!E24*'Tuition Fee Rates'!C7/12 -> 3531150 | E24: ='Student Headcount'!G24*'Tuition Fee Rates'!C8/12 -> 1901962.5 | F24: ='Student Headcount'!I24*'Tuition Fee Rates'!C9/12 -> 3396166.7 | G24: ='Student Headcount'!K24*'Tuition Fee Rates'!C10/12 -> 639291.67 | H24: 2791667 | I24: 553846 | J24: 2300833 | K24: 870833 | L24: 516667 | M24: =SUM(C24:L24) -> 23416792
A25: 45748 | B25: FY24/25 | C25: ='Student Headcount'!C25*'Tuition Fee Rates'!C6/12 -> 6881229.2 | D25: ='Student Headcount'!E25*'Tuition Fee Rates'!C7/12 -> 3504550 | E25: ='Student Headcount'!G25*'Tuition Fee Rates'!C8/12 -> 1497450 | F25: ='Student Headcount'!I25*'Tuition Fee Rates'!C9/12 -> 2719666.7 | G25: ='Student Headcount'!K25*'Tuition Fee Rates'!C10/12 -> 634825 | H25: 2791667 | I25: 553846 | J25: 2300833 | K25: 791667 | L25: 516667 | M25: =SUM(C25:L25) -> 22192401
A26: 45778 | B26: FY24/25 | C26: ='Student Headcount'!C26*'Tuition Fee Rates'!C6/12 -> 6937500 | D26: ='Student Headcount'!E26*'Tuition Fee Rates'!C7/12 -> 3511200 | E26: ='Student Headcount'!G26*'Tuition Fee Rates'!C8/12 -> 1216050 | F26: ='Student Headcount'!I26*'Tuition Fee Rates'!C9/12 -> 2155916.7 | G26: ='Student Headcount'!K26*'Tuition Fee Rates'!C10/12 -> 639291.67 | H26: 2652083 | I26: 3692308 | J26: 2091667 | K26: 712500 | L26: 516667 | M26: =SUM(C26:L26) -> 24125183
A27: 45809 | B27: FY24/25 | C27: ='Student Headcount'!C27*'Tuition Fee Rates'!C6/12 -> 6884312.5 | D27: ='Student Headcount'!E27*'Tuition Fee Rates'!C7/12 -> 3517850 | E27: ='Student Headcount'!G27*'Tuition Fee Rates'!C8/12 -> 963962.5 | F27: ='Student Headcount'!I27*'Tuition Fee Rates'!C9/12 -> 1703208.3 | G27: ='Student Headcount'!K27*'Tuition Fee Rates'!C10/12 -> 634825 | H27: 2652083 | I27: 553846 | J27: 1045833 | K27: 712500 | L27: 516667 | M27: =SUM(C27:L27) -> 19185087
A28: 45839 | B28: FY24/25 | C28: ='Student Headcount'!C28*'Tuition Fee Rates'!C6/12 -> 4770687.5 | D28: ='Student Headcount'!E28*'Tuition Fee Rates'!C7/12 -> 2402312.5 | E28: ='Student Headcount'!G28*'Tuition Fee Rates'!C8/12 -> 778875 | F28: ='Student Headcount'!I28*'Tuition Fee Rates'!C9/12 -> 1373500 | G28: ='Student Headcount'!K28*'Tuition Fee Rates'!C10/12 -> 492450 | H28: 3070833 | I28: 553846 | J28: 1045833 | K28: 791667 | L28: 516667 | M28: =SUM(C28:L28) -> 15796671
A29: 45870 | B29: FY25/26 | C29: ='Student Headcount'!C29*'Tuition Fee Rates'!D6/12 -> 4906552.1 | D29: ='Student Headcount'!E29*'Tuition Fee Rates'!D7/12 -> 2529712.5 | E29: ='Student Headcount'!G29*'Tuition Fee Rates'!D8/12 -> 639112.5 | F29: ='Student Headcount'!I29*'Tuition Fee Rates'!D9/12 -> 1141291.7 | G29: ='Student Headcount'!K29*'Tuition Fee Rates'!D10/12 -> 504454.17 | H29: 2610000 | I29: 3653846 | J29: 1310000 | K29: 750000 | L29: 541667 | M29: =SUM(C29:L29) -> 18586636
A30: 45901 | B30: FY25/26 | C30: ='Student Headcount'!C30*'Tuition Fee Rates'!D6/12 -> 7349895.8 | D30: ='Student Headcount'!E30*'Tuition Fee Rates'!D7/12 -> 3634825 | E30: ='Student Headcount'!G30*'Tuition Fee Rates'!D8/12 -> 6513600 | F30: ='Student Headcount'!I30*'Tuition Fee Rates'!D9/12 -> 10624583 | G30: ='Student Headcount'!K30*'Tuition Fee Rates'!D10/12 -> 662566.67 | H30: 2755000 | I30: 548077 | J30: 2838333 | K30: 916667 | L30: 541667 | M30: =SUM(C30:L30) -> 36385215
A31: 45931 | B31: FY25/26 | C31: ='Student Headcount'!C31*'Tuition Fee Rates'!D6/12 -> 7236270.4 | D31: ='Student Headcount'!E31*'Tuition Fee Rates'!D7/12 -> 3638316.7 | E31: ='Student Headcount'!G31*'Tuition Fee Rates'!D8/12 -> 5299200 | F31: ='Student Headcount'!I31*'Tuition Fee Rates'!D9/12 -> 8404708.3 | G31: ='Student Headcount'!K31*'Tuition Fee Rates'!D10/12 -> 653879.17 | H31: 2900000 | I31: 548077 | J31: 2838333 | K31: 916667 | L31: 541667 | M31: =SUM(C31:L31) -> 32977119
A32: 45962 | B32: FY25/26 | C32: ='Student Headcount'!C32*'Tuition Fee Rates'!D6/12 -> 7311755.8 | D32: ='Student Headcount'!E32*'Tuition Fee Rates'!D7/12 -> 3599908.3 | E32: ='Student Headcount'!G32*'Tuition Fee Rates'!D8/12 -> 4244362.5 | F32: ='Student Headcount'!I32*'Tuition Fee Rates'!D9/12 -> 6731291.7 | G32: ='Student Headcount'!K32*'Tuition Fee Rates'!D10/12 -> 652141.67 | H32: 2900000 | I32: 3653846 | J32: 2729167 | K32: 833333 | L32: 541667 | M32: =SUM(C32:L32) -> 33197473
A33: 45992 | B33: FY25/26 | C33: ='Student Headcount'!C33*'Tuition Fee Rates'!D6/12 -> 7322880 | D33: ='Student Headcount'!E33*'Tuition Fee Rates'!D7/12 -> 3601654.2 | E33: ='Student Headcount'!G33*'Tuition Fee Rates'!D8/12 -> 3364612.5 | F33: ='Student Headcount'!I33*'Tuition Fee Rates'!D9/12 -> 5319458.3 | G33: ='Student Headcount'!K33*'Tuition Fee Rates'!D10/12 -> 657933.33 | H33: 3045000 | I33: 548077 | J33: 2510833 | K33: 750000 | L33: 541667 | M33: =SUM(C33:L33) -> 27662115
A34: 46023 | B34: FY25/26 | C34: ='Student Headcount'!C34*'Tuition Fee Rates'!D6/12 -> 7318907.1 | D34: ='Student Headcount'!E34*'Tuition Fee Rates'!D7/12 -> 3599908.3 | E34: ='Student Headcount'!G34*'Tuition Fee Rates'!D8/12 -> 3111900 | F34: ='Student Headcount'!I34*'Tuition Fee Rates'!D9/12 -> 4885875 | G34: ='Student Headcount'!K34*'Tuition Fee Rates'!D10/12 -> 697895.83 | H34: 3045000 | I34: 548077 | J34: 2401667 | K34: 833333 | L34: 541667 | M34: =SUM(C34:L34) -> 26984230
A35: 46054 | B35: FY25/26 | C35: ='Student Headcount'!C35*'Tuition Fee Rates'!D6/12 -> 7235475.8 | D35: ='Student Headcount'!E35*'Tuition Fee Rates'!D7/12 -> 3613875 | E35: ='Student Headcount'!G35*'Tuition Fee Rates'!D8/12 -> 2490900 | F35: ='Student Headcount'!I35*'Tuition Fee Rates'!D9/12 -> 3861041.7 | G35: ='Student Headcount'!K35*'Tuition Fee Rates'!D10/12 -> 701370.83 | H35: 3045000 | I35: 3653846 | J35: 2401667 | K35: 916667 | L35: 541667 | M35: =SUM(C35:L35) -> 28461510
A36: 46082 | B36: FY25/26 | C36: ='Student Headcount'!C36*'Tuition Fee Rates'!D6/12 -> 7271232.1 | D36: ='Student Headcount'!E36*'Tuition Fee Rates'!D7/12 -> 3608637.5 | E36: ='Student Headcount'!G36*'Tuition Fee Rates'!D8/12 -> 1982887.5 | F36: ='Student Headcount'!I36*'Tuition Fee Rates'!D9/12 -> 3067333.3 | G36: ='Student Headcount'!K36*'Tuition Fee Rates'!D10/12 -> 709479.17 | H36: 2900000 | I36: 548077 | J36: 2401667 | K36: 916667 | L36: 541667 | M36: =SUM(C36:L36) -> 23947648
A37: 46113 | B37: FY25/26 | C37: ='Student Headcount'!C37*'Tuition Fee Rates'!D6/12 -> 7237859.6 | D37: ='Student Headcount'!E37*'Tuition Fee Rates'!D7/12 -> 3545787.5 | E37: ='Student Headcount'!G37*'Tuition Fee Rates'!D8/12 -> 1605975 | F37: ='Student Headcount'!I37*'Tuition Fee Rates'!D9/12 -> 2476083.3 | G37: ='Student Headcount'!K37*'Tuition Fee Rates'!D10/12 -> 695579.17 | H37: 2900000 | I37: 548077 | J37: 2401667 | K37: 833333 | L37: 541667 | M37: =SUM(C37:L37) -> 22786029
A38: 46143 | B38: FY25/26 | C38: ='Student Headcount'!C38*'Tuition Fee Rates'!D6/12 -> 7234681.2 | D38: ='Student Headcount'!E38*'Tuition Fee Rates'!D7/12 -> 3547533.3 | E38: ='Student Headcount'!G38*'Tuition Fee Rates'!D8/12 -> 1272187.5 | F38: ='Student Headcount'!I38*'Tuition Fee Rates'!D9/12 -> 1947541.7 | G38: ='Student Headcount'!K38*'Tuition Fee Rates'!D10/12 -> 696158.33 | H38: 2755000 | I38: 3653846 | J38: 2183333 | K38: 750000 | L38: 541667 | M38: =SUM(C38:L38) -> 24581948
A39: 46174 | B39: FY25/26 | C39: ='Student Headcount'!C39*'Tuition Fee Rates'!D6/12 -> 7305399.2 | D39: ='Student Headcount'!E39*'Tuition Fee Rates'!D7/12 -> 3568483.3 | E39: ='Student Headcount'!G39*'Tuition Fee Rates'!D8/12 -> 1021200 | F39: ='Student Headcount'!I39*'Tuition Fee Rates'!D9/12 -> 1555166.7 | G39: ='Student Headcount'!K39*'Tuition Fee Rates'!D10/12 -> 699054.17 | H39: 2755000 | I39: 548077 | J39: 1091667 | K39: 750000 | L39: 541667 | M39: =SUM(C39:L39) -> 19835714
A40: 46204 | B40: FY25/26 | C40: ='Student Headcount'!C40*'Tuition Fee Rates'!D6/12 -> 4959789.2 | D40: ='Student Headcount'!E40*'Tuition Fee Rates'!D7/12 -> 2430200 | E40: ='Student Headcount'!G40*'Tuition Fee Rates'!D8/12 -> 813337.5 | F40: ='Student Headcount'!I40*'Tuition Fee Rates'!D9/12 -> 1234458.3 | G40: ='Student Headcount'!K40*'Tuition Fee Rates'!D10/12 -> 540941.67 | H40: 3190000 | I40: 548077 | J40: 1091667 | K40: 833333 | L40: 541667 | M40: =SUM(C40:L40) -> 16183471
B42: FY Total (all 3 years) | C42: =SUM(C5:C40) -> 2.3973797e+08 | D42: =SUM(D5:D40) -> 1.1830054e+08 | E42: =SUM(E5:E40) -> 90210562 | F42: =SUM(F5:F40) -> 156665750 | G42: =SUM(G5:G40) -> 21512338 | H42: =SUM(H5:H40) -> 100300000 | I42: =SUM(I5:I40) -> 57200000 | J42: =SUM(J5:J40) -> 75300000 | ... M42: =SUM(M5:M40) -> 9.0642716e+08
A46: NOTE
A47: Tuition income = Student Headcount x Tuition Fee Rate / 12 . Other income lines are actuals. All figures in £.

Sheet Staff Costs
A1: Vector University — Staff Costs & Workforce (Monthly Actuals)
A4: Month | B4: FY | C4: Academic Staff Costs | D4: Professional Services Staff Costs | E4: Total Staff Costs | F4: Academic FTE | G4: Professional Services FTE
A5: 45139 | B5: FY23/24 | C5: 9833333 | D5: 5166667 | E5: =SUM(C5:D5) -> 15000000 | F5: 1150 | G5: 980
A6: 45170 | B6: FY23/24 | C6: 9833333 | D6: 5166667 | E6: =SUM(C6:D6) -> 15000000 | F6: 1150 | G6: 980
A7: 45200 | B7: FY23/24 | C7: 9833333 | D7: 5166667 | E7: =SUM(C7:D7) -> 15000000 | F7: 1150 | G7: 980
A8: 45231 | B8: FY23/24 | C8: 9833333 | D8: 5166667 | E8: =SUM(C8:D8) -> 15000000 | F8: 1150 | G8: 980
A9: 45261 | B9: FY23/24 | C9: 9833333 | D9: 5166667 | E9: =SUM(C9:D9) -> 15000000 | F9: 1150 | G9: 980
A10: 45292 | B10: FY23/24 | C10: 9833333 | D10: 5166667 | E10: =SUM(C10:D10) -> 15000000 | F10: 1150 | G10: 980
A11: 45323 | B11: FY23/24 | C11: 9833333 | D11: 5166667 | E11: =SUM(C11:D11) -> 15000000 | F11: 1150 | G11: 980
A12: 45352 | B12: FY23/24 | C12: 9833333 | D12: 5166667 | E12: =SUM(C12:D12) -> 15000000 | F12: 1150 | G12: 980
A13: 45383 | B13: FY23/24 | C13: 9833333 | D13: 5166667 | E13: =SUM(C13:D13) -> 15000000 | F13: 1150 | G13: 980
A14: 45413 | B14: FY23/24 | C14: 9833333 | D14: 5166667 | E14: =SUM(C14:D14) -> 15000000 | F14: 1150 | G14: 980
A15: 45444 | B15: FY23/24 | C15: 9833333 | D15: 5166667 | E15: =SUM(C15:D15) -> 15000000 | F15: 1150 | G15: 980
A16: 45474 | B16: FY23/24 | C16: 9833333 | D16: 5166667 | E16: =SUM(C16:D16) -> 15000000 | F16: 1150 | G16: 980
... A40: 46204 | B40: FY25/26 | C40: 10875000 | D40: 5683333 | E40: =SUM(C40:D40) -> 16558333 | F40: 1230 | G40: 1040

Sheet Operating Expenditure
A1: Vector University — Operating Expenditure (Monthly Actuals)
A4: Month | B4: FY | C4: Utilities | D4: Utilities MOM% | E4: IT & Digital Services | F4: IT MOM% | G4: Estates & Maintenance | H4: Estate&m MOM% | I4: Student Services | J4: Student s MOM% | K4: Marketing & Recruitment | L4: Marketing & Recruitment MOM% | M4: Professional Fees | N4: Professional fees MOM% | O4: Administration | P4: Admin Fees MOM% | Q4: Other Operating Expenditure | R4: other operating Expenditure MOM% | S4: Total Operating Expenditure
A5: 45139 | B5: FY23/24 | C5: 954545 | D5: =(C5-C6)/C5 -> -0.14285759 | E5: 1333333 | F5: =(E6-E5)/E5 -> 0 | G5: 2325203 | H5: =(G6-G5)/G5 -> 0 | I5: 1504132 | J5: =(I5-I6)/I5 -> 0.28571429 | K5: 1200000 | L5: =(K6-K5)/K5 -> -0.5 | M5: 333333 | N5: =(M5-M6)/M5 -> 0 | O5: 750000 | P5: =(O5-O6)/O5 -> 0 | Q5: 666667 | R5: =(Q6-Q5)/Q5 -> 0 | S5: =SUM(C5:Q5) -> 9067212.6
A6: 45170 | B6: FY23/24 | C6: 1090909 | D6: =(C6-C7)/C6 -> -0.24999977 | E6: 1333333 | F6: =(E7-E6)/E6 -> 0 | G6: 2325203 | H6: =(G7-G6)/G6 -> -0.38461545 | I6: 1074380 | J6: =(I6-I7)/I6 -> 0.1 | K6: 600000 | L6: =(K7-K6)/K6 -> -0.125 | M6: 333333 | N6: =(M6-M7)/M6 -> 0 | O6: 750000 | P6: =(O6-O7)/O6 -> 0 | Q6: 666667 | R6: =(Q7-Q6)/Q6 -> 0 | S6: =SUM(C6:Q6) -> 8173824.3
A7: 45200 | B7: FY23/24 | C7: 1363636 | D7: =(C7-C8)/C7 -> -0.30000015 | E7: 1333333 | F7: =(E8-E7)/E7 -> 0 | G7: 1430894 | H7: =(G8-G7)/G7 -> 0 | I7: 966942 | J7: =(I7-I8)/I7 -> 0 | K7: 525000 | L7: =(K8-K7)/K7 -> 0 | M7: 333333 | N7: =(M7-M8)/M7 -> 0 | O7: 750000 | P7: =(O7-O8)/O7 -> 0 | Q7: 666667 | R7: =(Q8-Q7)/Q7 -> 0 | S7: =SUM(C7:Q7) -> 7369804.7
A8: 45231 | B8: FY23/24 | C8: 1772727 | D8: =(C8-C9)/C8 -> -0.076923294 | E8: 1333333 | F8: =(E9-E8)/E8 -> 0 | G8: 1430894 | H8: =(G9-G8)/G8 -> 0 | I8: 966942 | J8: =(I8-I9)/I8 -> -0.44444444 | K8: 525000 | L8: =(K9-K8)/K8 -> 0.85714286 | M8: 333333 | N8: =(M8-M9)/M8 -> 0 | O8: 750000 | P8: =(O8-O9)/O8 -> 0 | Q8: 666667 | R8: =(Q9-Q8)/Q8 -> 0 | S8: =SUM(C8:Q8) -> 7778896.3
A9: 45261 | B9: FY23/24 | C9: 1909091 | D9: =(C9-C10)/C9 -> 0.071428759 | E9: 1333333 | F9: =(E10-E9)/E9 -> 0 | G9: 1430894 | H9: =(G10-G9)/G9 -> 0 | I9: 1396694 | J9: =(I9-I10)/I9 -> 0.23076923 | K9: 975000 | L9: =(K10-K9)/K9 -> 0.076923077 | M9: 333333 | N9: =(M9-M10)/M9 -> 0 | O9: 750000 | P9: =(O9-O10)/O9 -> 0 | Q9: 666667 | R9: =(Q10-Q9)/Q9 -> 0 | S9: =SUM(C9:Q9) -> 8795012.4
A10: 45292 | B10: FY23/24 | C10: 1772727 | D10: =(C10-C11)/C10 -> 0.15384602 | E10: 1333333 | F10: =(E11-E10)/E10 -> 0 | G10: 1430894 | H10: =(G11-G10)/G10 -> 0 | I10: 1074380 | J10: =(I10-I11)/I10 -> 0.1 | K10: 1050000 | L10: =(K11-K10)/K10 -> -0.071428571 | M10: 333333 | N10: =(M10-M11)/M10 -> -2.7500038 | O10: 750000 | P10: =(O10-O11)/O10 -> 0 | Q10: 666667 | R10: =(Q11-Q10)/Q10 -> 0 | S10: =SUM(C10:Q10) -> 8411331.4
A11: 45323 | B11: FY23/24 | C11: 1500000 | D11: =(C11-C12)/C11 -> 0.181818 | E11: 1333333 | F11: =(E12-E11)/E11 -> 0 | G11: 1430894 | H11: =(G12-G11)/G11 -> 0.12500017 | I11: 966942 | J11: =(I11-I12)/I11 -> 0 | K11: 975000 | L11: =(K12-K11)/K11 -> -0.30769231 | M11: 1250000 | N11: =(M11-M12)/M11 -> 0.7333336 | O11: 750000 | P11: =(O11-O12)/O11 -> 0 | Q11: 666667 | R11: =(Q12-Q11)/Q11 -> 0 | S11: =SUM(C11:Q11) -> 8872836.7
A12: 45352 | B12: FY23/24 | C12: 1227273 | D12: =(C12-C13)/C12 -> 0.22222277 | E12: 1333333 | F12: =(E13-E12)/E12 -> 0 | G12: 1609756 | H12: =(G13-G12)/G12 -> 0 | I12: 966942 | J12: =(I12-I13)/I12 -> 0 | K12: 675000 | L12: =(K13-K12)/K12 -> -0.22222222 | M12: 333333 | N12: =(M12-M13)/M12 -> 0 | O12: 750000 | P12: =(O12-O13)/O12 -> 0 | Q12: 666667 | R12: =(Q13-Q12)/Q12 -> 0 | S12: =SUM(C12:Q12) -> 7562304
A13: 45383 | B13: FY23/24 | C13: 954545 | D13: =(C13-C14)/C13 -> 0.14285654 | E13: 1333333 | F13: =(E14-E13)/E13 -> 0 | G13: 1609756 | H13: =(G14-G13)/G13 -> 0.2222225 | I13: 966942 | J13: =(I13-I14)/I13 -> 0 | K13: 525000 | L13: =(K14-K13)/K13 -> -0.14285714 | M13: 333333 | N13: =(M13-M14)/M13 -> 0 | O13: 750000 | P13: =(O13-O14)/O13 -> 0 | Q13: 666667 | R13: =(Q14-Q13)/Q13 -> 0 | S13: =SUM(C13:Q13) -> 7139576.2
A14: 45413 | B14: FY23/24 | C14: 818182 | D14: =(C14-C15)/C14 -> 0 | E14: 1333333 | F14: =(E15-E14)/E14 -> 0 | G14: 1967480 | H14: =(G15-G14)/G14 -> 0.27272704 | I14: 966942 | J14: =(I14-I15)/I14 -> -0.11111111 | K14: 450000 | L14: =(K15-K14)/K14 -> 0 | M14: 333333 | N14: =(M14-M15)/M14 -> 0 | O14: 750000 | P14: =(O14-O15)/O14 -> 0 | Q14: 666667 | R14: =(Q15-Q14)/Q14 -> 0 | S14: =SUM(C14:Q14) -> 7285937.2
A15: 45444 | B15: FY23/24 | C15: 818182 | D15: =(C15-C16)/C15 -> 0 | E15: 1333333 | F15: =(E16-E15)/E15 -> 0 | G15: 2504065 | H15: =(G16-G15)/G15 -> 0 | I15: 1074380 | J15: =(I15-I16)/I15 -> 0 | K15: 450000 | L15: =(K16-K15)/K15 -> 1.3333333 | M15: 333333 | N15: =(M15-M16)/M15 -> -0.25000225 | O15: 750000 | P15: =(O15-O16)/O15 -> 0 | Q15: 666667 | R15: =(Q16-Q15)/Q15 -> 0 | S15: =SUM(C15:Q15) -> 7929961.1
A16: 45474 | B16: FY23/24 | C16: 818182 | D16: =(C16-C17)/C16 -> -0.25999961 | E16: 1333333 | F16: =(E17-E16)/E16 -> 0.050000263 | G16: 2504065 | H16: =(G17-G16)/G16 -> -0.033441624 | I16: 1074380 | J16: =(I16-I17)/I16 -> -0.44307694 | K16: 1050000 | L16: =(K17-K16)/K16 -> 0.18095238 | M16: 416667 | N16: =(M16-M17)/M16 -> 0.18400065 | O16: 750000 | P16: =(O16-O17)/O16 -> -0.033333333 | Q16: 666667 | R16: =(Q17-Q16)/Q16 -> 0.024998988 | S16: =SUM(C16:Q16) -> 8613293.6
... A40: 46204 | B40: FY25/26 | C40: 954545 | D40: =(C40-C41)/C40 -> 1 | E40: 1466667 | F40: =(E41-E40)/E40 -> -1 | G40: 2708943 | H40: =(G41-G40)/G40 -> -1 | I40: 1140496 | J40: =(I40-I41)/I40 -> 1 | K40: 1120000 | L40: =(K41-K40)/K40 -> -1 | M40: 433333 | N40: =(M40-M41)/M40 -> 1 | O40: 800000 | P40: =(O40-O41)/O40 -> 1 | Q40: 700000 | R40: =(Q41-Q40)/Q40 -> -1 | S40: =SUM(C40:Q40) -> 9323985

Sheet Income Statement
A1: Vector University — Forecast Income Statement (Monthly Summary)
A4: Month | B4: FY | C4: Total Income | D4: Total Staff Costs | E4: Total Operating Expenditure | F4: Operating Surplus / (Deficit) | G4: Operating Margin %
A5: 45139 | B5: FY23/24 | C5: =Income!M5 -> 16137179 | D5: ='Staff Costs'!E5 -> 15000000 | E5: ='Operating Expenditure'!S5 -> 9067212.6 | F5: =C5-D5-E5 -> -7930033.3 | G5: =F5/C5 -> -0.49141384
A6: 45170 | B6: FY23/24 | C6: =Income!M6 -> 33586577 | D6: ='Staff Costs'!E6 -> 15000000 | E6: ='Operating Expenditure'!S6 -> 8173824.3 | F6: =C6-D6-E6 -> 10412752 | G6: =F6/C6 -> 0.3100272
A7: 45200 | B7: FY23/24 | C7: =Income!M7 -> 30596786 | D7: ='Staff Costs'!E7 -> 15000000 | E7: ='Operating Expenditure'!S7 -> 7369804.7 | F7: =C7-D7-E7 -> 8226981 | G7: =F7/C7 -> 0.26888383
A8: 45231 | B8: FY23/24 | C8: =Income!M8 -> 30849617 | D8: ='Staff Costs'!E8 -> 15000000 | E8: ='Operating Expenditure'!S8 -> 7778896.3 | F8: =C8-D8-E8 -> 8070720.8 | G8: =F8/C8 -> 0.26161494
A9: 45261 | B9: FY23/24 | C9: =Income!M9 -> 25563598 | D9: ='Staff Costs'!E9 -> 15000000 | E9: ='Operating Expenditure'!S9 -> 8795012.4 | F9: =C9-D9-E9 -> 1768585.5 | G9: =F9/C9 -> 0.069183746
A10: 45292 | B10: FY23/24 | C10: =Income!M10 -> 24915014 | D10: ='Staff Costs'!E10 -> 15000000 | E10: ='Operating Expenditure'!S10 -> 8411331.4 | F10: =C10-D10-E10 -> 1503683.1 | G10: =F10/C10 -> 0.060352486
A11: 45323 | B11: FY23/24 | C11: =Income!M11 -> 26575492 | D11: ='Staff Costs'!E11 -> 15000000 | E11: ='Operating Expenditure'!S11 -> 8872836.7 | F11: =C11-D11-E11 -> 2702655.1 | G11: =F11/C11 -> 0.10169727
A12: 45352 | B12: FY23/24 | C12: =Income!M12 -> 22199161 | D12: ='Staff Costs'!E12 -> 15000000 | E12: ='Operating Expenditure'!S12 -> 7562304 | F12: =C12-D12-E12 -> -363143.33 | G12: =F12/C12 -> -0.016358426
A13: 45383 | B13: FY23/24 | C13: =Income!M13 -> 21101098 | D13: ='Staff Costs'!E13 -> 15000000 | E13: ='Operating Expenditure'!S13 -> 7139576.2 | F13: =C13-D13-E13 -> -1038478.1 | G13: =F13/C13 -> -0.049214408
A14: 45413 | B14: FY23/24 | C14: =Income!M14 -> 22956887 | D14: ='Staff Costs'!E14 -> 15000000 | E14: ='Operating Expenditure'!S14 -> 7285937.2 | F14: =C14-D14-E14 -> 670950.17 | G14: =F14/C14 -> 0.029226531
A15: 45444 | B15: FY23/24 | C15: =Income!M15 -> 18323410 | D15: ='Staff Costs'!E15 -> 15000000 | E15: ='Operating Expenditure'!S15 -> 7929961.1 | F15: =C15-D15-E15 -> -4606551.1 | G15: =F15/C15 -> -0.2514025
A16: 45474 | B16: FY23/24 | C16: =Income!M16 -> 15014868 | D16: ='Staff Costs'!E16 -> 15000000 | E16: ='Operating Expenditure'!S16 -> 8613293.6 | F16: =C16-D16-E16 -> -8598425.3 | G16: =F16/C16 -> -0.57266072
... A40: 46204 | B40: FY25/26 | C40: =Income!M40 -> 16183471 | D40: ='Staff Costs'!E40 -> 16558333 | E40: ='Operating Expenditure'!S40 -> 9323985 | F40: =C40-D40-E40 -> -9698847.3 | G40: =F40/C40 -> -0.59930577
A43: Annual Summary (£)
A44: FY | B44: Total Income | C44: Total Staff Costs | D44: Total Operating Expenditure | E44: Operating Surplus / (Deficit) | F44: Operating Margin % | G44: YOY Income
A45: FY23/24 | B45: =SUM(C5:C16) -> 2.8781969e+08 | C45: =SUM(D5:D16) -> 180000000 | D45: =SUM(E5:E16) -> 96999991 | E45: =SUM(F5:F16) -> 10819697 | F45: =E45/B45 -> 0.037591927 | G45: =(B46-B45)/B45 -> 0.066703853
A46: FY24/25 | B46: =SUM(C17:C28) -> 3.0701837e+08 | C46: =SUM(D17:D28) -> 189500004 | D46: =SUM(E17:E28) -> 1.0119999e+08 | E46: =SUM(F17:F28) -> 16318375 | F46: =E46/B46 -> 0.053151136 | G46: =(B46-B45)/B46 -> 0.062532682
A47: FY25/26 | B47: =SUM(C29:C40) -> 3.1158911e+08 | C47: =SUM(D29:D40) -> 198699996 | D47: =SUM(E29:E40) -> 1.055e+08 | E47: =SUM(F29:F40) -> 7389111.5 | F47: =E47/B47 -> 0.02371428 | G47: =(B47-B46)/B47 -> 0.014669119

Sheet Cash Position
A1: Vector University — Cash Position (Monthly)
A4: Month | B4: FY | C4: Opening Cash | D4: Operating Surplus / (Deficit) | E4: Capital Expenditure | F4: Closing Cash
A5: 45139 | B5: FY23/24 | C5: 42000000 | D5: ='Income Statement'!F5 -> -7930033.3 | E5: 750000 | F5: =C5+D5-E5 -> 33319967
A6: 45170 | B6: FY23/24 | C6: =F5 -> 33319967 | D6: ='Income Statement'!F6 -> 10412752 | E6: 750000 | F6: =C6+D6-E6 -> 42982719
A7: 45200 | B7: FY23/24 | C7: =F6 -> 42982719 | D7: ='Income Statement'!F7 -> 8226981 | E7: 750000 | F7: =C7+D7-E7 -> 50459700
A8: 45231 | B8: FY23/24 | C8: =F7 -> 50459700 | D8: ='Income Statement'!F8 -> 8070720.8 | E8: 750000 | F8: =C8+D8-E8 -> 57780421
A9: 45261 | B9: FY23/24 | C9: =F8 -> 57780421 | D9: ='Income Statement'!F9 -> 1768585.5 | E9: 750000 | F9: =C9+D9-E9 -> 58799006
A10: 45292 | B10: FY23/24 | C10: =F9 -> 58799006 | D10: ='Income Statement'!F10 -> 1503683.1 | E10: 750000 | F10: =C10+D10-E10 -> 59552689
A11: 45323 | B11: FY23/24 | C11: =F10 -> 59552689 | D11: ='Income Statement'!F11 -> 2702655.1 | E11: 750000 | F11: =C11+D11-E11 -> 61505344
A12: 45352 | B12: FY23/24 | C12: =F11 -> 61505344 | D12: ='Income Statement'!F12 -> -363143.33 | E12: 750000 | F12: =C12+D12-E12 -> 60392201
A13: 45383 | B13: FY23/24 | C13: =F12 -> 60392201 | D13: ='Income Statement'!F13 -> -1038478.1 | E13: 750000 | F13: =C13+D13-E13 -> 58603723
A14: 45413 | B14: FY23/24 | C14: =F13 -> 58603723 | D14: ='Income Statement'!F14 -> 670950.17 | E14: 750000 | F14: =C14+D14-E14 -> 58524673
A15: 45444 | B15: FY23/24 | C15: =F14 -> 58524673 | D15: ='Income Statement'!F15 -> -4606551.1 | E15: 750000 | F15: =C15+D15-E15 -> 53168122
A16: 45474 | B16: FY23/24 | C16: =F15 -> 53168122 | D16: ='Income Statement'!F16 -> -8598425.3 | E16: 750000 | F16: =C16+D16-E16 -> 43819697
A17: 45505 | B17: FY24/25 | C17: =F16 -> 43819697 | D17: ='Income Statement'!F17 -> -7489796.6 | E17: 791667 | F17: =C17+D17-E17 -> 35538233
... A40: 46204 | B40: FY25/26 | C40: =F39 -> 58559364 | D40: ='Income Statement'!F40 -> -9698847.3 | E40: 833333 | F40: =C40+D40-E40 -> 48027183

Sheet Historical performance
A1: Vector University — Historical Performance Analysis
A3: Total Expenditure
A5: FY | B5: Sum of Total Operating Expenditure | C5: YOY
A6: FY23/24 | B6: 96999991 | C6: =(B7-B6)/B6 -> 0.043298973
A7: FY24/25 | B7: 1.0119999e+08 | C7: =(B8-B7)/B7 -> 0.042490215
A8: FY25/26 | B8: 1.055e+08 | C8: -
A9: Total Result | B9: 3.0369998e+08
A11: Breakdown of Total Operating Expenditure 1
B14: Data | F14: Utilities yoy % | G14: IT and digital services YOY % | H14: Estate and maintenance YOY%
A15: FY | B15: Sum of Total Operating Expenditure | C15: Sum of Utilities | D15: Sum of IT & Digital Services | E15: Sum of Estates & Maintenance | F15: =C15/B15 -> #VALUE! | G15: =D15/B15 -> #VALUE! | H15: =E15/B15 -> #VALUE!
A16: FY23/24 | B16: 96999991 | C16: 14999999 | D16: 15999996 | E16: 21999998 | F16: =C16/B16 -> 0.15463918 | G16: =D16/B16 -> 0.16494843 | H16: =E16/B16 -> 0.22680412
A17: FY24/25 | B17: 1.0119999e+08 | C17: 16199998 | D17: 16800000 | E17: 22900000 | F17: =C17/B17 -> 0.16007905 | G17: =D17/B17 -> 0.16600792 | H17: =E17/B17 -> 0.22628461
A18: FY25/26 | B18: 1.055e+08 | C18: 17499998 | D18: 17600004 | E18: 23799996 | F18: =C18/B18 -> 0.16587676 | G18: =D18/B18 -> 0.16682468 | H18: =E18/B18 -> 0.22559238
A19: Total Result | B19: 3.0369998e+08 | C19: 48699995 | D19: 50400000 | E19: 68699994
A21: Breakdown of Total Operating Expenditure 2
B23: Data | H23: Student Services yoy % | I23: Marketing&Recruitment YOY % | J23: Professional Fees YOY% | K23: Admin Fees YOY% | L23: Other OperatingExpenses YOY%
A24: FY | B24: Sum of Total Operating Expenditure | C24: Sum of Student Services | D24: Sum of Marketing & Recruitment | E24: Sum of Professional Fees | F24: Sum of Administration | G24: Sum of Other Operating Expenditure | H24: =C24/B24 -> #VALUE! | I24: =D24/B24 -> #VALUE! | J24: =E24/B24 -> #VALUE! | K24: =F24/B24 -> #VALUE! | L24: =G24/B24 -> #VALUE!
A25: FY23/24 | B25: 96999991 | C25: 12999998 | D25: 9000000 | E25: 4999997 | F25: 9000000 | G25: 8000004 | H25: =C25/B25 -> 0.13402061 | I25: =D25/B25 -> 0.092783514 | J25: =E25/B25 -> 0.051546366 | K25: =F25/B25 -> 0.092783514 | L25: =G25/B25 -> 0.082474276
A26: FY24/25 | B26: 1.0119999e+08 | C26: 13399998 | D26: 9300000 | E26: 5100000 | F26: 9300000 | G26: 8199996 | H26: =C26/B26 -> 0.13241106 | I26: =D26/B26 -> 0.091897242 | J26: =E26/B26 -> 0.050395262 | K26: =F26/B26 -> 0.091897242 | L26: =G26/B26 -> 0.081027636
A27: FY25/26 | B27: 1.055e+08 | C27: 13799999 | D27: 9600000 | E27: 5200003 | F27: 9600000 | G27: 8400000 | H27: =C27/B27 -> 0.13080568 | I27: =D27/B27 -> 0.090995261 | J27: =E27/B27 -> 0.049289128 | K27: =F27/B27 -> 0.090995261 | L27: =G27/B27 -> 0.079620853
A28: Total Result | B28: 3.0369998e+08 | C28: 40199995 | D28: 27900000 | E28: 15300000 | F28: 27900000 | G28: 24600000
A30: Breakdown of Total income
B32: Data
A33: FY | B33: Sum of Total Income | C33: Sum of UK Undergraduate Tuition | D33: Sum of International Undergraduate Tuition | E33: Sum of UK Postgraduate Tuition | F33: Sum of International Postgraduate Tuition | G33: Sum of Postgraduate Research (PGR) Tuition | H33: Sum of Research Grants & Contracts | I33: Sum of Government & Funding Body Grants | J33: Sum of Student Accommodation Income | K33: Sum of Commercial & Professional Services | L33: Sum of Other Operating Income
A34: FY23/24 | B34: 2.8781969e+08 | C34: 78105458 | D34: 37227333 | E34: 27295938 | F34: 48720750 | G34: 6470208.3 | H34: 32000000 | I34: 19000000 | J34: 24000000 | K34: 9000000 | L34: 6000000
A35: FY24/25 | B35: 3.0701837e+08 | C35: 78941812 | D35: 40154362 | E35: 30555350 | F35: 56696167 | G35: 7170675 | H35: 33500000 | I35: 19200000 | J35: 25099999 | K35: 9500000 | L35: 6200004
A36: FY25/26 | B36: 3.1158911e+08 | C36: 82690698 | D36: 40918842 | E36: 32359275 | F36: 51248833 | G36: 7871454.2 | H36: 34800000 | I36: 19000000 | J36: 26200001 | K36: 10000000 | L36: 6500004
A37: Total Result | B37: 9.0642716e+08 | C37: 2.3973797e+08 | D37: 1.1830054e+08 | E37: 90210562 | F37: 156665750 | G37: 21512338 | H37: 100300000 | I37: 57200000 | J37: 75300000 | K37: 28500000 | L37: 18700008

Sheet Historical KPI Summary
A1: Vector University — Historical KPI Summary & Corrected Analysis (FY23/24 – FY25/26)
A2: Corrects and extends the Day 2 historical review: annual KPI trend, tuition income ranking, and international recruitment dependency.
A4: A. Annual Financial KPI Trend
A5: FY | B5: Total Income (£) | C5: Income YoY % | D5: Total Staff Costs (£) | E5: Staff Cost YoY % | F5: Total Operating Expenditure (£) | G5: Opex YoY % | H5: Operating Surplus / (Deficit) (£) | I5: Operating Margin %
A6: FY23/24 | B6: ='Income Statement'!B45 -> 2.8781969e+08 | C6: ='Income Statement'!G45 -> 0.066703853 | D6: ='Income Statement'!C45 -> 180000000 | E6: n/a (no FY22/23 baseline) | F6: ='Income Statement'!D45 -> 96999991 | G6: n/a (no FY22/23 baseline) | H6: ='Income Statement'!E45 -> 10819697 | I6: ='Income Statement'!F45 -> 0.037591927
A7: FY24/25 | B7: ='Income Statement'!B46 -> 3.0701837e+08 | C7: ='Income Statement'!G46 -> 0.062532682 | D7: ='Income Statement'!C46 -> 189500004 | E7: =D7/D6-1 -> 0.0527778 | F7: ='Income Statement'!D46 -> 1.0119999e+08 | G7: =F7/F6-1 -> 0.043298973 | H7: ='Income Statement'!E46 -> 16318375 | I7: ='Income Statement'!F46 -> 0.053151136
A8: FY25/26 | B8: ='Income Statement'!B47 -> 3.1158911e+08 | C8: ='Income Statement'!G47 -> 0.014669119 | D8: ='Income Statement'!C47 -> 198699996 | E8: =D8/D7-1 -> 0.048548769 | F8: ='Income Statement'!D47 -> 1.055e+08 | G8: =F8/F7-1 -> 0.042490215 | H8: ='Income Statement'!E47 -> 7389111.5 | I8: ='Income Statement'!F47 -> 0.02371428
A10: B. Key Findings (corrected per 15-Sep-2026 feedback)
A11: 1. Income growth decelerated sharply from 6.7% in FY24/25 to just 1.5% in FY25/26 (after 6.3% growth the year before), while staff cost growth (5.3% → 4.9%) and operating cost growth (4.3% → 4.2%) continued at a broadly similar pace. Because staff costs and operating expenditure together represent c.90% of total costs and cannot be reduced as quickly as income can fall, a period of income deceleration compresses profitability disproportionately — exactly what the FY25/26 numbers show.
A12: 2. Operating margin rose from 3.8% (FY23/24) to a peak of 5.3% (FY24/25), then fell sharply to 2.4% (FY25/26). In cash terms, operating surplus fell from £16.32m in FY24/25 to £7.39m in FY25/26 — a decline of approximately 54.7% in a single year. This is the single most important finding in the historical data and is an early warning indicator for financial sustainability if income growth does not recover.
A13: 3. Correction: UK Undergraduate tuition, not International Postgraduate, is the University's largest individual tuition category — £82.69m in FY25/26 versus £51.25m for International Postgraduate. International Postgraduate is nonetheless the largest single INTERNATIONAL income stream and, combined with International Undergraduate (£40.92m), international tuition (£92.17m) represents c.42.9% of tuition income and c.29.6% of total University income — a material, though not majority, dependency (see Section D).
A15: C. Tuition Income by Category — FY25/26 (Ranked, Corrected)
A16: Rank | B16: Category | C16: FY25/26 Tuition Income (£) | D16: % of Total Tuition Income
A17: 1 | B17: UK Undergraduate | C17: =SUMIFS(Income!C:C,Income!$B:$B,"FY25/26") -> 82690698 | D17: =C17/C22 -> 0.38444857
A18: 2 | B18: International Postgraduate | C18: =SUMIFS(Income!F:F,Income!$B:$B,"FY25/26") -> 51248833 | D18: =C18/C22 -> 0.23826792
A19: 3 | B19: International Undergraduate | C19: =SUMIFS(Income!D:D,Income!$B:$B,"FY25/26") -> 40918842 | D19: =C19/C22 -> 0.19024135
A20: 4 | B20: UK Postgraduate | C20: =SUMIFS(Income!E:E,Income!$B:$B,"FY25/26") -> 32359275 | D20: =C20/C22 -> 0.15044591
A21: 5 | B21: Postgraduate Research (PGR) | C21: =SUMIFS(Income!G:G,Income!$B:$B,"FY25/26") -> 7871454.2 | D21: =C21/C22 -> 0.036596248
A22: Total | C22: =SUM(C17:C21) -> 2.150891e+08 | D22: =SUM(D17:D21) -> 1
A24: D. International Recruitment Dependency — FY25/26
A25: International Undergraduate tuition (£) | B25: =SUMIFS(Income!D:D,Income!$B:$B,"FY25/26") -> 40918842
A26: International Postgraduate tuition (£) | B26: =SUMIFS(Income!F:F,Income!$B:$B,"FY25/26") -> 51248833
A27: Total international tuition income (£) | B27: =B25+B26 -> 92167675
A28: Total tuition income, all categories (£) | B28: =C22 -> 2.150891e+08
A29: International share of total tuition income (%) | B29: =B27/B28 -> 0.42850927
A30: Total University income, FY25/26 (£) | B30: ='Income Statement'!B47 -> 3.1158911e+08
A31: International tuition as % of total University income | B31: =B27/B30 -> 0.29579877
A33: Sources: 'Income Statement' (annual summary, rows 45-47). Tuition income by category is summed directly from monthly actuals on the 'Income' tab via SUMIFS (not from the 'Historical performance' pivot tables, whose row positions shift whenever the pivot cache is refreshed). Staff Cost YoY % and Operating Expenditure YoY % are derived here (not present in the original Income Statement tab).

Sheet Scenario Assumptions
A1: Vector University — Scenario Assumptions (Base / Upside / Downside)
A2: Pick a scenario in the selector below and 'Forecast Assumptions' — and everything downstream (Population, Income, Staff Cost, Opex, Forecast Income Statement, Cash Flow) — recalculates for it. Base Case values are the original assumptions from the initial build; Upside and Downside are point-in-time adjustments (in percentage points) applied on top of them for the three tested levers.
A4: A. Scenario Selector
A5: Active Scenario: | B5: Base
A7: B. Scenario Adjustment Levers (percentage points, applied on top of Base)
A8: Lever | B8: Base | C8: Upside | D8: Downside
A9: Recruitment Growth Adjustment (applied to every category's Application Growth %, every year) | B9: 0 | C9: 0.02 | D9: -0.03
A10: Salary Inflation Adjustment (applied to Academic & Professional Services Salary Inflation %, every year) | B10: 0 | C10: -0.01 | D10: 0.015
A11: Operating Cost Inflation Adjustment (applied to Utilities & General Operating Cost Inflation %, every year) | B11: 0 | C11: -0.005 | D11: 0.01
A13: C. Selected Adjustment (driven by the Scenario Selector above)
A14: Lever | B14: Selected Value
A15: Recruitment Growth Adjustment (applied to every category's Application Growth %, every year) | B15: =IF(B5="Base",B9,IF(B5="Upside",C9,D9)) -> 0
A16: Salary Inflation Adjustment (applied to Academic & Professional Services Salary Inflation %, every year) | B16: =IF(B5="Base",B10,IF(B5="Upside",C10,D10)) -> 0
A17: Operating Cost Inflation Adjustment (applied to Utilities & General Operating Cost Inflation %, every year) | B17: =IF(B5="Base",B11,IF(B5="Upside",C11,D11)) -> 0
A19: D. Base Case Reference Values (original FY26/27–FY28/29 assumptions)
A20: Item | B20: FY26/27 | C20: FY27/28 | D20: FY28/29
A21: D1. Application Growth % by category
A22: UK Undergraduate | B22: 0.02 | C22: 0.02 | D22: 0.02
A23: International Undergraduate | B23: 0.01 | C23: 0.01 | D23: 0.02
A24: UK Postgraduate | B24: 0.02 | C24: 0.02 | D24: 0.02
A25: International Postgraduate | B25: 0.01 | C25: 0.02 | D25: 0.02
A26: Postgraduate Research (PGR) | B26: 0.02 | C26: 0.02 | D26: 0.02
A28: D2. Salary Inflation % by staff group
A29: Academic | B29: 0.045 | C29: 0.04 | D29: 0.04
A30: Professional Services | B30: 0.04 | C30: 0.04 | D30: 0.04
A32: D3. Operating Cost Inflation % by line
A33: Utilities | B33: 0.05 | C33: 0.04 | D33: 0.035
A34: General (IT/Estates/Student Services/Marketing/Prof Fees/Admin/Other) | B34: 0.035 | C34: 0.035 | D34: 0.035
A36: Blue cells are the editable inputs. Section D holds the original Base Case numbers (now referenced by 'Forecast Assumptions' rather than typed there directly); Section B holds the Upside/Downside deltas; Section C shows which delta is currently active. Change the selector in Section A to switch the whole model.

Sheet Forecast Assumptions
A1: Vector University — Forecast Assumptions (FY26/27 – FY28/29)
A4: A. Student Recruitment Assumptions (by category)
A5: Category | B5: Assumption | C5: FY26/27 | D5: FY27/28 | E5: FY28/29
A6: UK Undergraduate | B6: Application Growth % | C6: ='Scenario Assumptions'!B22+'Scenario Assumptions'!$B$15 -> 0.02 | D6: ='Scenario Assumptions'!C22+'Scenario Assumptions'!$B$15 -> 0.02 | E6: ='Scenario Assumptions'!D22+'Scenario Assumptions'!$B$15 -> 0.02
B7: Offer Rate % | C7: 0.78 | D7: 0.78 | E7: 0.78
B8: Acceptance / Yield Rate % | C8: 0.62 | D8: 0.62 | E8: 0.63
B9: Annual Withdrawal Rate % | C9: 0.018 | D9: 0.018 | E9: 0.018
B10: Typical Course Length (Years) | C10: 3 | D10: 3 | E10: 3
A11: International Undergraduate | B11: Application Growth % | C11: ='Scenario Assumptions'!B23+'Scenario Assumptions'!$B$15 -> 0.01 | D11: ='Scenario Assumptions'!C23+'Scenario Assumptions'!$B$15 -> 0.01 | E11: ='Scenario Assumptions'!D23+'Scenario Assumptions'!$B$15 -> 0.02
B12: Offer Rate % | C12: 0.7 | D12: 0.7 | E12: 0.7
B13: Acceptance / Yield Rate % | C13: 0.44 | D13: 0.44 | E13: 0.45
B14: Annual Withdrawal Rate % | C14: 0.033 | D14: 0.033 | E14: 0.033
B15: Typical Course Length (Years) | C15: 3 | D15: 3 | E15: 3
A16: UK Postgraduate | B16: Application Growth % | C16: ='Scenario Assumptions'!B24+'Scenario Assumptions'!$B$15 -> 0.02 | D16: ='Scenario Assumptions'!C24+'Scenario Assumptions'!$B$15 -> 0.02 | E16: ='Scenario Assumptions'!D24+'Scenario Assumptions'!$B$15 -> 0.02
B17: Offer Rate % | C17: 0.82 | D17: 0.82 | E17: 0.82
B18: Acceptance / Yield Rate % | C18: 0.68 | D18: 0.68 | E18: 0.69
B19: Annual Withdrawal Rate % | C19: 0.02 | D19: 0.02 | E19: 0.02
B20: Typical Course Length (Years) | C20: 1 | D20: 1 | E20: 1
A21: International Postgraduate | B21: Application Growth % | C21: ='Scenario Assumptions'!B25+'Scenario Assumptions'!$B$15 -> 0.01 | D21: ='Scenario Assumptions'!C25+'Scenario Assumptions'!$B$15 -> 0.02 | E21: ='Scenario Assumptions'!D25+'Scenario Assumptions'!$B$15 -> 0.02
B22: Offer Rate % | C22: 0.74 | D22: 0.73 | E22: 0.73
B23: Acceptance / Yield Rate % | C23: 0.44 | D23: 0.45 | E23: 0.45
B24: Annual Withdrawal Rate % | C24: 0.025 | D24: 0.025 | E24: 0.025
B25: Typical Course Length (Years) | C25: 1 | D25: 1 | E25: 1
A26: Postgraduate Research (PGR) | B26: Application Growth % | C26: ='Scenario Assumptions'!B26+'Scenario Assumptions'!$B$15 -> 0.02 | D26: ='Scenario Assumptions'!C26+'Scenario Assumptions'!$B$15 -> 0.02 | E26: ='Scenario Assumptions'!D26+'Scenario Assumptions'!$B$15 -> 0.02
B27: Offer Rate % | C27: 0.58 | D27: 0.58 | E27: 0.58
B28: Acceptance / Yield Rate % | C28: 0.75 | D28: 0.75 | E28: 0.75
B29: Annual Withdrawal Rate % | C29: 0.012 | D29: 0.012 | E29: 0.012
B30: Typical Course Length (Years) | C30: 4 | D30: 4 | E30: 4
A32: B. Tuition Fee Increase Assumptions (% YoY, by category)
A33: Item | B33: FY26/27 | C33: FY27/28 | D33: FY28/29
A34: UK Undergraduate | B34: 0 | C34: 0.02 | D34: 0.02
A35: International Undergraduate | B35: 0.04 | C35: 0.04 | D35: 0.045
A36: UK Postgraduate | B36: 0.03 | C36: 0.03 | D36: 0.03
A37: International Postgraduate | B37: 0.04 | C37: 0.04 | D37: 0.045
A38: Postgraduate Research (PGR) | B38: 0.03 | C38: 0.03 | D38: 0.03
A40: C. Other Income Growth Assumptions (% YoY, by income line)
A41: Item | B41: FY26/27 | C41: FY27/28 | D41: FY28/29
A42: Research Grants & Contracts | B42: 0.03 | C42: 0.03 | D42: 0.03
A43: Government & Funding Body Grants | B43: 0 | C43: 0 | D43: 0.01
A44: Student Accommodation Income | B44: 0.04 | C44: 0.04 | D44: 0.04
A45: Commercial & Professional Services | B45: 0.04 | C45: 0.04 | D45: 0.04
A46: Other Operating Income | B46: 0.02 | C46: 0.02 | D46: 0.02
A48: D. Staff Cost Assumptions (% YoY)
A49: Item | B49: FY26/27 | C49: FY27/28 | D49: FY28/29
A50: Academic Salary Inflation % | B50: ='Scenario Assumptions'!B29+'Scenario Assumptions'!$B$16 -> 0.045 | C50: ='Scenario Assumptions'!C29+'Scenario Assumptions'!$B$16 -> 0.04 | D50: ='Scenario Assumptions'!D29+'Scenario Assumptions'!$B$16 -> 0.04
A51: Professional Services Salary Inflation % | B51: ='Scenario Assumptions'!B30+'Scenario Assumptions'!$B$16 -> 0.04 | C51: ='Scenario Assumptions'!C30+'Scenario Assumptions'!$B$16 -> 0.04 | D51: ='Scenario Assumptions'!D30+'Scenario Assumptions'!$B$16 -> 0.04
A52: Academic FTE Growth % | B52: 0.02 | C52: 0.02 | D52: 0.02
A53: Professional Services FTE Growth % | B53: 0.015 | C53: 0.015 | D53: 0.015
A55: E. Operating Cost Inflation Assumptions (% YoY)
A56: Item | B56: FY26/27 | C56: FY27/28 | D56: FY28/29
A57: Utilities Inflation % | B57: ='Scenario Assumptions'!B33+'Scenario Assumptions'!$B$17 -> 0.05 | C57: ='Scenario Assumptions'!C33+'Scenario Assumptions'!$B$17 -> 0.04 | D57: ='Scenario Assumptions'!D33+'Scenario Assumptions'!$B$17 -> 0.035
A58: General Operating Cost Inflation % (IT, Estates, Student Services, Marketing, Professional Fees, Admin, Other) | B58: ='Scenario Assumptions'!B34+'Scenario Assumptions'!$B$17 -> 0.035 | C58: ='Scenario Assumptions'!C34+'Scenario Assumptions'!$B$17 -> 0.035 | D58: ='Scenario Assumptions'!D34+'Scenario Assumptions'!$B$17 -> 0.035
A60: F. Capital Expenditure & Opening Cash
A61: Item | B61: FY26/27 | C61: FY27/28 | D61: FY28/29
A62: Planned Capital Expenditure (£) | B62: 10500000 | C62: 11000000 | D62: 11500000
A63: Opening Cash Balance, 1-Aug-2026 (£) | B63: ='Cash Position'!F40 -> 48027183

Sheet Population Forecast
A1: Vector University — 36-Month Student Population Forecast (FY26/27 – FY28/29)
A2: Methodology: Applications are back-solved from FY25/26 New Enrolments ÷ (Offer Rate × Yield Rate), then grown by each category's Application Growth % assumption; New Enrolments = Applications × Offer Rate × Yield Rate for that year. Monthly population = the forecast September (intake-month) population for that financial year, shaped by the category's FY25/26 monthly seasonal pattern — which is why Undergraduate and PGR populations stay relatively stable month to month while taught Postgraduate populations show the sharp September-intake, steady-decay pattern seen in the historical data.
A4: A. Annual New Enrolment & Population Roll-Forward (FY26/27 – FY28/29)
A5: Category | B5: FY | C5: Opening Population | D5: Applications | E5: Application Growth % | F5: Offer Rate % | G5: Yield Rate % | H5: New Enrolments | I5: Withdrawal Rate % | J5: Withdrawals | K5: Graduates | L5: Closing Population | M5: Retention Rate %
A6: UK Undergraduate | B6: FY26/27 | C6: ='Student Flow Summary'!G7 -> 6273 | D6: =('Student Flow Summary'!D7/(F6*G6))*(1+E6) -> 6538.4615 | E6: ='Forecast Assumptions'!C6 -> 0.02 | F6: ='Forecast Assumptions'!C7 -> 0.78 | G6: ='Forecast Assumptions'!C8 -> 0.62 | H6: =D6*F6*G6 -> 3162 | I6: ='Forecast Assumptions'!C9 -> 0.018 | J6: =I6*(C6+H6) -> 169.83 | K6: ='Student Flow Summary'!F7*(H6/'Student Flow Summary'!D7) -> 2907 | L6: =C6+H6-J6-K6 -> 6358.17 | M6: =1-J6/(C6+H6) -> 0.982
A7: UK Undergraduate | B7: FY27/28 | C7: =L6 -> 6358.17 | D7: =D6*(1+E7) -> 6669.2308 | E7: ='Forecast Assumptions'!D6 -> 0.02 | F7: ='Forecast Assumptions'!D7 -> 0.78 | G7: ='Forecast Assumptions'!D8 -> 0.62 | H7: =D7*F7*G7 -> 3225.24 | I7: ='Forecast Assumptions'!D9 -> 0.018 | J7: =I7*(C7+H7) -> 172.50138 | K7: =K6*(H7/H6) -> 2965.14 | L7: =C7+H7-J7-K7 -> 6445.7686 | M7: =1-J7/(C7+H7) -> 0.982
A8: UK Undergraduate | B8: FY28/29 | C8: =L7 -> 6445.7686 | D8: =D7*(1+E8) -> 6802.6154 | E8: ='Forecast Assumptions'!E6 -> 0.02 | F8: ='Forecast Assumptions'!E7 -> 0.78 | G8: ='Forecast Assumptions'!E8 -> 0.63 | H8: =D8*F8*G8 -> 3342.8052 | I8: ='Forecast Assumptions'!E9 -> 0.018 | J8: =I8*(C8+H8) -> 176.19433 | K8: =K7*(H8/H7) -> 3073.2241 | L8: =C8+H8-J8-K8 -> 6539.1554 | M8: =1-J8/(C8+H8) -> 0.982
A9: International Undergraduate | B9: FY26/27 | C9: ='Student Flow Summary'!G10 -> 1408 | D9: =('Student Flow Summary'!D10/(F9*G9))*(1+E9) -> 2115.0974 | E9: ='Forecast Assumptions'!C11 -> 0.01 | F9: ='Forecast Assumptions'!C12 -> 0.7 | G9: ='Forecast Assumptions'!C13 -> 0.44 | H9: =D9*F9*G9 -> 651.45 | I9: ='Forecast Assumptions'!C14 -> 0.033 | J9: =I9*(C9+H9) -> 67.96185 | K9: ='Student Flow Summary'!F10*(H9/'Student Flow Summary'!D10) -> 628.22 | L9: =C9+H9-J9-K9 -> 1363.2682 | M9: =1-J9/(C9+H9) -> 0.967
A10: International Undergraduate | B10: FY27/28 | C10: =L9 -> 1363.2682 | D10: =D9*(1+E10) -> 2136.2484 | E10: ='Forecast Assumptions'!D11 -> 0.01 | F10: ='Forecast Assumptions'!D12 -> 0.7 | G10: ='Forecast Assumptions'!D13 -> 0.44 | H10: =D10*F10*G10 -> 657.9645 | I10: ='Forecast Assumptions'!D14 -> 0.033 | J10: =I10*(C10+H10) -> 66.700677 | K10: =K9*(H10/H9) -> 634.5022 | L10: =C10+H10-J10-K10 -> 1320.0298 | M10: =1-J10/(C10+H10) -> 0.967
A11: International Undergraduate | B11: FY28/29 | C11: =L10 -> 1320.0298 | D11: =D10*(1+E11) -> 2178.9733 | E11: ='Forecast Assumptions'!E11 -> 0.02 | F11: ='Forecast Assumptions'!E12 -> 0.7 | G11: ='Forecast Assumptions'!E13 -> 0.45 | H11: =D11*F11*G11 -> 686.3766 | I11: ='Forecast Assumptions'!E14 -> 0.033 | J11: =I11*(C11+H11) -> 66.21141 | K11: =K10*(H11/H10) -> 661.90116 | L11: =C11+H11-J11-K11 -> 1278.2938 | M11: =1-J11/(C11+H11) -> 0.967
A12: UK Postgraduate | B12: FY26/27 | C12: ='Student Flow Summary'!G13 -> 947 | D12: =('Student Flow Summary'!D13/(F12*G12))*(1+E12) -> 13759.756 | E12: ='Forecast Assumptions'!C16 -> 0.02 | F12: ='Forecast Assumptions'!C17 -> 0.82 | G12: ='Forecast Assumptions'!C18 -> 0.68 | H12: =D12*F12*G12 -> 7672.44 | I12: ='Forecast Assumptions'!C19 -> 0.02 | J12: =I12*(C12+H12) -> 172.3888 | K12: ='Student Flow Summary'!F13*(H12/'Student Flow Summary'!D13) -> 7038 | L12: =C12+H12-J12-K12 -> 1409.0512 | M12: =1-J12/(C12+H12) -> 0.98
A13: UK Postgraduate | B13: FY27/28 | C13: =L12 -> 1409.0512 | D13: =D12*(1+E13) -> 14034.951 | E13: ='Forecast Assumptions'!D16 -> 0.02 | F13: ='Forecast Assumptions'!D17 -> 0.82 | G13: ='Forecast Assumptions'!D18 -> 0.68 | H13: =D13*F13*G13 -> 7825.8888 | I13: ='Forecast Assumptions'!D19 -> 0.02 | J13: =I13*(C13+H13) -> 184.6988 | K13: =K12*(H13/H12) -> 7178.76 | L13: =C13+H13-J13-K13 -> 1871.4812 | M13: =1-J13/(C13+H13) -> 0.98
A14: UK Postgraduate | B14: FY28/29 | C14: =L13 -> 1871.4812 | D14: =D13*(1+E14) -> 14315.65 | E14: ='Forecast Assumptions'!E16 -> 0.02 | F14: ='Forecast Assumptions'!E17 -> 0.82 | G14: ='Forecast Assumptions'!E18 -> 0.69 | H14: =D14*F14*G14 -> 8099.7949 | I14: ='Forecast Assumptions'!E19 -> 0.02 | J14: =I14*(C14+H14) -> 199.42552 | K14: =K13*(H14/H13) -> 7430.0166 | L14: =C14+H14-J14-K14 -> 2341.834 | M14: =1-J14/(C14+H14) -> 0.98
A15: International Postgraduate | B15: FY26/27 | C15: ='Student Flow Summary'!G16 -> 689 | D15: =('Student Flow Summary'!D16/(F15*G15))*(1+E15) -> 17938.667 | E15: ='Forecast Assumptions'!C21 -> 0.01 | F15: ='Forecast Assumptions'!C22 -> 0.74 | G15: ='Forecast Assumptions'!C23 -> 0.44 | H15: =D15*F15*G15 -> 5840.83 | I15: ='Forecast Assumptions'!C24 -> 0.025 | J15: =I15*(C15+H15) -> 163.24575 | K15: ='Student Flow Summary'!F16*(H15/'Student Flow Summary'!D16) -> 5477.23 | L15: =C15+H15-J15-K15 -> 889.35425 | M15: =1-J15/(C15+H15) -> 0.975
A16: International Postgraduate | B16: FY27/28 | C16: =L15 -> 889.35425 | D16: =D15*(1+E16) -> 18297.44 | E16: ='Forecast Assumptions'!D21 -> 0.02 | F16: ='Forecast Assumptions'!D22 -> 0.73 | G16: ='Forecast Assumptions'!D23 -> 0.45 | H16: =D16*F16*G16 -> 6010.7092 | I16: ='Forecast Assumptions'!D24 -> 0.025 | J16: =I16*(C16+H16) -> 172.50159 | K16: =K15*(H16/H15) -> 5636.534 | L16: =C16+H16-J16-K16 -> 1091.0279 | M16: =1-J16/(C16+H16) -> 0.975
A17: International Postgraduate | B17: FY28/29 | C17: =L16 -> 1091.0279 | D17: =D16*(1+E17) -> 18663.389 | E17: ='Forecast Assumptions'!E21 -> 0.02 | F17: ='Forecast Assumptions'!E22 -> 0.73 | G17: ='Forecast Assumptions'!E23 -> 0.45 | H17: =D17*F17*G17 -> 6130.9234 | I17: ='Forecast Assumptions'!E24 -> 0.025 | J17: =I17*(C17+H17) -> 180.54878 | K17: =K16*(H17/H16) -> 5749.2646 | L17: =C17+H17-J17-K17 -> 1292.1378 | M17: =1-J17/(C17+H17) -> 0.975
A18: Postgraduate Research (PGR) | B18: FY26/27 | C18: ='Student Flow Summary'!G19 -> 930 | D18: =('Student Flow Summary'!D19/(F18*G18))*(1+E18) -> 794.89655 | E18: ='Forecast Assumptions'!C26 -> 0.02 | F18: ='Forecast Assumptions'!C27 -> 0.58 | G18: ='Forecast Assumptions'!C28 -> 0.75 | H18: =D18*F18*G18 -> 345.78 | I18: ='Forecast Assumptions'!C29 -> 0.012 | J18: =I18*(C18+H18) -> 15.30936 | K18: ='Student Flow Summary'!F19*(H18/'Student Flow Summary'!D19) -> 278.46 | L18: =C18+H18-J18-K18 -> 982.01064 | M18: =1-J18/(C18+H18) -> 0.988
A19: Postgraduate Research (PGR) | B19: FY27/28 | C19: =L18 -> 982.01064 | D19: =D18*(1+E19) -> 810.79448 | E19: ='Forecast Assumptions'!D26 -> 0.02 | F19: ='Forecast Assumptions'!D27 -> 0.58 | G19: ='Forecast Assumptions'!D28 -> 0.75 | H19: =D19*F19*G19 -> 352.6956 | I19: ='Forecast Assumptions'!D29 -> 0.012 | J19: =I19*(C19+H19) -> 16.016475 | K19: =K18*(H19/H18) -> 284.0292 | L19: =C19+H19-J19-K19 -> 1034.6606 | M19: =1-J19/(C19+H19) -> 0.988
A20: Postgraduate Research (PGR) | B20: FY28/29 | C20: =L19 -> 1034.6606 | D20: =D19*(1+E20) -> 827.01037 | E20: ='Forecast Assumptions'!E26 -> 0.02 | F20: ='Forecast Assumptions'!E27 -> 0.58 | G20: ='Forecast Assumptions'!E28 -> 0.75 | H20: =D20*F20*G20 -> 359.74951 | I20: ='Forecast Assumptions'!E29 -> 0.012 | J20: =I20*(C20+H20) -> 16.732921 | K20: =K19*(H20/H19) -> 289.70978 | L20: =C20+H20-J20-K20 -> 1087.9674 | M20: =1-J20/(C20+H20) -> 0.988
A22: B. FY25/26 Monthly Seasonal Shape (index vs. September = 1.00)
A23: Category | B23: Aug | C23: Sep | D23: Oct | E23: Nov | F23: Dec | G23: Jan | H23: Feb | I23: Mar | J23: Apr | K23: May | L23: Jun | M23: Jul
A24: UK Undergraduate | B24: ='Student Headcount'!C29/'Student Headcount'!$C$30 -> 0.66756757 | C24: ='Student Headcount'!C30/'Student Headcount'!$C$30 -> 1 | D24: ='Student Headcount'!C31/'Student Headcount'!$C$30 -> 0.98454054 | E24: ='Student Headcount'!C32/'Student Headcount'!$C$30 -> 0.99481081 | F24: ='Student Headcount'!C33/'Student Headcount'!$C$30 -> 0.99632432 | G24: ='Student Headcount'!C34/'Student Headcount'!$C$30 -> 0.99578378 | H24: ='Student Headcount'!C35/'Student Headcount'!$C$30 -> 0.98443243 | I24: ='Student Headcount'!C36/'Student Headcount'!$C$30 -> 0.9892973 | J24: ='Student Headcount'!C37/'Student Headcount'!$C$30 -> 0.98475676 | K24: ='Student Headcount'!C38/'Student Headcount'!$C$30 -> 0.98432432 | L24: ='Student Headcount'!C39/'Student Headcount'!$C$30 -> 0.99394595 | M24: ='Student Headcount'!C40/'Student Headcount'!$C$30 -> 0.67481081
A25: International Undergraduate | B25: ='Student Headcount'!E29/'Student Headcount'!$E$30 -> 0.69596542 | C25: ='Student Headcount'!E30/'Student Headcount'!$E$30 -> 1 | D25: ='Student Headcount'!E31/'Student Headcount'!$E$30 -> 1.0009606 | E25: ='Student Headcount'!E32/'Student Headcount'!$E$30 -> 0.99039385 | F25: ='Student Headcount'!E33/'Student Headcount'!$E$30 -> 0.99087416 | G25: ='Student Headcount'!E34/'Student Headcount'!$E$30 -> 0.99039385 | H25: ='Student Headcount'!E35/'Student Headcount'!$E$30 -> 0.99423631 | I25: ='Student Headcount'!E36/'Student Headcount'!$E$30 -> 0.99279539 | J25: ='Student Headcount'!E37/'Student Headcount'!$E$30 -> 0.97550432 | K25: ='Student Headcount'!E38/'Student Headcount'!$E$30 -> 0.97598463 | L25: ='Student Headcount'!E39/'Student Headcount'!$E$30 -> 0.98174832 | M25: ='Student Headcount'!E40/'Student Headcount'!$E$30 -> 0.6685879
A26: UK Postgraduate | B26: ='Student Headcount'!G29/'Student Headcount'!$G$30 -> 0.098119703 | C26: ='Student Headcount'!G30/'Student Headcount'!$G$30 -> 1 | D26: ='Student Headcount'!G31/'Student Headcount'!$G$30 -> 0.81355932 | E26: ='Student Headcount'!G32/'Student Headcount'!$G$30 -> 0.65161547 | F26: ='Student Headcount'!G33/'Student Headcount'!$G$30 -> 0.51655191 | G26: ='Student Headcount'!G34/'Student Headcount'!$G$30 -> 0.47775424 | H26: ='Student Headcount'!G35/'Student Headcount'!$G$30 -> 0.38241525 | I26: ='Student Headcount'!G36/'Student Headcount'!$G$30 -> 0.30442267 | J26: ='Student Headcount'!G37/'Student Headcount'!$G$30 -> 0.2465572 | K26: ='Student Headcount'!G38/'Student Headcount'!$G$30 -> 0.1953125 | L26: ='Student Headcount'!G39/'Student Headcount'!$G$30 -> 0.15677966 | M26: ='Student Headcount'!G40/'Student Headcount'!$G$30 -> 0.12486758
A27: International Postgraduate | B27: ='Student Headcount'!I29/'Student Headcount'!$I$30 -> 0.1074199 | C27: ='Student Headcount'!I30/'Student Headcount'!$I$30 -> 1 | D27: ='Student Headcount'!I31/'Student Headcount'!$I$30 -> 0.79106239 | E27: ='Student Headcount'!I32/'Student Headcount'!$I$30 -> 0.63355818 | F27: ='Student Headcount'!I33/'Student Headcount'!$I$30 -> 0.50067454 | G27: ='Student Headcount'!I34/'Student Headcount'!$I$30 -> 0.45986509 | H27: ='Student Headcount'!I35/'Student Headcount'!$I$30 -> 0.36340641 | I27: ='Student Headcount'!I36/'Student Headcount'!$I$30 -> 0.28870152 | J27: ='Student Headcount'!I37/'Student Headcount'!$I$30 -> 0.23305228 | K27: ='Student Headcount'!I38/'Student Headcount'!$I$30 -> 0.18330523 | L27: ='Student Headcount'!I39/'Student Headcount'!$I$30 -> 0.14637437 | M27: ='Student Headcount'!I40/'Student Headcount'!$I$30 -> 0.11618887
A28: Postgraduate Research (PGR) | B28: ='Student Headcount'!K29/'Student Headcount'!$K$30 -> 0.76136364 | C28: ='Student Headcount'!K30/'Student Headcount'!$K$30 -> 1 | D28: ='Student Headcount'!K31/'Student Headcount'!$K$30 -> 0.98688811 | E28: ='Student Headcount'!K32/'Student Headcount'!$K$30 -> 0.98426573 | F28: ='Student Headcount'!K33/'Student Headcount'!$K$30 -> 0.99300699 | G28: ='Student Headcount'!K34/'Student Headcount'!$K$30 -> 1.0533217 | H28: ='Student Headcount'!K35/'Student Headcount'!$K$30 -> 1.0585664 | I28: ='Student Headcount'!K36/'Student Headcount'!$K$30 -> 1.0708042 | J28: ='Student Headcount'!K37/'Student Headcount'!$K$30 -> 1.0498252 | K28: ='Student Headcount'!K38/'Student Headcount'!$K$30 -> 1.0506993 | L28: ='Student Headcount'!K39/'Student Headcount'!$K$30 -> 1.0550699 | M28: ='Student Headcount'!K40/'Student Headcount'!$K$30 -> 0.81643357
A30: C. September Anchor Population Forecast, by Financial Year
A31: Category | B31: FY25/26 Actual (Sep) | C31: FY26/27 | D31: FY27/28 | E31: FY28/29
A32: UK Undergraduate | B32: ='Student Headcount'!C30 -> 9250 | C32: =B32*(H6/'Student Flow Summary'!D7) -> 9435 | D32: =C32*(H7/H6) -> 9623.7 | E32: =D32*(H8/H7) -> 9974.4994
A33: International Undergraduate | B33: ='Student Headcount'!E30 -> 2082 | C33: =B33*(H9/'Student Flow Summary'!D10) -> 2102.82 | D33: =C33*(H10/H9) -> 2123.8482 | E33: =D33*(H11/H10) -> 2215.5598
A34: UK Postgraduate | B34: ='Student Headcount'!G30 -> 7552 | C34: =B34*(H12/'Student Flow Summary'!D13) -> 7703.04 | D34: =C34*(H13/H12) -> 7857.1008 | E34: =D34*(H14/H13) -> 8132.0993
A35: International Postgraduate | B35: ='Student Headcount'!I30 -> 5930 | C35: =B35*(H15/'Student Flow Summary'!D16) -> 5989.3 | D35: =C35*(H16/H15) -> 6163.4974 | E35: =D35*(H17/H16) -> 6286.7673
A36: Postgraduate Research (PGR) | B36: ='Student Headcount'!K30 -> 1144 | C36: =B36*(H18/'Student Flow Summary'!D19) -> 1166.88 | D36: =C36*(H19/H18) -> 1190.2176 | E36: =D36*(H20/H19) -> 1214.022
A38: D. Monthly Student Population Forecast — 36 Months (Aug 2026 – Jul 2029)
A39: Month | B39: FY | C39: UK Undergraduate | D39: International Undergraduate | E39: UK Postgraduate | F39: International Postgraduate | G39: Postgraduate Research (PGR) | H39: Total
A40: 46235 | B40: FY26/27 | C40: =B24*C32 -> 6298.5 | D40: =B25*C33 -> 1463.49 | E40: =B26*C34 -> 755.82 | F40: =B27*C35 -> 643.37 | G40: =B28*C36 -> 888.42 | H40: =SUM(C40:G40) -> 10049.6
A41: 46266 | B41: FY26/27 | C41: =C24*C32 -> 9435 | D41: =C25*C33 -> 2102.82 | E41: =C26*C34 -> 7703.04 | F41: =C27*C35 -> 5989.3 | G41: =C28*C36 -> 1166.88 | H41: =SUM(C41:G41) -> 26397.04
A42: 46296 | B42: FY26/27 | C42: =D24*C32 -> 9289.14 | D42: =D25*C33 -> 2104.84 | E42: =D26*C34 -> 6266.88 | F42: =D27*C35 -> 4737.91 | G42: =D28*C36 -> 1151.58 | H42: =SUM(C42:G42) -> 23550.35
A43: 46327 | B43: FY26/27 | C43: =E24*C32 -> 9386.04 | D43: =E25*C33 -> 2082.62 | E43: =E26*C34 -> 5019.42 | F43: =E27*C35 -> 3794.57 | G43: =E28*C36 -> 1148.52 | H43: =SUM(C43:G43) -> 21431.17
A44: 46357 | B44: FY26/27 | C44: =F24*C32 -> 9400.32 | D44: =F25*C33 -> 2083.63 | E44: =F26*C34 -> 3979.02 | F44: =F27*C35 -> 2998.69 | G44: =F28*C36 -> 1158.72 | H44: =SUM(C44:G44) -> 19620.38
A45: 46388 | B45: FY26/27 | C45: =G24*C32 -> 9395.22 | D45: =G25*C33 -> 2082.62 | E45: =G26*C34 -> 3680.16 | F45: =G27*C35 -> 2754.27 | G45: =G28*C36 -> 1229.1 | H45: =SUM(C45:G45) -> 19141.37
A46: 46419 | B46: FY26/27 | C46: =H24*C32 -> 9288.12 | D46: =H25*C33 -> 2090.7 | E46: =H26*C34 -> 2945.76 | F46: =H27*C35 -> 2176.55 | G46: =H28*C36 -> 1235.22 | H46: =SUM(C46:G46) -> 17736.35
A47: 46447 | B47: FY26/27 | C47: =I24*C32 -> 9334.02 | D47: =I25*C33 -> 2087.67 | E47: =I26*C34 -> 2344.98 | F47: =I27*C35 -> 1729.12 | G47: =I28*C36 -> 1249.5 | H47: =SUM(C47:G47) -> 16745.29
A48: 46478 | B48: FY26/27 | C48: =J24*C32 -> 9291.18 | D48: =J25*C33 -> 2051.31 | E48: =J26*C34 -> 1899.24 | F48: =J27*C35 -> 1395.82 | G48: =J28*C36 -> 1225.02 | H48: =SUM(C48:G48) -> 15862.57
A49: 46508 | B49: FY26/27 | C49: =K24*C32 -> 9287.1 | D49: =K25*C33 -> 2052.32 | E49: =K26*C34 -> 1504.5 | F49: =K27*C35 -> 1097.87 | G49: =K28*C36 -> 1226.04 | H49: =SUM(C49:G49) -> 15167.83
A50: 46539 | B50: FY26/27 | C50: =L24*C32 -> 9377.88 | D50: =L25*C33 -> 2064.44 | E50: =L26*C34 -> 1207.68 | F50: =L27*C35 -> 876.68 | G50: =L28*C36 -> 1231.14 | H50: =SUM(C50:G50) -> 14757.82
A51: 46569 | B51: FY26/27 | C51: =M24*C32 -> 6366.84 | D51: =M25*C33 -> 1405.92 | E51: =M26*C34 -> 961.86 | F51: =M27*C35 -> 695.89 | G51: =M28*C36 -> 952.68 | H51: =SUM(C51:G51) -> 10383.19
A52: 46600 | B52: FY27/28 | C52: =B24*D32 -> 6424.47 | D52: =B25*D33 -> 1478.1249 | E52: =B26*D34 -> 770.9364 | F52: =B27*D35 -> 662.08227 | G52: =B28*D36 -> 906.1884 | H52: =SUM(C52:G52) -> 10241.802
A53: 46631 | B53: FY27/28 | C53: =C24*D32 -> 9623.7 | D53: =C25*D33 -> 2123.8482 | E53: =C26*D34 -> 7857.1008 | F53: =C27*D35 -> 6163.4974 | G53: =C28*D36 -> 1190.2176 | H53: =SUM(C53:G53) -> 26958.364
A54: 46661 | B54: FY27/28 | C54: =D24*D32 -> 9474.9228 | D54: =D25*D33 -> 2125.8884 | E54: =D26*D34 -> 6392.2176 | F54: =D27*D35 -> 4875.711 | G54: =D28*D36 -> 1174.6116 | H54: =SUM(C54:G54) -> 24043.351
A55: 46692 | B55: FY27/28 | C55: =E24*D32 -> 9573.7608 | D55: =E25*D33 -> 2103.4462 | E55: =E26*D34 -> 5119.8084 | F55: =E27*D35 -> 3904.9342 | G55: =E28*D36 -> 1171.4904 | H55: =SUM(C55:G55) -> 21873.44
A56: 46722 | B56: FY27/28 | C56: =F24*D32 -> 9588.3264 | D56: =F25*D33 -> 2104.4663 | E56: =F26*D34 -> 4058.6004 | F56: =F27*D35 -> 3085.9062 | G56: =F28*D36 -> 1181.8944 | H56: =SUM(C56:G56) -> 20019.194
A57: 46753 | B57: FY27/28 | C57: =G24*D32 -> 9583.1244 | D57: =G25*D33 -> 2103.4462 | E57: =G26*D34 -> 3753.7632 | F57: =G27*D35 -> 2834.3773 | G57: =G28*D36 -> 1253.682 | H57: =SUM(C57:G57) -> 19528.393
A58: 46784 | B58: FY27/28 | C58: =H24*D32 -> 9473.8824 | D58: =H25*D33 -> 2111.607 | E58: =H26*D34 -> 3004.6752 | F58: =H27*D35 -> 2239.8544 | G58: =H28*D36 -> 1259.9244 | H58: =SUM(C58:G58) -> 18089.943
A59: 46813 | B59: FY27/28 | C59: =I24*D32 -> 9520.7004 | D59: =I25*D33 -> 2108.5467 | E59: =I26*D34 -> 2391.8796 | F59: =I27*D35 -> 1779.4111 | G59: =I28*D36 -> 1274.49 | H59: =SUM(C59:G59) -> 17075.028
A60: 46844 | B60: FY27/28 | C60: =J24*D32 -> 9477.0036 | D60: =J25*D33 -> 2071.8231 | E60: =J26*D34 -> 1937.2248 | F60: =J27*D35 -> 1436.4171 | G60: =J28*D36 -> 1249.5204 | H60: =SUM(C60:G60) -> 16171.989
A61: 46874 | B61: FY27/28 | C61: =K24*D32 -> 9472.842 | D61: =K25*D33 -> 2072.8432 | E61: =K26*D34 -> 1534.59 | F61: =K27*D35 -> 1129.8013 | G61: =K28*D36 -> 1250.5608 | H61: =SUM(C61:G61) -> 15460.637
A62: 46905 | B62: FY27/28 | C62: =L24*D32 -> 9565.4376 | D62: =L25*D33 -> 2085.0844 | E62: =L26*D34 -> 1231.8336 | F62: =L27*D35 -> 902.17803 | G62: =L28*D36 -> 1255.7628 | H62: =SUM(C62:G62) -> 15040.296
A63: 46935 | B63: FY27/28 | C63: =M24*D32 -> 6494.1768 | D63: =M25*D33 -> 1419.9792 | E63: =M26*D34 -> 981.0972 | F63: =M27*D35 -> 716.1298 | G63: =M28*D36 -> 971.7336 | H63: =SUM(C63:G63) -> 10583.117
A64: 46966 | B64: FY28/29 | C64: =B24*E32 -> 6658.6523 | D64: =B25*E33 -> 1541.953 | E64: =B26*E34 -> 797.91917 | F64: =B27*E35 -> 675.32391 | G64: =B28*E36 -> 924.31217 | H64: =SUM(C64:G64) -> 10598.161
A65: 46997 | B65: FY28/29 | C65: =C24*E32 -> 9974.4994 | D65: =C25*E33 -> 2215.5598 | E65: =C26*E34 -> 8132.0993 | F65: =C27*E35 -> 6286.7673 | G65: =C28*E36 -> 1214.022 | H65: =SUM(C65:G65) -> 27822.948
A66: 47027 | B66: FY28/29 | C66: =D24*E32 -> 9820.299 | D66: =D25*E33 -> 2217.6881 | E66: =D26*E34 -> 6615.9452 | F66: =D27*E35 -> 4973.2252 | G66: =D28*E36 -> 1198.1038 | H66: =SUM(C66:G66) -> 24825.261
A67: 47058 | B67: FY28/29 | C67: =E24*E32 -> 9922.7398 | D67: =E25*E33 -> 2194.2768 | E67: =E26*E34 -> 5299.0017 | F67: =E27*E35 -> 3983.0329 | G67: =E28*E36 -> 1194.9202 | H67: =SUM(C67:G67) -> 22593.971
A68: 47088 | B68: FY28/29 | C68: =F24*E32 -> 9937.8364 | D68: =F25*E33 -> 2195.341 | E68: =F26*E34 -> 4200.6514 | F68: =F27*E35 -> 3147.6243 | G68: =F28*E36 -> 1205.5323 | H68: =SUM(C68:G68) -> 20686.985
A69: 47119 | B69: FY28/29 | C69: =G24*E32 -> 9932.4447 | D69: =G25*E33 -> 2194.2768 | E69: =G26*E34 -> 3885.1449 | F69: =G27*E35 -> 2891.0648 | G69: =G28*E36 -> 1278.7556 | H69: =SUM(C69:G69) -> 20181.687
A70: 47150 | B70: FY28/29 | C70: =H24*E32 -> 9819.2207 | D70: =H25*E33 -> 2202.79 | E70: =H26*E34 -> 3109.8388 | F70: =H27*E35 -> 2284.6515 | G70: =H28*E36 -> 1285.1229 | H70: =SUM(C70:G70) -> 18701.624
A71: 47178 | B71: FY28/29 | C71: =I24*E32 -> 9867.7453 | D71: =I25*E33 -> 2199.5976 | E71: =I26*E34 -> 2475.5954 | F71: =I27*E35 -> 1814.9993 | G71: =I28*E36 -> 1299.9798 | H71: =SUM(C71:G71) -> 17657.917
A72: 47209 | B72: FY28/29 | C72: =J24*E32 -> 9822.4557 | D72: =J25*E33 -> 2161.2882 | E72: =J26*E34 -> 2005.0277 | F72: =J27*E35 -> 1465.1454 | G72: =J28*E36 -> 1274.5108 | H72: =SUM(C72:G72) -> 16728.428
A73: 47239 | B73: FY28/29 | C73: =K24*E32 -> 9818.1424 | D73: =K25*E33 -> 2162.3523 | E73: =K26*E34 -> 1588.3006 | F73: =K27*E35 -> 1152.3973 | G73: =K28*E36 -> 1275.572 | H73: =SUM(C73:G73) -> 15996.765
A74: 47270 | B74: FY28/29 | C74: =L24*E32 -> 9914.1132 | D74: =L25*E33 -> 2175.1221 | E74: =L26*E34 -> 1274.9478 | F74: =L27*E35 -> 920.22159 | G74: =L28*E36 -> 1280.8781 | H74: =SUM(C74:G74) -> 15565.283
A75: 47300 | B75: FY28/29 | C75: =M24*E32 -> 6730.9 | D75: =M25*E33 -> 1481.2965 | E75: =M26*E34 -> 1015.4356 | F75: =M27*E35 -> 730.45239 | G75: =M28*E36 -> 991.16827 | H75: =SUM(C75:G75) -> 10949.253
A77: Note: Headcount is modelled as a rolling monthly balance (opening + new enrolments − withdrawals − graduates), profiled using the FY25/26 seasonal shape in Section B. Annual New Enrolment and Closing Population totals reconcile to Section A. All figures are students (headcount), not FTE.

Sheet Income Forecast
A1: Vector University — 36-Month Income Forecast (FY26/27 – FY28/29)
A2: Methodology: Tuition income = forecast student headcount (from 'Population Forecast') × forecast annual tuition fee rate ÷ 12, consistent with the University's existing convention (see 'Income' tab note). Non-tuition income lines are grown from the same calendar month a year earlier using the YoY growth assumptions in 'Forecast Assumptions' Section C.
A4: A. Tuition Fee Rate Forecast (£ per student per year)
A5: Category | B5: FY25/26 Rate | C5: FY26/27 Increase % | D5: FY26/27 Rate | E5: FY27/28 Increase % | F5: FY27/28 Rate | G5: FY28/29 Increase % | H5: FY28/29 Rate
A6: UK Undergraduate | B6: ='Tuition Fee Rates'!D6 -> 9535 | C6: ='Forecast Assumptions'!B34 -> 0 | D6: =B6*(1+C6) -> 9535 | E6: ='Forecast Assumptions'!C34 -> 0.02 | F6: =D6*(1+E6) -> 9725.7 | G6: ='Forecast Assumptions'!D34 -> 0.02 | H6: =F6*(1+G6) -> 9920.214
A7: International Undergraduate | B7: ='Tuition Fee Rates'!D7 -> 20950 | C7: ='Forecast Assumptions'!B35 -> 0.04 | D7: =B7*(1+C7) -> 21788 | E7: ='Forecast Assumptions'!C35 -> 0.04 | F7: =D7*(1+E7) -> 22659.52 | G7: ='Forecast Assumptions'!D35 -> 0.045 | H7: =F7*(1+G7) -> 23679.198
A8: UK Postgraduate | B8: ='Tuition Fee Rates'!D8 -> 10350 | C8: ='Forecast Assumptions'!B36 -> 0.03 | D8: =B8*(1+C8) -> 10660.5 | E8: ='Forecast Assumptions'!C36 -> 0.03 | F8: =D8*(1+E8) -> 10980.315 | G8: ='Forecast Assumptions'!D36 -> 0.03 | H8: =F8*(1+G8) -> 11309.724
A9: International Postgraduate | B9: ='Tuition Fee Rates'!D9 -> 21500 | C9: ='Forecast Assumptions'!B37 -> 0.04 | D9: =B9*(1+C9) -> 22360 | E9: ='Forecast Assumptions'!C37 -> 0.04 | F9: =D9*(1+E9) -> 23254.4 | G9: ='Forecast Assumptions'!D37 -> 0.045 | H9: =F9*(1+G9) -> 24300.848
A10: Postgraduate Research (PGR) | B10: ='Tuition Fee Rates'!D10 -> 6950 | C10: ='Forecast Assumptions'!B38 -> 0.03 | D10: =B10*(1+C10) -> 7158.5 | E10: ='Forecast Assumptions'!C38 -> 0.03 | F10: =D10*(1+E10) -> 7373.255 | G10: ='Forecast Assumptions'!D38 -> 0.03 | H10: =F10*(1+G10) -> 7594.4527
A12: B. Monthly Income Forecast — 36 Months (Aug 2026 – Jul 2029)
A13: Month | B13: FY | C13: UK UG Tuition | D13: Intl UG Tuition | E13: UK PG Tuition | F13: Intl PG Tuition | G13: PGR Tuition | H13: Research Grants & Contracts | I13: Government & Funding Body Grants | J13: Student Accommodation Income | K13: Commercial & Professional Services | L13: Other Operating Income | M13: Total Income
A14: 46235 | B14: FY26/27 | C14: ='Population Forecast'!C40*D6/12 -> 5004683.1 | D14: ='Population Forecast'!D40*D7/12 -> 2657210 | E14: ='Population Forecast'!E40*D8/12 -> 671451.59 | F14: ='Population Forecast'!F40*D9/12 -> 1198812.8 | G14: ='Population Forecast'!G40*D10/12 -> 529979.55 | H14: =Income!H29*(1+'Forecast Assumptions'!B42) -> 2688300 | I14: =Income!I29*(1+'Forecast Assumptions'!B43) -> 3653846 | J14: =Income!J29*(1+'Forecast Assumptions'!B44) -> 1362400 | K14: =Income!K29*(1+'Forecast Assumptions'!B45) -> 780000 | L14: =Income!L29*(1+'Forecast Assumptions'!B46) -> 552500.34 | M14: =SUM(C14:L14) -> 19099183
A15: 46266 | B15: FY26/27 | C15: ='Population Forecast'!C41*D6/12 -> 7496893.8 | D15: ='Population Forecast'!D41*D7/12 -> 3818020.2 | E15: ='Population Forecast'!E41*D8/12 -> 6843188.2 | F15: ='Population Forecast'!F41*D9/12 -> 11160062 | G15: ='Population Forecast'!G41*D10/12 -> 696092.54 | H15: =Income!H30*(1+'Forecast Assumptions'!B42) -> 2837650 | I15: =Income!I30*(1+'Forecast Assumptions'!B43) -> 548077 | J15: =Income!J30*(1+'Forecast Assumptions'!B44) -> 2951866.3 | K15: =Income!K30*(1+'Forecast Assumptions'!B45) -> 953333.68 | L15: =Income!L30*(1+'Forecast Assumptions'!B46) -> 552500.34 | M15: =SUM(C15:L15) -> 37857684
A16: 46296 | B16: FY26/27 | C16: ='Population Forecast'!C42*D6/12 -> 7380995.8 | D16: ='Population Forecast'!D42*D7/12 -> 3821687.8 | E16: ='Population Forecast'!E42*D8/12 -> 5567339.5 | F16: ='Population Forecast'!F42*D9/12 -> 8828305.6 | G16: ='Population Forecast'!G42*D10/12 -> 686965.45 | H16: =Income!H31*(1+'Forecast Assumptions'!B42) -> 2987000 | I16: =Income!I31*(1+'Forecast Assumptions'!B43) -> 548077 | J16: =Income!J31*(1+'Forecast Assumptions'!B44) -> 2951866.3 | K16: =Income!K31*(1+'Forecast Assumptions'!B45) -> 953333.68 | L16: =Income!L31*(1+'Forecast Assumptions'!B46) -> 552500.34 | M16: =SUM(C16:L16) -> 34278072
A17: 46327 | B17: FY26/27 | C17: ='Population Forecast'!C43*D6/12 -> 7457991 | D17: ='Population Forecast'!D43*D7/12 -> 3781343.7 | E17: ='Population Forecast'!E43*D8/12 -> 4459127.2 | F17: ='Population Forecast'!F43*D9/12 -> 7070548.8 | G17: ='Population Forecast'!G43*D10/12 -> 685140.04 | H17: =Income!H32*(1+'Forecast Assumptions'!B42) -> 2987000 | I17: =Income!I32*(1+'Forecast Assumptions'!B43) -> 3653846 | J17: =Income!J32*(1+'Forecast Assumptions'!B44) -> 2838333.7 | K17: =Income!K32*(1+'Forecast Assumptions'!B45) -> 866666.32 | L17: =Income!L32*(1+'Forecast Assumptions'!B46) -> 552500.34 | M17: =SUM(C17:L17) -> 34352497
A18: 46357 | B18: FY26/27 | C18: ='Population Forecast'!C44*D6/12 -> 7469337.6 | D18: ='Population Forecast'!D44*D7/12 -> 3783177.5 | E18: ='Population Forecast'!E44*D8/12 -> 3534861.9 | F18: ='Population Forecast'!F44*D9/12 -> 5587559 | G18: ='Population Forecast'!G44*D10/12 -> 691224.76 | H18: =Income!H33*(1+'Forecast Assumptions'!B42) -> 3136350 | I18: =Income!I33*(1+'Forecast Assumptions'!B43) -> 548077 | J18: =Income!J33*(1+'Forecast Assumptions'!B44) -> 2611266.3 | K18: =Income!K33*(1+'Forecast Assumptions'!B45) -> 780000 | L18: =Income!L33*(1+'Forecast Assumptions'!B46) -> 552500.34 | M18: =SUM(C18:L18) -> 28694354
A19: 46388 | B19: FY26/27 | C19: ='Population Forecast'!C45*D6/12 -> 7465285.2 | D19: ='Population Forecast'!D45*D7/12 -> 3781343.7 | E19: ='Population Forecast'!E45*D8/12 -> 3269362.1 | F19: ='Population Forecast'!F45*D9/12 -> 5132123.1 | G19: ='Population Forecast'!G45*D10/12 -> 733209.36 | H19: =Income!H34*(1+'Forecast Assumptions'!B42) -> 3136350 | I19: =Income!I34*(1+'Forecast Assumptions'!B43) -> 548077 | J19: =Income!J34*(1+'Forecast Assumptions'!B44) -> 2497733.7 | K19: =Income!K34*(1+'Forecast Assumptions'!B45) -> 866666.32 | L19: =Income!L34*(1+'Forecast Assumptions'!B46) -> 552500.34 | M19: =SUM(C19:L19) -> 27982651
A20: 46419 | B20: FY26/27 | C20: ='Population Forecast'!C46*D6/12 -> 7380185.3 | D20: ='Population Forecast'!D46*D7/12 -> 3796014.3 | E20: ='Population Forecast'!E46*D8/12 -> 2616939.5 | F20: ='Population Forecast'!F46*D9/12 -> 4055638.2 | G20: ='Population Forecast'!G46*D10/12 -> 736860.2 | H20: =Income!H35*(1+'Forecast Assumptions'!B42) -> 3136350 | I20: =Income!I35*(1+'Forecast Assumptions'!B43) -> 3653846 | J20: =Income!J35*(1+'Forecast Assumptions'!B44) -> 2497733.7 | K20: =Income!K35*(1+'Forecast Assumptions'!B45) -> 953333.68 | L20: =Income!L35*(1+'Forecast Assumptions'!B46) -> 552500.34 | M20: =SUM(C20:L20) -> 29379401
A21: 46447 | B21: FY26/27 | C21: ='Population Forecast'!C47*D6/12 -> 7416656.7 | D21: ='Population Forecast'!D47*D7/12 -> 3790512.8 | E21: ='Population Forecast'!E47*D8/12 -> 2083221.6 | F21: ='Population Forecast'!F47*D9/12 -> 3221926.9 | G21: ='Population Forecast'!G47*D10/12 -> 745378.81 | H21: =Income!H36*(1+'Forecast Assumptions'!B42) -> 2987000 | I21: =Income!I36*(1+'Forecast Assumptions'!B43) -> 548077 | J21: =Income!J36*(1+'Forecast Assumptions'!B44) -> 2497733.7 | K21: =Income!K36*(1+'Forecast Assumptions'!B45) -> 953333.68 | L21: =Income!L36*(1+'Forecast Assumptions'!B46) -> 552500.34 | M21: =SUM(C21:L21) -> 24796342
A22: 46478 | B22: FY26/27 | C22: ='Population Forecast'!C48*D6/12 -> 7382616.8 | D22: ='Population Forecast'!D48*D7/12 -> 3724495.2 | E22: ='Population Forecast'!E48*D8/12 -> 1687237.3 | F22: ='Population Forecast'!F48*D9/12 -> 2600877.9 | G22: ='Population Forecast'!G48*D10/12 -> 730775.47 | H22: =Income!H37*(1+'Forecast Assumptions'!B42) -> 2987000 | I22: =Income!I37*(1+'Forecast Assumptions'!B43) -> 548077 | J22: =Income!J37*(1+'Forecast Assumptions'!B44) -> 2497733.7 | K22: =Income!K37*(1+'Forecast Assumptions'!B45) -> 866666.32 | L22: =Income!L37*(1+'Forecast Assumptions'!B46) -> 552500.34 | M22: =SUM(C22:L22) -> 23577980
A23: 46508 | B23: FY26/27 | C23: ='Population Forecast'!C49*D6/12 -> 7379374.9 | D23: ='Population Forecast'!D49*D7/12 -> 3726329 | E23: ='Population Forecast'!E49*D8/12 -> 1336560.2 | F23: ='Population Forecast'!F49*D9/12 -> 2045697.8 | G23: ='Population Forecast'!G49*D10/12 -> 731383.94 | H23: =Income!H38*(1+'Forecast Assumptions'!B42) -> 2837650 | I23: =Income!I38*(1+'Forecast Assumptions'!B43) -> 3653846 | J23: =Income!J38*(1+'Forecast Assumptions'!B44) -> 2270666.3 | K23: =Income!K38*(1+'Forecast Assumptions'!B45) -> 780000 | L23: =Income!L38*(1+'Forecast Assumptions'!B46) -> 552500.34 | M23: =SUM(C23:L23) -> 25314008
A24: 46539 | B24: FY26/27 | C24: ='Population Forecast'!C50*D6/12 -> 7451507.2 | D24: ='Population Forecast'!D50*D7/12 -> 3748334.9 | E24: ='Population Forecast'!E50*D8/12 -> 1072872.7 | F24: ='Population Forecast'!F50*D9/12 -> 1633547.1 | G24: ='Population Forecast'!G50*D10/12 -> 734426.31 | H24: =Income!H39*(1+'Forecast Assumptions'!B42) -> 2837650 | I24: =Income!I39*(1+'Forecast Assumptions'!B43) -> 548077 | J24: =Income!J39*(1+'Forecast Assumptions'!B44) -> 1135333.7 | K24: =Income!K39*(1+'Forecast Assumptions'!B45) -> 780000 | L24: =Income!L39*(1+'Forecast Assumptions'!B46) -> 552500.34 | M24: =SUM(C24:L24) -> 20494249
A25: 46569 | B25: FY26/27 | C25: ='Population Forecast'!C51*D6/12 -> 5058985 | D25: ='Population Forecast'!D51*D7/12 -> 2552682.1 | E25: ='Population Forecast'!E51*D8/12 -> 854492.38 | F25: ='Population Forecast'!F51*D9/12 -> 1296675 | G25: ='Population Forecast'!G51*D10/12 -> 568313.31 | H25: =Income!H40*(1+'Forecast Assumptions'!B42) -> 3285700 | I25: =Income!I40*(1+'Forecast Assumptions'!B43) -> 548077 | J25: =Income!J40*(1+'Forecast Assumptions'!B44) -> 1135333.7 | K25: =Income!K40*(1+'Forecast Assumptions'!B45) -> 866666.32 | L25: =Income!L40*(1+'Forecast Assumptions'!B46) -> 552500.34 | M25: =SUM(C25:L25) -> 16719425
A26: 46600 | B26: FY27/28 | C26: ='Population Forecast'!C52*F6/12 -> 5206872.3 | D26: ='Population Forecast'!D52*F7/12 -> 2791133.4 | E26: ='Population Forecast'!E52*F8/12 -> 705427.04 | F26: ='Population Forecast'!F52*F9/12 -> 1283027.2 | G26: ='Population Forecast'!G52*F10/12 -> 556796.51 | H26: =H14*(1+'Forecast Assumptions'!C42) -> 2768949 | I26: =I14*(1+'Forecast Assumptions'!C43) -> 3653846 | J26: =J14*(1+'Forecast Assumptions'!C44) -> 1416896 | K26: =K14*(1+'Forecast Assumptions'!C45) -> 811200 | L26: =L14*(1+'Forecast Assumptions'!C46) -> 563550.35 | M26: =SUM(C26:L26) -> 19757698
A27: 46631 | B27: FY27/28 | C27: ='Population Forecast'!C53*F6/12 -> 7799768.3 | D27: ='Population Forecast'!D53*F7/12 -> 4010448.4 | E27: ='Population Forecast'!E53*F8/12 -> 7189453.5 | F27: ='Population Forecast'!F53*F9/12 -> 11944036 | G27: ='Population Forecast'!G53*F10/12 -> 731314.82 | H27: =H15*(1+'Forecast Assumptions'!C42) -> 2922779.5 | I27: =I15*(1+'Forecast Assumptions'!C43) -> 548077 | J27: =J15*(1+'Forecast Assumptions'!C44) -> 3069941 | K27: =K15*(1+'Forecast Assumptions'!C45) -> 991467.03 | L27: =L15*(1+'Forecast Assumptions'!C46) -> 563550.35 | M27: =SUM(C27:L27) -> 39770836
A28: 46661 | B28: FY27/28 | C28: ='Population Forecast'!C54*F6/12 -> 7679188.1 | D28: ='Population Forecast'!D54*F7/12 -> 4014300.9 | E28: ='Population Forecast'!E54*F8/12 -> 5849046.9 | F28: ='Population Forecast'!F54*F9/12 -> 9448477.8 | G28: ='Population Forecast'!G54*F10/12 -> 721725.9 | H28: =H16*(1+'Forecast Assumptions'!C42) -> 3076610 | I28: =I16*(1+'Forecast Assumptions'!C43) -> 548077 | J28: =J16*(1+'Forecast Assumptions'!C44) -> 3069941 | K28: =K16*(1+'Forecast Assumptions'!C45) -> 991467.03 | L28: =L16*(1+'Forecast Assumptions'!C46) -> 563550.35 | M28: =SUM(C28:L28) -> 35962385
A29: 46692 | B29: FY27/28 | C29: ='Population Forecast'!C55*F6/12 -> 7759293.8 | D29: ='Population Forecast'!D55*F7/12 -> 3971923.4 | E29: ='Population Forecast'!E55*F8/12 -> 4684759.1 | F29: ='Population Forecast'!F55*F9/12 -> 7567241.8 | G29: ='Population Forecast'!G55*F10/12 -> 719808.12 | H29: =H17*(1+'Forecast Assumptions'!C42) -> 3076610 | I29: =I17*(1+'Forecast Assumptions'!C43) -> 3653846 | J29: =J17*(1+'Forecast Assumptions'!C44) -> 2951867 | K29: =K17*(1+'Forecast Assumptions'!C45) -> 901332.97 | L29: =L17*(1+'Forecast Assumptions'!C46) -> 563550.35 | M29: =SUM(C29:L29) -> 35850233
A30: 46722 | B30: FY27/28 | C30: ='Population Forecast'!C56*F6/12 -> 7771098.8 | D30: ='Population Forecast'!D56*F7/12 -> 3973849.7 | E30: ='Population Forecast'!E56*F8/12 -> 3713725.9 | F30: ='Population Forecast'!F56*F9/12 -> 5980074.8 | G30: ='Population Forecast'!G56*F10/12 -> 726200.73 | H30: =H18*(1+'Forecast Assumptions'!C42) -> 3230440.5 | I30: =I18*(1+'Forecast Assumptions'!C43) -> 548077 | J30: =J18*(1+'Forecast Assumptions'!C44) -> 2715717 | K30: =K18*(1+'Forecast Assumptions'!C45) -> 811200 | L30: =L18*(1+'Forecast Assumptions'!C46) -> 563550.35 | M30: =SUM(C30:L30) -> 30033935
A31: 46753 | B31: FY27/28 | C31: ='Population Forecast'!C57*F6/12 -> 7766882.7 | D31: ='Population Forecast'!D57*F7/12 -> 3971923.4 | E31: ='Population Forecast'!E57*F8/12 -> 3434791.9 | F31: ='Population Forecast'!F57*F9/12 -> 5492645.3 | G31: ='Population Forecast'!G57*F10/12 -> 770309.76 | H31: =H19*(1+'Forecast Assumptions'!C42) -> 3230440.5 | I31: =I19*(1+'Forecast Assumptions'!C43) -> 548077 | J31: =J19*(1+'Forecast Assumptions'!C44) -> 2597643 | K31: =K19*(1+'Forecast Assumptions'!C45) -> 901332.97 | L31: =L19*(1+'Forecast Assumptions'!C46) -> 563550.35 | M31: =SUM(C31:L31) -> 29277597
A32: 46784 | B32: FY27/28 | C32: ='Population Forecast'!C58*F6/12 -> 7678344.8 | D32: ='Population Forecast'!D58*F7/12 -> 3987333.4 | E32: ='Population Forecast'!E58*F8/12 -> 2749356.7 | F32: ='Population Forecast'!F58*F9/12 -> 4340539.3 | G32: ='Population Forecast'!G58*F10/12 -> 774145.32 | H32: =H20*(1+'Forecast Assumptions'!C42) -> 3230440.5 | I32: =I20*(1+'Forecast Assumptions'!C43) -> 3653846 | J32: =J20*(1+'Forecast Assumptions'!C44) -> 2597643 | K32: =K20*(1+'Forecast Assumptions'!C45) -> 991467.03 | L32: =L20*(1+'Forecast Assumptions'!C46) -> 563550.35 | M32: =SUM(C32:L32) -> 30566666
A33: 46813 | B33: FY27/28 | C33: ='Population Forecast'!C59*F6/12 -> 7716289.7 | D33: ='Population Forecast'!D59*F7/12 -> 3981554.7 | E33: ='Population Forecast'!E59*F8/12 -> 2188632.6 | F33: ='Population Forecast'!F59*F9/12 -> 3448261.4 | G33: ='Population Forecast'!G59*F10/12 -> 783094.98 | H33: =H21*(1+'Forecast Assumptions'!C42) -> 3076610 | I33: =I21*(1+'Forecast Assumptions'!C43) -> 548077 | J33: =J21*(1+'Forecast Assumptions'!C44) -> 2597643 | K33: =K21*(1+'Forecast Assumptions'!C45) -> 991467.03 | L33: =L21*(1+'Forecast Assumptions'!C46) -> 563550.35 | M33: =SUM(C33:L33) -> 25895181
A34: 46844 | B34: FY27/28 | C34: ='Population Forecast'!C60*F6/12 -> 7680874.5 | D34: ='Population Forecast'!D60*F7/12 -> 3912209.7 | E34: ='Population Forecast'!E60*F8/12 -> 1772611.5 | F34: ='Population Forecast'!F60*F9/12 -> 2783584.8 | G34: ='Population Forecast'!G60*F10/12 -> 767752.71 | H34: =H22*(1+'Forecast Assumptions'!C42) -> 3076610 | I34: =I22*(1+'Forecast Assumptions'!C43) -> 548077 | J34: =J22*(1+'Forecast Assumptions'!C44) -> 2597643 | K34: =K22*(1+'Forecast Assumptions'!C45) -> 901332.97 | L34: =L22*(1+'Forecast Assumptions'!C46) -> 563550.35 | M34: =SUM(C34:L34) -> 24604247
A35: 46874 | B35: FY27/28 | C35: ='Population Forecast'!C61*F6/12 -> 7677501.6 | D35: ='Population Forecast'!D61*F7/12 -> 3914136 | E35: ='Population Forecast'!E61*F8/12 -> 1404190.1 | F35: ='Population Forecast'!F61*F9/12 -> 2189404.3 | G35: ='Population Forecast'!G61*F10/12 -> 768391.97 | H35: =H23*(1+'Forecast Assumptions'!C42) -> 2922779.5 | I35: =I23*(1+'Forecast Assumptions'!C43) -> 3653846 | J35: =J23*(1+'Forecast Assumptions'!C44) -> 2361493 | K35: =K23*(1+'Forecast Assumptions'!C45) -> 811200 | L35: =L23*(1+'Forecast Assumptions'!C46) -> 563550.35 | M35: =SUM(C35:L35) -> 26266493
A36: 46905 | B36: FY27/28 | C36: ='Population Forecast'!C62*F6/12 -> 7752548 | D36: ='Population Forecast'!D62*F7/12 -> 3937251 | E36: ='Population Forecast'!E62*F8/12 -> 1127160.1 | F36: ='Population Forecast'!F62*F9/12 -> 1748300.7 | G36: ='Population Forecast'!G62*F10/12 -> 771588.28 | H36: =H24*(1+'Forecast Assumptions'!C42) -> 2922779.5 | I36: =I24*(1+'Forecast Assumptions'!C43) -> 548077 | J36: =J24*(1+'Forecast Assumptions'!C44) -> 1180747 | K36: =K24*(1+'Forecast Assumptions'!C45) -> 811200 | L36: =L24*(1+'Forecast Assumptions'!C46) -> 563550.35 | M36: =SUM(C36:L36) -> 21363202
A37: 46935 | B37: FY27/28 | C37: ='Population Forecast'!C63*F6/12 -> 5263367.9 | D37: ='Population Forecast'!D63*F7/12 -> 2681337.3 | E37: ='Population Forecast'!E63*F8/12 -> 897729.69 | F37: ='Population Forecast'!F63*F9/12 -> 1387764.1 | G37: ='Population Forecast'!G63*F10/12 -> 597069.97 | H37: =H25*(1+'Forecast Assumptions'!C42) -> 3384271 | I37: =I25*(1+'Forecast Assumptions'!C43) -> 548077 | J37: =J25*(1+'Forecast Assumptions'!C44) -> 1180747 | K37: =K25*(1+'Forecast Assumptions'!C45) -> 901332.97 | L37: =L25*(1+'Forecast Assumptions'!C46) -> 563550.35 | M37: =SUM(C37:L37) -> 17405247
A38: 46966 | B38: FY28/29 | C38: ='Population Forecast'!C64*H6/12 -> 5504604.6 | D38: ='Population Forecast'!D64*H7/12 -> 3042684.3 | E38: ='Population Forecast'!E64*H8/12 -> 752020.5 | F38: ='Population Forecast'!F64*H9/12 -> 1367578.6 | G38: ='Population Forecast'!G64*H10/12 -> 584970.42 | H38: =H26*(1+'Forecast Assumptions'!D42) -> 2852017.5 | I38: =I26*(1+'Forecast Assumptions'!D43) -> 3690384.5 | J38: =J26*(1+'Forecast Assumptions'!D44) -> 1473571.8 | K38: =K26*(1+'Forecast Assumptions'!D45) -> 843648 | L38: =L26*(1+'Forecast Assumptions'!D46) -> 574821.35 | M38: =SUM(C38:L38) -> 20686302
A39: 46997 | B39: FY28/29 | C39: ='Population Forecast'!C65*H6/12 -> 8245764 | D39: ='Population Forecast'!D65*H7/12 -> 4371890.1 | E39: ='Population Forecast'!E65*H8/12 -> 7664316.9 | F39: ='Population Forecast'!F65*H9/12 -> 12731148 | G39: ='Population Forecast'!G65*H10/12 -> 768319.35 | H39: =H27*(1+'Forecast Assumptions'!D42) -> 3010462.9 | I39: =I27*(1+'Forecast Assumptions'!D43) -> 553557.77 | J39: =J27*(1+'Forecast Assumptions'!D44) -> 3192738.6 | K39: =K27*(1+'Forecast Assumptions'!D45) -> 1031125.7 | L39: =L27*(1+'Forecast Assumptions'!D46) -> 574821.35 | M39: =SUM(C39:L39) -> 42144145
A40: 47027 | B40: FY28/29 | C40: ='Population Forecast'!C66*H6/12 -> 8118289 | D40: ='Population Forecast'!D66*H7/12 -> 4376089.8 | E40: ='Population Forecast'!E66*H8/12 -> 6235376.4 | F40: ='Population Forecast'!F66*H9/12 -> 10071133 | G40: ='Population Forecast'!G66*H10/12 -> 758245.24 | H40: =H28*(1+'Forecast Assumptions'!D42) -> 3168908.3 | I40: =I28*(1+'Forecast Assumptions'!D43) -> 553557.77 | J40: =J28*(1+'Forecast Assumptions'!D44) -> 3192738.6 | K40: =K28*(1+'Forecast Assumptions'!D45) -> 1031125.7 | L40: =L28*(1+'Forecast Assumptions'!D46) -> 574821.35 | M40: =SUM(C40:L40) -> 38080285
A41: 47058 | B41: FY28/29 | C41: ='Population Forecast'!C67*H6/12 -> 8202975.2 | D41: ='Population Forecast'!D67*H7/12 -> 4329893 | E41: ='Population Forecast'!E67*H8/12 -> 4994187.4 | F41: ='Population Forecast'!F67*H9/12 -> 8065923 | G41: ='Population Forecast'!G67*H10/12 -> 756230.41 | H41: =H29*(1+'Forecast Assumptions'!D42) -> 3168908.3 | I41: =I29*(1+'Forecast Assumptions'!D43) -> 3690384.5 | J41: =J29*(1+'Forecast Assumptions'!D44) -> 3069941.7 | K41: =K29*(1+'Forecast Assumptions'!D45) -> 937386.29 | L41: =L29*(1+'Forecast Assumptions'!D46) -> 574821.35 | M41: =SUM(C41:L41) -> 37790651
A42: 47088 | B42: FY28/29 | C42: ='Population Forecast'!C68*H6/12 -> 8215455.3 | D42: ='Population Forecast'!D68*H7/12 -> 4331992.9 | E42: ='Population Forecast'!E68*H8/12 -> 3959017.5 | F42: ='Population Forecast'!F68*H9/12 -> 6374161.7 | G42: ='Population Forecast'!G68*H10/12 -> 762946.49 | H42: =H30*(1+'Forecast Assumptions'!D42) -> 3327353.7 | I42: =I30*(1+'Forecast Assumptions'!D43) -> 553557.77 | J42: =J30*(1+'Forecast Assumptions'!D44) -> 2824345.7 | K42: =K30*(1+'Forecast Assumptions'!D45) -> 843648 | L42: =L30*(1+'Forecast Assumptions'!D46) -> 574821.35 | M42: =SUM(C42:L42) -> 31767300
A43: 47119 | B43: FY28/29 | C43: ='Population Forecast'!C69*H6/12 -> 8210998.1 | D43: ='Population Forecast'!D69*H7/12 -> 4329893 | E43: ='Population Forecast'!E69*H8/12 -> 3661659.9 | F43: ='Population Forecast'!F69*H9/12 -> 5854610.6 | G43: ='Population Forecast'!G69*H10/12 -> 809287.43 | H43: =H31*(1+'Forecast Assumptions'!D42) -> 3327353.7 | I43: =I31*(1+'Forecast Assumptions'!D43) -> 553557.77 | J43: =J31*(1+'Forecast Assumptions'!D44) -> 2701548.7 | K43: =K31*(1+'Forecast Assumptions'!D45) -> 937386.29 | L43: =L31*(1+'Forecast Assumptions'!D46) -> 574821.35 | M43: =SUM(C43:L43) -> 30961117
A44: 47150 | B44: FY28/29 | C44: ='Population Forecast'!C70*H6/12 -> 8117397.5 | D44: ='Population Forecast'!D70*H7/12 -> 4346691.8 | E44: ='Population Forecast'!E70*H8/12 -> 2930951.7 | F44: ='Population Forecast'!F70*H9/12 -> 4626580.8 | G44: ='Population Forecast'!G70*H10/12 -> 813317.08 | H44: =H32*(1+'Forecast Assumptions'!D42) -> 3327353.7 | I44: =I32*(1+'Forecast Assumptions'!D43) -> 3690384.5 | J44: =J32*(1+'Forecast Assumptions'!D44) -> 2701548.7 | K44: =K32*(1+'Forecast Assumptions'!D45) -> 1031125.7 | L44: =L32*(1+'Forecast Assumptions'!D46) -> 574821.35 | M44: =SUM(C44:L44) -> 32160173
A45: 47178 | B45: FY28/29 | C45: ='Population Forecast'!C71*H6/12 -> 8157512.1 | D45: ='Population Forecast'!D71*H7/12 -> 4340392.3 | E45: ='Population Forecast'!E71*H8/12 -> 2333191.8 | F45: ='Population Forecast'!F71*H9/12 -> 3675501.8 | G45: ='Population Forecast'!G71*H10/12 -> 822719.59 | H45: =H33*(1+'Forecast Assumptions'!D42) -> 3168908.3 | I45: =I33*(1+'Forecast Assumptions'!D43) -> 553557.77 | J45: =J33*(1+'Forecast Assumptions'!D44) -> 2701548.7 | K45: =K33*(1+'Forecast Assumptions'!D45) -> 1031125.7 | L45: =L33*(1+'Forecast Assumptions'!D46) -> 574821.35 | M45: =SUM(C45:L45) -> 27359279
A46: 47209 | B46: FY28/29 | C46: ='Population Forecast'!C72*H6/12 -> 8120071.9 | D46: ='Population Forecast'!D72*H7/12 -> 4264797.7 | E46: ='Population Forecast'!E72*H8/12 -> 1889692.5 | F46: ='Population Forecast'!F72*H9/12 -> 2967023.1 | G46: ='Population Forecast'!G72*H10/12 -> 806601 | H46: =H34*(1+'Forecast Assumptions'!D42) -> 3168908.3 | I46: =I34*(1+'Forecast Assumptions'!D43) -> 553557.77 | J46: =J34*(1+'Forecast Assumptions'!D44) -> 2701548.7 | K46: =K34*(1+'Forecast Assumptions'!D45) -> 937386.29 | L46: =L34*(1+'Forecast Assumptions'!D46) -> 574821.35 | M46: =SUM(C46:L46) -> 25984409
A47: 47239 | B47: FY28/29 | C47: ='Population Forecast'!C73*H6/12 -> 8116506.1 | D47: ='Population Forecast'!D73*H7/12 -> 4266897.5 | E47: ='Population Forecast'!E73*H8/12 -> 1496936.9 | F47: ='Population Forecast'!F73*H9/12 -> 2333686 | G47: ='Population Forecast'!G73*H10/12 -> 807272.61 | H47: =H35*(1+'Forecast Assumptions'!D42) -> 3010462.9 | I47: =I35*(1+'Forecast Assumptions'!D43) -> 3690384.5 | J47: =J35*(1+'Forecast Assumptions'!D44) -> 2455952.7 | K47: =K35*(1+'Forecast Assumptions'!D45) -> 843648 | L47: =L35*(1+'Forecast Assumptions'!D46) -> 574821.35 | M47: =SUM(C47:L47) -> 27596569
A48: 47270 | B48: FY28/29 | C48: ='Population Forecast'!C74*H6/12 -> 8195843.7 | D48: ='Population Forecast'!D74*H7/12 -> 4292095.7 | E48: ='Population Forecast'!E74*H8/12 -> 1201609 | F48: ='Population Forecast'!F74*H9/12 -> 1863513.8 | G48: ='Population Forecast'!G74*H10/12 -> 810630.65 | H48: =H36*(1+'Forecast Assumptions'!D42) -> 3010462.9 | I48: =I36*(1+'Forecast Assumptions'!D43) -> 553557.77 | J48: =J36*(1+'Forecast Assumptions'!D44) -> 1227976.9 | K48: =K36*(1+'Forecast Assumptions'!D45) -> 843648 | L48: =L36*(1+'Forecast Assumptions'!D46) -> 574821.35 | M48: =SUM(C48:L48) -> 22574160
A49: 47300 | B49: FY28/29 | C49: ='Population Forecast'!C75*H6/12 -> 5564330.7 | D49: ='Population Forecast'!D75*H7/12 -> 2922992.8 | E49: ='Population Forecast'!E75*H8/12 -> 957024.74 | F49: ='Population Forecast'!F75*H9/12 -> 1479217.7 | G49: ='Population Forecast'!G75*H10/12 -> 627281.71 | H49: =H37*(1+'Forecast Assumptions'!D42) -> 3485799.1 | I49: =I37*(1+'Forecast Assumptions'!D43) -> 553557.77 | J49: =J37*(1+'Forecast Assumptions'!D44) -> 1227976.9 | K49: =K37*(1+'Forecast Assumptions'!D45) -> 937386.29 | L49: =L37*(1+'Forecast Assumptions'!D46) -> 574821.35 | M49: =SUM(C49:L49) -> 18330389
A51: C. Annual Income Summary
A52: FY | B52: Total Tuition Income (£) | C52: Total Other Income (£) | D52: Total Income (£) | E52: Income YoY %
A53: FY25/26 (actual) | B53: =SUMIFS(Income!C:C,Income!$B:$B,"FY25/26")+SUMIFS(Income!D:D,Income!$B:$B,"FY25/26")+SUMIFS(Income!E:E,Income!$B:$B,"FY25/26")+SUMIFS(Income!F:F,Income!$B:$B,"FY25/26")+SUMIFS(Income!G:G,Income!$B:$B,"FY25/26") -> 2.150891e+08 | C53: =SUMIFS(Income!H:H,Income!$B:$B,"FY25/26")+SUMIFS(Income!I:I,Income!$B:$B,"FY25/26")+SUMIFS(Income!J:J,Income!$B:$B,"FY25/26")+SUMIFS(Income!K:K,Income!$B:$B,"FY25/26")+SUMIFS(Income!L:L,Income!$B:$B,"FY25/26") -> 96500005 | D53: =B53+C53 -> 3.1158911e+08
A54: FY26/27 | B54: =SUM(C14:G25) -> 2.2342384e+08 | C54: =SUM(H14:L25) -> 99122005 | D54: =B54+C54 -> 3.2254585e+08 | E54: =D54/D53-1 -> 0.035164066
A55: FY27/28 | B55: =SUM(C26:G37) -> 2.3491787e+08 | C55: =SUM(H26:L37) -> 1.0183585e+08 | D55: =B55+C55 -> 3.3675372e+08 | E55: =D55/D54-1 -> 0.044049153
A56: FY28/29 | B56: =SUM(C38:G49) -> 2.5059994e+08 | C56: =SUM(H38:L49) -> 1.0483483e+08 | D56: =B56+C56 -> 3.5543478e+08 | E56: =D56/D55-1 -> 0.055473951
A58: Sources: 'Population Forecast' (headcount), 'Tuition Fee Rates' & 'Forecast Assumptions' Section B (fee increases), 'Income' & 'Forecast Assumptions' Section C (other income growth). FY25/26 actual total income summed directly from 'Income' via SUMIFS for a clean YoY comparison.

Sheet Staff Cost Forecast
A1: Vector University — 36-Month Staff Cost & Workforce Forecast (FY26/27 – FY28/29)
A2: Methodology: Academic and Professional Services staff costs are grown from the same calendar month a year earlier by (1 + Salary Inflation %) × (1 + FTE Growth %) for that financial year, consistent with the combined effect of pay awards and headcount growth on the total pay bill. FTE is grown on the same basis for workforce planning reference.
A4: A. Annual Growth Assumptions & FTE Forecast
A5: Staff Group | B5: FY26/27 Salary Inflation % | C5: FY26/27 FTE Growth % | D5: FY26/27 FTE | E5: FY27/28 Salary Inflation % | F5: FY27/28 FTE Growth % | G5: FY27/28 FTE | H5: FY28/29 Salary Inflation % | I5: FY28/29 FTE Growth % | J5: FY28/29 FTE
A6: Academic | B6: ='Forecast Assumptions'!B50 -> 0.045 | C6: ='Forecast Assumptions'!B52 -> 0.02 | D6: ='Staff Costs'!F40*(1+C6) -> 1254.6 | E6: ='Forecast Assumptions'!C50 -> 0.04 | F6: ='Forecast Assumptions'!C52 -> 0.02 | G6: =D6*(1+F6) -> 1279.692 | H6: ='Forecast Assumptions'!D50 -> 0.04 | I6: ='Forecast Assumptions'!D52 -> 0.02 | J6: =G6*(1+I6) -> 1305.2858
A7: Professional Services | B7: ='Forecast Assumptions'!B51 -> 0.04 | C7: ='Forecast Assumptions'!B53 -> 0.015 | D7: ='Staff Costs'!G40*(1+C7) -> 1055.6 | E7: ='Forecast Assumptions'!C51 -> 0.04 | F7: ='Forecast Assumptions'!C53 -> 0.015 | G7: =D7*(1+F7) -> 1071.434 | H7: ='Forecast Assumptions'!D51 -> 0.04 | I7: ='Forecast Assumptions'!D53 -> 0.015 | J7: =G7*(1+I7) -> 1087.5055
A9: B. Monthly Staff Cost Forecast — 36 Months (Aug 2026 – Jul 2029)
A10: Month | B10: FY | C10: Academic Staff Costs (£) | D10: Professional Services Staff Costs (£) | E10: Total Staff Costs (£) | F10: Academic FTE | G10: Professional Services FTE
A11: 46235 | B11: FY26/27 | C11: ='Staff Costs'!C29*(1+B6)*(1+C6) -> 11591662 | D11: ='Staff Costs'!D29*(1+B7)*(1+C7) -> 5999326.3 | E11: =C11+D11 -> 17590989 | F11: =D6 -> 1254.6 | G11: =D7 -> 1055.6
A12: 46266 | B12: FY26/27 | C12: ='Staff Costs'!C30*(1+B6)*(1+C6) -> 11591662 | D12: ='Staff Costs'!D30*(1+B7)*(1+C7) -> 5999326.3 | E12: =C12+D12 -> 17590989 | F12: =D6 -> 1254.6 | G12: =D7 -> 1055.6
A13: 46296 | B13: FY26/27 | C13: ='Staff Costs'!C31*(1+B6)*(1+C6) -> 11591662 | D13: ='Staff Costs'!D31*(1+B7)*(1+C7) -> 5999326.3 | E13: =C13+D13 -> 17590989 | F13: =D6 -> 1254.6 | G13: =D7 -> 1055.6
A14: 46327 | B14: FY26/27 | C14: ='Staff Costs'!C32*(1+B6)*(1+C6) -> 11591662 | D14: ='Staff Costs'!D32*(1+B7)*(1+C7) -> 5999326.3 | E14: =C14+D14 -> 17590989 | F14: =D6 -> 1254.6 | G14: =D7 -> 1055.6
A15: 46357 | B15: FY26/27 | C15: ='Staff Costs'!C33*(1+B6)*(1+C6) -> 11591662 | D15: ='Staff Costs'!D33*(1+B7)*(1+C7) -> 5999326.3 | E15: =C15+D15 -> 17590989 | F15: =D6 -> 1254.6 | G15: =D7 -> 1055.6
A16: 46388 | B16: FY26/27 | C16: ='Staff Costs'!C34*(1+B6)*(1+C6) -> 11591662 | D16: ='Staff Costs'!D34*(1+B7)*(1+C7) -> 5999326.3 | E16: =C16+D16 -> 17590989 | F16: =D6 -> 1254.6 | G16: =D7 -> 1055.6
A17: 46419 | B17: FY26/27 | C17: ='Staff Costs'!C35*(1+B6)*(1+C6) -> 11591662 | D17: ='Staff Costs'!D35*(1+B7)*(1+C7) -> 5999326.3 | E17: =C17+D17 -> 17590989 | F17: =D6 -> 1254.6 | G17: =D7 -> 1055.6
A18: 46447 | B18: FY26/27 | C18: ='Staff Costs'!C36*(1+B6)*(1+C6) -> 11591662 | D18: ='Staff Costs'!D36*(1+B7)*(1+C7) -> 5999326.3 | E18: =C18+D18 -> 17590989 | F18: =D6 -> 1254.6 | G18: =D7 -> 1055.6
A19: 46478 | B19: FY26/27 | C19: ='Staff Costs'!C37*(1+B6)*(1+C6) -> 11591662 | D19: ='Staff Costs'!D37*(1+B7)*(1+C7) -> 5999326.3 | E19: =C19+D19 -> 17590989 | F19: =D6 -> 1254.6 | G19: =D7 -> 1055.6
A20: 46508 | B20: FY26/27 | C20: ='Staff Costs'!C38*(1+B6)*(1+C6) -> 11591662 | D20: ='Staff Costs'!D38*(1+B7)*(1+C7) -> 5999326.3 | E20: =C20+D20 -> 17590989 | F20: =D6 -> 1254.6 | G20: =D7 -> 1055.6
A21: 46539 | B21: FY26/27 | C21: ='Staff Costs'!C39*(1+B6)*(1+C6) -> 11591662 | D21: ='Staff Costs'!D39*(1+B7)*(1+C7) -> 5999326.3 | E21: =C21+D21 -> 17590989 | F21: =D6 -> 1254.6 | G21: =D7 -> 1055.6
A22: 46569 | B22: FY26/27 | C22: ='Staff Costs'!C40*(1+B6)*(1+C6) -> 11591662 | D22: ='Staff Costs'!D40*(1+B7)*(1+C7) -> 5999326.3 | E22: =C22+D22 -> 17590989 | F22: =D6 -> 1254.6 | G22: =D7 -> 1055.6
A23: 46600 | B23: FY27/28 | C23: =C11*(1+E6)*(1+F6) -> 12296436 | D23: =D11*(1+E7)*(1+F7) -> 6332888.9 | E23: =C23+D23 -> 18629324 | F23: =G6 -> 1279.692 | G23: =G7 -> 1071.434
A24: 46631 | B24: FY27/28 | C24: =C12*(1+E6)*(1+F6) -> 12296436 | D24: =D12*(1+E7)*(1+F7) -> 6332888.9 | E24: =C24+D24 -> 18629324 | F24: =G6 -> 1279.692 | G24: =G7 -> 1071.434
A25: 46661 | B25: FY27/28 | C25: =C13*(1+E6)*(1+F6) -> 12296436 | D25: =D13*(1+E7)*(1+F7) -> 6332888.9 | E25: =C25+D25 -> 18629324 | F25: =G6 -> 1279.692 | G25: =G7 -> 1071.434
A26: 46692 | B26: FY27/28 | C26: =C14*(1+E6)*(1+F6) -> 12296436 | D26: =D14*(1+E7)*(1+F7) -> 6332888.9 | E26: =C26+D26 -> 18629324 | F26: =G6 -> 1279.692 | G26: =G7 -> 1071.434
A27: 46722 | B27: FY27/28 | C27: =C15*(1+E6)*(1+F6) -> 12296436 | D27: =D15*(1+E7)*(1+F7) -> 6332888.9 | E27: =C27+D27 -> 18629324 | F27: =G6 -> 1279.692 | G27: =G7 -> 1071.434
A28: 46753 | B28: FY27/28 | C28: =C16*(1+E6)*(1+F6) -> 12296436 | D28: =D16*(1+E7)*(1+F7) -> 6332888.9 | E28: =C28+D28 -> 18629324 | F28: =G6 -> 1279.692 | G28: =G7 -> 1071.434
A29: 46784 | B29: FY27/28 | C29: =C17*(1+E6)*(1+F6) -> 12296436 | D29: =D17*(1+E7)*(1+F7) -> 6332888.9 | E29: =C29+D29 -> 18629324 | F29: =G6 -> 1279.692 | G29: =G7 -> 1071.434
A30: 46813 | B30: FY27/28 | C30: =C18*(1+E6)*(1+F6) -> 12296436 | D30: =D18*(1+E7)*(1+F7) -> 6332888.9 | E30: =C30+D30 -> 18629324 | F30: =G6 -> 1279.692 | G30: =G7 -> 1071.434
A31: 46844 | B31: FY27/28 | C31: =C19*(1+E6)*(1+F6) -> 12296436 | D31: =D19*(1+E7)*(1+F7) -> 6332888.9 | E31: =C31+D31 -> 18629324 | F31: =G6 -> 1279.692 | G31: =G7 -> 1071.434
A32: 46874 | B32: FY27/28 | C32: =C20*(1+E6)*(1+F6) -> 12296436 | D32: =D20*(1+E7)*(1+F7) -> 6332888.9 | E32: =C32+D32 -> 18629324 | F32: =G6 -> 1279.692 | G32: =G7 -> 1071.434
A33: 46905 | B33: FY27/28 | C33: =C21*(1+E6)*(1+F6) -> 12296436 | D33: =D21*(1+E7)*(1+F7) -> 6332888.9 | E33: =C33+D33 -> 18629324 | F33: =G6 -> 1279.692 | G33: =G7 -> 1071.434
A34: 46935 | B34: FY27/28 | C34: =C22*(1+E6)*(1+F6) -> 12296436 | D34: =D22*(1+E7)*(1+F7) -> 6332888.9 | E34: =C34+D34 -> 18629324 | F34: =G6 -> 1279.692 | G34: =G7 -> 1071.434
A35: 46966 | B35: FY28/29 | C35: =C23*(1+H6)*(1+I6) -> 13044059 | D35: =D23*(1+H7)*(1+I7) -> 6684997.5 | E35: =C35+D35 -> 19729056 | F35: =J6 -> 1305.2858 | G35: =J7 -> 1087.5055
A36: 46997 | B36: FY28/29 | C36: =C24*(1+H6)*(1+I6) -> 13044059 | D36: =D24*(1+H7)*(1+I7) -> 6684997.5 | E36: =C36+D36 -> 19729056 | F36: =J6 -> 1305.2858 | G36: =J7 -> 1087.5055
A37: 47027 | B37: FY28/29 | C37: =C25*(1+H6)*(1+I6) -> 13044059 | D37: =D25*(1+H7)*(1+I7) -> 6684997.5 | E37: =C37+D37 -> 19729056 | F37: =J6 -> 1305.2858 | G37: =J7 -> 1087.5055
A38: 47058 | B38: FY28/29 | C38: =C26*(1+H6)*(1+I6) -> 13044059 | D38: =D26*(1+H7)*(1+I7) -> 6684997.5 | E38: =C38+D38 -> 19729056 | F38: =J6 -> 1305.2858 | G38: =J7 -> 1087.5055
A39: 47088 | B39: FY28/29 | C39: =C27*(1+H6)*(1+I6) -> 13044059 | D39: =D27*(1+H7)*(1+I7) -> 6684997.5 | E39: =C39+D39 -> 19729056 | F39: =J6 -> 1305.2858 | G39: =J7 -> 1087.5055
A40: 47119 | B40: FY28/29 | C40: =C28*(1+H6)*(1+I6) -> 13044059 | D40: =D28*(1+H7)*(1+I7) -> 6684997.5 | E40: =C40+D40 -> 19729056 | F40: =J6 -> 1305.2858 | G40: =J7 -> 1087.5055
A41: 47150 | B41: FY28/29 | C41: =C29*(1+H6)*(1+I6) -> 13044059 | D41: =D29*(1+H7)*(1+I7) -> 6684997.5 | E41: =C41+D41 -> 19729056 | F41: =J6 -> 1305.2858 | G41: =J7 -> 1087.5055
A42: 47178 | B42: FY28/29 | C42: =C30*(1+H6)*(1+I6) -> 13044059 | D42: =D30*(1+H7)*(1+I7) -> 6684997.5 | E42: =C42+D42 -> 19729056 | F42: =J6 -> 1305.2858 | G42: =J7 -> 1087.5055
A43: 47209 | B43: FY28/29 | C43: =C31*(1+H6)*(1+I6) -> 13044059 | D43: =D31*(1+H7)*(1+I7) -> 6684997.5 | E43: =C43+D43 -> 19729056 | F43: =J6 -> 1305.2858 | G43: =J7 -> 1087.5055
A44: 47239 | B44: FY28/29 | C44: =C32*(1+H6)*(1+I6) -> 13044059 | D44: =D32*(1+H7)*(1+I7) -> 6684997.5 | E44: =C44+D44 -> 19729056 | F44: =J6 -> 1305.2858 | G44: =J7 -> 1087.5055
A45: 47270 | B45: FY28/29 | C45: =C33*(1+H6)*(1+I6) -> 13044059 | D45: =D33*(1+H7)*(1+I7) -> 6684997.5 | E45: =C45+D45 -> 19729056 | F45: =J6 -> 1305.2858 | G45: =J7 -> 1087.5055
A46: 47300 | B46: FY28/29 | C46: =C34*(1+H6)*(1+I6) -> 13044059 | D46: =D34*(1+H7)*(1+I7) -> 6684997.5 | E46: =C46+D46 -> 19729056 | F46: =J6 -> 1305.2858 | G46: =J7 -> 1087.5055
A48: Sources: 'Staff Costs' (FY25/26 monthly actuals, baseline FTE), 'Forecast Assumptions' Section D (salary inflation and FTE growth). Total pay bill growth = (1 + Salary Inflation %) × (1 + FTE Growth %) − 1, applied to the same calendar month a year earlier.

Sheet Opex Forecast
A1: Vector University — 36-Month Operating Expenditure Forecast (FY26/27 – FY28/29)
A2: Methodology: Each cost line is grown from the same calendar month a year earlier by its FY inflation assumption — Utilities Inflation % for Utilities, and General Operating Cost Inflation % (IT, Estates, Student Services, Marketing, Professional Fees, Administration, Other) for the remaining lines — per 'Forecast Assumptions' Section E.
A4: A. Annual Cost Inflation Assumptions
A5: Cost Line | B5: FY26/27 Inflation % | C5: FY27/28 Inflation % | D5: FY28/29 Inflation %
A6: Utilities | B6: ='Forecast Assumptions'!B57 -> 0.05 | C6: ='Forecast Assumptions'!C57 -> 0.04 | D6: ='Forecast Assumptions'!D57 -> 0.035
A7: IT & Digital Services | B7: ='Forecast Assumptions'!B58 -> 0.035 | C7: ='Forecast Assumptions'!C58 -> 0.035 | D7: ='Forecast Assumptions'!D58 -> 0.035
A8: Estates & Maintenance | B8: ='Forecast Assumptions'!B58 -> 0.035 | C8: ='Forecast Assumptions'!C58 -> 0.035 | D8: ='Forecast Assumptions'!D58 -> 0.035
A9: Student Services | B9: ='Forecast Assumptions'!B58 -> 0.035 | C9: ='Forecast Assumptions'!C58 -> 0.035 | D9: ='Forecast Assumptions'!D58 -> 0.035
A10: Marketing & Recruitment | B10: ='Forecast Assumptions'!B58 -> 0.035 | C10: ='Forecast Assumptions'!C58 -> 0.035 | D10: ='Forecast Assumptions'!D58 -> 0.035
A11: Professional Fees | B11: ='Forecast Assumptions'!B58 -> 0.035 | C11: ='Forecast Assumptions'!C58 -> 0.035 | D11: ='Forecast Assumptions'!D58 -> 0.035
A12: Administration | B12: ='Forecast Assumptions'!B58 -> 0.035 | C12: ='Forecast Assumptions'!C58 -> 0.035 | D12: ='Forecast Assumptions'!D58 -> 0.035
A13: Other Operating Expenditure | B13: ='Forecast Assumptions'!B58 -> 0.035 | C13: ='Forecast Assumptions'!C58 -> 0.035 | D13: ='Forecast Assumptions'!D58 -> 0.035
A15: B. Monthly Operating Expenditure Forecast — 36 Months (Aug 2026 – Jul 2029)
A16: Month | B16: FY | C16: Utilities | D16: IT & Digital Services | E16: Estates & Maintenance | F16: Student Services | G16: Marketing & Recruitment | H16: Professional Fees | I16: Administration | J16: Other Operating Expenditure | K16: Total Operating Expenditure
A17: 46235 | B17: FY26/27 | C17: ='Operating Expenditure'!C29*(1+B6) -> 1169317.8 | D17: ='Operating Expenditure'!E29*(1+B7) -> 1518000.3 | E17: ='Operating Expenditure'!G29*(1+B8) -> 2603487.6 | F17: ='Operating Expenditure'!I29*(1+B9) -> 1652578.3 | G17: ='Operating Expenditure'!K29*(1+B10) -> 1324800 | H17: ='Operating Expenditure'!M29*(1+B11) -> 358800.34 | I17: ='Operating Expenditure'!O29*(1+B12) -> 828000 | J17: ='Operating Expenditure'!Q29*(1+B13) -> 724500 | K17: =SUM(C17:J17) -> 10179484
A18: 46266 | B18: FY26/27 | C18: ='Operating Expenditure'!C30*(1+B6) -> 1336363.4 | D18: ='Operating Expenditure'!E30*(1+B7) -> 1518000.3 | E18: ='Operating Expenditure'!G30*(1+B8) -> 2603487.6 | F18: ='Operating Expenditure'!I30*(1+B9) -> 1180413.4 | G18: ='Operating Expenditure'!K30*(1+B10) -> 662400 | H18: ='Operating Expenditure'!M30*(1+B11) -> 358800.34 | I18: ='Operating Expenditure'!O30*(1+B12) -> 828000 | J18: ='Operating Expenditure'!Q30*(1+B13) -> 724500 | K18: =SUM(C18:J18) -> 9211965
A19: 46296 | B19: FY26/27 | C19: ='Operating Expenditure'!C31*(1+B6) -> 1670454.4 | D19: ='Operating Expenditure'!E31*(1+B7) -> 1518000.3 | E19: ='Operating Expenditure'!G31*(1+B8) -> 1602145.8 | F19: ='Operating Expenditure'!I31*(1+B9) -> 1062371.6 | G19: ='Operating Expenditure'!K31*(1+B10) -> 579600 | H19: ='Operating Expenditure'!M31*(1+B11) -> 358800.34 | I19: ='Operating Expenditure'!O31*(1+B12) -> 828000 | J19: ='Operating Expenditure'!Q31*(1+B13) -> 724500 | K19: =SUM(C19:J19) -> 8343872.6
A20: 46327 | B20: FY26/27 | C20: ='Operating Expenditure'!C32*(1+B6) -> 2171591.1 | D20: ='Operating Expenditure'!E32*(1+B7) -> 1518000.3 | E20: ='Operating Expenditure'!G32*(1+B8) -> 1602145.8 | F20: ='Operating Expenditure'!I32*(1+B9) -> 1062371.6 | G20: ='Operating Expenditure'!K32*(1+B10) -> 579600 | H20: ='Operating Expenditure'!M32*(1+B11) -> 358800.34 | I20: ='Operating Expenditure'!O32*(1+B12) -> 828000 | J20: ='Operating Expenditure'!Q32*(1+B13) -> 724500 | K20: =SUM(C20:J20) -> 8845009.2
A21: 46357 | B21: FY26/27 | C21: ='Operating Expenditure'!C33*(1+B6) -> 2338636.6 | D21: ='Operating Expenditure'!E33*(1+B7) -> 1518000.3 | E21: ='Operating Expenditure'!G33*(1+B8) -> 1602145.8 | F21: ='Operating Expenditure'!I33*(1+B9) -> 1534537.6 | G21: ='Operating Expenditure'!K33*(1+B10) -> 1076400 | H21: ='Operating Expenditure'!M33*(1+B11) -> 358800.34 | I21: ='Operating Expenditure'!O33*(1+B12) -> 828000 | J21: ='Operating Expenditure'!Q33*(1+B13) -> 724500 | K21: =SUM(C21:J21) -> 9981020.8
A22: 46388 | B22: FY26/27 | C22: ='Operating Expenditure'!C34*(1+B6) -> 2171591.1 | D22: ='Operating Expenditure'!E34*(1+B7) -> 1518000.3 | E22: ='Operating Expenditure'!G34*(1+B8) -> 1602145.8 | F22: ='Operating Expenditure'!I34*(1+B9) -> 1180413.4 | G22: ='Operating Expenditure'!K34*(1+B10) -> 1159200 | H22: ='Operating Expenditure'!M34*(1+B11) -> 358800.34 | I22: ='Operating Expenditure'!O34*(1+B12) -> 828000 | J22: ='Operating Expenditure'!Q34*(1+B13) -> 724500 | K22: =SUM(C22:J22) -> 9542651
A23: 46419 | B23: FY26/27 | C23: ='Operating Expenditure'!C35*(1+B6) -> 1837500 | D23: ='Operating Expenditure'!E35*(1+B7) -> 1518000.3 | E23: ='Operating Expenditure'!G35*(1+B8) -> 1602145.8 | F23: ='Operating Expenditure'!I35*(1+B9) -> 1062371.6 | G23: ='Operating Expenditure'!K35*(1+B10) -> 1076400 | H23: ='Operating Expenditure'!M35*(1+B11) -> 1345500 | I23: ='Operating Expenditure'!O35*(1+B12) -> 828000 | J23: ='Operating Expenditure'!Q35*(1+B13) -> 724500 | K23: =SUM(C23:J23) -> 9994417.8
A24: 46447 | B24: FY26/27 | C24: ='Operating Expenditure'!C36*(1+B6) -> 1503408.9 | D24: ='Operating Expenditure'!E36*(1+B7) -> 1518000.3 | E24: ='Operating Expenditure'!G36*(1+B8) -> 1802414.2 | F24: ='Operating Expenditure'!I36*(1+B9) -> 1062371.6 | G24: ='Operating Expenditure'!K36*(1+B10) -> 745200 | H24: ='Operating Expenditure'!M36*(1+B11) -> 358800.34 | I24: ='Operating Expenditure'!O36*(1+B12) -> 828000 | J24: ='Operating Expenditure'!Q36*(1+B13) -> 724500 | K24: =SUM(C24:J24) -> 8542695.4
A25: 46478 | B25: FY26/27 | C25: ='Operating Expenditure'!C37*(1+B6) -> 1169317.8 | D25: ='Operating Expenditure'!E37*(1+B7) -> 1518000.3 | E25: ='Operating Expenditure'!G37*(1+B8) -> 1802414.2 | F25: ='Operating Expenditure'!I37*(1+B9) -> 1062371.6 | G25: ='Operating Expenditure'!K37*(1+B10) -> 579600 | H25: ='Operating Expenditure'!M37*(1+B11) -> 358800.34 | I25: ='Operating Expenditure'!O37*(1+B12) -> 828000 | J25: ='Operating Expenditure'!Q37*(1+B13) -> 724500 | K25: =SUM(C25:J25) -> 8043004.3
A26: 46508 | B26: FY26/27 | C26: ='Operating Expenditure'!C38*(1+B6) -> 1002272.2 | D26: ='Operating Expenditure'!E38*(1+B7) -> 1518000.3 | E26: ='Operating Expenditure'!G38*(1+B8) -> 2202950.9 | F26: ='Operating Expenditure'!I38*(1+B9) -> 1062371.6 | G26: ='Operating Expenditure'!K38*(1+B10) -> 496800 | H26: ='Operating Expenditure'!M38*(1+B11) -> 358800.34 | I26: ='Operating Expenditure'!O38*(1+B12) -> 828000 | J26: ='Operating Expenditure'!Q38*(1+B13) -> 724500 | K26: =SUM(C26:J26) -> 8193695.5
A27: 46539 | B27: FY26/27 | C27: ='Operating Expenditure'!C39*(1+B6) -> 1002272.2 | D27: ='Operating Expenditure'!E39*(1+B7) -> 1518000.3 | E27: ='Operating Expenditure'!G39*(1+B8) -> 2803756 | F27: ='Operating Expenditure'!I39*(1+B9) -> 1180413.4 | G27: ='Operating Expenditure'!K39*(1+B10) -> 496800 | H27: ='Operating Expenditure'!M39*(1+B11) -> 358800.34 | I27: ='Operating Expenditure'!O39*(1+B12) -> 828000 | J27: ='Operating Expenditure'!Q39*(1+B13) -> 724500 | K27: =SUM(C27:J27) -> 8912542.3
A28: 46569 | B28: FY26/27 | C28: ='Operating Expenditure'!C40*(1+B6) -> 1002272.2 | D28: ='Operating Expenditure'!E40*(1+B7) -> 1518000.3 | E28: ='Operating Expenditure'!G40*(1+B8) -> 2803756 | F28: ='Operating Expenditure'!I40*(1+B9) -> 1180413.4 | G28: ='Operating Expenditure'!K40*(1+B10) -> 1159200 | H28: ='Operating Expenditure'!M40*(1+B11) -> 448499.66 | I28: ='Operating Expenditure'!O40*(1+B12) -> 828000 | J28: ='Operating Expenditure'!Q40*(1+B13) -> 724500 | K28: =SUM(C28:J28) -> 9664641.6
A29: 46600 | B29: FY27/28 | C29: =C17*(1+C6) -> 1216090.5 | D29: =D17*(1+C7) -> 1571130.4 | E29: =E17*(1+C8) -> 2694609.7 | F29: =F17*(1+C9) -> 1710418.5 | G29: =G17*(1+C10) -> 1371168 | H29: =H17*(1+C11) -> 371358.36 | I29: =I17*(1+C12) -> 856980 | J29: =J17*(1+C13) -> 749857.5 | K29: =SUM(C29:J29) -> 10541613
A30: 46631 | B30: FY27/28 | C30: =C18*(1+C6) -> 1389817.9 | D30: =D18*(1+C7) -> 1571130.4 | E30: =E18*(1+C8) -> 2694609.7 | F30: =F18*(1+C9) -> 1221727.8 | G30: =G18*(1+C10) -> 685584 | H30: =H18*(1+C11) -> 371358.36 | I30: =I18*(1+C12) -> 856980 | J30: =J18*(1+C13) -> 749857.5 | K30: =SUM(C30:J30) -> 9541065.6
A31: 46661 | B31: FY27/28 | C31: =C19*(1+C6) -> 1737272.6 | D31: =D19*(1+C7) -> 1571130.4 | E31: =E19*(1+C8) -> 1658220.9 | F31: =F19*(1+C9) -> 1099554.6 | G31: =G19*(1+C10) -> 599886 | H31: =H19*(1+C11) -> 371358.36 | I31: =I19*(1+C12) -> 856980 | J31: =J19*(1+C13) -> 749857.5 | K31: =SUM(C31:J31) -> 8644260.4
A32: 46692 | B32: FY27/28 | C32: =C20*(1+C6) -> 2258454.7 | D32: =D20*(1+C7) -> 1571130.4 | E32: =E20*(1+C8) -> 1658220.9 | F32: =F20*(1+C9) -> 1099554.6 | G32: =G20*(1+C10) -> 599886 | H32: =H20*(1+C11) -> 371358.36 | I32: =I20*(1+C12) -> 856980 | J32: =J20*(1+C13) -> 749857.5 | K32: =SUM(C32:J32) -> 9165442.5
A33: 46722 | B33: FY27/28 | C33: =C21*(1+C6) -> 2432182.1 | D33: =D21*(1+C7) -> 1571130.4 | E33: =E21*(1+C8) -> 1658220.9 | F33: =F21*(1+C9) -> 1588246.4 | G33: =G21*(1+C10) -> 1114074 | H33: =H21*(1+C11) -> 371358.36 | I33: =I21*(1+C12) -> 856980 | J33: =J21*(1+C13) -> 749857.5 | K33: =SUM(C33:J33) -> 10342050
A34: 46753 | B34: FY27/28 | C34: =C22*(1+C6) -> 2258454.7 | D34: =D22*(1+C7) -> 1571130.4 | E34: =E22*(1+C8) -> 1658220.9 | F34: =F22*(1+C9) -> 1221727.8 | G34: =G22*(1+C10) -> 1199772 | H34: =H22*(1+C11) -> 371358.36 | I34: =I22*(1+C12) -> 856980 | J34: =J22*(1+C13) -> 749857.5 | K34: =SUM(C34:J34) -> 9887501.7
A35: 46784 | B35: FY27/28 | C35: =C23*(1+C6) -> 1911000 | D35: =D23*(1+C7) -> 1571130.4 | E35: =E23*(1+C8) -> 1658220.9 | F35: =F23*(1+C9) -> 1099554.6 | G35: =G23*(1+C10) -> 1114074 | H35: =H23*(1+C11) -> 1392592.5 | I35: =I23*(1+C12) -> 856980 | J35: =J23*(1+C13) -> 749857.5 | K35: =SUM(C35:J35) -> 10353410
A36: 46813 | B36: FY27/28 | C36: =C24*(1+C6) -> 1563545.3 | D36: =D24*(1+C7) -> 1571130.4 | E36: =E24*(1+C8) -> 1865498.7 | F36: =F24*(1+C9) -> 1099554.6 | G36: =G24*(1+C10) -> 771282 | H36: =H24*(1+C11) -> 371358.36 | I36: =I24*(1+C12) -> 856980 | J36: =J24*(1+C13) -> 749857.5 | K36: =SUM(C36:J36) -> 8849206.8
A37: 46844 | B37: FY27/28 | C37: =C25*(1+C6) -> 1216090.5 | D37: =D25*(1+C7) -> 1571130.4 | E37: =E25*(1+C8) -> 1865498.7 | F37: =F25*(1+C9) -> 1099554.6 | G37: =G25*(1+C10) -> 599886 | H37: =H25*(1+C11) -> 371358.36 | I37: =I25*(1+C12) -> 856980 | J37: =J25*(1+C13) -> 749857.5 | K37: =SUM(C37:J37) -> 8330356
A38: 46874 | B38: FY27/28 | C38: =C26*(1+C6) -> 1042363.1 | D38: =D26*(1+C7) -> 1571130.4 | E38: =E26*(1+C8) -> 2280054.2 | F38: =F26*(1+C9) -> 1099554.6 | G38: =G26*(1+C10) -> 514188 | H38: =H26*(1+C11) -> 371358.36 | I38: =I26*(1+C12) -> 856980 | J38: =J26*(1+C13) -> 749857.5 | K38: =SUM(C38:J38) -> 8485486.2
A39: 46905 | B39: FY27/28 | C39: =C27*(1+C6) -> 1042363.1 | D39: =D27*(1+C7) -> 1571130.4 | E39: =E27*(1+C8) -> 2901887.5 | F39: =F27*(1+C9) -> 1221727.8 | G39: =G27*(1+C10) -> 514188 | H39: =H27*(1+C11) -> 371358.36 | I39: =I27*(1+C12) -> 856980 | J39: =J27*(1+C13) -> 749857.5 | K39: =SUM(C39:J39) -> 9229492.6
A40: 46935 | B40: FY27/28 | C40: =C28*(1+C6) -> 1042363.1 | D40: =D28*(1+C7) -> 1571130.4 | E40: =E28*(1+C8) -> 2901887.5 | F40: =F28*(1+C9) -> 1221727.8 | G40: =G28*(1+C10) -> 1199772 | H40: =H28*(1+C11) -> 464197.14 | I40: =I28*(1+C12) -> 856980 | J40: =J28*(1+C13) -> 749857.5 | K40: =SUM(C40:J40) -> 10007915
A41: 46966 | B41: FY28/29 | C41: =C29*(1+D6) -> 1258653.7 | D41: =D29*(1+D7) -> 1626119.9 | E41: =E29*(1+D8) -> 2788921.1 | F41: =F29*(1+D9) -> 1770283.2 | G41: =G29*(1+D10) -> 1419158.9 | H41: =H29*(1+D11) -> 384355.9 | I41: =I29*(1+D12) -> 886974.3 | J41: =J29*(1+D13) -> 776102.51 | K41: =SUM(C41:J41) -> 10910569
A42: 46997 | B42: FY28/29 | C42: =C30*(1+D6) -> 1438461.5 | D42: =D30*(1+D7) -> 1626119.9 | E42: =E30*(1+D8) -> 2788921.1 | F42: =F30*(1+D9) -> 1264488.3 | G42: =G30*(1+D10) -> 709579.44 | H42: =H30*(1+D11) -> 384355.9 | I42: =I30*(1+D12) -> 886974.3 | J42: =J30*(1+D13) -> 776102.51 | K42: =SUM(C42:J42) -> 9875002.9
A43: 47027 | B43: FY28/29 | C43: =C31*(1+D6) -> 1798077.2 | D43: =D31*(1+D7) -> 1626119.9 | E43: =E31*(1+D8) -> 1716258.7 | F43: =F31*(1+D9) -> 1138039 | G43: =G31*(1+D10) -> 620882.01 | H43: =H31*(1+D11) -> 384355.9 | I43: =I31*(1+D12) -> 886974.3 | J43: =J31*(1+D13) -> 776102.51 | K43: =SUM(C43:J43) -> 8946809.5
A44: 47058 | B44: FY28/29 | C44: =C32*(1+D6) -> 2337500.7 | D44: =D32*(1+D7) -> 1626119.9 | E44: =E32*(1+D8) -> 1716258.7 | F44: =F32*(1+D9) -> 1138039 | G44: =G32*(1+D10) -> 620882.01 | H44: =H32*(1+D11) -> 384355.9 | I44: =I32*(1+D12) -> 886974.3 | J44: =J32*(1+D13) -> 776102.51 | K44: =SUM(C44:J44) -> 9486233
A45: 47088 | B45: FY28/29 | C45: =C33*(1+D6) -> 2517308.5 | D45: =D33*(1+D7) -> 1626119.9 | E45: =E33*(1+D8) -> 1716258.7 | F45: =F33*(1+D9) -> 1643835 | G45: =G33*(1+D10) -> 1153066.6 | H45: =H33*(1+D11) -> 384355.9 | I45: =I33*(1+D12) -> 886974.3 | J45: =J33*(1+D13) -> 776102.51 | K45: =SUM(C45:J45) -> 10704021
A46: 47119 | B46: FY28/29 | C46: =C34*(1+D6) -> 2337500.7 | D46: =D34*(1+D7) -> 1626119.9 | E46: =E34*(1+D8) -> 1716258.7 | F46: =F34*(1+D9) -> 1264488.3 | G46: =G34*(1+D10) -> 1241764 | H46: =H34*(1+D11) -> 384355.9 | I46: =I34*(1+D12) -> 886974.3 | J46: =J34*(1+D13) -> 776102.51 | K46: =SUM(C46:J46) -> 10233564
A47: 47150 | B47: FY28/29 | C47: =C35*(1+D6) -> 1977885 | D47: =D35*(1+D7) -> 1626119.9 | E47: =E35*(1+D8) -> 1716258.7 | F47: =F35*(1+D9) -> 1138039 | G47: =G35*(1+D10) -> 1153066.6 | H47: =H35*(1+D11) -> 1441333.2 | I47: =I35*(1+D12) -> 886974.3 | J47: =J35*(1+D13) -> 776102.51 | K47: =SUM(C47:J47) -> 10715779
A48: 47178 | B48: FY28/29 | C48: =C36*(1+D6) -> 1618269.3 | D48: =D36*(1+D7) -> 1626119.9 | E48: =E36*(1+D8) -> 1930791.2 | F48: =F36*(1+D9) -> 1138039 | G48: =G36*(1+D10) -> 798276.87 | H48: =H36*(1+D11) -> 384355.9 | I48: =I36*(1+D12) -> 886974.3 | J48: =J36*(1+D13) -> 776102.51 | K48: =SUM(C48:J48) -> 9158929
A49: 47209 | B49: FY28/29 | C49: =C37*(1+D6) -> 1258653.7 | D49: =D37*(1+D7) -> 1626119.9 | E49: =E37*(1+D8) -> 1930791.2 | F49: =F37*(1+D9) -> 1138039 | G49: =G37*(1+D10) -> 620882.01 | H49: =H37*(1+D11) -> 384355.9 | I49: =I37*(1+D12) -> 886974.3 | J49: =J37*(1+D13) -> 776102.51 | K49: =SUM(C49:J49) -> 8621918.5
A50: 47239 | B50: FY28/29 | C50: =C38*(1+D6) -> 1078845.8 | D50: =D38*(1+D7) -> 1626119.9 | E50: =E38*(1+D8) -> 2359856.1 | F50: =F38*(1+D9) -> 1138039 | G50: =G38*(1+D10) -> 532184.58 | H50: =H38*(1+D11) -> 384355.9 | I50: =I38*(1+D12) -> 886974.3 | J50: =J38*(1+D13) -> 776102.51 | K50: =SUM(C50:J50) -> 8782478.2
A51: 47270 | B51: FY28/29 | C51: =C39*(1+D6) -> 1078845.8 | D51: =D39*(1+D7) -> 1626119.9 | E51: =E39*(1+D8) -> 3003453.5 | F51: =F39*(1+D9) -> 1264488.3 | G51: =G39*(1+D10) -> 532184.58 | H51: =H39*(1+D11) -> 384355.9 | I51: =I39*(1+D12) -> 886974.3 | J51: =J39*(1+D13) -> 776102.51 | K51: =SUM(C51:J51) -> 9552524.9
A52: 47300 | B52: FY28/29 | C52: =C40*(1+D6) -> 1078845.8 | D52: =D40*(1+D7) -> 1626119.9 | E52: =E40*(1+D8) -> 3003453.5 | F52: =F40*(1+D9) -> 1264488.3 | G52: =G40*(1+D10) -> 1241764 | H52: =H40*(1+D11) -> 480444.04 | I52: =I40*(1+D12) -> 886974.3 | J52: =J40*(1+D13) -> 776102.51 | K52: =SUM(C52:J52) -> 10358192
A54: Source: 'Operating Expenditure' (FY25/26 monthly actuals), 'Forecast Assumptions' Section E (cost inflation).

Sheet Forecast Income Statement
A1: Vector University — Forecast Income Statement (Monthly Summary, FY26/27 – FY28/29)
A2: Combines 'Income Forecast', 'Staff Cost Forecast' and 'Opex Forecast' into a single monthly operating result, on the same layout as the historical 'Income Statement' tab.
A4: Month | B4: FY | C4: Total Income | D4: Total Staff Costs | E4: Total Operating Expenditure | F4: Operating Surplus / (Deficit) | G4: Operating Margin %
A5: 46235 | B5: FY26/27 | C5: ='Income Forecast'!M14 -> 19099183 | D5: ='Staff Cost Forecast'!E11 -> 17590989 | E5: ='Opex Forecast'!K17 -> 10179484 | F5: =C5-D5-E5 -> -8671289.9 | G5: =F5/C5 -> -0.45401364
A6: 46266 | B6: FY26/27 | C6: ='Income Forecast'!M15 -> 37857684 | D6: ='Staff Cost Forecast'!E12 -> 17590989 | E6: ='Opex Forecast'!K18 -> 9211965 | F6: =C6-D6-E6 -> 11054730 | G6: =F6/C6 -> 0.29200757
A7: 46296 | B7: FY26/27 | C7: ='Income Forecast'!M16 -> 34278072 | D7: ='Staff Cost Forecast'!E13 -> 17590989 | E7: ='Opex Forecast'!K19 -> 8343872.6 | F7: =C7-D7-E7 -> 8343210.2 | G7: =F7/C7 -> 0.24339789
A8: 46327 | B8: FY26/27 | C8: ='Income Forecast'!M17 -> 34352497 | D8: ='Staff Cost Forecast'!E14 -> 17590989 | E8: ='Opex Forecast'!K20 -> 8845009.2 | F8: =C8-D8-E8 -> 7916499 | G8: =F8/C8 -> 0.23044901
A9: 46357 | B9: FY26/27 | C9: ='Income Forecast'!M18 -> 28694354 | D9: ='Staff Cost Forecast'!E15 -> 17590989 | E9: ='Opex Forecast'!K21 -> 9981020.8 | F9: =C9-D9-E9 -> 1122344.9 | G9: =F9/C9 -> 0.039113788
A10: 46388 | B10: FY26/27 | C10: ='Income Forecast'!M19 -> 27982651 | D10: ='Staff Cost Forecast'!E16 -> 17590989 | E10: ='Opex Forecast'!K22 -> 9542651 | F10: =C10-D10-E10 -> 849011.07 | G10: =F10/C10 -> 0.030340623
A11: 46419 | B11: FY26/27 | C11: ='Income Forecast'!M20 -> 29379401 | D11: ='Staff Cost Forecast'!E17 -> 17590989 | E11: ='Opex Forecast'!K23 -> 9994417.8 | F11: =C11-D11-E11 -> 1793994.6 | G11: =F11/C11 -> 0.061063009
A12: 46447 | B12: FY26/27 | C12: ='Income Forecast'!M21 -> 24796342 | D12: ='Staff Cost Forecast'!E18 -> 17590989 | E12: ='Opex Forecast'!K24 -> 8542695.4 | F12: =C12-D12-E12 -> -1337342.6 | G12: =F12/C12 -> -0.053933061
A13: 46478 | B13: FY26/27 | C13: ='Income Forecast'!M22 -> 23577980 | D13: ='Staff Cost Forecast'!E19 -> 17590989 | E13: ='Opex Forecast'!K25 -> 8043004.3 | F13: =C13-D13-E13 -> -2056013.1 | G13: =F13/C13 -> -0.08720056
A14: 46508 | B14: FY26/27 | C14: ='Income Forecast'!M23 -> 25314008 | D14: ='Staff Cost Forecast'!E20 -> 17590989 | E14: ='Opex Forecast'!K26 -> 8193695.5 | F14: =C14-D14-E14 -> -470675.84 | G14: =F14/C14 -> -0.018593493
A15: 46539 | B15: FY26/27 | C15: ='Income Forecast'!M24 -> 20494249 | D15: ='Staff Cost Forecast'!E21 -> 17590989 | E15: ='Opex Forecast'!K27 -> 8912542.3 | F15: =C15-D15-E15 -> -6009282 | G15: =F15/C15 -> -0.29321796
A16: 46569 | B16: FY26/27 | C16: ='Income Forecast'!M25 -> 16719425 | D16: ='Staff Cost Forecast'!E22 -> 17590989 | E16: ='Opex Forecast'!K28 -> 9664641.6 | F16: =C16-D16-E16 -> -10536205 | G16: =F16/C16 -> -0.63017749
... A40: 47300 | B40: FY28/29 | C40: ='Income Forecast'!M49 -> 18330389 | D40: ='Staff Cost Forecast'!E46 -> 19729056 | E40: ='Opex Forecast'!K52 -> 10358192 | F40: =C40-D40-E40 -> -11756860 | G40: =F40/C40 -> -0.64138626
A42: Annual Summary (£)
A43: FY | B43: Total Income | C43: Total Staff Costs | D43: Total Operating Expenditure | E43: Operating Surplus / (Deficit) | F43: Operating Margin % | G43: YoY Income Growth
A44: FY25/26 (actual) | B44: ='Income Statement'!B47 -> 3.1158911e+08 | C44: ='Income Statement'!C47 -> 198699996 | D44: ='Income Statement'!D47 -> 1.055e+08 | E44: ='Income Statement'!E47 -> 7389111.5 | F44: ='Income Statement'!F47 -> 0.02371428
A45: FY26/27 | B45: =SUM(C5:C16) -> 3.2254585e+08 | C45: =SUM(D5:D16) -> 2.1109187e+08 | D45: =SUM(E5:E16) -> 1.09455e+08 | E45: =B45-C45-D45 -> 1998981.6 | F45: =E45/B45 -> 0.0061975114 | G45: =B45/B44-1 -> 0.035164066
A46: FY27/28 | B46: =SUM(C17:C28) -> 3.3675372e+08 | C46: =SUM(D17:D28) -> 2.2355189e+08 | D46: =SUM(E17:E28) -> 1.133778e+08 | E46: =B46-C46-D46 -> -175974.46 | F46: =E46/B46 -> -0.00052256129 | G46: =B46/B45-1 -> 0.044049153
A47: FY28/29 | B47: =SUM(C29:C40) -> 3.5543478e+08 | C47: =SUM(D29:D40) -> 2.3674868e+08 | D47: =SUM(E29:E40) -> 1.1734602e+08 | E47: =B47-C47-D47 -> 1340078.9 | F47: =E47/B47 -> 0.0037702526 | G47: =B47/B46-1 -> 0.055473951
A49: Sources: 'Income Forecast', 'Staff Cost Forecast', 'Opex Forecast'. FY25/26 actual row links to the historical 'Income Statement' tab for a clean like-for-like comparison.

Sheet Cash Flow Forecast
A1: Vector University — Forecast Cash Position (Monthly, FY26/27 – FY28/29)
A2: Methodology: Opening cash at 1-Aug-2026 and annual planned capital expenditure are per 'Forecast Assumptions' Section F. Capital expenditure is spread evenly across the 12 months of each financial year. Closing cash = Opening cash + Operating Surplus/(Deficit) − Capital Expenditure.
A4: Month | B4: FY | C4: Opening Cash | D4: Operating Surplus / (Deficit) | E4: Capital Expenditure | F4: Closing Cash
A5: 46235 | B5: FY26/27 | C5: ='Forecast Assumptions'!B63 -> 48027183 | D5: ='Forecast Income Statement'!F5 -> -8671289.9 | E5: ='Forecast Assumptions'!B62/12 -> 875000 | F5: =C5+D5-E5 -> 38480893
A6: 46266 | B6: FY26/27 | C6: =F5 -> 38480893 | D6: ='Forecast Income Statement'!F6 -> 11054730 | E6: ='Forecast Assumptions'!B62/12 -> 875000 | F6: =C6+D6-E6 -> 48660624
A7: 46296 | B7: FY26/27 | C7: =F6 -> 48660624 | D7: ='Forecast Income Statement'!F7 -> 8343210.2 | E7: ='Forecast Assumptions'!B62/12 -> 875000 | F7: =C7+D7-E7 -> 56128834
A8: 46327 | B8: FY26/27 | C8: =F7 -> 56128834 | D8: ='Forecast Income Statement'!F8 -> 7916499 | E8: ='Forecast Assumptions'!B62/12 -> 875000 | F8: =C8+D8-E8 -> 63170333
A9: 46357 | B9: FY26/27 | C9: =F8 -> 63170333 | D9: ='Forecast Income Statement'!F9 -> 1122344.9 | E9: ='Forecast Assumptions'!B62/12 -> 875000 | F9: =C9+D9-E9 -> 63417678
A10: 46388 | B10: FY26/27 | C10: =F9 -> 63417678 | D10: ='Forecast Income Statement'!F10 -> 849011.07 | E10: ='Forecast Assumptions'!B62/12 -> 875000 | F10: =C10+D10-E10 -> 63391689
A11: 46419 | B11: FY26/27 | C11: =F10 -> 63391689 | D11: ='Forecast Income Statement'!F11 -> 1793994.6 | E11: ='Forecast Assumptions'!B62/12 -> 875000 | F11: =C11+D11-E11 -> 64310684
A12: 46447 | B12: FY26/27 | C12: =F11 -> 64310684 | D12: ='Forecast Income Statement'!F12 -> -1337342.6 | E12: ='Forecast Assumptions'!B62/12 -> 875000 | F12: =C12+D12-E12 -> 62098341
A13: 46478 | B13: FY26/27 | C13: =F12 -> 62098341 | D13: ='Forecast Income Statement'!F13 -> -2056013.1 | E13: ='Forecast Assumptions'!B62/12 -> 875000 | F13: =C13+D13-E13 -> 59167328
A14: 46508 | B14: FY26/27 | C14: =F13 -> 59167328 | D14: ='Forecast Income Statement'!F14 -> -470675.84 | E14: ='Forecast Assumptions'!B62/12 -> 875000 | F14: =C14+D14-E14 -> 57821652
A15: 46539 | B15: FY26/27 | C15: =F14 -> 57821652 | D15: ='Forecast Income Statement'!F15 -> -6009282 | E15: ='Forecast Assumptions'!B62/12 -> 875000 | F15: =C15+D15-E15 -> 50937370
A16: 46569 | B16: FY26/27 | C16: =F15 -> 50937370 | D16: ='Forecast Income Statement'!F16 -> -10536205 | E16: ='Forecast Assumptions'!B62/12 -> 875000 | F16: =C16+D16-E16 -> 39526165
A17: 46600 | B17: FY27/28 | C17: =F16 -> 39526165 | D17: ='Forecast Income Statement'!F17 -> -9413239.6 | E17: ='Forecast Assumptions'!C62/12 -> 916666.67 | F17: =C17+D17-E17 -> 29196259
A18: 46631 | B18: FY27/28 | C18: =F17 -> 29196259 | D18: ='Forecast Income Statement'!F18 -> 11600446 | E18: ='Forecast Assumptions'!C62/12 -> 916666.67 | F18: =C18+D18-E18 -> 39880038
A19: 46661 | B19: FY27/28 | C19: =F18 -> 39880038 | D19: ='Forecast Income Statement'!F19 -> 8688800.1 | E19: ='Forecast Assumptions'!C62/12 -> 916666.67 | F19: =C19+D19-E19 -> 47652171
A20: 46692 | B20: FY27/28 | C20: =F19 -> 47652171 | D20: ='Forecast Income Statement'!F20 -> 8055465.6 | E20: ='Forecast Assumptions'!C62/12 -> 916666.67 | F20: =C20+D20-E20 -> 54790970
A21: 46722 | B21: FY27/28 | C21: =F20 -> 54790970 | D21: ='Forecast Income Statement'!F21 -> 1062560.6 | E21: ='Forecast Assumptions'!C62/12 -> 916666.67 | F21: =C21+D21-E21 -> 54936864
A22: 46753 | B22: FY27/28 | C22: =F21 -> 54936864 | D22: ='Forecast Income Statement'!F22 -> 760770.77 | E22: ='Forecast Assumptions'!C62/12 -> 916666.67 | F22: =C22+D22-E22 -> 54780968
A23: 46784 | B23: FY27/28 | C23: =F22 -> 54780968 | D23: ='Forecast Income Statement'!F23 -> 1583932.1 | E23: ='Forecast Assumptions'!C62/12 -> 916666.67 | F23: =C23+D23-E23 -> 55448234
A24: 46813 | B24: FY27/28 | C24: =F23 -> 55448234 | D24: ='Forecast Income Statement'!F24 -> -1583350.5 | E24: ='Forecast Assumptions'!C62/12 -> 916666.67 | F24: =C24+D24-E24 -> 52948216
A25: 46844 | B25: FY27/28 | C25: =F24 -> 52948216 | D25: ='Forecast Income Statement'!F25 -> -2355433.8 | E25: ='Forecast Assumptions'!C62/12 -> 916666.67 | F25: =C25+D25-E25 -> 49676116
A26: 46874 | B26: FY27/28 | C26: =F25 -> 49676116 | D26: ='Forecast Income Statement'!F26 -> -848317.81 | E26: ='Forecast Assumptions'!C62/12 -> 916666.67 | F26: =C26+D26-E26 -> 47911131
A27: 46905 | B27: FY27/28 | C27: =F26 -> 47911131 | D27: ='Forecast Income Statement'!F27 -> -6495615.1 | E27: ='Forecast Assumptions'!C62/12 -> 916666.67 | F27: =C27+D27-E27 -> 40498850
A28: 46935 | B28: FY27/28 | C28: =F27 -> 40498850 | D28: ='Forecast Income Statement'!F28 -> -11231993 | E28: ='Forecast Assumptions'!C62/12 -> 916666.67 | F28: =C28+D28-E28 -> 28350190
A29: 46966 | B29: FY28/29 | C29: =F28 -> 28350190 | D29: ='Forecast Income Statement'!F29 -> -9953324.1 | E29: ='Forecast Assumptions'!D62/12 -> 958333.33 | F29: =C29+D29-E29 -> 17438533
A30: 46997 | B30: FY28/29 | C30: =F29 -> 17438533 | D30: ='Forecast Income Statement'!F30 -> 12540086 | E30: ='Forecast Assumptions'!D62/12 -> 958333.33 | F30: =C30+D30-E30 -> 29020285
A31: 47027 | B31: FY28/29 | C31: =F30 -> 29020285 | D31: ='Forecast Income Statement'!F31 -> 9404418.8 | E31: ='Forecast Assumptions'!D62/12 -> 958333.33 | F31: =C31+D31-E31 -> 37466371
A32: 47058 | B32: FY28/29 | C32: =F31 -> 37466371 | D32: ='Forecast Income Statement'!F32 -> 8575361.9 | E32: ='Forecast Assumptions'!D62/12 -> 958333.33 | F32: =C32+D32-E32 -> 45083399
A33: 47088 | B33: FY28/29 | C33: =F32 -> 45083399 | D33: ='Forecast Income Statement'!F33 -> 1334222.6 | E33: ='Forecast Assumptions'!D62/12 -> 958333.33 | F33: =C33+D33-E33 -> 45459288
A34: 47119 | B34: FY28/29 | C34: =F33 -> 45459288 | D34: ='Forecast Income Statement'!F34 -> 998496.3 | E34: ='Forecast Assumptions'!D62/12 -> 958333.33 | F34: =C34+D34-E34 -> 45499451
A35: 47150 | B35: FY28/29 | C35: =F34 -> 45499451 | D35: ='Forecast Income Statement'!F35 -> 1715337.3 | E35: ='Forecast Assumptions'!D62/12 -> 958333.33 | F35: =C35+D35-E35 -> 46256455
A36: 47178 | B36: FY28/29 | C36: =F35 -> 46256455 | D36: ='Forecast Income Statement'!F36 -> -1528705.9 | E36: ='Forecast Assumptions'!D62/12 -> 958333.33 | F36: =C36+D36-E36 -> 43769416
A37: 47209 | B37: FY28/29 | C37: =F36 -> 43769416 | D37: ='Forecast Income Statement'!F37 -> -2366566.3 | E37: ='Forecast Assumptions'!D62/12 -> 958333.33 | F37: =C37+D37-E37 -> 40444516
A38: 47239 | B38: FY28/29 | C38: =F37 -> 40444516 | D38: ='Forecast Income Statement'!F38 -> -914966.02 | E38: ='Forecast Assumptions'!D62/12 -> 958333.33 | F38: =C38+D38-E38 -> 38571217
A39: 47270 | B39: FY28/29 | C39: =F38 -> 38571217 | D39: ='Forecast Income Statement'!F39 -> -6707421.5 | E39: ='Forecast Assumptions'!D62/12 -> 958333.33 | F39: =C39+D39-E39 -> 30905462
A40: 47300 | B40: FY28/29 | C40: =F39 -> 30905462 | D40: ='Forecast Income Statement'!F40 -> -11756860 | E40: ='Forecast Assumptions'!D62/12 -> 958333.33 | F40: =C40+D40-E40 -> 18190269
A42: Annual Summary (£)
A43: FY | B43: Opening Cash | C43: Operating Surplus / (Deficit) | D43: Capital Expenditure | E43: Closing Cash | F43: Closing Cash YoY %
A44: FY25/26 (actual) | E44: ='Cash Position'!F40 -> 48027183
A45: FY26/27 | B45: =C5 -> 48027183 | C45: =SUM(D5:D16) -> 1998981.6 | D45: =SUM(E5:E16) -> 10500000 | E45: =F16 -> 39526165 | F45: =E45/E44-1 -> -0.17700431
A46: FY27/28 | B46: =C17 -> 39526165 | C46: =SUM(D17:D28) -> -175974.46 | D46: =SUM(E17:E28) -> 11000000 | E46: =F28 -> 28350190 | F46: =E46/E45-1 -> -0.28274877
A47: FY28/29 | B47: =C29 -> 28350190 | C47: =SUM(D29:D40) -> 1340078.9 | D47: =SUM(E29:E40) -> 11500000 | E47: =F40 -> 18190269 | F47: =E47/E46-1 -> -0.35837224
A49: Sources: 'Forecast Income Statement' (operating surplus/deficit), 'Forecast Assumptions' Section F (opening cash, capital expenditure). FY25/26 closing cash links to the historical 'Cash Position' tab.

Sheet Scenario Comparison
A1: Vector University — Scenario Comparison: Base / Upside / Downside (Annual)
A2: Runs the same driver logic as 'Population Forecast' / 'Income Forecast' / 'Staff Cost Forecast' / 'Opex Forecast', at annual grain, for all three scenarios side by side (independent of the live selector on 'Scenario Assumptions', which only drives the detailed monthly model). Operating expenditure is combined into Utilities and one General Opex line (matching the two inflation rates in the assumptions) rather than the 8 separate lines in 'Opex Forecast', to keep the comparison readable. Fee rates, other income growth, FTE growth and capital expenditure are unaffected by these scenarios and are held the same as the Base Case build.
A4: A. Recruitment Engine — New Enrolments & September Anchor, by Scenario
A5: Category | B5: Scenario | C5: FY26/27 Applications | D5: FY26/27 New Enrolments | E5: FY27/28 Applications | F5: FY27/28 New Enrolments | G5: FY28/29 Applications | H5: FY28/29 New Enrolments | I5: FY26/27 Sept Anchor | J5: FY27/28 Sept Anchor | K5: FY28/29 Sept Anchor
A6: UK Undergraduate | B6: Base | C6: =('Student Flow Summary'!D7/('Forecast Assumptions'!C7*'Forecast Assumptions'!C8))*(1+('Scenario Assumptions'!B22+'Scenario Assumptions'!$B$9)) -> 6538.4615 | D6: =C6*'Forecast Assumptions'!C7*'Forecast Assumptions'!C8 -> 3162 | E6: =C6*(1+('Scenario Assumptions'!C22+'Scenario Assumptions'!$B$9)) -> 6669.2308 | F6: =E6*'Forecast Assumptions'!D7*'Forecast Assumptions'!D8 -> 3225.24 | G6: =E6*(1+('Scenario Assumptions'!D22+'Scenario Assumptions'!$B$9)) -> 6802.6154 | H6: =G6*'Forecast Assumptions'!E7*'Forecast Assumptions'!E8 -> 3342.8052 | I6: ='Student Headcount'!C30*(D6/'Student Flow Summary'!D7) -> 9435 | J6: =I6*(F6/D6) -> 9623.7 | K6: =J6*(H6/F6) -> 9974.4994
A7: UK Undergraduate | B7: Upside | C7: =('Student Flow Summary'!D7/('Forecast Assumptions'!C7*'Forecast Assumptions'!C8))*(1+('Scenario Assumptions'!B22+'Scenario Assumptions'!$C$9)) -> 6666.6667 | D7: =C7*'Forecast Assumptions'!C7*'Forecast Assumptions'!C8 -> 3224 | E7: =C7*(1+('Scenario Assumptions'!C22+'Scenario Assumptions'!$C$9)) -> 6933.3333 | F7: =E7*'Forecast Assumptions'!D7*'Forecast Assumptions'!D8 -> 3352.96 | G7: =E7*(1+('Scenario Assumptions'!D22+'Scenario Assumptions'!$C$9)) -> 7210.6667 | H7: =G7*'Forecast Assumptions'!E7*'Forecast Assumptions'!E8 -> 3543.3216 | I7: ='Student Headcount'!C30*(D7/'Student Flow Summary'!D7) -> 9620 | J7: =I7*(F7/D7) -> 10004.8 | K7: =J7*(H7/F7) -> 10572.814
A8: UK Undergraduate | B8: Downside | C8: =('Student Flow Summary'!D7/('Forecast Assumptions'!C7*'Forecast Assumptions'!C8))*(1+('Scenario Assumptions'!B22+'Scenario Assumptions'!$D$9)) -> 6346.1538 | D8: =C8*'Forecast Assumptions'!C7*'Forecast Assumptions'!C8 -> 3069 | E8: =C8*(1+('Scenario Assumptions'!C22+'Scenario Assumptions'!$D$9)) -> 6282.6923 | F8: =E8*'Forecast Assumptions'!D7*'Forecast Assumptions'!D8 -> 3038.31 | G8: =E8*(1+('Scenario Assumptions'!D22+'Scenario Assumptions'!$D$9)) -> 6219.8654 | H8: =G8*'Forecast Assumptions'!E7*'Forecast Assumptions'!E8 -> 3056.4419 | I8: ='Student Headcount'!C30*(D8/'Student Flow Summary'!D7) -> 9157.5 | J8: =I8*(F8/D8) -> 9065.925 | K8: =J8*(H8/F8) -> 9120.0281
A9: International Undergraduate | B9: Base | C9: =('Student Flow Summary'!D10/('Forecast Assumptions'!C12*'Forecast Assumptions'!C13))*(1+('Scenario Assumptions'!B23+'Scenario Assumptions'!$B$9)) -> 2115.0974 | D9: =C9*'Forecast Assumptions'!C12*'Forecast Assumptions'!C13 -> 651.45 | E9: =C9*(1+('Scenario Assumptions'!C23+'Scenario Assumptions'!$B$9)) -> 2136.2484 | F9: =E9*'Forecast Assumptions'!D12*'Forecast Assumptions'!D13 -> 657.9645 | G9: =E9*(1+('Scenario Assumptions'!D23+'Scenario Assumptions'!$B$9)) -> 2178.9733 | H9: =G9*'Forecast Assumptions'!E12*'Forecast Assumptions'!E13 -> 686.3766 | I9: ='Student Headcount'!E30*(D9/'Student Flow Summary'!D10) -> 2102.82 | J9: =I9*(F9/D9) -> 2123.8482 | K9: =J9*(H9/F9) -> 2215.5598
A10: International Undergraduate | B10: Upside | C10: =('Student Flow Summary'!D10/('Forecast Assumptions'!C12*'Forecast Assumptions'!C13))*(1+('Scenario Assumptions'!B23+'Scenario Assumptions'!$C$9)) -> 2156.9805 | D10: =C10*'Forecast Assumptions'!C12*'Forecast Assumptions'!C13 -> 664.35 | E10: =C10*(1+('Scenario Assumptions'!C23+'Scenario Assumptions'!$C$9)) -> 2221.6899 | F10: =E10*'Forecast Assumptions'!D12*'Forecast Assumptions'!D13 -> 684.2805 | G10: =E10*(1+('Scenario Assumptions'!D23+'Scenario Assumptions'!$C$9)) -> 2310.5575 | H10: =G10*'Forecast Assumptions'!E12*'Forecast Assumptions'!E13 -> 727.82562 | I10: ='Student Headcount'!E30*(D10/'Student Flow Summary'!D10) -> 2144.46 | J10: =I10*(F10/D10) -> 2208.7938 | K10: =J10*(H10/F10) -> 2349.3534
A11: International Undergraduate | B11: Downside | C11: =('Student Flow Summary'!D10/('Forecast Assumptions'!C12*'Forecast Assumptions'!C13))*(1+('Scenario Assumptions'!B23+'Scenario Assumptions'!$D$9)) -> 2052.2727 | D11: =C11*'Forecast Assumptions'!C12*'Forecast Assumptions'!C13 -> 632.1 | E11: =C11*(1+('Scenario Assumptions'!C23+'Scenario Assumptions'!$D$9)) -> 2011.2273 | F11: =E11*'Forecast Assumptions'!D12*'Forecast Assumptions'!D13 -> 619.458 | G11: =E11*(1+('Scenario Assumptions'!D23+'Scenario Assumptions'!$D$9)) -> 1991.115 | H11: =G11*'Forecast Assumptions'!E12*'Forecast Assumptions'!E13 -> 627.20123 | I11: ='Student Headcount'!E30*(D11/'Student Flow Summary'!D10) -> 2040.36 | J11: =I11*(F11/D11) -> 1999.5528 | K11: =J11*(H11/F11) -> 2024.5472
A12: UK Postgraduate | B12: Base | C12: =('Student Flow Summary'!D13/('Forecast Assumptions'!C17*'Forecast Assumptions'!C18))*(1+('Scenario Assumptions'!B24+'Scenario Assumptions'!$B$9)) -> 13759.756 | D12: =C12*'Forecast Assumptions'!C17*'Forecast Assumptions'!C18 -> 7672.44 | E12: =C12*(1+('Scenario Assumptions'!C24+'Scenario Assumptions'!$B$9)) -> 14034.951 | F12: =E12*'Forecast Assumptions'!D17*'Forecast Assumptions'!D18 -> 7825.8888 | G12: =E12*(1+('Scenario Assumptions'!D24+'Scenario Assumptions'!$B$9)) -> 14315.65 | H12: =G12*'Forecast Assumptions'!E17*'Forecast Assumptions'!E18 -> 8099.7949 | I12: ='Student Headcount'!G30*(D12/'Student Flow Summary'!D13) -> 7703.04 | J12: =I12*(F12/D12) -> 7857.1008 | K12: =J12*(H12/F12) -> 8132.0993
A13: UK Postgraduate | B13: Upside | C13: =('Student Flow Summary'!D13/('Forecast Assumptions'!C17*'Forecast Assumptions'!C18))*(1+('Scenario Assumptions'!B24+'Scenario Assumptions'!$C$9)) -> 14029.555 | D13: =C13*'Forecast Assumptions'!C17*'Forecast Assumptions'!C18 -> 7822.88 | E13: =C13*(1+('Scenario Assumptions'!C24+'Scenario Assumptions'!$C$9)) -> 14590.737 | F13: =E13*'Forecast Assumptions'!D17*'Forecast Assumptions'!D18 -> 8135.7952 | G13: =E13*(1+('Scenario Assumptions'!D24+'Scenario Assumptions'!$C$9)) -> 15174.367 | H13: =G13*'Forecast Assumptions'!E17*'Forecast Assumptions'!E18 -> 8585.6568 | I13: ='Student Headcount'!G30*(D13/'Student Flow Summary'!D13) -> 7854.08 | J13: =I13*(F13/D13) -> 8168.2432 | K13: =J13*(H13/F13) -> 8619.899
A14: UK Postgraduate | B14: Downside | C14: =('Student Flow Summary'!D13/('Forecast Assumptions'!C17*'Forecast Assumptions'!C18))*(1+('Scenario Assumptions'!B24+'Scenario Assumptions'!$D$9)) -> 13355.057 | D14: =C14*'Forecast Assumptions'!C17*'Forecast Assumptions'!C18 -> 7446.78 | E14: =C14*(1+('Scenario Assumptions'!C24+'Scenario Assumptions'!$D$9)) -> 13221.507 | F14: =E14*'Forecast Assumptions'!D17*'Forecast Assumptions'!D18 -> 7372.3122 | G14: =E14*(1+('Scenario Assumptions'!D24+'Scenario Assumptions'!$D$9)) -> 13089.292 | H14: =G14*'Forecast Assumptions'!E17*'Forecast Assumptions'!E18 -> 7405.9213 | I14: ='Student Headcount'!G30*(D14/'Student Flow Summary'!D13) -> 7476.48 | J14: =I14*(F14/D14) -> 7401.7152 | K14: =J14*(H14/F14) -> 7435.4583
A15: International Postgraduate | B15: Base | C15: =('Student Flow Summary'!D16/('Forecast Assumptions'!C22*'Forecast Assumptions'!C23))*(1+('Scenario Assumptions'!B25+'Scenario Assumptions'!$B$9)) -> 17938.667 | D15: =C15*'Forecast Assumptions'!C22*'Forecast Assumptions'!C23 -> 5840.83 | E15: =C15*(1+('Scenario Assumptions'!C25+'Scenario Assumptions'!$B$9)) -> 18297.44 | F15: =E15*'Forecast Assumptions'!D22*'Forecast Assumptions'!D23 -> 6010.7092 | G15: =E15*(1+('Scenario Assumptions'!D25+'Scenario Assumptions'!$B$9)) -> 18663.389 | H15: =G15*'Forecast Assumptions'!E22*'Forecast Assumptions'!E23 -> 6130.9234 | I15: ='Student Headcount'!I30*(D15/'Student Flow Summary'!D16) -> 5989.3 | J15: =I15*(F15/D15) -> 6163.4974 | K15: =J15*(H15/F15) -> 6286.7673
A16: International Postgraduate | B16: Upside | C16: =('Student Flow Summary'!D16/('Forecast Assumptions'!C22*'Forecast Assumptions'!C23))*(1+('Scenario Assumptions'!B25+'Scenario Assumptions'!$C$9)) -> 18293.888 | D16: =C16*'Forecast Assumptions'!C22*'Forecast Assumptions'!C23 -> 5956.49 | E16: =C16*(1+('Scenario Assumptions'!C25+'Scenario Assumptions'!$C$9)) -> 19025.644 | F16: =E16*'Forecast Assumptions'!D22*'Forecast Assumptions'!D23 -> 6249.924 | G16: =E16*(1+('Scenario Assumptions'!D25+'Scenario Assumptions'!$C$9)) -> 19786.669 | H16: =G16*'Forecast Assumptions'!E22*'Forecast Assumptions'!E23 -> 6499.9209 | I16: ='Student Headcount'!I30*(D16/'Student Flow Summary'!D16) -> 6107.9 | J16: =I16*(F16/D16) -> 6408.7929 | K16: =J16*(H16/F16) -> 6665.1446
A17: International Postgraduate | B17: Downside | C17: =('Student Flow Summary'!D16/('Forecast Assumptions'!C22*'Forecast Assumptions'!C23))*(1+('Scenario Assumptions'!B25+'Scenario Assumptions'!$D$9)) -> 17405.835 | D17: =C17*'Forecast Assumptions'!C22*'Forecast Assumptions'!C23 -> 5667.34 | E17: =C17*(1+('Scenario Assumptions'!C25+'Scenario Assumptions'!$D$9)) -> 17231.777 | F17: =E17*'Forecast Assumptions'!D22*'Forecast Assumptions'!D23 -> 5660.6388 | G17: =E17*(1+('Scenario Assumptions'!D25+'Scenario Assumptions'!$D$9)) -> 17059.459 | H17: =G17*'Forecast Assumptions'!E22*'Forecast Assumptions'!E23 -> 5604.0324 | I17: ='Student Headcount'!I30*(D17/'Student Flow Summary'!D16) -> 5811.4 | J17: =I17*(F17/D17) -> 5804.5284 | K17: =J17*(H17/F17) -> 5746.4831
A18: Postgraduate Research (PGR) | B18: Base | C18: =('Student Flow Summary'!D19/('Forecast Assumptions'!C27*'Forecast Assumptions'!C28))*(1+('Scenario Assumptions'!B26+'Scenario Assumptions'!$B$9)) -> 794.89655 | D18: =C18*'Forecast Assumptions'!C27*'Forecast Assumptions'!C28 -> 345.78 | E18: =C18*(1+('Scenario Assumptions'!C26+'Scenario Assumptions'!$B$9)) -> 810.79448 | F18: =E18*'Forecast Assumptions'!D27*'Forecast Assumptions'!D28 -> 352.6956 | G18: =E18*(1+('Scenario Assumptions'!D26+'Scenario Assumptions'!$B$9)) -> 827.01037 | H18: =G18*'Forecast Assumptions'!E27*'Forecast Assumptions'!E28 -> 359.74951 | I18: ='Student Headcount'!K30*(D18/'Student Flow Summary'!D19) -> 1166.88 | J18: =I18*(F18/D18) -> 1190.2176 | K18: =J18*(H18/F18) -> 1214.022
A19: Postgraduate Research (PGR) | B19: Upside | C19: =('Student Flow Summary'!D19/('Forecast Assumptions'!C27*'Forecast Assumptions'!C28))*(1+('Scenario Assumptions'!B26+'Scenario Assumptions'!$C$9)) -> 810.48276 | D19: =C19*'Forecast Assumptions'!C27*'Forecast Assumptions'!C28 -> 352.56 | E19: =C19*(1+('Scenario Assumptions'!C26+'Scenario Assumptions'!$C$9)) -> 842.90207 | F19: =E19*'Forecast Assumptions'!D27*'Forecast Assumptions'!D28 -> 366.6624 | G19: =E19*(1+('Scenario Assumptions'!D26+'Scenario Assumptions'!$C$9)) -> 876.61815 | H19: =G19*'Forecast Assumptions'!E27*'Forecast Assumptions'!E28 -> 381.3289 | I19: ='Student Headcount'!K30*(D19/'Student Flow Summary'!D19) -> 1189.76 | J19: =I19*(F19/D19) -> 1237.3504 | K19: =J19*(H19/F19) -> 1286.8444
A20: Postgraduate Research (PGR) | B20: Downside | C20: =('Student Flow Summary'!D19/('Forecast Assumptions'!C27*'Forecast Assumptions'!C28))*(1+('Scenario Assumptions'!B26+'Scenario Assumptions'!$D$9)) -> 771.51724 | D20: =C20*'Forecast Assumptions'!C27*'Forecast Assumptions'!C28 -> 335.61 | E20: =C20*(1+('Scenario Assumptions'!C26+'Scenario Assumptions'!$D$9)) -> 763.80207 | F20: =E20*'Forecast Assumptions'!D27*'Forecast Assumptions'!D28 -> 332.2539 | G20: =E20*(1+('Scenario Assumptions'!D26+'Scenario Assumptions'!$D$9)) -> 756.16405 | H20: =G20*'Forecast Assumptions'!E27*'Forecast Assumptions'!E28 -> 328.93136 | I20: ='Student Headcount'!K30*(D20/'Student Flow Summary'!D19) -> 1132.56 | J20: =I20*(F20/D20) -> 1121.2344 | K20: =J20*(H20/F20) -> 1110.0221
A22: B. Tuition Income by Category and Scenario (Annual, £)
A23: Category | B23: Scenario | C23: FY26/27 | D23: FY27/28 | E23: FY28/29
A24: UK Undergraduate | B24: Base | C24: =I6*(SUM('Population Forecast'!B24:M24))*'Income Forecast'!D6/12 -> 84344512 | D24: =J6*(SUM('Population Forecast'!B24:M24))*'Income Forecast'!F6/12 -> 87752031 | E24: =K6*(SUM('Population Forecast'!B24:M24))*'Income Forecast'!H6/12 -> 92769748
A25: UK Undergraduate | B25: Upside | C25: =I7*(SUM('Population Forecast'!B24:M24))*'Income Forecast'!D6/12 -> 85998326 | D25: =J7*(SUM('Population Forecast'!B24:M24))*'Income Forecast'!F6/12 -> 91227025 | E25: =K7*(SUM('Population Forecast'!B24:M24))*'Income Forecast'!H6/12 -> 98334493
A26: UK Undergraduate | B26: Downside | C26: =I8*(SUM('Population Forecast'!B24:M24))*'Income Forecast'!D6/12 -> 81863791 | D26: =J8*(SUM('Population Forecast'!B24:M24))*'Income Forecast'!F6/12 -> 82666057 | E26: =K8*(SUM('Population Forecast'!B24:M24))*'Income Forecast'!H6/12 -> 84822574
A27: International Undergraduate | B27: Base | C27: =I9*(SUM('Population Forecast'!B25:M25))*'Income Forecast'!D7/12 -> 42981151 | D27: =J9*(SUM('Population Forecast'!B25:M25))*'Income Forecast'!F7/12 -> 45147401 | E27: =K9*(SUM('Population Forecast'!B25:M25))*'Income Forecast'!H7/12 -> 49216311
A28: International Undergraduate | B28: Upside | C28: =I10*(SUM('Population Forecast'!B25:M25))*'Income Forecast'!D7/12 -> 43832263 | D28: =J10*(SUM('Population Forecast'!B25:M25))*'Income Forecast'!F7/12 -> 46953120 | E28: =K10*(SUM('Population Forecast'!B25:M25))*'Income Forecast'!H7/12 -> 52188393
A29: International Undergraduate | B29: Downside | C29: =I11*(SUM('Population Forecast'!B25:M25))*'Income Forecast'!D7/12 -> 41704483 | D29: =J11*(SUM('Population Forecast'!B25:M25))*'Income Forecast'!F7/12 -> 42505210 | E29: =K11*(SUM('Population Forecast'!B25:M25))*'Income Forecast'!H7/12 -> 44973168
A30: UK Postgraduate | B30: Base | C30: =I12*(SUM('Population Forecast'!B26:M26))*'Income Forecast'!D8/12 -> 33996654 | D30: =J12*(SUM('Population Forecast'!B26:M26))*'Income Forecast'!F8/12 -> 35716885 | E30: =K12*(SUM('Population Forecast'!B26:M26))*'Income Forecast'!H8/12 -> 38075985
A31: UK Postgraduate | B31: Upside | C31: =I13*(SUM('Population Forecast'!B26:M26))*'Income Forecast'!D8/12 -> 34663255 | D31: =J13*(SUM('Population Forecast'!B26:M26))*'Income Forecast'!F8/12 -> 37131279 | E31: =K13*(SUM('Population Forecast'!B26:M26))*'Income Forecast'!H8/12 -> 40359953
A32: UK Postgraduate | B32: Downside | C32: =I14*(SUM('Population Forecast'!B26:M26))*'Income Forecast'!D8/12 -> 32996753 | D32: =J14*(SUM('Population Forecast'!B26:M26))*'Income Forecast'!F8/12 -> 33646789 | E32: =K14*(SUM('Population Forecast'!B26:M26))*'Income Forecast'!H8/12 -> 34814184
A33: International Postgraduate | B33: Base | C33: =I15*(SUM('Population Forecast'!B27:M27))*'Income Forecast'!D9/12 -> 53831775 | D33: =J15*(SUM('Population Forecast'!B27:M27))*'Income Forecast'!F9/12 -> 57613357 | E33: =K15*(SUM('Population Forecast'!B27:M27))*'Income Forecast'!H9/12 -> 61410078
A34: International Postgraduate | B34: Upside | C34: =I16*(SUM('Population Forecast'!B27:M27))*'Income Forecast'!D9/12 -> 54897750 | D34: =J16*(SUM('Population Forecast'!B27:M27))*'Income Forecast'!F9/12 -> 59906260 | E34: =K16*(SUM('Population Forecast'!B27:M27))*'Income Forecast'!H9/12 -> 65106123
A35: International Postgraduate | B35: Downside | C35: =I17*(SUM('Population Forecast'!B27:M27))*'Income Forecast'!D9/12 -> 52232811 | D35: =J17*(SUM('Population Forecast'!B27:M27))*'Income Forecast'!F9/12 -> 54257891 | E35: =K17*(SUM('Population Forecast'!B27:M27))*'Income Forecast'!H9/12 -> 56132501
A36: Postgraduate Research (PGR) | B36: Base | C36: =I18*(SUM('Population Forecast'!B28:M28))*'Income Forecast'!D10/12 -> 8269749.7 | D36: =J18*(SUM('Population Forecast'!B28:M28))*'Income Forecast'!F10/12 -> 8688199.1 | E36: =K18*(SUM('Population Forecast'!B28:M28))*'Income Forecast'!H10/12 -> 9127822
A37: Postgraduate Research (PGR) | B37: Upside | C37: =I19*(SUM('Population Forecast'!B28:M28))*'Income Forecast'!D10/12 -> 8431901.7 | D37: =J19*(SUM('Population Forecast'!B28:M28))*'Income Forecast'!F10/12 -> 9032253.1 | E37: =K19*(SUM('Population Forecast'!B28:M28))*'Income Forecast'!H10/12 -> 9675349.5
A38: Postgraduate Research (PGR) | B38: Downside | C38: =I20*(SUM('Population Forecast'!B28:M28))*'Income Forecast'!D10/12 -> 8026521.8 | D38: =J20*(SUM('Population Forecast'!B28:M28))*'Income Forecast'!F10/12 -> 8184644.3 | E38: =K20*(SUM('Population Forecast'!B28:M28))*'Income Forecast'!H10/12 -> 8345881.8
A40: C. Staff Cost & Operating Expenditure Engine, by Scenario (Annual, £)
A41: Scenario | B41: FY | C41: Academic Staff Cost | D41: Professional Services Staff Cost | E41: Total Staff Cost | F41: Utilities | G41: General Opex | H41: Total Opex
A42: Base | B42: FY26/27 | C42: ='Staff Costs'!C40*12*(1+('Scenario Assumptions'!B29+'Scenario Assumptions'!$B$10))*(1+'Forecast Assumptions'!B52) -> 139099950 | D42: ='Staff Costs'!D40*12*(1+('Scenario Assumptions'!B30+'Scenario Assumptions'!$B$10))*(1+'Forecast Assumptions'!B53) -> 71991916 | E42: =C42+D42 -> 2.1109187e+08 | F42: =(SUMIFS('Operating Expenditure'!C:C,'Operating Expenditure'!$B:$B,"FY25/26"))*(1+('Scenario Assumptions'!B33+'Scenario Assumptions'!$B$11)) -> 18374998 | G42: =(SUMIFS('Operating Expenditure'!E:E,'Operating Expenditure'!$B:$B,"FY25/26")+SUMIFS('Operating Expenditure'!G:G,'Operating Expenditure'!$B:$B,"FY25/26")+SUMIFS('Operating Expenditure'!I:I,'Operating Expenditure'!$B:$B,"FY25/26")+SUMIFS('Operating Expenditure'!K:K,'Operating Expenditure'!$B:$B,"FY25/26")+SUMIFS('Operating Expenditure'!M:M,'Operating Expenditure'!$B:$B,"FY25/26")+SUMIFS('Operating Expenditure'!O:O,'Operating Expenditure'!$B:$B,"FY25/26")+SUMIFS('Operating Expenditure'!Q:Q,'Operating Expenditure'!$B:$B,"FY25/26"))*(1+('Scenario Assumptions'!B34+'Scenario Assumptions'!$B$11)) -> 91080002 | H42: =F42+G42 -> 1.09455e+08
A43: Base | B43: FY27/28 | C43: =C42*(1+('Scenario Assumptions'!C29+'Scenario Assumptions'!$B$10))*(1+'Forecast Assumptions'!C52) -> 1.4755723e+08 | D43: =D42*(1+('Scenario Assumptions'!C30+'Scenario Assumptions'!$B$10))*(1+'Forecast Assumptions'!C53) -> 75994666 | E43: =C43+D43 -> 2.2355189e+08 | F43: =F42*(1+('Scenario Assumptions'!C33+'Scenario Assumptions'!$B$11)) -> 19109998 | G43: =G42*(1+('Scenario Assumptions'!C34+'Scenario Assumptions'!$B$11)) -> 94267802 | H43: =F43+G43 -> 1.133778e+08
A44: Base | B44: FY28/29 | C44: =C43*(1+('Scenario Assumptions'!D29+'Scenario Assumptions'!$B$10))*(1+'Forecast Assumptions'!D52) -> 1.5652871e+08 | D44: =D43*(1+('Scenario Assumptions'!D30+'Scenario Assumptions'!$B$10))*(1+'Forecast Assumptions'!D53) -> 80219970 | E44: =C44+D44 -> 2.3674868e+08 | F44: =F43*(1+('Scenario Assumptions'!D33+'Scenario Assumptions'!$B$11)) -> 19778848 | G44: =G43*(1+('Scenario Assumptions'!D34+'Scenario Assumptions'!$B$11)) -> 97567175 | H44: =F44+G44 -> 1.1734602e+08
A45: Upside | B45: FY26/27 | C45: ='Staff Costs'!C40*12*(1+('Scenario Assumptions'!B29+'Scenario Assumptions'!$C$10))*(1+'Forecast Assumptions'!B52) -> 137768850 | D45: ='Staff Costs'!D40*12*(1+('Scenario Assumptions'!B30+'Scenario Assumptions'!$C$10))*(1+'Forecast Assumptions'!B53) -> 71299686 | E45: =C45+D45 -> 2.0906854e+08 | F45: =(SUMIFS('Operating Expenditure'!C:C,'Operating Expenditure'!$B:$B,"FY25/26"))*(1+('Scenario Assumptions'!B33+'Scenario Assumptions'!$C$11)) -> 18287498 | G45: =(SUMIFS('Operating Expenditure'!E:E,'Operating Expenditure'!$B:$B,"FY25/26")+SUMIFS('Operating Expenditure'!G:G,'Operating Expenditure'!$B:$B,"FY25/26")+SUMIFS('Operating Expenditure'!I:I,'Operating Expenditure'!$B:$B,"FY25/26")+SUMIFS('Operating Expenditure'!K:K,'Operating Expenditure'!$B:$B,"FY25/26")+SUMIFS('Operating Expenditure'!M:M,'Operating Expenditure'!$B:$B,"FY25/26")+SUMIFS('Operating Expenditure'!O:O,'Operating Expenditure'!$B:$B,"FY25/26")+SUMIFS('Operating Expenditure'!Q:Q,'Operating Expenditure'!$B:$B,"FY25/26"))*(1+('Scenario Assumptions'!B34+'Scenario Assumptions'!$C$11)) -> 90640002 | H45: =F45+G45 -> 1.089275e+08
A46: Upside | B46: FY27/28 | C46: =C45*(1+('Scenario Assumptions'!C29+'Scenario Assumptions'!$C$10))*(1+'Forecast Assumptions'!C52) -> 1.4473995e+08 | D46: =D45*(1+('Scenario Assumptions'!C30+'Scenario Assumptions'!$C$10))*(1+'Forecast Assumptions'!C53) -> 74540257 | E46: =C46+D46 -> 2.1928021e+08 | F46: =F45*(1+('Scenario Assumptions'!C33+'Scenario Assumptions'!$C$11)) -> 18927560 | G46: =G45*(1+('Scenario Assumptions'!C34+'Scenario Assumptions'!$C$11)) -> 93359202 | H46: =F46+G46 -> 1.1228676e+08
A47: Upside | B47: FY28/29 | C47: =C46*(1+('Scenario Assumptions'!D29+'Scenario Assumptions'!$C$10))*(1+'Forecast Assumptions'!D52) -> 1.520638e+08 | D47: =D46*(1+('Scenario Assumptions'!D30+'Scenario Assumptions'!$C$10))*(1+'Forecast Assumptions'!D53) -> 77928111 | E47: =C47+D47 -> 2.2999191e+08 | F47: =F46*(1+('Scenario Assumptions'!D33+'Scenario Assumptions'!$C$11)) -> 19495387 | G47: =G46*(1+('Scenario Assumptions'!D34+'Scenario Assumptions'!$C$11)) -> 96159978 | H47: =F47+G47 -> 1.1565537e+08
A48: Downside | B48: FY26/27 | C48: ='Staff Costs'!C40*12*(1+('Scenario Assumptions'!B29+'Scenario Assumptions'!$D$10))*(1+'Forecast Assumptions'!B52) -> 141096600 | D48: ='Staff Costs'!D40*12*(1+('Scenario Assumptions'!B30+'Scenario Assumptions'!$D$10))*(1+'Forecast Assumptions'!B53) -> 73030261 | E48: =C48+D48 -> 2.1412686e+08 | F48: =(SUMIFS('Operating Expenditure'!C:C,'Operating Expenditure'!$B:$B,"FY25/26"))*(1+('Scenario Assumptions'!B33+'Scenario Assumptions'!$D$11)) -> 18549998 | G48: =(SUMIFS('Operating Expenditure'!E:E,'Operating Expenditure'!$B:$B,"FY25/26")+SUMIFS('Operating Expenditure'!G:G,'Operating Expenditure'!$B:$B,"FY25/26")+SUMIFS('Operating Expenditure'!I:I,'Operating Expenditure'!$B:$B,"FY25/26")+SUMIFS('Operating Expenditure'!K:K,'Operating Expenditure'!$B:$B,"FY25/26")+SUMIFS('Operating Expenditure'!M:M,'Operating Expenditure'!$B:$B,"FY25/26")+SUMIFS('Operating Expenditure'!O:O,'Operating Expenditure'!$B:$B,"FY25/26")+SUMIFS('Operating Expenditure'!Q:Q,'Operating Expenditure'!$B:$B,"FY25/26"))*(1+('Scenario Assumptions'!B34+'Scenario Assumptions'!$D$11)) -> 91960002 | H48: =F48+G48 -> 1.1051e+08
A49: Downside | B49: FY27/28 | C49: =C48*(1+('Scenario Assumptions'!C29+'Scenario Assumptions'!$D$10))*(1+'Forecast Assumptions'!C52) -> 1.5183405e+08 | D49: =D48*(1+('Scenario Assumptions'!C30+'Scenario Assumptions'!$D$10))*(1+'Forecast Assumptions'!C53) -> 78202629 | E49: =C49+D49 -> 2.3003668e+08 | F49: =F48*(1+('Scenario Assumptions'!C33+'Scenario Assumptions'!$D$11)) -> 19477498 | G49: =G48*(1+('Scenario Assumptions'!C34+'Scenario Assumptions'!$D$11)) -> 96098202 | H49: =F49+G49 -> 1.155757e+08
A50: Downside | B50: FY28/29 | C50: =C49*(1+('Scenario Assumptions'!D29+'Scenario Assumptions'!$D$10))*(1+'Forecast Assumptions'!D52) -> 1.6338862e+08 | D50: =D49*(1+('Scenario Assumptions'!D30+'Scenario Assumptions'!$D$10))*(1+'Forecast Assumptions'!D53) -> 83741330 | E50: =C50+D50 -> 2.4712995e+08 | F50: =F49*(1+('Scenario Assumptions'!D33+'Scenario Assumptions'!$D$11)) -> 20353985 | G50: =G49*(1+('Scenario Assumptions'!D34+'Scenario Assumptions'!$D$11)) -> 1.0042262e+08 | H50: =F50+G50 -> 1.2077661e+08
A52: D. Scenario Income Statement & Cash Summary (Annual, £)
A53: Scenario | B53: FY | C53: Total Income | D53: Total Staff Cost | E53: Total Opex | F53: Operating Surplus / (Deficit) | G53: Operating Margin % | H53: Closing Cash
A54: Base | B54: FY26/27 | C54: =(C24+C27+C30+C33+C36)+'Income Forecast'!C54 -> 3.2254585e+08 | D54: =E42 -> 2.1109187e+08 | E54: =H42 -> 1.09455e+08 | F54: =C54-D54-E54 -> 1998981.6 | G54: =F54/C54 -> 0.0061975114 | H54: ='Forecast Assumptions'!B63+F54-'Forecast Assumptions'!B62 -> 39526165
A55: Base | B55: FY27/28 | C55: =(D24+D27+D30+D33+D36)+'Income Forecast'!C55 -> 3.3675372e+08 | D55: =E43 -> 2.2355189e+08 | E55: =H43 -> 1.133778e+08 | F55: =C55-D55-E55 -> -175974.46 | G55: =F55/C55 -> -0.00052256129 | H55: =H54+F55-'Forecast Assumptions'!C62 -> 28350190
A56: Base | B56: FY28/29 | C56: =(E24+E27+E30+E33+E36)+'Income Forecast'!C56 -> 3.5543478e+08 | D56: =E44 -> 2.3674868e+08 | E56: =H44 -> 1.1734602e+08 | F56: =C56-D56-E56 -> 1340078.9 | G56: =F56/C56 -> 0.0037702526 | H56: =H55+F56-'Forecast Assumptions'!D62 -> 18190269
A57: Upside | B57: FY26/27 | C57: =(C25+C28+C31+C34+C37)+'Income Forecast'!C54 -> 3.269455e+08 | D57: =E45 -> 2.0906854e+08 | E57: =H45 -> 1.089275e+08 | F57: =C57-D57-E57 -> 8949466.1 | G57: =F57/C57 -> 0.02737296 | H57: ='Forecast Assumptions'!B63+F57-'Forecast Assumptions'!B62 -> 46476649
A58: Upside | B58: FY27/28 | C58: =(D25+D28+D31+D34+D37)+'Income Forecast'!C55 -> 3.4608578e+08 | D58: =E46 -> 2.1928021e+08 | E58: =H46 -> 1.1228676e+08 | F58: =C58-D58-E58 -> 14518809 | G58: =F58/C58 -> 0.041951475 | H58: =H57+F58-'Forecast Assumptions'!C62 -> 49995458
A59: Upside | B59: FY28/29 | C59: =(E25+E28+E31+E34+E37)+'Income Forecast'!C56 -> 3.7049915e+08 | D59: =E47 -> 2.2999191e+08 | E59: =H47 -> 1.1565537e+08 | F59: =C59-D59-E59 -> 24851873 | G59: =F59/C59 -> 0.067076735 | H59: =H58+F59-'Forecast Assumptions'!D62 -> 63347332
A60: Downside | B60: FY26/27 | C60: =(C26+C29+C32+C35+C38)+'Income Forecast'!C54 -> 3.1594637e+08 | D60: =E48 -> 2.1412686e+08 | E60: =H48 -> 1.1051e+08 | F60: =C60-D60-E60 -> -8690495.3 | G60: =F60/C60 -> -0.027506236 | H60: ='Forecast Assumptions'!B63+F60-'Forecast Assumptions'!B62 -> 28836688
A61: Downside | B61: FY27/28 | C61: =(D26+D29+D32+D35+D38)+'Income Forecast'!C55 -> 3.2309644e+08 | D61: =E49 -> 2.3003668e+08 | E61: =H49 -> 1.155757e+08 | F61: =C61-D61-E61 -> -22515945 | G61: =F61/C61 -> -0.069688001 | H61: =H60+F61-'Forecast Assumptions'!C62 -> -4679256.8
A62: Downside | B62: FY28/29 | C62: =(E26+E29+E32+E35+E38)+'Income Forecast'!C56 -> 3.3392314e+08 | D62: =E50 -> 2.4712995e+08 | E62: =H50 -> 1.2077661e+08 | F62: =C62-D62-E62 -> -33983416 | G62: =F62/C62 -> -0.10177017 | H62: =H61+F62-'Forecast Assumptions'!D62 -> -50162673
A64: Sources: 'Scenario Assumptions', 'Forecast Assumptions', 'Student Flow Summary', 'Student Headcount', 'Population Forecast' (seasonal shape), 'Income Forecast' (fee rates and other income), 'Staff Costs' & 'Operating Expenditure' (FY25/26 baselines). Base Case figures in Section D reconcile closely to 'Forecast Income Statement' / 'Cash Flow Forecast' (small differences only where those combine 8 opex lines and this sheet combines them into 2).

Sheet Recruitment Break-Even
A1: Vector University — Student Recruitment Break-Even Analysis (FY27/28)
A2: Tests a single lever: a uniform Recruitment Growth Adjustment (percentage points, applied to every category's Application Growth % in both FY26/27 and FY27/28, i.e. a sustained shift in recruitment performance) — holding salary and cost inflation at Base. FY27/28 is used as the target year because it is the Base Case's projected deficit year. Answers: how far would recruitment need to improve (or could it fall) before the University is back to break-even, or to its FY25/26 margin?
A4: A. Recruitment Growth Adjustment Tested (percentage points)
A5: Adjustment (pts) | B5: -0.04 | C5: -0.03 | D5: -0.02 | E5: -0.01 | F5: 0 | G5: 0.01 | H5: 0.02 | I5: 0.03 | J5: 0.04
A7: B. New Enrolments & September Anchor by Category, under Each Tested Adjustment
A8: UK Undergraduate
A9: Applications FY26/27 | B9: =('Student Flow Summary'!D7/('Forecast Assumptions'!C7*'Forecast Assumptions'!C8))*(1+'Scenario Assumptions'!B22+B$5) -> 6282.0513 | C9: =('Student Flow Summary'!D7/('Forecast Assumptions'!C7*'Forecast Assumptions'!C8))*(1+'Scenario Assumptions'!B22+C$5) -> 6346.1538 | D9: =('Student Flow Summary'!D7/('Forecast Assumptions'!C7*'Forecast Assumptions'!C8))*(1+'Scenario Assumptions'!B22+D$5) -> 6410.2564 | E9: =('Student Flow Summary'!D7/('Forecast Assumptions'!C7*'Forecast Assumptions'!C8))*(1+'Scenario Assumptions'!B22+E$5) -> 6474.359 | F9: =('Student Flow Summary'!D7/('Forecast Assumptions'!C7*'Forecast Assumptions'!C8))*(1+'Scenario Assumptions'!B22+F$5) -> 6538.4615 | G9: =('Student Flow Summary'!D7/('Forecast Assumptions'!C7*'Forecast Assumptions'!C8))*(1+'Scenario Assumptions'!B22+G$5) -> 6602.5641 | H9: =('Student Flow Summary'!D7/('Forecast Assumptions'!C7*'Forecast Assumptions'!C8))*(1+'Scenario Assumptions'!B22+H$5) -> 6666.6667 | I9: =('Student Flow Summary'!D7/('Forecast Assumptions'!C7*'Forecast Assumptions'!C8))*(1+'Scenario Assumptions'!B22+I$5) -> 6730.7692 | J9: =('Student Flow Summary'!D7/('Forecast Assumptions'!C7*'Forecast Assumptions'!C8))*(1+'Scenario Assumptions'!B22+J$5) -> 6794.8718
A10: New Enrolments FY26/27 | B10: =B9*'Forecast Assumptions'!C7*'Forecast Assumptions'!C8 -> 3038 | C10: =C9*'Forecast Assumptions'!C7*'Forecast Assumptions'!C8 -> 3069 | D10: =D9*'Forecast Assumptions'!C7*'Forecast Assumptions'!C8 -> 3100 | E10: =E9*'Forecast Assumptions'!C7*'Forecast Assumptions'!C8 -> 3131 | F10: =F9*'Forecast Assumptions'!C7*'Forecast Assumptions'!C8 -> 3162 | G10: =G9*'Forecast Assumptions'!C7*'Forecast Assumptions'!C8 -> 3193 | H10: =H9*'Forecast Assumptions'!C7*'Forecast Assumptions'!C8 -> 3224 | I10: =I9*'Forecast Assumptions'!C7*'Forecast Assumptions'!C8 -> 3255 | J10: =J9*'Forecast Assumptions'!C7*'Forecast Assumptions'!C8 -> 3286
A11: Applications FY27/28 | B11: =B9*(1+'Scenario Assumptions'!C22+B$5) -> 6156.4103 | C11: =C9*(1+'Scenario Assumptions'!C22+C$5) -> 6282.6923 | D11: =D9*(1+'Scenario Assumptions'!C22+D$5) -> 6410.2564 | E11: =E9*(1+'Scenario Assumptions'!C22+E$5) -> 6539.1026 | F11: =F9*(1+'Scenario Assumptions'!C22+F$5) -> 6669.2308 | G11: =G9*(1+'Scenario Assumptions'!C22+G$5) -> 6800.641 | H11: =H9*(1+'Scenario Assumptions'!C22+H$5) -> 6933.3333 | I11: =I9*(1+'Scenario Assumptions'!C22+I$5) -> 7067.3077 | J11: =J9*(1+'Scenario Assumptions'!C22+J$5) -> 7202.5641
A12: New Enrolments FY27/28 | B12: =B11*'Forecast Assumptions'!D7*'Forecast Assumptions'!D8 -> 2977.24 | C12: =C11*'Forecast Assumptions'!D7*'Forecast Assumptions'!D8 -> 3038.31 | D12: =D11*'Forecast Assumptions'!D7*'Forecast Assumptions'!D8 -> 3100 | E12: =E11*'Forecast Assumptions'!D7*'Forecast Assumptions'!D8 -> 3162.31 | F12: =F11*'Forecast Assumptions'!D7*'Forecast Assumptions'!D8 -> 3225.24 | G12: =G11*'Forecast Assumptions'!D7*'Forecast Assumptions'!D8 -> 3288.79 | H12: =H11*'Forecast Assumptions'!D7*'Forecast Assumptions'!D8 -> 3352.96 | I12: =I11*'Forecast Assumptions'!D7*'Forecast Assumptions'!D8 -> 3417.75 | J12: =J11*'Forecast Assumptions'!D7*'Forecast Assumptions'!D8 -> 3483.16
A13: Sept Anchor FY26/27 | B13: ='Student Headcount'!C30*(B10/'Student Flow Summary'!D7) -> 9065 | C13: ='Student Headcount'!C30*(C10/'Student Flow Summary'!D7) -> 9157.5 | D13: ='Student Headcount'!C30*(D10/'Student Flow Summary'!D7) -> 9250 | E13: ='Student Headcount'!C30*(E10/'Student Flow Summary'!D7) -> 9342.5 | F13: ='Student Headcount'!C30*(F10/'Student Flow Summary'!D7) -> 9435 | G13: ='Student Headcount'!C30*(G10/'Student Flow Summary'!D7) -> 9527.5 | H13: ='Student Headcount'!C30*(H10/'Student Flow Summary'!D7) -> 9620 | I13: ='Student Headcount'!C30*(I10/'Student Flow Summary'!D7) -> 9712.5 | J13: ='Student Headcount'!C30*(J10/'Student Flow Summary'!D7) -> 9805
A14: Sept Anchor FY27/28 | B14: =B13*(B12/B10) -> 8883.7 | C14: =C13*(C12/C10) -> 9065.925 | D14: =D13*(D12/D10) -> 9250 | E14: =E13*(E12/E10) -> 9435.925 | F14: =F13*(F12/F10) -> 9623.7 | G14: =G13*(G12/G10) -> 9813.325 | H14: =H13*(H12/H10) -> 10004.8 | I14: =I13*(I12/I10) -> 10198.125 | J14: =J13*(J12/J10) -> 10393.3
A15: International Undergraduate
A16: Applications FY26/27 | B16: =('Student Flow Summary'!D10/('Forecast Assumptions'!C12*'Forecast Assumptions'!C13))*(1+'Scenario Assumptions'!B23+B$5) -> 2031.3312 | C16: =('Student Flow Summary'!D10/('Forecast Assumptions'!C12*'Forecast Assumptions'!C13))*(1+'Scenario Assumptions'!B23+C$5) -> 2052.2727 | D16: =('Student Flow Summary'!D10/('Forecast Assumptions'!C12*'Forecast Assumptions'!C13))*(1+'Scenario Assumptions'!B23+D$5) -> 2073.2143 | E16: =('Student Flow Summary'!D10/('Forecast Assumptions'!C12*'Forecast Assumptions'!C13))*(1+'Scenario Assumptions'!B23+E$5) -> 2094.1558 | F16: =('Student Flow Summary'!D10/('Forecast Assumptions'!C12*'Forecast Assumptions'!C13))*(1+'Scenario Assumptions'!B23+F$5) -> 2115.0974 | G16: =('Student Flow Summary'!D10/('Forecast Assumptions'!C12*'Forecast Assumptions'!C13))*(1+'Scenario Assumptions'!B23+G$5) -> 2136.039 | H16: =('Student Flow Summary'!D10/('Forecast Assumptions'!C12*'Forecast Assumptions'!C13))*(1+'Scenario Assumptions'!B23+H$5) -> 2156.9805 | I16: =('Student Flow Summary'!D10/('Forecast Assumptions'!C12*'Forecast Assumptions'!C13))*(1+'Scenario Assumptions'!B23+I$5) -> 2177.9221 | J16: =('Student Flow Summary'!D10/('Forecast Assumptions'!C12*'Forecast Assumptions'!C13))*(1+'Scenario Assumptions'!B23+J$5) -> 2198.8636
A17: New Enrolments FY26/27 | B17: =B16*'Forecast Assumptions'!C12*'Forecast Assumptions'!C13 -> 625.65 | C17: =C16*'Forecast Assumptions'!C12*'Forecast Assumptions'!C13 -> 632.1 | D17: =D16*'Forecast Assumptions'!C12*'Forecast Assumptions'!C13 -> 638.55 | E17: =E16*'Forecast Assumptions'!C12*'Forecast Assumptions'!C13 -> 645 | F17: =F16*'Forecast Assumptions'!C12*'Forecast Assumptions'!C13 -> 651.45 | G17: =G16*'Forecast Assumptions'!C12*'Forecast Assumptions'!C13 -> 657.9 | H17: =H16*'Forecast Assumptions'!C12*'Forecast Assumptions'!C13 -> 664.35 | I17: =I16*'Forecast Assumptions'!C12*'Forecast Assumptions'!C13 -> 670.8 | J17: =J16*'Forecast Assumptions'!C12*'Forecast Assumptions'!C13 -> 677.25
A18: Applications FY27/28 | B18: =B16*(1+'Scenario Assumptions'!C23+B$5) -> 1970.3912 | C18: =C16*(1+'Scenario Assumptions'!C23+C$5) -> 2011.2273 | D18: =D16*(1+'Scenario Assumptions'!C23+D$5) -> 2052.4821 | E18: =E16*(1+'Scenario Assumptions'!C23+E$5) -> 2094.1558 | F18: =F16*(1+'Scenario Assumptions'!C23+F$5) -> 2136.2484 | G18: =G16*(1+'Scenario Assumptions'!C23+G$5) -> 2178.7597 | H18: =H16*(1+'Scenario Assumptions'!C23+H$5) -> 2221.6899 | I18: =I16*(1+'Scenario Assumptions'!C23+I$5) -> 2265.039 | J18: =J16*(1+'Scenario Assumptions'!C23+J$5) -> 2308.8068
A19: New Enrolments FY27/28 | B19: =B18*'Forecast Assumptions'!D12*'Forecast Assumptions'!D13 -> 606.8805 | C19: =C18*'Forecast Assumptions'!D12*'Forecast Assumptions'!D13 -> 619.458 | D19: =D18*'Forecast Assumptions'!D12*'Forecast Assumptions'!D13 -> 632.1645 | E19: =E18*'Forecast Assumptions'!D12*'Forecast Assumptions'!D13 -> 645 | F19: =F18*'Forecast Assumptions'!D12*'Forecast Assumptions'!D13 -> 657.9645 | G19: =G18*'Forecast Assumptions'!D12*'Forecast Assumptions'!D13 -> 671.058 | H19: =H18*'Forecast Assumptions'!D12*'Forecast Assumptions'!D13 -> 684.2805 | I19: =I18*'Forecast Assumptions'!D12*'Forecast Assumptions'!D13 -> 697.632 | J19: =J18*'Forecast Assumptions'!D12*'Forecast Assumptions'!D13 -> 711.1125
A20: Sept Anchor FY26/27 | B20: ='Student Headcount'!E30*(B17/'Student Flow Summary'!D10) -> 2019.54 | C20: ='Student Headcount'!E30*(C17/'Student Flow Summary'!D10) -> 2040.36 | D20: ='Student Headcount'!E30*(D17/'Student Flow Summary'!D10) -> 2061.18 | E20: ='Student Headcount'!E30*(E17/'Student Flow Summary'!D10) -> 2082 | F20: ='Student Headcount'!E30*(F17/'Student Flow Summary'!D10) -> 2102.82 | G20: ='Student Headcount'!E30*(G17/'Student Flow Summary'!D10) -> 2123.64 | H20: ='Student Headcount'!E30*(H17/'Student Flow Summary'!D10) -> 2144.46 | I20: ='Student Headcount'!E30*(I17/'Student Flow Summary'!D10) -> 2165.28 | J20: ='Student Headcount'!E30*(J17/'Student Flow Summary'!D10) -> 2186.1
A21: Sept Anchor FY27/28 | B21: =B20*(B19/B17) -> 1958.9538 | C21: =C20*(C19/C17) -> 1999.5528 | D21: =D20*(D19/D17) -> 2040.5682 | E21: =E20*(E19/E17) -> 2082 | F21: =F20*(F19/F17) -> 2123.8482 | G21: =G20*(G19/G17) -> 2166.1128 | H21: =H20*(H19/H17) -> 2208.7938 | I21: =I20*(I19/I17) -> 2251.8912 | J21: =J20*(J19/J17) -> 2295.405
A22: UK Postgraduate
A23: Applications FY26/27 | B23: =('Student Flow Summary'!D13/('Forecast Assumptions'!C17*'Forecast Assumptions'!C18))*(1+'Scenario Assumptions'!B24+B$5) -> 13220.158 | C23: =('Student Flow Summary'!D13/('Forecast Assumptions'!C17*'Forecast Assumptions'!C18))*(1+'Scenario Assumptions'!B24+C$5) -> 13355.057 | D23: =('Student Flow Summary'!D13/('Forecast Assumptions'!C17*'Forecast Assumptions'!C18))*(1+'Scenario Assumptions'!B24+D$5) -> 13489.957 | E23: =('Student Flow Summary'!D13/('Forecast Assumptions'!C17*'Forecast Assumptions'!C18))*(1+'Scenario Assumptions'!B24+E$5) -> 13624.857 | F23: =('Student Flow Summary'!D13/('Forecast Assumptions'!C17*'Forecast Assumptions'!C18))*(1+'Scenario Assumptions'!B24+F$5) -> 13759.756 | G23: =('Student Flow Summary'!D13/('Forecast Assumptions'!C17*'Forecast Assumptions'!C18))*(1+'Scenario Assumptions'!B24+G$5) -> 13894.656 | H23: =('Student Flow Summary'!D13/('Forecast Assumptions'!C17*'Forecast Assumptions'!C18))*(1+'Scenario Assumptions'!B24+H$5) -> 14029.555 | I23: =('Student Flow Summary'!D13/('Forecast Assumptions'!C17*'Forecast Assumptions'!C18))*(1+'Scenario Assumptions'!B24+I$5) -> 14164.455 | J23: =('Student Flow Summary'!D13/('Forecast Assumptions'!C17*'Forecast Assumptions'!C18))*(1+'Scenario Assumptions'!B24+J$5) -> 14299.354
A24: New Enrolments FY26/27 | B24: =B23*'Forecast Assumptions'!C17*'Forecast Assumptions'!C18 -> 7371.56 | C24: =C23*'Forecast Assumptions'!C17*'Forecast Assumptions'!C18 -> 7446.78 | D24: =D23*'Forecast Assumptions'!C17*'Forecast Assumptions'!C18 -> 7522 | E24: =E23*'Forecast Assumptions'!C17*'Forecast Assumptions'!C18 -> 7597.22 | F24: =F23*'Forecast Assumptions'!C17*'Forecast Assumptions'!C18 -> 7672.44 | G24: =G23*'Forecast Assumptions'!C17*'Forecast Assumptions'!C18 -> 7747.66 | H24: =H23*'Forecast Assumptions'!C17*'Forecast Assumptions'!C18 -> 7822.88 | I24: =I23*'Forecast Assumptions'!C17*'Forecast Assumptions'!C18 -> 7898.1 | J24: =J23*'Forecast Assumptions'!C17*'Forecast Assumptions'!C18 -> 7973.32
A25: Applications FY27/28 | B25: =B23*(1+'Scenario Assumptions'!C24+B$5) -> 12955.755 | C25: =C23*(1+'Scenario Assumptions'!C24+C$5) -> 13221.507 | D25: =D23*(1+'Scenario Assumptions'!C24+D$5) -> 13489.957 | E25: =E23*(1+'Scenario Assumptions'!C24+E$5) -> 13761.105 | F25: =F23*(1+'Scenario Assumptions'!C24+F$5) -> 14034.951 | G25: =G23*(1+'Scenario Assumptions'!C24+G$5) -> 14311.495 | H25: =H23*(1+'Scenario Assumptions'!C24+H$5) -> 14590.737 | I25: =I23*(1+'Scenario Assumptions'!C24+I$5) -> 14872.678 | J25: =J23*(1+'Scenario Assumptions'!C24+J$5) -> 15157.316
A26: New Enrolments FY27/28 | B26: =B25*'Forecast Assumptions'!D17*'Forecast Assumptions'!D18 -> 7224.1288 | C26: =C25*'Forecast Assumptions'!D17*'Forecast Assumptions'!D18 -> 7372.3122 | D26: =D25*'Forecast Assumptions'!D17*'Forecast Assumptions'!D18 -> 7522 | E26: =E25*'Forecast Assumptions'!D17*'Forecast Assumptions'!D18 -> 7673.1922 | F26: =F25*'Forecast Assumptions'!D17*'Forecast Assumptions'!D18 -> 7825.8888 | G26: =G25*'Forecast Assumptions'!D17*'Forecast Assumptions'!D18 -> 7980.0898 | H26: =H25*'Forecast Assumptions'!D17*'Forecast Assumptions'!D18 -> 8135.7952 | I26: =I25*'Forecast Assumptions'!D17*'Forecast Assumptions'!D18 -> 8293.005 | J26: =J25*'Forecast Assumptions'!D17*'Forecast Assumptions'!D18 -> 8451.7192
A27: Sept Anchor FY26/27 | B27: ='Student Headcount'!G30*(B24/'Student Flow Summary'!D13) -> 7400.96 | C27: ='Student Headcount'!G30*(C24/'Student Flow Summary'!D13) -> 7476.48 | D27: ='Student Headcount'!G30*(D24/'Student Flow Summary'!D13) -> 7552 | E27: ='Student Headcount'!G30*(E24/'Student Flow Summary'!D13) -> 7627.52 | F27: ='Student Headcount'!G30*(F24/'Student Flow Summary'!D13) -> 7703.04 | G27: ='Student Headcount'!G30*(G24/'Student Flow Summary'!D13) -> 7778.56 | H27: ='Student Headcount'!G30*(H24/'Student Flow Summary'!D13) -> 7854.08 | I27: ='Student Headcount'!G30*(I24/'Student Flow Summary'!D13) -> 7929.6 | J27: ='Student Headcount'!G30*(J24/'Student Flow Summary'!D13) -> 8005.12
A28: Sept Anchor FY27/28 | B28: =B27*(B26/B24) -> 7252.9408 | C28: =C27*(C26/C24) -> 7401.7152 | D28: =D27*(D26/D24) -> 7552 | E28: =E27*(E26/E24) -> 7703.7952 | F28: =F27*(F26/F24) -> 7857.1008 | G28: =G27*(G26/G24) -> 8011.9168 | H28: =H27*(H26/H24) -> 8168.2432 | I28: =I27*(I26/I24) -> 8326.08 | J28: =J27*(J26/J24) -> 8485.4272
A29: International Postgraduate
A30: Applications FY26/27 | B30: =('Student Flow Summary'!D16/('Forecast Assumptions'!C22*'Forecast Assumptions'!C23))*(1+'Scenario Assumptions'!B25+B$5) -> 17228.225 | C30: =('Student Flow Summary'!D16/('Forecast Assumptions'!C22*'Forecast Assumptions'!C23))*(1+'Scenario Assumptions'!B25+C$5) -> 17405.835 | D30: =('Student Flow Summary'!D16/('Forecast Assumptions'!C22*'Forecast Assumptions'!C23))*(1+'Scenario Assumptions'!B25+D$5) -> 17583.446 | E30: =('Student Flow Summary'!D16/('Forecast Assumptions'!C22*'Forecast Assumptions'!C23))*(1+'Scenario Assumptions'!B25+E$5) -> 17761.057 | F30: =('Student Flow Summary'!D16/('Forecast Assumptions'!C22*'Forecast Assumptions'!C23))*(1+'Scenario Assumptions'!B25+F$5) -> 17938.667 | G30: =('Student Flow Summary'!D16/('Forecast Assumptions'!C22*'Forecast Assumptions'!C23))*(1+'Scenario Assumptions'!B25+G$5) -> 18116.278 | H30: =('Student Flow Summary'!D16/('Forecast Assumptions'!C22*'Forecast Assumptions'!C23))*(1+'Scenario Assumptions'!B25+H$5) -> 18293.888 | I30: =('Student Flow Summary'!D16/('Forecast Assumptions'!C22*'Forecast Assumptions'!C23))*(1+'Scenario Assumptions'!B25+I$5) -> 18471.499 | J30: =('Student Flow Summary'!D16/('Forecast Assumptions'!C22*'Forecast Assumptions'!C23))*(1+'Scenario Assumptions'!B25+J$5) -> 18649.109
A31: New Enrolments FY26/27 | B31: =B30*'Forecast Assumptions'!C22*'Forecast Assumptions'!C23 -> 5609.51 | C31: =C30*'Forecast Assumptions'!C22*'Forecast Assumptions'!C23 -> 5667.34 | D31: =D30*'Forecast Assumptions'!C22*'Forecast Assumptions'!C23 -> 5725.17 | E31: =E30*'Forecast Assumptions'!C22*'Forecast Assumptions'!C23 -> 5783 | F31: =F30*'Forecast Assumptions'!C22*'Forecast Assumptions'!C23 -> 5840.83 | G31: =G30*'Forecast Assumptions'!C22*'Forecast Assumptions'!C23 -> 5898.66 | H31: =H30*'Forecast Assumptions'!C22*'Forecast Assumptions'!C23 -> 5956.49 | I31: =I30*'Forecast Assumptions'!C22*'Forecast Assumptions'!C23 -> 6014.32 | J31: =J30*'Forecast Assumptions'!C22*'Forecast Assumptions'!C23 -> 6072.15
A32: Applications FY27/28 | B32: =B30*(1+'Scenario Assumptions'!C25+B$5) -> 16883.66 | C32: =C30*(1+'Scenario Assumptions'!C25+C$5) -> 17231.777 | D32: =D30*(1+'Scenario Assumptions'!C25+D$5) -> 17583.446 | E32: =E30*(1+'Scenario Assumptions'!C25+E$5) -> 17938.667 | F32: =F30*(1+'Scenario Assumptions'!C25+F$5) -> 18297.44 | G32: =G30*(1+'Scenario Assumptions'!C25+G$5) -> 18659.766 | H32: =H30*(1+'Scenario Assumptions'!C25+H$5) -> 19025.644 | I32: =I30*(1+'Scenario Assumptions'!C25+I$5) -> 19395.074 | J32: =J30*(1+'Scenario Assumptions'!C25+J$5) -> 19768.056
A33: New Enrolments FY27/28 | B33: =B32*'Forecast Assumptions'!D22*'Forecast Assumptions'!D23 -> 5546.2824 | C33: =C32*'Forecast Assumptions'!D22*'Forecast Assumptions'!D23 -> 5660.6388 | D33: =D32*'Forecast Assumptions'!D22*'Forecast Assumptions'!D23 -> 5776.162 | E33: =E32*'Forecast Assumptions'!D22*'Forecast Assumptions'!D23 -> 5892.8521 | F33: =F32*'Forecast Assumptions'!D22*'Forecast Assumptions'!D23 -> 6010.7092 | G33: =G32*'Forecast Assumptions'!D22*'Forecast Assumptions'!D23 -> 6129.7331 | H33: =H32*'Forecast Assumptions'!D22*'Forecast Assumptions'!D23 -> 6249.924 | I33: =I32*'Forecast Assumptions'!D22*'Forecast Assumptions'!D23 -> 6371.2817 | J33: =J32*'Forecast Assumptions'!D22*'Forecast Assumptions'!D23 -> 6493.8064
A34: Sept Anchor FY26/27 | B34: ='Student Headcount'!I30*(B31/'Student Flow Summary'!D16) -> 5752.1 | C34: ='Student Headcount'!I30*(C31/'Student Flow Summary'!D16) -> 5811.4 | D34: ='Student Headcount'!I30*(D31/'Student Flow Summary'!D16) -> 5870.7 | E34: ='Student Headcount'!I30*(E31/'Student Flow Summary'!D16) -> 5930 | F34: ='Student Headcount'!I30*(F31/'Student Flow Summary'!D16) -> 5989.3 | G34: ='Student Headcount'!I30*(G31/'Student Flow Summary'!D16) -> 6048.6 | H34: ='Student Headcount'!I30*(H31/'Student Flow Summary'!D16) -> 6107.9 | I34: ='Student Headcount'!I30*(I31/'Student Flow Summary'!D16) -> 6167.2 | J34: ='Student Headcount'!I30*(J31/'Student Flow Summary'!D16) -> 6226.5
A35: Sept Anchor FY27/28 | B35: =B34*(B33/B31) -> 5687.2652 | C35: =C34*(C33/C31) -> 5804.5284 | D35: =D34*(D33/D31) -> 5922.9882 | E35: =E34*(E33/E31) -> 6042.6445 | F35: =F34*(F33/F31) -> 6163.4974 | G35: =G34*(G33/G31) -> 6285.5468 | H35: =H34*(H33/H31) -> 6408.7929 | I35: =I34*(I33/I31) -> 6533.2354 | J35: =J34*(J33/J31) -> 6658.8746
A36: Postgraduate Research (PGR)
A37: Applications FY26/27 | B37: =('Student Flow Summary'!D19/('Forecast Assumptions'!C27*'Forecast Assumptions'!C28))*(1+'Scenario Assumptions'!B26+B$5) -> 763.72414 | C37: =('Student Flow Summary'!D19/('Forecast Assumptions'!C27*'Forecast Assumptions'!C28))*(1+'Scenario Assumptions'!B26+C$5) -> 771.51724 | D37: =('Student Flow Summary'!D19/('Forecast Assumptions'!C27*'Forecast Assumptions'!C28))*(1+'Scenario Assumptions'!B26+D$5) -> 779.31034 | E37: =('Student Flow Summary'!D19/('Forecast Assumptions'!C27*'Forecast Assumptions'!C28))*(1+'Scenario Assumptions'!B26+E$5) -> 787.10345 | F37: =('Student Flow Summary'!D19/('Forecast Assumptions'!C27*'Forecast Assumptions'!C28))*(1+'Scenario Assumptions'!B26+F$5) -> 794.89655 | G37: =('Student Flow Summary'!D19/('Forecast Assumptions'!C27*'Forecast Assumptions'!C28))*(1+'Scenario Assumptions'!B26+G$5) -> 802.68966 | H37: =('Student Flow Summary'!D19/('Forecast Assumptions'!C27*'Forecast Assumptions'!C28))*(1+'Scenario Assumptions'!B26+H$5) -> 810.48276 | I37: =('Student Flow Summary'!D19/('Forecast Assumptions'!C27*'Forecast Assumptions'!C28))*(1+'Scenario Assumptions'!B26+I$5) -> 818.27586 | J37: =('Student Flow Summary'!D19/('Forecast Assumptions'!C27*'Forecast Assumptions'!C28))*(1+'Scenario Assumptions'!B26+J$5) -> 826.06897
A38: New Enrolments FY26/27 | B38: =B37*'Forecast Assumptions'!C27*'Forecast Assumptions'!C28 -> 332.22 | C38: =C37*'Forecast Assumptions'!C27*'Forecast Assumptions'!C28 -> 335.61 | D38: =D37*'Forecast Assumptions'!C27*'Forecast Assumptions'!C28 -> 339 | E38: =E37*'Forecast Assumptions'!C27*'Forecast Assumptions'!C28 -> 342.39 | F38: =F37*'Forecast Assumptions'!C27*'Forecast Assumptions'!C28 -> 345.78 | G38: =G37*'Forecast Assumptions'!C27*'Forecast Assumptions'!C28 -> 349.17 | H38: =H37*'Forecast Assumptions'!C27*'Forecast Assumptions'!C28 -> 352.56 | I38: =I37*'Forecast Assumptions'!C27*'Forecast Assumptions'!C28 -> 355.95 | J38: =J37*'Forecast Assumptions'!C27*'Forecast Assumptions'!C28 -> 359.34
A39: Applications FY27/28 | B39: =B37*(1+'Scenario Assumptions'!C26+B$5) -> 748.44966 | C39: =C37*(1+'Scenario Assumptions'!C26+C$5) -> 763.80207 | D39: =D37*(1+'Scenario Assumptions'!C26+D$5) -> 779.31034 | E39: =E37*(1+'Scenario Assumptions'!C26+E$5) -> 794.97448 | F39: =F37*(1+'Scenario Assumptions'!C26+F$5) -> 810.79448 | G39: =G37*(1+'Scenario Assumptions'!C26+G$5) -> 826.77034 | H39: =H37*(1+'Scenario Assumptions'!C26+H$5) -> 842.90207 | I39: =I37*(1+'Scenario Assumptions'!C26+I$5) -> 859.18966 | J39: =J37*(1+'Scenario Assumptions'!C26+J$5) -> 875.6331
A40: New Enrolments FY27/28 | B40: =B39*'Forecast Assumptions'!D27*'Forecast Assumptions'!D28 -> 325.5756 | C40: =C39*'Forecast Assumptions'!D27*'Forecast Assumptions'!D28 -> 332.2539 | D40: =D39*'Forecast Assumptions'!D27*'Forecast Assumptions'!D28 -> 339 | E40: =E39*'Forecast Assumptions'!D27*'Forecast Assumptions'!D28 -> 345.8139 | F40: =F39*'Forecast Assumptions'!D27*'Forecast Assumptions'!D28 -> 352.6956 | G40: =G39*'Forecast Assumptions'!D27*'Forecast Assumptions'!D28 -> 359.6451 | H40: =H39*'Forecast Assumptions'!D27*'Forecast Assumptions'!D28 -> 366.6624 | I40: =I39*'Forecast Assumptions'!D27*'Forecast Assumptions'!D28 -> 373.7475 | J40: =J39*'Forecast Assumptions'!D27*'Forecast Assumptions'!D28 -> 380.9004
A41: Sept Anchor FY26/27 | B41: ='Student Headcount'!K30*(B38/'Student Flow Summary'!D19) -> 1121.12 | C41: ='Student Headcount'!K30*(C38/'Student Flow Summary'!D19) -> 1132.56 | D41: ='Student Headcount'!K30*(D38/'Student Flow Summary'!D19) -> 1144 | E41: ='Student Headcount'!K30*(E38/'Student Flow Summary'!D19) -> 1155.44 | F41: ='Student Headcount'!K30*(F38/'Student Flow Summary'!D19) -> 1166.88 | G41: ='Student Headcount'!K30*(G38/'Student Flow Summary'!D19) -> 1178.32 | H41: ='Student Headcount'!K30*(H38/'Student Flow Summary'!D19) -> 1189.76 | I41: ='Student Headcount'!K30*(I38/'Student Flow Summary'!D19) -> 1201.2 | J41: ='Student Headcount'!K30*(J38/'Student Flow Summary'!D19) -> 1212.64
A42: Sept Anchor FY27/28 | B42: =B41*(B40/B38) -> 1098.6976 | C42: =C41*(C40/C38) -> 1121.2344 | D42: =D41*(D40/D38) -> 1144 | E42: =E41*(E40/E38) -> 1166.9944 | F42: =F41*(F40/F38) -> 1190.2176 | G42: =G41*(G40/G38) -> 1213.6696 | H42: =H41*(H40/H38) -> 1237.3504 | I42: =I41*(I40/I38) -> 1261.26 | J42: =J41*(J40/J38) -> 1285.3984
A44: C. FY27/28 Tuition Income by Category, under Each Tested Adjustment (£)
A45: UK Undergraduate | B45: =B14*(SUM('Population Forecast'!B24:M24))*'Income Forecast'!F6/12 -> 81004470 | C45: =C14*(SUM('Population Forecast'!B24:M24))*'Income Forecast'!F6/12 -> 82666057 | D45: =D14*(SUM('Population Forecast'!B24:M24))*'Income Forecast'!F6/12 -> 84344512 | E45: =E14*(SUM('Population Forecast'!B24:M24))*'Income Forecast'!F6/12 -> 86039837 | F45: =F14*(SUM('Population Forecast'!B24:M24))*'Income Forecast'!F6/12 -> 87752031 | G45: =G14*(SUM('Population Forecast'!B24:M24))*'Income Forecast'!F6/12 -> 89481093 | H45: =H14*(SUM('Population Forecast'!B24:M24))*'Income Forecast'!F6/12 -> 91227025 | I45: =I14*(SUM('Population Forecast'!B24:M24))*'Income Forecast'!F6/12 -> 92989825 | J45: =J14*(SUM('Population Forecast'!B24:M24))*'Income Forecast'!F6/12 -> 94769494
A46: International Undergraduate | B46: =B21*(SUM('Population Forecast'!B25:M25))*'Income Forecast'!F7/12 -> 41642182 | C46: =C21*(SUM('Population Forecast'!B25:M25))*'Income Forecast'!F7/12 -> 42505210 | D46: =D21*(SUM('Population Forecast'!B25:M25))*'Income Forecast'!F7/12 -> 43377089 | E46: =E21*(SUM('Population Forecast'!B25:M25))*'Income Forecast'!F7/12 -> 44257819 | F46: =F21*(SUM('Population Forecast'!B25:M25))*'Income Forecast'!F7/12 -> 45147401 | G46: =G21*(SUM('Population Forecast'!B25:M25))*'Income Forecast'!F7/12 -> 46045835 | H46: =H21*(SUM('Population Forecast'!B25:M25))*'Income Forecast'!F7/12 -> 46953120 | I46: =I21*(SUM('Population Forecast'!B25:M25))*'Income Forecast'!F7/12 -> 47869257 | J46: =J21*(SUM('Population Forecast'!B25:M25))*'Income Forecast'!F7/12 -> 48794246
A47: UK Postgraduate | B47: =B28*(SUM('Population Forecast'!B26:M26))*'Income Forecast'!F8/12 -> 32970489 | C47: =C28*(SUM('Population Forecast'!B26:M26))*'Income Forecast'!F8/12 -> 33646789 | D47: =D28*(SUM('Population Forecast'!B26:M26))*'Income Forecast'!F8/12 -> 34329955 | E47: =E28*(SUM('Population Forecast'!B26:M26))*'Income Forecast'!F8/12 -> 35019987 | F47: =F28*(SUM('Population Forecast'!B26:M26))*'Income Forecast'!F8/12 -> 35716885 | G47: =G28*(SUM('Population Forecast'!B26:M26))*'Income Forecast'!F8/12 -> 36420649 | H47: =H28*(SUM('Population Forecast'!B26:M26))*'Income Forecast'!F8/12 -> 37131279 | I47: =I28*(SUM('Population Forecast'!B26:M26))*'Income Forecast'!F8/12 -> 37848775 | J47: =J28*(SUM('Population Forecast'!B26:M26))*'Income Forecast'!F8/12 -> 38573137
A48: International Postgraduate | B48: =B35*(SUM('Population Forecast'!B27:M27))*'Income Forecast'!F9/12 -> 53161772 | C48: =C35*(SUM('Population Forecast'!B27:M27))*'Income Forecast'!F9/12 -> 54257891 | D48: =D35*(SUM('Population Forecast'!B27:M27))*'Income Forecast'!F9/12 -> 55365195 | E48: =E35*(SUM('Population Forecast'!B27:M27))*'Income Forecast'!F9/12 -> 56483684 | F48: =F35*(SUM('Population Forecast'!B27:M27))*'Income Forecast'!F9/12 -> 57613357 | G48: =G35*(SUM('Population Forecast'!B27:M27))*'Income Forecast'!F9/12 -> 58754216 | H48: =H35*(SUM('Population Forecast'!B27:M27))*'Income Forecast'!F9/12 -> 59906260 | I48: =I35*(SUM('Population Forecast'!B27:M27))*'Income Forecast'!F9/12 -> 61069488 | J48: =J35*(SUM('Population Forecast'!B27:M27))*'Income Forecast'!F9/12 -> 62243901
A49: Postgraduate Research (PGR) | B49: =B42*(SUM('Population Forecast'!B28:M28))*'Income Forecast'!F10/12 -> 8020133 | C49: =C42*(SUM('Population Forecast'!B28:M28))*'Income Forecast'!F10/12 -> 8184644.3 | D49: =D42*(SUM('Population Forecast'!B28:M28))*'Income Forecast'!F10/12 -> 8350825.7 | E49: =E42*(SUM('Population Forecast'!B28:M28))*'Income Forecast'!F10/12 -> 8518677.3 | F49: =F42*(SUM('Population Forecast'!B28:M28))*'Income Forecast'!F10/12 -> 8688199.1 | G49: =G42*(SUM('Population Forecast'!B28:M28))*'Income Forecast'!F10/12 -> 8859391 | H49: =H42*(SUM('Population Forecast'!B28:M28))*'Income Forecast'!F10/12 -> 9032253.1 | I49: =I42*(SUM('Population Forecast'!B28:M28))*'Income Forecast'!F10/12 -> 9206785.4 | J49: =J42*(SUM('Population Forecast'!B28:M28))*'Income Forecast'!F10/12 -> 9382987.8
A50: Total Tuition Income | B50: =SUM(B45:B49) -> 2.1679905e+08 | C50: =SUM(C45:C49) -> 2.2126059e+08 | D50: =SUM(D45:D49) -> 2.2576758e+08 | E50: =SUM(E45:E49) -> 2.3032e+08 | F50: =SUM(F45:F49) -> 2.3491787e+08 | G50: =SUM(G45:G49) -> 2.3956118e+08 | H50: =SUM(H45:H49) -> 2.4424994e+08 | I50: =SUM(I45:I49) -> 2.4898413e+08 | J50: =SUM(J45:J49) -> 2.5376377e+08
A52: D. FY27/28 Income Statement Outcome, under Each Tested Adjustment
A53: Other Income (unaffected by recruitment; Base Case) | B53: ='Income Forecast'!C55 -> 1.0183585e+08 | C53: ='Income Forecast'!C55 -> 1.0183585e+08 | D53: ='Income Forecast'!C55 -> 1.0183585e+08 | E53: ='Income Forecast'!C55 -> 1.0183585e+08 | F53: ='Income Forecast'!C55 -> 1.0183585e+08 | G53: ='Income Forecast'!C55 -> 1.0183585e+08 | H53: ='Income Forecast'!C55 -> 1.0183585e+08 | I53: ='Income Forecast'!C55 -> 1.0183585e+08 | J53: ='Income Forecast'!C55 -> 1.0183585e+08
A54: Total Income | B54: =B50+B53 -> 3.1863489e+08 | C54: =C50+C53 -> 3.2309644e+08 | D54: =D50+D53 -> 3.2760342e+08 | E54: =E50+E53 -> 3.3215585e+08 | F54: =F50+F53 -> 3.3675372e+08 | G54: =G50+G53 -> 3.4139703e+08 | H54: =H50+H53 -> 3.4608578e+08 | I54: =I50+I53 -> 3.5081998e+08 | J54: =J50+J53 -> 3.5559961e+08
A55: Total Staff Cost + Opex (unaffected by recruitment; Base Case) | B55: ='Scenario Comparison'!D55+'Scenario Comparison'!E55 -> 3.3692969e+08 | C55: ='Scenario Comparison'!D55+'Scenario Comparison'!E55 -> 3.3692969e+08 | D55: ='Scenario Comparison'!D55+'Scenario Comparison'!E55 -> 3.3692969e+08 | E55: ='Scenario Comparison'!D55+'Scenario Comparison'!E55 -> 3.3692969e+08 | F55: ='Scenario Comparison'!D55+'Scenario Comparison'!E55 -> 3.3692969e+08 | G55: ='Scenario Comparison'!D55+'Scenario Comparison'!E55 -> 3.3692969e+08 | H55: ='Scenario Comparison'!D55+'Scenario Comparison'!E55 -> 3.3692969e+08 | I55: ='Scenario Comparison'!D55+'Scenario Comparison'!E55 -> 3.3692969e+08 | J55: ='Scenario Comparison'!D55+'Scenario Comparison'!E55 -> 3.3692969e+08
A56: Operating Surplus / (Deficit) | B56: =B54-B55 -> -18294803 | C56: =C54-C55 -> -13833258 | D56: =D54-D55 -> -9326271.5 | E56: =E54-E55 -> -4773843.7 | F56: =F54-F55 -> -175974.46 | G56: =G54-G55 -> 4467336.3 | H56: =H54-H55 -> 9156088.6 | I56: =I54-I55 -> 13890282 | J56: =J54-J55 -> 18669918
A57: Operating Margin % | B57: =B56/B54 -> -0.057416194 | C57: =C56/C54 -> -0.042814641 | D57: =D56/D54 -> -0.028468175 | E57: =E56/E54 -> -0.014372301 | F57: =F56/F54 -> -0.00052256129 | G57: =G56/G54 -> 0.013085458 | H57: =H56/H54 -> 0.026456125 | I57: =I56/I54 -> 0.039593762 | J57: =J56/J54 -> 0.052502638
A59: E. Break-Even Recruitment Growth Adjustment (linear estimate)
A60: Adjustment needed for FY27/28 margin = 0% (break-even) | B60: =FORECAST(0,B5:J5,B57:J57) -> 0.00096667773
A61: Adjustment needed to restore FY25/26's 2.4% margin | B61: =FORECAST('Forecast Income Statement'!F44,B5:J5,B57:J57) -> 0.018223161
A63: FORECAST() fits a straight line through the 9 tested points and solves for the recruitment adjustment at the target margin — a standard linear break-even estimate, not an exact solve (the underlying relationship is very slightly non-linear because of compounding). Recruitment growth here means applications, not enrolled headcount directly — offer and yield rates are unchanged.

Sheet Sustainability Ratios
A1: Vector University — 3-Year Financial Sustainability Assessment
A2: Base Case sustainability indicators: operating performance, cost structure, tuition and international dependency, per-student unit economics, and cash reserves — FY25/26 actual alongside the three forecast years, plus a set of formula-driven risk flags against typical higher-education sustainability thresholds.
A4: A. Sustainability KPI Trend (Base Case)
A5: FY | B5: Total Income (£) | C5: Operating Surplus / (Deficit) (£) | D5: Operating Margin % | E5: Staff Cost Ratio % | F5: Total Cost Ratio % | G5: International Tuition % of Tuition Income | H5: Average Student Headcount | I5: Income per Student (£) | J5: Cost per Student (£) | K5: Closing Cash (£) | L5: Months' Cash Cover
A6: FY25/26 (actual) | B6: ='Forecast Income Statement'!B44 -> 3.1158911e+08 | C6: ='Forecast Income Statement'!E44 -> 7389111.5 | D6: ='Forecast Income Statement'!F44 -> 0.02371428 | E6: ='Forecast Income Statement'!C44/B6 -> 0.63769879 | F6: =('Forecast Income Statement'!C44+'Forecast Income Statement'!D44)/B6 -> 0.97628572 | G6: =(SUMIFS(Income!D:D,Income!$B:$B,"FY25/26")+SUMIFS(Income!F:F,Income!$B:$B,"FY25/26"))/(SUMIFS(Income!C:C,Income!$B:$B,"FY25/26")+SUMIFS(Income!D:D,Income!$B:$B,"FY25/26")+SUMIFS(Income!E:E,Income!$B:$B,"FY25/26")+SUMIFS(Income!F:F,Income!$B:$B,"FY25/26")+SUMIFS(Income!G:G,Income!$B:$B,"FY25/26")) -> 0.42850927 | H6: =AVERAGE('Student Headcount'!M29:M40) -> 17856.692 | I6: =B6/H6 -> 17449.43 | J6: =('Forecast Income Statement'!C44+'Forecast Income Statement'!D44)/H6 -> 17035.63 | K6: ='Cash Flow Forecast'!E44 -> 48027183 | L6: =K6/(('Forecast Income Statement'!C44+'Forecast Income Statement'!D44)/12) -> 1.8945635
A7: FY26/27 | B7: ='Forecast Income Statement'!B45 -> 3.2254585e+08 | C7: ='Forecast Income Statement'!E45 -> 1998981.6 | D7: ='Forecast Income Statement'!F45 -> 0.0061975114 | E7: ='Forecast Income Statement'!C45/B7 -> 0.65445538 | F7: =('Forecast Income Statement'!C45+'Forecast Income Statement'!D45)/B7 -> 0.99380249 | G7: =(SUM('Income Forecast'!D14:D25)+SUM('Income Forecast'!F14:F25))/SUM('Income Forecast'!C14:G25) -> 0.43331511 | H7: =AVERAGE('Population Forecast'!H40:H51) -> 17570.247 | I7: =B7/H7 -> 18357.503 | J7: =('Forecast Income Statement'!C45+'Forecast Income Statement'!D45)/H7 -> 18243.732 | K7: ='Cash Flow Forecast'!E45 -> 39526165 | L7: =K7/(('Forecast Income Statement'!C45+'Forecast Income Statement'!D45)/12) -> 1.4797024
A8: FY27/28 | B8: ='Forecast Income Statement'!B46 -> 3.3675372e+08 | C8: ='Forecast Income Statement'!E46 -> -175974.46 | D8: ='Forecast Income Statement'!F46 -> -0.00052256129 | E8: ='Forecast Income Statement'!C46/B8 -> 0.66384387 | F8: =('Forecast Income Statement'!C46+'Forecast Income Statement'!D46)/B8 -> 1.0005226 | G8: =(SUM('Income Forecast'!D26:D37)+SUM('Income Forecast'!F26:F37))/SUM('Income Forecast'!C26:G37) -> 0.4374327 | H8: =AVERAGE('Population Forecast'!H52:H63) -> 17923.796 | I8: =B8/H8 -> 18788.08 | J8: =('Forecast Income Statement'!C46+'Forecast Income Statement'!D46)/H8 -> 18797.898 | K8: ='Cash Flow Forecast'!E46 -> 28350190 | L8: =K8/(('Forecast Income Statement'!C46+'Forecast Income Statement'!D46)/12) -> 1.009713
